Workbook

Sheet 01_Cover
A1: 01_Cover

Sheet 02_Index
A1: 02_Index

Sheet 03_Assumptions
A1: 03_Assumptions | TITAN Grid v2.0 Harmonized
A2: Use only yellow cells if you need to overwrite review inputs after management confirmation.
A3: Locked project metrics
A4: Total Project Cost (TPC) | B4: 27796156 | C4: EUR | D4: Locked 24.03.2026
A5: Direct CAPEX (BoQ) | B5: 24715200 | C5: EUR | D5: Locked 24.03.2026
A6: Contingency | B6: 2471520 | C6: EUR | D6: 10.0% of Direct CAPEX
A7: Escalation | B7: 609436 | C7: EUR | D7: Locked 24.03.2026
A8: Debt | B8: 16677694 | C8: EUR | D8: Locked 24.03.2026
A9: Equity | B9: 11118462 | C9: EUR | D9: Locked 24.03.2026
A10: Total IDC (capitalized) | B10: 1031579 | C10: EUR | D10: Locked 24.03.2026
A11: Average DSCR | B11: 3.07 | C11: x | D11: Locked 24.03.2026
A12: Minimum DSCR | B12: 1.68 | C12: x | D12: Locked 24.03.2026
A13: Revenue - Year 1 ops | B13: 8000000 | C13: EUR | D13: Locked 24.03.2026
A14: Revenue - Year 5 ops | B14: 28000000 | C14: EUR | D14: Locked 24.03.2026
A15: Revenue - Year 12 ops | B15: 32163198 | C15: EUR | D15: Locked 24.03.2026
... A18: Net Working Capital - Year 5 | B18: 5753425 | C18: EUR | D18: Locked 24.03.2026
A19: Net Working Capital % of Revenue | B19: =C18/C14 | C19: % | D19: Derived from locked Year 5 values
A22: Review inputs (explicitly flagged)
A23: Debt interest rate | B23: 0.045 | C23: % | D23: Review input - confirm latest debt pricing
A24: Tax rate | B24: 0.09 | C24: % | D24: Review input - confirm tax treatment
A25: Maintenance CAPEX % of revenue | B25: 0.01 | C25: % | D25: Review input
A26: EBITDA margin in first operating year | B26: 0.14 | C26: % | D26: Review input
A27: Principal grace period | B27: 2 | C27: years | D27: Review input
A28: Debt tenor | B28: 10 | C28: years | D28: Review input
A29: DSRA months | B29: 6 | C29: months | D29: Review input
A30: Default DSCR | B30: 1.2 | C30: x | D30: Covenant threshold
A31: Cash lock-up DSCR | B31: 1.3 | C31: x | D31: Covenant threshold
A32: Cash sweep trigger DSCR | B32: 1.5 | C32: x | D32: Covenant threshold
A33: Cash sweep % | B33: 0.5 | C33: % | D33: Covenant parameter
A36: Timeline
A37: Calendar Year | B37: 2026 | C37: 2027 | D37: 2028 | E37: 2029 | F37: 2030 | G37: 2031 | H37: 2032 | I37: 2033 | J37: 2034 | K37: 2035 | L37: 2036 | M37: 2037 | N37: 2038 | O37: 2039 | P37: 2040
A38: Operating Year | B38: 0 | C38: 0 | D38: 0 | E38: 1 | F38: 2 | G38: 3 | H38: 4 | I38: 5 | J38: 6 | K38: 7 | L38: 8 | M38: 9 | N38: 10 | O38: 11 | P38: 12

Sheet 04_CAPEX_Master
A1: 04_CAPEX_Master
A3: ID | B3: Desc | C3: Amount
C4: 0
C5: 0
C6: 0
C7: 0
C8: 0
C9: 0
C10: =SUM(C4:C9)

Sheet 05_CAPEX_Phasing
A1: 05_CAPEX_Phasing | Harmonized
A3: Use of funds
A4: Line Item | B4: 2026 | C4: 2027 | D4: 2028 | E4: 2029 | F4: 2030 | G4: 2031 | H4: 2032 | I4: 2033 | J4: 2034 | K4: 2035 | L4: 2036 | M4: 2037 | N4: 2038 | O4: 2039 | P4: 2040 | Q4: Total
A5: Direct CAPEX | B5: ='03_Assumptions'!B5*20% | C5: ='03_Assumptions'!B5*50% | D5: ='03_Assumptions'!B5*30% | Q5: =SUM(B5:P5)
A6: Contingency | B6: ='03_Assumptions'!B6*20% | C6: ='03_Assumptions'!B6*50% | D6: ='03_Assumptions'!B6*30% | Q6: =SUM(B6:P6)
A7: Escalation | B7: ='03_Assumptions'!B7*20% | C7: ='03_Assumptions'!B7*50% | D7: ='03_Assumptions'!B7*30% | Q7: =SUM(B7:P7)
A8: TPC | B8: =B5+B6+B7 | C8: =C5+C6+C7 | D8: =D5+D6+D7 | E8: =E5+E6+E7 | F8: =F5+F6+F7 | G8: =G5+G6+G7 | H8: =H5+H6+H7 | I8: =I5+I6+I7 | ... P8: =P5+P6+P7 | Q8: =SUM(B8:P8)
A9: IDC | B9: ='03_Assumptions'!B10*20% | C9: ='03_Assumptions'!B10*50% | D9: ='03_Assumptions'!B10*30% | Q9: =SUM(B9:P9)
A10: Total Funding Requirement | B10: =B8+B9 | C10: =C8+C9 | D10: =D8+D9 | E10: =E8+E9 | F10: =F8+F9 | G10: =G8+G9 | H10: =H8+H9 | I10: =I8+I9 | ... P10: =P8+P9 | Q10: =SUM(B10:P10)

Sheet 06_OPEX
A1: 06_OPEX | Revenue, EBITDA, WC
A3: Operating build-up
A4: Line Item | B4: 2026 | C4: 2027 | D4: 2028 | E4: 2029 | F4: 2030 | G4: 2031 | H4: 2032 | I4: 2033 | J4: 2034 | K4: 2035 | L4: 2036 | M4: 2037 | N4: 2038 | O4: 2039 | P4: 2040 | Q4: Total
A5: Operating Year | B5: =IF(B$4<2029,0,B$4-2029+1) | C5: =IF(C$4<2029,0,C$4-2029+1) | D5: =IF(D$4<2029,0,D$4-2029+1) | E5: =IF(E$4<2029,0,E$4-2029+1) | F5: =IF(F$4<2029,0,F$4-2029+1) | G5: =IF(G$4<2029,0,G$4-2029+1) | H5: =IF(H$4<2029,0,H$4-2029+1) | I5: =IF(I$4<2029,0,I$4-2029+1) | ... P5: =IF(P$4<2029,0,P$4-2029+1) | Q5: =SUM(B5:P5)
A6: Revenue | B6: =IF(B5=0,0,IF(B5=1,'03_Assumptions'!B13,IF(B5<=5,'03_Assumptions'!B13+(('03_Assumptions'!B14-'03_Assumptions'!B13)/4)*(B5-1),'03_Assumptions'!B14*(1+'03_Assumptions'!B16)^(B5-5)))) | C6: =IF(C5=0,0,IF(C5=1,'03_Assumptions'!B13,IF(C5<=5,'03_Assumptions'!B13+(('03_Assumptions'!B14-'03_Assumptions'!B13)/4)*(C5-1),'03_Assumptions'!B14*(1+'03_Assumptions'!B16)^(C5-5)))) | D6: =IF(D5=0,0,IF(D5=1,'03_Assumptions'!B13,IF(D5<=5,'03_Assumptions'!B13+(('03_Assumptions'!B14-'03_Assumptions'!B13)/4)*(D5-1),'03_Assumptions'!B14*(1+'03_Assumptions'!B16)^(D5-5)))) | E6: =IF(E5=0,0,IF(E5=1,'03_Assumptions'!B13,IF(E5<=5,'03_Assumptions'!B13+(('03_Assumptions'!B14-'03_Assumptions'!B13)/4)*(E5-1),'03_Assumptions'!B14*(1+'03_Assumptions'!B16)^(E5-5)))) | F6: =IF(F5=0,0,IF(F5=1,'03_Assumptions'!B13,IF(F5<=5,'03_Assumptions'!B13+(('03_Assumptions'!B14-'03_Assumptions'!B13)/4)*(F5-1),'03_Assumptions'!B14*(1+'03_Assumptions'!B16)^(F5-5)))) | G6: =IF(G5=0,0,IF(G5=1,'03_Assumptions'!B13,IF(G5<=5,'03_Assumptions'!B13+(('03_Assumptions'!B14-'03_Assumptions'!B13)/4)*(G5-1),'03_Assumptions'!B14*(1+'03_Assumptions'!B16)^(G5-5)))) | H6: =IF(H5=0,0,IF(H5=1,'03_Assumptions'!B13,IF(H5<=5,'03_Assumptions'!B13+(('03_Assumptions'!B14-'03_Assumptions'!B13)/4)*(H5-1),'03_Assumptions'!B14*(1+'03_Assumptions'!B16)^(H5-5)))) | I6: =IF(I5=0,0,IF(I5=1,'03_Assumptions'!B13,IF(I5<=5,'03_Assumptions'!B13+(('03_Assumptions'!B14-'03_Assumptions'!B13)/4)*(I5-1),'03_Assumptions'!B14*(1+'03_Assumptions'!B16)^(I5-5)))) | J6: =IF(J5=0,0,IF(J5=1,'03_Assumptions'!B13,IF(J5<=5,'03_Assumptions'!B13+(('03_Assumptions'!B14-'03_Assumptions'!B13)/4)*(J5-1),'03_Assumptions'!B14*(1+'03_Assumptions'!B16)^(J5-5)))) | K6: =IF(K5=0,0,IF(K5=1,'03_Assumptions'!B13,IF(K5<=5,'03_Assumptions'!B13+(('03_Assumptions'!B14-'03_Assumptions'!B13)/4)*(K5-1),'03_Assumptions'!B14*(1+'03_Assumptions'!B16)^(K5-5)))) | L6: =IF(L5=0,0,IF(L5=1,'03_Assumptions'!B13,IF(L5<=5,'03_Assumptions'!B13+(('03_Assumptions'!B14-'03_Assumptions'!B13)/4)*(L5-1),'03_Assumptions'!B14*(1+'03_Assumptions'!B16)^(L5-5)))) | M6: =IF(M5=0,0,IF(M5=1,'03_Assumptions'!B13,IF(M5<=5,'03_Assumptions'!B13+(('03_Assumptions'!B14-'03_Assumptions'!B13)/4)*(M5-1),'03_Assumptions'!B14*(1+'03_Assumptions'!B16)^(M5-5)))) | N6: =IF(N5=0,0,IF(N5=1,'03_Assumptions'!B13,IF(N5<=5,'03_Assumptions'!B13+(('03_Assumptions'!B14-'03_Assumptions'!B13)/4)*(N5-1),'03_Assumptions'!B14*(1+'03_Assumptions'!B16)^(N5-5)))) | O6: =IF(O5=0,0,IF(O5=1,'03_Assumptions'!B13,IF(O5<=5,'03_Assumptions'!B13+(('03_Assumptions'!B14-'03_Assumptions'!B13)/4)*(O5-1),'03_Assumptions'!B14*(1+'03_Assumptions'!B16)^(O5-5)))) | P6: =IF(P5=0,0,IF(P5=1,'03_Assumptions'!B13,IF(P5<=5,'03_Assumptions'!B13+(('03_Assumptions'!B14-'03_Assumptions'!B13)/4)*(P5-1),'03_Assumptions'!B14*(1+'03_Assumptions'!B16)^(P5-5)))) | Q6: =SUM(B6:P6)
A7: EBITDA Margin | B7: =IF(B5=0,0,IF(B5>=5,'03_Assumptions'!B16,'03_Assumptions'!B26+(('03_Assumptions'!B16-'03_Assumptions'!B26)/4)*(B5-1))) | C7: =IF(C5=0,0,IF(C5>=5,'03_Assumptions'!B16,'03_Assumptions'!B26+(('03_Assumptions'!B16-'03_Assumptions'!B26)/4)*(C5-1))) | D7: =IF(D5=0,0,IF(D5>=5,'03_Assumptions'!B16,'03_Assumptions'!B26+(('03_Assumptions'!B16-'03_Assumptions'!B26)/4)*(D5-1))) | E7: =IF(E5=0,0,IF(E5>=5,'03_Assumptions'!B16,'03_Assumptions'!B26+(('03_Assumptions'!B16-'03_Assumptions'!B26)/4)*(E5-1))) | F7: =IF(F5=0,0,IF(F5>=5,'03_Assumptions'!B16,'03_Assumptions'!B26+(('03_Assumptions'!B16-'03_Assumptions'!B26)/4)*(F5-1))) | G7: =IF(G5=0,0,IF(G5>=5,'03_Assumptions'!B16,'03_Assumptions'!B26+(('03_Assumptions'!B16-'03_Assumptions'!B26)/4)*(G5-1))) | H7: =IF(H5=0,0,IF(H5>=5,'03_Assumptions'!B16,'03_Assumptions'!B26+(('03_Assumptions'!B16-'03_Assumptions'!B26)/4)*(H5-1))) | I7: =IF(I5=0,0,IF(I5>=5,'03_Assumptions'!B16,'03_Assumptions'!B26+(('03_Assumptions'!B16-'03_Assumptions'!B26)/4)*(I5-1))) | J7: =IF(J5=0,0,IF(J5>=5,'03_Assumptions'!B16,'03_Assumptions'!B26+(('03_Assumptions'!B16-'03_Assumptions'!B26)/4)*(J5-1))) | K7: =IF(K5=0,0,IF(K5>=5,'03_Assumptions'!B16,'03_Assumptions'!B26+(('03_Assumptions'!B16-'03_Assumptions'!B26)/4)*(K5-1))) | L7: =IF(L5=0,0,IF(L5>=5,'03_Assumptions'!B16,'03_Assumptions'!B26+(('03_Assumptions'!B16-'03_Assumptions'!B26)/4)*(L5-1))) | M7: =IF(M5=0,0,IF(M5>=5,'03_Assumptions'!B16,'03_Assumptions'!B26+(('03_Assumptions'!B16-'03_Assumptions'!B26)/4)*(M5-1))) | N7: =IF(N5=0,0,IF(N5>=5,'03_Assumptions'!B16,'03_Assumptions'!B26+(('03_Assumptions'!B16-'03_Assumptions'!B26)/4)*(N5-1))) | O7: =IF(O5=0,0,IF(O5>=5,'03_Assumptions'!B16,'03_Assumptions'!B26+(('03_Assumptions'!B16-'03_Assumptions'!B26)/4)*(O5-1))) | P7: =IF(P5=0,0,IF(P5>=5,'03_Assumptions'!B16,'03_Assumptions'!B26+(('03_Assumptions'!B16-'03_Assumptions'!B26)/4)*(P5-1))) | Q7: =SUM(B7:P7)
A8: EBITDA | B8: =B6*B7 | C8: =C6*C7 | D8: =D6*D7 | E8: =E6*E7 | F8: =F6*F7 | G8: =G6*G7 | H8: =H6*H7 | I8: =I6*I7 | ... P8: =P6*P7 | Q8: =SUM(B8:P8)
A9: Tax Rate | B9: =IF(B5=0,0,'03_Assumptions'!B24) | C9: =IF(C5=0,0,'03_Assumptions'!B24) | D9: =IF(D5=0,0,'03_Assumptions'!B24) | E9: =IF(E5=0,0,'03_Assumptions'!B24) | F9: =IF(F5=0,0,'03_Assumptions'!B24) | G9: =IF(G5=0,0,'03_Assumptions'!B24) | H9: =IF(H5=0,0,'03_Assumptions'!B24) | I9: =IF(I5=0,0,'03_Assumptions'!B24) | J9: =IF(J5=0,0,'03_Assumptions'!B24) | K9: =IF(K5=0,0,'03_Assumptions'!B24) | L9: =IF(L5=0,0,'03_Assumptions'!B24) | M9: =IF(M5=0,0,'03_Assumptions'!B24) | N9: =IF(N5=0,0,'03_Assumptions'!B24) | O9: =IF(O5=0,0,'03_Assumptions'!B24) | P9: =IF(P5=0,0,'03_Assumptions'!B24) | Q9: =SUM(B9:P9)
A10: Cash Taxes | B10: =MAX(0,B8*B9) | C10: =MAX(0,C8*C9) | D10: =MAX(0,D8*D9) | E10: =MAX(0,E8*E9) | F10: =MAX(0,F8*F9) | G10: =MAX(0,G8*G9) | H10: =MAX(0,H8*H9) | I10: =MAX(0,I8*I9) | ... P10: =MAX(0,P8*P9) | Q10: =SUM(B10:P10)
A11: NWC % of Revenue | B11: =IF(B5=0,0,'03_Assumptions'!B19) | C11: =IF(C5=0,0,'03_Assumptions'!B19) | D11: =IF(D5=0,0,'03_Assumptions'!B19) | E11: =IF(E5=0,0,'03_Assumptions'!B19) | F11: =IF(F5=0,0,'03_Assumptions'!B19) | G11: =IF(G5=0,0,'03_Assumptions'!B19) | H11: =IF(H5=0,0,'03_Assumptions'!B19) | I11: =IF(I5=0,0,'03_Assumptions'!B19) | J11: =IF(J5=0,0,'03_Assumptions'!B19) | K11: =IF(K5=0,0,'03_Assumptions'!B19) | L11: =IF(L5=0,0,'03_Assumptions'!B19) | M11: =IF(M5=0,0,'03_Assumptions'!B19) | N11: =IF(N5=0,0,'03_Assumptions'!B19) | O11: =IF(O5=0,0,'03_Assumptions'!B19) | P11: =IF(P5=0,0,'03_Assumptions'!B19) | Q11: =SUM(B11:P11)
A12: Net Working Capital | B12: =B6*B11 | C12: =C6*C11 | D12: =D6*D11 | E12: =E6*E11 | F12: =F6*F11 | G12: =G6*G11 | H12: =H6*H11 | I12: =I6*I11 | ... P12: =P6*P11 | Q12: =SUM(B12:P12)
A13: Delta NWC | B13: =B12 | C13: =C12-B12 | D13: =D12-C12 | E13: =E12-D12 | F13: =F12-E12 | G13: =G12-F12 | H13: =H12-G12 | I13: =I12-H12 | J13: =J12-I12 | ... P13: =P12-O12 | Q13: =SUM(B13:P13)
A14: Maintenance CAPEX | B14: =B6*'03_Assumptions'!B25 | C14: =C6*'03_Assumptions'!B25 | D14: =D6*'03_Assumptions'!B25 | E14: =E6*'03_Assumptions'!B25 | F14: =F6*'03_Assumptions'!B25 | G14: =G6*'03_Assumptions'!B25 | H14: =H6*'03_Assumptions'!B25 | I14: =I6*'03_Assumptions'!B25 | J14: =J6*'03_Assumptions'!B25 | K14: =K6*'03_Assumptions'!B25 | L14: =L6*'03_Assumptions'!B25 | M14: =M6*'03_Assumptions'!B25 | N14: =N6*'03_Assumptions'!B25 | O14: =O6*'03_Assumptions'!B25 | P14: =P6*'03_Assumptions'!B25 | Q14: =SUM(B14:P14)
A17: Note: Year 2-Year 4 revenue is linear interpolation between locked Year 1 and locked Year 5. Review if management has an approved annual ramp.

Sheet 07_Funding
A1: 07_Funding | Sources & Uses
A3: Sources & Uses
A4: Use / Source | B4: Amount
A5: Direct CAPEX | B5: ='03_Assumptions'!B5
A6: Contingency | B6: ='03_Assumptions'!B6
A7: Escalation | B7: ='03_Assumptions'!B7
A8: TPC | B8: ='03_Assumptions'!B4
A9: IDC | B9: ='03_Assumptions'!B10
A10: Total Uses | B10: =SUM(B8:B9)
A12: Debt | B12: ='03_Assumptions'!B8
A13: Equity | B13: ='03_Assumptions'!B9
A14: Total Sources (ex-IDC) | B14: =SUM(B12:B13)
A15: Funding Gap / IDC bridge | B15: =B10-B14
A17: Check | B17: =IF(ABS(B15)<=1,"OK - Balanced","CHECK IDC FUNDING")

Sheet 08_Debt
A1: 08_Debt | Annual debt schedule
A3: Debt schedule
A4: Line Item | B4: 2026 | C4: 2027 | D4: 2028 | E4: 2029 | F4: 2030 | G4: 2031 | H4: 2032 | I4: 2033 | J4: 2034 | K4: 2035 | L4: 2036 | M4: 2037 | N4: 2038 | O4: 2039 | P4: 2040 | Q4: Total
A5: Opening Debt | B5: 0 | C5: =B11 | D5: =C11 | E5: =D11 | F5: =E11 | G5: =F11 | H5: =G11 | I5: =H11 | J5: =I11 | ... P5: =O11 | Q5: =SUM(B5:P5)
A6: Debt Drawdown | B6: ='03_Assumptions'!B8*20% | C6: ='03_Assumptions'!B8*50% | D6: ='03_Assumptions'!B8*30% | E6: 0 | F6: 0 | G6: 0 | H6: 0 | I6: 0 | J6: 0 | K6: 0 | L6: 0 | M6: 0 | N6: 0 | O6: 0 | P6: 0 | Q6: =SUM(B6:P6)
A7: Capitalized IDC | B7: ='03_Assumptions'!B10*20% | C7: ='03_Assumptions'!B10*50% | D7: ='03_Assumptions'!B10*30% | E7: 0 | F7: 0 | G7: 0 | H7: 0 | I7: 0 | J7: 0 | K7: 0 | L7: 0 | M7: 0 | N7: 0 | O7: 0 | P7: 0 | Q7: =SUM(B7:P7)
A8: Interest Rate | B8: ='03_Assumptions'!B23 | C8: ='03_Assumptions'!B23 | D8: ='03_Assumptions'!B23 | E8: ='03_Assumptions'!B23 | F8: ='03_Assumptions'!B23 | G8: ='03_Assumptions'!B23 | H8: ='03_Assumptions'!B23 | I8: ='03_Assumptions'!B23 | J8: ='03_Assumptions'!B23 | K8: ='03_Assumptions'!B23 | L8: ='03_Assumptions'!B23 | M8: ='03_Assumptions'!B23 | N8: ='03_Assumptions'!B23 | O8: ='03_Assumptions'!B23 | P8: ='03_Assumptions'!B23 | Q8: =SUM(B8:P8)
A9: Interest Expense | B9: =(B5+(B6+B7)/2)*B8 | C9: =(C5+(C6+C7)/2)*C8 | D9: =(D5+(D6+D7)/2)*D8 | E9: =(E5+(E6+E7)/2)*E8 | F9: =(F5+(F6+F7)/2)*F8 | G9: =(G5+(G6+G7)/2)*G8 | H9: =(H5+(H6+H7)/2)*H8 | I9: =(I5+(I6+I7)/2)*I8 | ... P9: =(P5+(P6+P7)/2)*P8 | Q9: =SUM(B9:P9)
A10: Principal Repayment | B10: =IF(AND(B$4>=2029+'03_Assumptions'!B27,B$4<2029+'03_Assumptions'!B27+'03_Assumptions'!B28),MAX(0,('03_Assumptions'!B8+'03_Assumptions'!B10)/('03_Assumptions'!B28-'03_Assumptions'!B27)),0) | C10: =IF(AND(C$4>=2029+'03_Assumptions'!B27,C$4<2029+'03_Assumptions'!B27+'03_Assumptions'!B28),MAX(0,('03_Assumptions'!B8+'03_Assumptions'!B10)/('03_Assumptions'!B28-'03_Assumptions'!B27)),0) | D10: =IF(AND(D$4>=2029+'03_Assumptions'!B27,D$4<2029+'03_Assumptions'!B27+'03_Assumptions'!B28),MAX(0,('03_Assumptions'!B8+'03_Assumptions'!B10)/('03_Assumptions'!B28-'03_Assumptions'!B27)),0) | E10: =IF(AND(E$4>=2029+'03_Assumptions'!B27,E$4<2029+'03_Assumptions'!B27+'03_Assumptions'!B28),MAX(0,('03_Assumptions'!B8+'03_Assumptions'!B10)/('03_Assumptions'!B28-'03_Assumptions'!B27)),0) | F10: =IF(AND(F$4>=2029+'03_Assumptions'!B27,F$4<2029+'03_Assumptions'!B27+'03_Assumptions'!B28),MAX(0,('03_Assumptions'!B8+'03_Assumptions'!B10)/('03_Assumptions'!B28-'03_Assumptions'!B27)),0) | G10: =IF(AND(G$4>=2029+'03_Assumptions'!B27,G$4<2029+'03_Assumptions'!B27+'03_Assumptions'!B28),MAX(0,('03_Assumptions'!B8+'03_Assumptions'!B10)/('03_Assumptions'!B28-'03_Assumptions'!B27)),0) | H10: =IF(AND(H$4>=2029+'03_Assumptions'!B27,H$4<2029+'03_Assumptions'!B27+'03_Assumptions'!B28),MAX(0,('03_Assumptions'!B8+'03_Assumptions'!B10)/('03_Assumptions'!B28-'03_Assumptions'!B27)),0) | I10: =IF(AND(I$4>=2029+'03_Assumptions'!B27,I$4<2029+'03_Assumptions'!B27+'03_Assumptions'!B28),MAX(0,('03_Assumptions'!B8+'03_Assumptions'!B10)/('03_Assumptions'!B28-'03_Assumptions'!B27)),0) | J10: =IF(AND(J$4>=2029+'03_Assumptions'!B27,J$4<2029+'03_Assumptions'!B27+'03_Assumptions'!B28),MAX(0,('03_Assumptions'!B8+'03_Assumptions'!B10)/('03_Assumptions'!B28-'03_Assumptions'!B27)),0) | K10: =IF(AND(K$4>=2029+'03_Assumptions'!B27,K$4<2029+'03_Assumptions'!B27+'03_Assumptions'!B28),MAX(0,('03_Assumptions'!B8+'03_Assumptions'!B10)/('03_Assumptions'!B28-'03_Assumptions'!B27)),0) | L10: =IF(AND(L$4>=2029+'03_Assumptions'!B27,L$4<2029+'03_Assumptions'!B27+'03_Assumptions'!B28),MAX(0,('03_Assumptions'!B8+'03_Assumptions'!B10)/('03_Assumptions'!B28-'03_Assumptions'!B27)),0) | M10: =IF(AND(M$4>=2029+'03_Assumptions'!B27,M$4<2029+'03_Assumptions'!B27+'03_Assumptions'!B28),MAX(0,('03_Assumptions'!B8+'03_Assumptions'!B10)/('03_Assumptions'!B28-'03_Assumptions'!B27)),0) | N10: =IF(AND(N$4>=2029+'03_Assumptions'!B27,N$4<2029+'03_Assumptions'!B27+'03_Assumptions'!B28),MAX(0,('03_Assumptions'!B8+'03_Assumptions'!B10)/('03_Assumptions'!B28-'03_Assumptions'!B27)),0) | O10: =IF(AND(O$4>=2029+'03_Assumptions'!B27,O$4<2029+'03_Assumptions'!B27+'03_Assumptions'!B28),MAX(0,('03_Assumptions'!B8+'03_Assumptions'!B10)/('03_Assumptions'!B28-'03_Assumptions'!B27)),0) | P10: =IF(AND(P$4>=2029+'03_Assumptions'!B27,P$4<2029+'03_Assumptions'!B27+'03_Assumptions'!B28),MAX(0,('03_Assumptions'!B8+'03_Assumptions'!B10)/('03_Assumptions'!B28-'03_Assumptions'!B27)),0) | Q10: =SUM(B10:P10)
A11: Closing Debt | B11: =MAX(0,B5+B6+B7+B9-B10) | C11: =MAX(0,C5+C6+C7+C9-C10) | D11: =MAX(0,D5+D6+D7+D9-D10) | E11: =MAX(0,E5+E6+E7+E9-E10) | F11: =MAX(0,F5+F6+F7+F9-F10) | G11: =MAX(0,G5+G6+G7+G9-G10) | H11: =MAX(0,H5+H6+H7+H9-H10) | I11: =MAX(0,I5+I6+I7+I9-I10) | ... P11: =MAX(0,P5+P6+P7+P9-P10) | Q11: =SUM(B11:P11)
A12: Debt Service | B12: =B9+B10 | C12: =C9+C10 | D12: =D9+D10 | E12: =E9+E10 | F12: =F9+F10 | G12: =G9+G10 | H12: =H9+H10 | I12: =I9+I10 | ... P12: =P9+P10 | Q12: =SUM(B12:P12)

Sheet 09_CashFlow
A1: 09_CashFlow | CFADS build
A3: Cash flow available for debt service
A4: Line Item | B4: 2026 | C4: 2027 | D4: 2028 | E4: 2029 | F4: 2030 | G4: 2031 | H4: 2032 | I4: 2033 | J4: 2034 | K4: 2035 | L4: 2036 | M4: 2037 | N4: 2038 | O4: 2039 | P4: 2040 | Q4: Total
A5: Revenue | B5: ='06_OPEX'!B6 | C5: ='06_OPEX'!C6 | D5: ='06_OPEX'!D6 | E5: ='06_OPEX'!E6 | F5: ='06_OPEX'!F6 | G5: ='06_OPEX'!G6 | H5: ='06_OPEX'!H6 | I5: ='06_OPEX'!I6 | ... P5: ='06_OPEX'!P6 | Q5: =SUM(B5:P5)
A6: EBITDA | B6: ='06_OPEX'!B8 | C6: ='06_OPEX'!C8 | D6: ='06_OPEX'!D8 | E6: ='06_OPEX'!E8 | F6: ='06_OPEX'!F8 | G6: ='06_OPEX'!G8 | H6: ='06_OPEX'!H8 | I6: ='06_OPEX'!I8 | ... P6: ='06_OPEX'!P8 | Q6: =SUM(B6:P6)
A7: Cash Taxes | B7: ='06_OPEX'!B10 | C7: ='06_OPEX'!C10 | D7: ='06_OPEX'!D10 | E7: ='06_OPEX'!E10 | F7: ='06_OPEX'!F10 | G7: ='06_OPEX'!G10 | H7: ='06_OPEX'!H10 | I7: ='06_OPEX'!I10 | ... P7: ='06_OPEX'!P10 | Q7: =SUM(B7:P7)
A8: Delta NWC | B8: ='06_OPEX'!B13 | C8: ='06_OPEX'!C13 | D8: ='06_OPEX'!D13 | E8: ='06_OPEX'!E13 | F8: ='06_OPEX'!F13 | G8: ='06_OPEX'!G13 | H8: ='06_OPEX'!H13 | I8: ='06_OPEX'!I13 | ... P8: ='06_OPEX'!P13 | Q8: =SUM(B8:P8)
A9: Maintenance CAPEX | B9: ='06_OPEX'!B14 | C9: ='06_OPEX'!C14 | D9: ='06_OPEX'!D14 | E9: ='06_OPEX'!E14 | F9: ='06_OPEX'!F14 | G9: ='06_OPEX'!G14 | H9: ='06_OPEX'!H14 | I9: ='06_OPEX'!I14 | ... P9: ='06_OPEX'!P14 | Q9: =SUM(B9:P9)
A10: CFADS | B10: =B6-B7-B8-B9 | C10: =C6-C7-C8-C9 | D10: =D6-D7-D8-D9 | E10: =E6-E7-E8-E9 | F10: =F6-F7-F8-F9 | G10: =G6-G7-G8-G9 | H10: =H6-H7-H8-H9 | I10: =I6-I7-I8-I9 | ... P10: =P6-P7-P8-P9 | Q10: =SUM(B10:P10)
A11: Debt Service | B11: ='08_Debt'!B12 | C11: ='08_Debt'!C12 | D11: ='08_Debt'!D12 | E11: ='08_Debt'!E12 | F11: ='08_Debt'!F12 | G11: ='08_Debt'!G12 | H11: ='08_Debt'!H12 | I11: ='08_Debt'!I12 | ... P11: ='08_Debt'!P12 | Q11: =SUM(B11:P11)
A12: FCFE pre-distributions | B12: =B10-B11 | C12: =C10-C11 | D12: =D10-D11 | E12: =E10-E11 | F12: =F10-F11 | G12: =G10-G11 | H12: =H10-H11 | I12: =I10-I11 | ... P12: =P10-P11 | Q12: =SUM(B12:P12)

Sheet CFADS_DSCR_AUDIT
A1: CFADS_DSCR_AUDIT | Bank-grade audit engine
A3: CFADS and DSCR
A4: Line Item | B4: 2026 | C4: 2027 | D4: 2028 | E4: 2029 | F4: 2030 | G4: 2031 | H4: 2032 | I4: 2033 | J4: 2034 | K4: 2035 | L4: 2036 | M4: 2037 | N4: 2038 | O4: 2039 | P4: 2040 | Q4: Total
A5: Revenue | B5: ='09_CashFlow'!B5 | C5: ='09_CashFlow'!C5 | D5: ='09_CashFlow'!D5 | E5: ='09_CashFlow'!E5 | F5: ='09_CashFlow'!F5 | G5: ='09_CashFlow'!G5 | H5: ='09_CashFlow'!H5 | I5: ='09_CashFlow'!I5 | ... P5: ='09_CashFlow'!P5 | Q5: =SUM(B5:P5)
A6: EBITDA | B6: ='09_CashFlow'!B6 | C6: ='09_CashFlow'!C6 | D6: ='09_CashFlow'!D6 | E6: ='09_CashFlow'!E6 | F6: ='09_CashFlow'!F6 | G6: ='09_CashFlow'!G6 | H6: ='09_CashFlow'!H6 | I6: ='09_CashFlow'!I6 | ... P6: ='09_CashFlow'!P6 | Q6: =SUM(B6:P6)
A7: Cash Taxes | B7: ='09_CashFlow'!B7 | C7: ='09_CashFlow'!C7 | D7: ='09_CashFlow'!D7 | E7: ='09_CashFlow'!E7 | F7: ='09_CashFlow'!F7 | G7: ='09_CashFlow'!G7 | H7: ='09_CashFlow'!H7 | I7: ='09_CashFlow'!I7 | ... P7: ='09_CashFlow'!P7 | Q7: =SUM(B7:P7)
A8: Delta NWC | B8: ='09_CashFlow'!B8 | C8: ='09_CashFlow'!C8 | D8: ='09_CashFlow'!D8 | E8: ='09_CashFlow'!E8 | F8: ='09_CashFlow'!F8 | G8: ='09_CashFlow'!G8 | H8: ='09_CashFlow'!H8 | I8: ='09_CashFlow'!I8 | ... P8: ='09_CashFlow'!P8 | Q8: =SUM(B8:P8)
A9: Maintenance CAPEX | B9: ='09_CashFlow'!B9 | C9: ='09_CashFlow'!C9 | D9: ='09_CashFlow'!D9 | E9: ='09_CashFlow'!E9 | F9: ='09_CashFlow'!F9 | G9: ='09_CashFlow'!G9 | H9: ='09_CashFlow'!H9 | I9: ='09_CashFlow'!I9 | ... P9: ='09_CashFlow'!P9 | Q9: =SUM(B9:P9)
A10: CFADS | B10: ='09_CashFlow'!B10 | C10: ='09_CashFlow'!C10 | D10: ='09_CashFlow'!D10 | E10: ='09_CashFlow'!E10 | F10: ='09_CashFlow'!F10 | G10: ='09_CashFlow'!G10 | H10: ='09_CashFlow'!H10 | I10: ='09_CashFlow'!I10 | ... P10: ='09_CashFlow'!P10 | Q10: =SUM(B10:P10)
A11: Interest | B11: ='08_Debt'!B9 | C11: ='08_Debt'!C9 | D11: ='08_Debt'!D9 | E11: ='08_Debt'!E9 | F11: ='08_Debt'!F9 | G11: ='08_Debt'!G9 | H11: ='08_Debt'!H9 | I11: ='08_Debt'!I9 | ... P11: ='08_Debt'!P9 | Q11: =SUM(B11:P11)
A12: Principal | B12: ='08_Debt'!B10 | C12: ='08_Debt'!C10 | D12: ='08_Debt'!D10 | E12: ='08_Debt'!E10 | F12: ='08_Debt'!F10 | G12: ='08_Debt'!G10 | H12: ='08_Debt'!H10 | I12: ='08_Debt'!I10 | ... P12: ='08_Debt'!P10 | Q12: =SUM(B12:P12)
A13: Debt Service | B13: ='08_Debt'!B12 | C13: ='08_Debt'!C12 | D13: ='08_Debt'!D12 | E13: ='08_Debt'!E12 | F13: ='08_Debt'!F12 | G13: ='08_Debt'!G12 | H13: ='08_Debt'!H12 | I13: ='08_Debt'!I12 | ... P13: ='08_Debt'!P12 | Q13: =SUM(B13:P13)
A14: DSCR | B14: =IFERROR(B10/B13,0) | C14: =IFERROR(C10/C13,0) | D14: =IFERROR(D10/D13,0) | E14: =IFERROR(E10/E13,0) | F14: =IFERROR(F10/F13,0) | G14: =IFERROR(G10/G13,0) | H14: =IFERROR(H10/H13,0) | I14: =IFERROR(I10/I13,0) | ... P14: =IFERROR(P10/P13,0) | Q14: =AVERAGE(B14:P14)
A15: CFADS Positive? | B15: =IF(B10>0,"OK","FLAG") | C15: =IF(C10>0,"OK","FLAG") | D15: =IF(D10>0,"OK","FLAG") | E15: =IF(E10>0,"OK","FLAG") | F15: =IF(F10>0,"OK","FLAG") | G15: =IF(G10>0,"OK","FLAG") | H15: =IF(H10>0,"OK","FLAG") | I15: =IF(I10>0,"OK","FLAG") | ... P15: =IF(P10>0,"OK","FLAG")
A16: DSCR >= 1.20x? | B16: =IF(B14>='03_Assumptions'!B30,"OK","BREACH") | C16: =IF(C14>='03_Assumptions'!B30,"OK","BREACH") | D16: =IF(D14>='03_Assumptions'!B30,"OK","BREACH") | E16: =IF(E14>='03_Assumptions'!B30,"OK","BREACH") | F16: =IF(F14>='03_Assumptions'!B30,"OK","BREACH") | G16: =IF(G14>='03_Assumptions'!B30,"OK","BREACH") | H16: =IF(H14>='03_Assumptions'!B30,"OK","BREACH") | I16: =IF(I14>='03_Assumptions'!B30,"OK","BREACH") | J16: =IF(J14>='03_Assumptions'!B30,"OK","BREACH") | K16: =IF(K14>='03_Assumptions'!B30,"OK","BREACH") | L16: =IF(L14>='03_Assumptions'!B30,"OK","BREACH") | M16: =IF(M14>='03_Assumptions'!B30,"OK","BREACH") | N16: =IF(N14>='03_Assumptions'!B30,"OK","BREACH") | O16: =IF(O14>='03_Assumptions'!B30,"OK","BREACH") | P16: =IF(P14>='03_Assumptions'!B30,"OK","BREACH")
A19: Minimum DSCR | B19: =MIN(B14:P14)
A20: Average DSCR | B20: =AVERAGE(B14:P14)
A21: Locked minimum DSCR | B21: ='03_Assumptions'!B12
A22: Locked average DSCR | B22: ='03_Assumptions'!B11
A23: Min DSCR check | B23: =IF(ROUND(B19,2)=ROUND(B21,2),"OK","CHECK")
A24: Avg DSCR check | B24: =IF(ROUND(B20,2)=ROUND(B22,2),"OK","CHECK")

Sheet COVENANTS_ENGINE
A1: COVENANTS_ENGINE | Lock-up, sweep, triggers
A3: Covenant monitoring
A4: Line Item | B4: 2026 | C4: 2027 | D4: 2028 | E4: 2029 | F4: 2030 | G4: 2031 | H4: 2032 | I4: 2033 | J4: 2034 | K4: 2035 | L4: 2036 | M4: 2037 | N4: 2038 | O4: 2039 | P4: 2040 | Q4: Total
A5: DSCR | B5: ='CFADS_DSCR_AUDIT'!B14 | C5: ='CFADS_DSCR_AUDIT'!C14 | D5: ='CFADS_DSCR_AUDIT'!D14 | E5: ='CFADS_DSCR_AUDIT'!E14 | F5: ='CFADS_DSCR_AUDIT'!F14 | G5: ='CFADS_DSCR_AUDIT'!G14 | H5: ='CFADS_DSCR_AUDIT'!H14 | I5: ='CFADS_DSCR_AUDIT'!I14 | ... P5: ='CFADS_DSCR_AUDIT'!P14
A6: CFADS | B6: ='CFADS_DSCR_AUDIT'!B10 | C6: ='CFADS_DSCR_AUDIT'!C10 | D6: ='CFADS_DSCR_AUDIT'!D10 | E6: ='CFADS_DSCR_AUDIT'!E10 | F6: ='CFADS_DSCR_AUDIT'!F10 | G6: ='CFADS_DSCR_AUDIT'!G10 | H6: ='CFADS_DSCR_AUDIT'!H10 | I6: ='CFADS_DSCR_AUDIT'!I10 | ... P6: ='CFADS_DSCR_AUDIT'!P10
A7: Debt Service | B7: ='CFADS_DSCR_AUDIT'!B13 | C7: ='CFADS_DSCR_AUDIT'!C13 | D7: ='CFADS_DSCR_AUDIT'!D13 | E7: ='CFADS_DSCR_AUDIT'!E13 | F7: ='CFADS_DSCR_AUDIT'!F13 | G7: ='CFADS_DSCR_AUDIT'!G13 | H7: ='CFADS_DSCR_AUDIT'!H13 | I7: ='CFADS_DSCR_AUDIT'!I13 | ... P7: ='CFADS_DSCR_AUDIT'!P13
A8: Default test | B8: =IF(B5<'03_Assumptions'!B30,"DEFAULT","OK") | C8: =IF(C5<'03_Assumptions'!B30,"DEFAULT","OK") | D8: =IF(D5<'03_Assumptions'!B30,"DEFAULT","OK") | E8: =IF(E5<'03_Assumptions'!B30,"DEFAULT","OK") | F8: =IF(F5<'03_Assumptions'!B30,"DEFAULT","OK") | G8: =IF(G5<'03_Assumptions'!B30,"DEFAULT","OK") | H8: =IF(H5<'03_Assumptions'!B30,"DEFAULT","OK") | I8: =IF(I5<'03_Assumptions'!B30,"DEFAULT","OK") | J8: =IF(J5<'03_Assumptions'!B30,"DEFAULT","OK") | K8: =IF(K5<'03_Assumptions'!B30,"DEFAULT","OK") | L8: =IF(L5<'03_Assumptions'!B30,"DEFAULT","OK") | M8: =IF(M5<'03_Assumptions'!B30,"DEFAULT","OK") | N8: =IF(N5<'03_Assumptions'!B30,"DEFAULT","OK") | O8: =IF(O5<'03_Assumptions'!B30,"DEFAULT","OK") | P8: =IF(P5<'03_Assumptions'!B30,"DEFAULT","OK")
A9: Lock-up test | B9: =IF(B5<'03_Assumptions'!B31,"LOCKED","FREE") | C9: =IF(C5<'03_Assumptions'!B31,"LOCKED","FREE") | D9: =IF(D5<'03_Assumptions'!B31,"LOCKED","FREE") | E9: =IF(E5<'03_Assumptions'!B31,"LOCKED","FREE") | F9: =IF(F5<'03_Assumptions'!B31,"LOCKED","FREE") | G9: =IF(G5<'03_Assumptions'!B31,"LOCKED","FREE") | H9: =IF(H5<'03_Assumptions'!B31,"LOCKED","FREE") | I9: =IF(I5<'03_Assumptions'!B31,"LOCKED","FREE") | J9: =IF(J5<'03_Assumptions'!B31,"LOCKED","FREE") | K9: =IF(K5<'03_Assumptions'!B31,"LOCKED","FREE") | L9: =IF(L5<'03_Assumptions'!B31,"LOCKED","FREE") | M9: =IF(M5<'03_Assumptions'!B31,"LOCKED","FREE") | N9: =IF(N5<'03_Assumptions'!B31,"LOCKED","FREE") | O9: =IF(O5<'03_Assumptions'!B31,"LOCKED","FREE") | P9: =IF(P5<'03_Assumptions'!B31,"LOCKED","FREE")
A10: Sweep test | B10: =IF(B5>'03_Assumptions'!B32,"SWEEP ACTIVE","NO SWEEP") | C10: =IF(C5>'03_Assumptions'!B32,"SWEEP ACTIVE","NO SWEEP") | D10: =IF(D5>'03_Assumptions'!B32,"SWEEP ACTIVE","NO SWEEP") | E10: =IF(E5>'03_Assumptions'!B32,"SWEEP ACTIVE","NO SWEEP") | F10: =IF(F5>'03_Assumptions'!B32,"SWEEP ACTIVE","NO SWEEP") | G10: =IF(G5>'03_Assumptions'!B32,"SWEEP ACTIVE","NO SWEEP") | H10: =IF(H5>'03_Assumptions'!B32,"SWEEP ACTIVE","NO SWEEP") | I10: =IF(I5>'03_Assumptions'!B32,"SWEEP ACTIVE","NO SWEEP") | J10: =IF(J5>'03_Assumptions'!B32,"SWEEP ACTIVE","NO SWEEP") | K10: =IF(K5>'03_Assumptions'!B32,"SWEEP ACTIVE","NO SWEEP") | L10: =IF(L5>'03_Assumptions'!B32,"SWEEP ACTIVE","NO SWEEP") | M10: =IF(M5>'03_Assumptions'!B32,"SWEEP ACTIVE","NO SWEEP") | N10: =IF(N5>'03_Assumptions'!B32,"SWEEP ACTIVE","NO SWEEP") | O10: =IF(O5>'03_Assumptions'!B32,"SWEEP ACTIVE","NO SWEEP") | P10: =IF(P5>'03_Assumptions'!B32,"SWEEP ACTIVE","NO SWEEP")
A11: Excess Cash | B11: =MAX(0,B6-B7) | C11: =MAX(0,C6-C7) | D11: =MAX(0,D6-D7) | E11: =MAX(0,E6-E7) | F11: =MAX(0,F6-F7) | G11: =MAX(0,G6-G7) | H11: =MAX(0,H6-H7) | I11: =MAX(0,I6-I7) | ... P11: =MAX(0,P6-P7)
A12: Sweep Amount | B12: =IF(B5>'03_Assumptions'!B32,B11*'03_Assumptions'!B33,0) | C12: =IF(C5>'03_Assumptions'!B32,C11*'03_Assumptions'!B33,0) | D12: =IF(D5>'03_Assumptions'!B32,D11*'03_Assumptions'!B33,0) | E12: =IF(E5>'03_Assumptions'!B32,E11*'03_Assumptions'!B33,0) | F12: =IF(F5>'03_Assumptions'!B32,F11*'03_Assumptions'!B33,0) | G12: =IF(G5>'03_Assumptions'!B32,G11*'03_Assumptions'!B33,0) | H12: =IF(H5>'03_Assumptions'!B32,H11*'03_Assumptions'!B33,0) | I12: =IF(I5>'03_Assumptions'!B32,I11*'03_Assumptions'!B33,0) | J12: =IF(J5>'03_Assumptions'!B32,J11*'03_Assumptions'!B33,0) | K12: =IF(K5>'03_Assumptions'!B32,K11*'03_Assumptions'!B33,0) | L12: =IF(L5>'03_Assumptions'!B32,L11*'03_Assumptions'!B33,0) | M12: =IF(M5>'03_Assumptions'!B32,M11*'03_Assumptions'!B33,0) | N12: =IF(N5>'03_Assumptions'!B32,N11*'03_Assumptions'!B33,0) | O12: =IF(O5>'03_Assumptions'!B32,O11*'03_Assumptions'!B33,0) | P12: =IF(P5>'03_Assumptions'!B32,P11*'03_Assumptions'!B33,0)
A13: DSRA Required | B13: =B7*'03_Assumptions'!B29/12 | C13: =C7*'03_Assumptions'!B29/12 | D13: =D7*'03_Assumptions'!B29/12 | E13: =E7*'03_Assumptions'!B29/12 | F13: =F7*'03_Assumptions'!B29/12 | G13: =G7*'03_Assumptions'!B29/12 | H13: =H7*'03_Assumptions'!B29/12 | I13: =I7*'03_Assumptions'!B29/12 | J13: =J7*'03_Assumptions'!B29/12 | K13: =K7*'03_Assumptions'!B29/12 | L13: =L7*'03_Assumptions'!B29/12 | M13: =M7*'03_Assumptions'!B29/12 | N13: =N7*'03_Assumptions'!B29/12 | O13: =O7*'03_Assumptions'!B29/12 | P13: =P7*'03_Assumptions'!B29/12
A14: Distribution Allowed | B14: =IF(AND(B5>='03_Assumptions'!B31,B8="OK"),"YES","NO") | C14: =IF(AND(C5>='03_Assumptions'!B31,C8="OK"),"YES","NO") | D14: =IF(AND(D5>='03_Assumptions'!B31,D8="OK"),"YES","NO") | E14: =IF(AND(E5>='03_Assumptions'!B31,E8="OK"),"YES","NO") | F14: =IF(AND(F5>='03_Assumptions'!B31,F8="OK"),"YES","NO") | G14: =IF(AND(G5>='03_Assumptions'!B31,G8="OK"),"YES","NO") | H14: =IF(AND(H5>='03_Assumptions'!B31,H8="OK"),"YES","NO") | I14: =IF(AND(I5>='03_Assumptions'!B31,I8="OK"),"YES","NO") | J14: =IF(AND(J5>='03_Assumptions'!B31,J8="OK"),"YES","NO") | K14: =IF(AND(K5>='03_Assumptions'!B31,K8="OK"),"YES","NO") | L14: =IF(AND(L5>='03_Assumptions'!B31,L8="OK"),"YES","NO") | M14: =IF(AND(M5>='03_Assumptions'!B31,M8="OK"),"YES","NO") | N14: =IF(AND(N5>='03_Assumptions'!B31,N8="OK"),"YES","NO") | O14: =IF(AND(O5>='03_Assumptions'!B31,O8="OK"),"YES","NO") | P14: =IF(AND(P5>='03_Assumptions'!B31,P8="OK"),"YES","NO")
A15: Status | B15: =IF(B8="DEFAULT","RED",IF(B9="LOCKED","YELLOW",IF(B10="SWEEP ACTIVE","GREEN+SWEEP","GREEN"))) | C15: =IF(C8="DEFAULT","RED",IF(C9="LOCKED","YELLOW",IF(C10="SWEEP ACTIVE","GREEN+SWEEP","GREEN"))) | D15: =IF(D8="DEFAULT","RED",IF(D9="LOCKED","YELLOW",IF(D10="SWEEP ACTIVE","GREEN+SWEEP","GREEN"))) | E15: =IF(E8="DEFAULT","RED",IF(E9="LOCKED","YELLOW",IF(E10="SWEEP ACTIVE","GREEN+SWEEP","GREEN"))) | F15: =IF(F8="DEFAULT","RED",IF(F9="LOCKED","YELLOW",IF(F10="SWEEP ACTIVE","GREEN+SWEEP","GREEN"))) | G15: =IF(G8="DEFAULT","RED",IF(G9="LOCKED","YELLOW",IF(G10="SWEEP ACTIVE","GREEN+SWEEP","GREEN"))) | H15: =IF(H8="DEFAULT","RED",IF(H9="LOCKED","YELLOW",IF(H10="SWEEP ACTIVE","GREEN+SWEEP","GREEN"))) | I15: =IF(I8="DEFAULT","RED",IF(I9="LOCKED","YELLOW",IF(I10="SWEEP ACTIVE","GREEN+SWEEP","GREEN"))) | ... P15: =IF(P8="DEFAULT","RED",IF(P9="LOCKED","YELLOW",IF(P10="SWEEP ACTIVE","GREEN+SWEEP","GREEN")))
A18: Any default? | B18: =IF(COUNTIF(B8:P8,"DEFAULT")=0,"NO","YES")
A19: Any lock-up? | B19: =IF(COUNTIF(B9:P9,"LOCKED")=0,"NO","YES")
A20: Any sweep? | B20: =IF(COUNTIF(B10:P10,"SWEEP ACTIVE")=0,"NO","YES")

Sheet 10_Valuation
A1: 10_Valuation | Returns
A3: Project and equity returns
A4: Metric | B4: Value
A5: Project IRR | B5: =IRR('09_CashFlow'!B10:P10)
A6: Equity IRR | B6: =IRR({'-20%*'03_Assumptions'!B9,'-50%*'03_Assumptions'!B9,'-30%*'03_Assumptions'!B9,0,0,0,0,0,0,0,0,0,0,0,0}+0)
A7: Average DSCR | B7: ='CFADS_DSCR_AUDIT'!B20
A8: Minimum DSCR | B8: ='CFADS_DSCR_AUDIT'!B19

Sheet 11_Dashboard
A1: 11_Dashboard | TITAN Grid
A3: Key metrics
A4: TPC | B4: ='03_Assumptions'!B4
A5: Direct CAPEX | B5: ='03_Assumptions'!B5
A6: Debt | B6: ='03_Assumptions'!B8
A7: Equity | B7: ='03_Assumptions'!B9
A8: IDC | B8: ='03_Assumptions'!B10
A9: Average DSCR | B9: ='CFADS_DSCR_AUDIT'!B20
A10: Minimum DSCR | B10: ='CFADS_DSCR_AUDIT'!B19
A11: Revenue Year 1 | B11: ='03_Assumptions'!B13
A12: Revenue Year 5 | B12: ='03_Assumptions'!B14
A13: Revenue Year 12 | B13: ='03_Assumptions'!B15

Sheet 12_QA_Audit
A1: 12_QA_Audit | Automated checks
A3: Core QA
A4: Check | B4: Status
A5: TPC = Direct CAPEX + Contingency + Escalation | B5: =IF(ABS('03_Assumptions'!B4-('03_Assumptions'!B5+'03_Assumptions'!B6+'03_Assumptions'!B7))<=1,"OK","FAIL")
A6: Sources = Uses incl. IDC | B6: =IF(ABS('07_Funding'!B10-('03_Assumptions'!B8+'03_Assumptions'!B9))<=1,"OK","CHECK IDC")
A7: Minimum DSCR >= 1.20x | B7: =IF('CFADS_DSCR_AUDIT'!B19>=1.2,"OK","FAIL")
A8: Debt amortizes to zero by end of tenor | B8: =IF(INDEX('08_Debt'!B11:P11,1,COLUMNS('08_Debt'!B11:P11))<=1,"OK","FAIL")
A9: No covenant default in base case | B9: =IF('COVENANTS_ENGINE'!B18="NO","OK","FAIL")
A10: Locked min DSCR matched | B10: ='CFADS_DSCR_AUDIT'!B23
A11: Locked avg DSCR matched | B11: ='CFADS_DSCR_AUDIT'!B24
