Workbook

Sheet README
A1: UNI-MAK CANONICAL MEMORY / BANK-GRADE CAPEX MODEL
A2: Section | B2: Value | C2: Comment
A3: Model status | B3: Working bank-grade model | C3: Canonical baseline set to segment breakdown total of €67.5m.
A4: Workbook purpose | B4: Working bank-grade model | C4: Canonical baseline set to annual phasing implied by segment-by-year memory: €68.3m.
A5: Core assumptions | B5: Construction + funding + DSCR + risk | C5: Supports CAPEX phasing, S-curve monthly cash flow, debt/equity/grant draw schedule, DSCR-ready debt service view, Monte Carlo contingency analytics, and dashboard.
A6: Debt structure | B6: Illustrative | C6: Debt share 55%, Equity 35%, Grants 10%, interest 7.0%, repayment tenor 8 years, first repayment in 2030. Replace with term sheet once available.
A7: CFADS | B7: Illustrative placeholder | C7: 2030-2037 CFADS assumptions are placeholders for DSCR testing and should be replaced with operating model outputs.
A8: Monte Carlo | B8: 500 trials | C8: Deterministic random seeds are embedded for reproducibility. Excel recalc still works on formulas tied to the seed sheet.
A12: Sheet map
A13: Sheet | B13: Use
A14: INPUTS | B14: Project assumptions, annual CAPEX, funding, DSCR, S-curve and Monte Carlo drivers
A15: SEGMENT_CANONICAL | B15: Canonical segment x year memory retained from previous consistency cleanup
A16: YEARLY_CAPEX | B16: Annual phasing and year-over-year profile
A17: S_CURVE | B17: Monthly within-year weights using blended logistic + Gompertz curves
A18: CAPEX_MONTHLY | B18: 48-month cash flow profile and cumulative S-curve
A19: FUNDING_DRAWS | B19: Monthly debt/equity/grant schedule with IDC and annual funding summary
A20: DSCR_SCHEDULE | B20: Construction debt bridge into annual debt service / DSCR view
A21: MONTE_CARLO | B21: Contingency stress test with percentile outputs
A22: DASHBOARD | B22: Management control tower

Sheet INPUTS
A1: MODEL INPUTS / ASSUMPTIONS
A3: Item | B3: Value | C3: Units | D3: Comment
A4: Project | B4: Transformer Plant - Phase Implementation | D4: User-provided CAPEX_TIMELINE_001.
A5: Currency | B5: EUR | D5: Presentation currency.
A6: Base total CAPEX | B6: =SEGMENT_CANONICAL!F16 | C6: EUR | D6: Canonical baseline from segment breakdown.
A7: Base contingency | B7: =SEGMENT_CANONICAL!F15 | C7: EUR | D7: Source: segment breakdown / Contingency total.
A8: CAPEX ex contingency | B8: =B6-B7 | C8: EUR | D8: Derived.
A9: COD / repayment start | B9: 2030 | C9: Year | D9: Illustrative; update when term sheet is fixed.
A12: Year | B12: Annual CAPEX | C12: % of Total | D12: Comment | F12: Funding assumption | G12: Value | H12: Units | I12: Comment
A13: 2026 | B13: =SEGMENT_CANONICAL!B16 | C13: =B13/$B$6 | D13: Canonical annual phasing from segment-by-year cleanup. | F13: Debt share | G13: 0.55 | H13: % | I13: Senior debt share of total CAPEX.
A14: 2027 | B14: =SEGMENT_CANONICAL!C16 | C14: =B14/$B$6 | D14: Canonical annual phasing from segment-by-year cleanup. | F14: Equity share | G14: 0.35 | H14: % | I14: Sponsor equity share of total CAPEX.
A15: 2028 | B15: =SEGMENT_CANONICAL!D16 | C15: =B15/$B$6 | D15: Canonical annual phasing from segment-by-year cleanup. | F15: Grant share | G15: 0.1 | H15: % | I15: Grant share of total CAPEX.
A16: 2029 | B16: =SEGMENT_CANONICAL!E16 | C16: =B16/$B$6 | D16: Canonical annual phasing from segment-by-year cleanup. | F16: Funding share check | G16: =SUM(G13:G15) | H16: % | I16: Must equal 100.0%.
F17: Annual debt interest | G17: 0.07 | H17: % | I17: Construction and operating debt rate.
F18: Repayment tenor | G18: 8 | H18: Years | I18: Fixed annuity assumption.
F19: Minimum DSCR | G19: 1.25 | H19: x | I19: Bank covenant test.
A22: Year | B22: Blend α | C22: Logistic k | D22: Logistic x0 | E22: Gompertz b | F22: Gompertz c | H22: Ops Year | I22: CFADS | J22: Comment
A23: 2026 | B23: 0.45 | C23: 0.65 | D23: 7 | E23: 0.42 | F23: 7.8 | H23: 2030 | I23: 7000000 | J23: Illustrative placeholder; replace with operating model.
A24: 2027 | B24: 0.6 | C24: 0.8 | D24: 6 | E24: 0.55 | F24: 6 | H24: 2031 | I24: 8500000 | J24: Illustrative placeholder; replace with operating model.
A25: 2028 | B25: 0.35 | C25: 0.7 | D25: 7 | E25: 0.5 | F25: 7.5 | H25: 2032 | I25: 10500000 | J25: Illustrative placeholder; replace with operating model.
A26: 2029 | B26: 0.5 | C26: 0.75 | D26: 6.5 | E26: 0.5 | F26: 7 | H26: 2033 | I26: 12000000 | J26: Illustrative placeholder; replace with operating model.
H27: 2034 | I27: 13500000 | J27: Illustrative placeholder; replace with operating model.
H28: 2035 | I28: 14500000 | J28: Illustrative placeholder; replace with operating model.
H29: 2036 | I29: 15000000 | J29: Illustrative placeholder; replace with operating model.
H30: 2037 | I30: 15000000 | J30: Illustrative placeholder; replace with operating model.
F32: Monte Carlo input | G32: Value | H32: Units | I32: Comment
F33: Trials | G33: 500 | H33: count | I33: Deterministic seeds embedded in hidden sheet.
F34: Delay max months | G34: 6 | H34: months | I34: Permit / contractor delay stress.
F35: Delay cost / month | G35: 0.0035 | H35: % | I35: Applies to civil exposure.
F36: Materials mean shock | G36: 0.04 | H36: % | I36: Normal shock mean.
F37: Materials std dev | G37: 0.03 | H37: % | I37: Normal shock sigma.
F38: Lead-time event probability | G38: 0.3 | H38: % | I38: Equipment procurement event.
F39: Lead-time event impact | G39: 0.06 | H39: % | I39: Applies to equipment exposure.
F40: Commissioning probability | G40: 0.25 | H40: % | I40: Commissioning event.
F41: Commissioning impact | G41: 0.04 | H41: % | I41: Applies to commissioning exposure.
F42: Civil exposure | G42: 0.35 | H42: % | I42: Share of CAPEX exposed to civil risk.
F43: Equipment exposure | G43: 0.4 | H43: % | I43: Share of CAPEX exposed to equipment risk.
F44: Commissioning exposure | G44: 0.1 | H44: % | I44: Share of CAPEX exposed to commissioning risk.
F46: Funding share status | G46: =IF(ABS(G16-1)<0.0001,"OK","ERROR")
F47: Canonical total check | G47: =IF(B6=SEGMENT_CANONICAL!F16,"OK","CHECK")

Sheet SEGMENT_CANONICAL
A1: CANONICAL SEGMENT PHASING MEMORY
A3: Segment | B3: 2026 | C3: 2027 | D3: 2028 | E3: 2029 | F3: Total | G3: Comment
A4: Civil works | B4: 1000000 | C4: 14000000 | D4: 2000000 | E4: 1255000 | F4: =SUM(B4:E4) | G4: Canonical memory retained from segment-led normalization.
A5: Production equipment | B5: 0 | C5: 0 | D5: 8000000 | E5: 2000000 | F5: =SUM(B5:E5) | G5: Canonical memory retained from segment-led normalization.
A6: Testing hall | B6: 0 | C6: 0 | D6: 4000000 | E6: 1000000 | F6: =SUM(B6:E6) | G6: Canonical memory retained from segment-led normalization.
A7: Drying systems | B7: 0 | C7: 0 | D7: 1500000 | E7: 500000 | F7: =SUM(B7:E7) | G7: Canonical memory retained from segment-led normalization.
A8: Utilities | B8: 0 | C8: 2000000 | D8: 2000000 | E8: 625000 | F8: =SUM(B8:E8) | G8: Canonical memory retained from segment-led normalization.
A9: Logistics | B9: 0 | C9: 3000000 | D9: 10000000 | E9: 2445000 | F9: =SUM(B9:E9) | G9: Canonical memory retained from segment-led normalization.
A10: IT | B10: 100000 | C10: 200000 | D10: 1500000 | E10: 292000 | F10: =SUM(B10:E10) | G10: Canonical memory retained from segment-led normalization.
A11: Engineering | B11: 625000 | C11: 0 | D11: 0 | E11: 0 | F11: =SUM(B11:E11) | G11: Canonical memory retained from segment-led normalization.
A12: Project management | B12: 500000 | C12: 500000 | D12: 500000 | E12: 500000 | F12: =SUM(B12:E12) | G12: Canonical memory retained from segment-led normalization.
A13: Renewables | B13: 0 | C13: 0 | D13: 1000000 | E13: 0 | F13: =SUM(B13:E13) | G13: Canonical memory retained from segment-led normalization.
A14: QA / transport / security | B14: 0 | C14: 0 | D14: 500000 | E14: 1500000 | F14: =SUM(B14:E14) | G14: Canonical memory retained from segment-led normalization.
A15: Contingency | B15: 1000000 | C15: 3000000 | D15: 1000000 | E15: 258000 | F15: =SUM(B15:E15) | G15: Canonical memory retained from segment-led normalization.
A16: TOTAL | B16: =SUM(B4:B15) | C16: =SUM(C4:C15) | D16: =SUM(D4:D15) | E16: =SUM(E4:E15) | F16: =SUM(F4:F15)

Sheet YEARLY_CAPEX
A1: ANNUAL CAPEX PHASING
A3: Year | B3: Annual CAPEX | C3: % Total | D3: YoY Change | E3: Cumulative CAPEX | F3: Cumulative %
A4: 2026 | B4: =INDEX(INPUTS!$B$13:$B$16,MATCH(A4,INPUTS!$A$13:$A$16,0)) | C4: =B4/INPUTS!$B$6 | E4: =SUM($B$4:B4) | F4: =E4/INPUTS!$B$6
A5: 2027 | B5: =INDEX(INPUTS!$B$13:$B$16,MATCH(A5,INPUTS!$A$13:$A$16,0)) | C5: =B5/INPUTS!$B$6 | D5: =B5/B4-1 | E5: =SUM($B$4:B5) | F5: =E5/INPUTS!$B$6
A6: 2028 | B6: =INDEX(INPUTS!$B$13:$B$16,MATCH(A6,INPUTS!$A$13:$A$16,0)) | C6: =B6/INPUTS!$B$6 | D6: =B6/B5-1 | E6: =SUM($B$4:B6) | F6: =E6/INPUTS!$B$6
A7: 2029 | B7: =INDEX(INPUTS!$B$13:$B$16,MATCH(A7,INPUTS!$A$13:$A$16,0)) | C7: =B7/INPUTS!$B$6 | D7: =B7/B6-1 | E7: =SUM($B$4:B7) | F7: =E7/INPUTS!$B$6

Sheet S_CURVE
A1: BLENDED MONTHLY CAPEX S-CURVE (LOGISTIC + GOMPERTZ)
A3: Month # | B3: 2026 | C3: 2027 | D3: 2028 | E3: 2029
A4: 1 | B4: =(INPUTS!$B$23*(((1/(1+EXP(-INPUTS!$C$23*(1-INPUTS!$D$23))))-(1/(1+EXP(-INPUTS!$C$23*(0-INPUTS!$D$23)))))/((1/(1+EXP(-INPUTS!$C$23*(12-INPUTS!$D$23))))-(1/(1+EXP(-INPUTS!$C$23*(0-INPUTS!$D$23))))))+(1-INPUTS!$B$23)*(((EXP(-EXP(-INPUTS!$E$23*(1-INPUTS!$F$23))))-(EXP(-EXP(-INPUTS!$E$23*(0-INPUTS!$F$23)))))/((EXP(-EXP(-INPUTS!$E$23*(12-INPUTS!$F$23))))-(EXP(-EXP(-INPUTS!$E$23*(0-INPUTS!$F$23))))))) | C4: =(INPUTS!$B$24*(((1/(1+EXP(-INPUTS!$C$24*(1-INPUTS!$D$24))))-(1/(1+EXP(-INPUTS!$C$24*(0-INPUTS!$D$24)))))/((1/(1+EXP(-INPUTS!$C$24*(12-INPUTS!$D$24))))-(1/(1+EXP(-INPUTS!$C$24*(0-INPUTS!$D$24))))))+(1-INPUTS!$B$24)*(((EXP(-EXP(-INPUTS!$E$24*(1-INPUTS!$F$24))))-(EXP(-EXP(-INPUTS!$E$24*(0-INPUTS!$F$24)))))/((EXP(-EXP(-INPUTS!$E$24*(12-INPUTS!$F$24))))-(EXP(-EXP(-INPUTS!$E$24*(0-INPUTS!$F$24))))))) | D4: =(INPUTS!$B$25*(((1/(1+EXP(-INPUTS!$C$25*(1-INPUTS!$D$25))))-(1/(1+EXP(-INPUTS!$C$25*(0-INPUTS!$D$25)))))/((1/(1+EXP(-INPUTS!$C$25*(12-INPUTS!$D$25))))-(1/(1+EXP(-INPUTS!$C$25*(0-INPUTS!$D$25))))))+(1-INPUTS!$B$25)*(((EXP(-EXP(-INPUTS!$E$25*(1-INPUTS!$F$25))))-(EXP(-EXP(-INPUTS!$E$25*(0-INPUTS!$F$25)))))/((EXP(-EXP(-INPUTS!$E$25*(12-INPUTS!$F$25))))-(EXP(-EXP(-INPUTS!$E$25*(0-INPUTS!$F$25))))))) | E4: =(INPUTS!$B$26*(((1/(1+EXP(-INPUTS!$C$26*(1-INPUTS!$D$26))))-(1/(1+EXP(-INPUTS!$C$26*(0-INPUTS!$D$26)))))/((1/(1+EXP(-INPUTS!$C$26*(12-INPUTS!$D$26))))-(1/(1+EXP(-INPUTS!$C$26*(0-INPUTS!$D$26))))))+(1-INPUTS!$B$26)*(((EXP(-EXP(-INPUTS!$E$26*(1-INPUTS!$F$26))))-(EXP(-EXP(-INPUTS!$E$26*(0-INPUTS!$F$26)))))/((EXP(-EXP(-INPUTS!$E$26*(12-INPUTS!$F$26))))-(EXP(-EXP(-INPUTS!$E$26*(0-INPUTS!$F$26)))))))
A5: 2 | B5: =(INPUTS!$B$23*(((1/(1+EXP(-INPUTS!$C$23*(2-INPUTS!$D$23))))-(1/(1+EXP(-INPUTS!$C$23*(1-INPUTS!$D$23)))))/((1/(1+EXP(-INPUTS!$C$23*(12-INPUTS!$D$23))))-(1/(1+EXP(-INPUTS!$C$23*(0-INPUTS!$D$23))))))+(1-INPUTS!$B$23)*(((EXP(-EXP(-INPUTS!$E$23*(2-INPUTS!$F$23))))-(EXP(-EXP(-INPUTS!$E$23*(1-INPUTS!$F$23)))))/((EXP(-EXP(-INPUTS!$E$23*(12-INPUTS!$F$23))))-(EXP(-EXP(-INPUTS!$E$23*(0-INPUTS!$F$23))))))) | C5: =(INPUTS!$B$24*(((1/(1+EXP(-INPUTS!$C$24*(2-INPUTS!$D$24))))-(1/(1+EXP(-INPUTS!$C$24*(1-INPUTS!$D$24)))))/((1/(1+EXP(-INPUTS!$C$24*(12-INPUTS!$D$24))))-(1/(1+EXP(-INPUTS!$C$24*(0-INPUTS!$D$24))))))+(1-INPUTS!$B$24)*(((EXP(-EXP(-INPUTS!$E$24*(2-INPUTS!$F$24))))-(EXP(-EXP(-INPUTS!$E$24*(1-INPUTS!$F$24)))))/((EXP(-EXP(-INPUTS!$E$24*(12-INPUTS!$F$24))))-(EXP(-EXP(-INPUTS!$E$24*(0-INPUTS!$F$24))))))) | D5: =(INPUTS!$B$25*(((1/(1+EXP(-INPUTS!$C$25*(2-INPUTS!$D$25))))-(1/(1+EXP(-INPUTS!$C$25*(1-INPUTS!$D$25)))))/((1/(1+EXP(-INPUTS!$C$25*(12-INPUTS!$D$25))))-(1/(1+EXP(-INPUTS!$C$25*(0-INPUTS!$D$25))))))+(1-INPUTS!$B$25)*(((EXP(-EXP(-INPUTS!$E$25*(2-INPUTS!$F$25))))-(EXP(-EXP(-INPUTS!$E$25*(1-INPUTS!$F$25)))))/((EXP(-EXP(-INPUTS!$E$25*(12-INPUTS!$F$25))))-(EXP(-EXP(-INPUTS!$E$25*(0-INPUTS!$F$25))))))) | E5: =(INPUTS!$B$26*(((1/(1+EXP(-INPUTS!$C$26*(2-INPUTS!$D$26))))-(1/(1+EXP(-INPUTS!$C$26*(1-INPUTS!$D$26)))))/((1/(1+EXP(-INPUTS!$C$26*(12-INPUTS!$D$26))))-(1/(1+EXP(-INPUTS!$C$26*(0-INPUTS!$D$26))))))+(1-INPUTS!$B$26)*(((EXP(-EXP(-INPUTS!$E$26*(2-INPUTS!$F$26))))-(EXP(-EXP(-INPUTS!$E$26*(1-INPUTS!$F$26)))))/((EXP(-EXP(-INPUTS!$E$26*(12-INPUTS!$F$26))))-(EXP(-EXP(-INPUTS!$E$26*(0-INPUTS!$F$26)))))))
A6: 3 | B6: =(INPUTS!$B$23*(((1/(1+EXP(-INPUTS!$C$23*(3-INPUTS!$D$23))))-(1/(1+EXP(-INPUTS!$C$23*(2-INPUTS!$D$23)))))/((1/(1+EXP(-INPUTS!$C$23*(12-INPUTS!$D$23))))-(1/(1+EXP(-INPUTS!$C$23*(0-INPUTS!$D$23))))))+(1-INPUTS!$B$23)*(((EXP(-EXP(-INPUTS!$E$23*(3-INPUTS!$F$23))))-(EXP(-EXP(-INPUTS!$E$23*(2-INPUTS!$F$23)))))/((EXP(-EXP(-INPUTS!$E$23*(12-INPUTS!$F$23))))-(EXP(-EXP(-INPUTS!$E$23*(0-INPUTS!$F$23))))))) | C6: =(INPUTS!$B$24*(((1/(1+EXP(-INPUTS!$C$24*(3-INPUTS!$D$24))))-(1/(1+EXP(-INPUTS!$C$24*(2-INPUTS!$D$24)))))/((1/(1+EXP(-INPUTS!$C$24*(12-INPUTS!$D$24))))-(1/(1+EXP(-INPUTS!$C$24*(0-INPUTS!$D$24))))))+(1-INPUTS!$B$24)*(((EXP(-EXP(-INPUTS!$E$24*(3-INPUTS!$F$24))))-(EXP(-EXP(-INPUTS!$E$24*(2-INPUTS!$F$24)))))/((EXP(-EXP(-INPUTS!$E$24*(12-INPUTS!$F$24))))-(EXP(-EXP(-INPUTS!$E$24*(0-INPUTS!$F$24))))))) | D6: =(INPUTS!$B$25*(((1/(1+EXP(-INPUTS!$C$25*(3-INPUTS!$D$25))))-(1/(1+EXP(-INPUTS!$C$25*(2-INPUTS!$D$25)))))/((1/(1+EXP(-INPUTS!$C$25*(12-INPUTS!$D$25))))-(1/(1+EXP(-INPUTS!$C$25*(0-INPUTS!$D$25))))))+(1-INPUTS!$B$25)*(((EXP(-EXP(-INPUTS!$E$25*(3-INPUTS!$F$25))))-(EXP(-EXP(-INPUTS!$E$25*(2-INPUTS!$F$25)))))/((EXP(-EXP(-INPUTS!$E$25*(12-INPUTS!$F$25))))-(EXP(-EXP(-INPUTS!$E$25*(0-INPUTS!$F$25))))))) | E6: =(INPUTS!$B$26*(((1/(1+EXP(-INPUTS!$C$26*(3-INPUTS!$D$26))))-(1/(1+EXP(-INPUTS!$C$26*(2-INPUTS!$D$26)))))/((1/(1+EXP(-INPUTS!$C$26*(12-INPUTS!$D$26))))-(1/(1+EXP(-INPUTS!$C$26*(0-INPUTS!$D$26))))))+(1-INPUTS!$B$26)*(((EXP(-EXP(-INPUTS!$E$26*(3-INPUTS!$F$26))))-(EXP(-EXP(-INPUTS!$E$26*(2-INPUTS!$F$26)))))/((EXP(-EXP(-INPUTS!$E$26*(12-INPUTS!$F$26))))-(EXP(-EXP(-INPUTS!$E$26*(0-INPUTS!$F$26)))))))
A7: 4 | B7: =(INPUTS!$B$23*(((1/(1+EXP(-INPUTS!$C$23*(4-INPUTS!$D$23))))-(1/(1+EXP(-INPUTS!$C$23*(3-INPUTS!$D$23)))))/((1/(1+EXP(-INPUTS!$C$23*(12-INPUTS!$D$23))))-(1/(1+EXP(-INPUTS!$C$23*(0-INPUTS!$D$23))))))+(1-INPUTS!$B$23)*(((EXP(-EXP(-INPUTS!$E$23*(4-INPUTS!$F$23))))-(EXP(-EXP(-INPUTS!$E$23*(3-INPUTS!$F$23)))))/((EXP(-EXP(-INPUTS!$E$23*(12-INPUTS!$F$23))))-(EXP(-EXP(-INPUTS!$E$23*(0-INPUTS!$F$23))))))) | C7: =(INPUTS!$B$24*(((1/(1+EXP(-INPUTS!$C$24*(4-INPUTS!$D$24))))-(1/(1+EXP(-INPUTS!$C$24*(3-INPUTS!$D$24)))))/((1/(1+EXP(-INPUTS!$C$24*(12-INPUTS!$D$24))))-(1/(1+EXP(-INPUTS!$C$24*(0-INPUTS!$D$24))))))+(1-INPUTS!$B$24)*(((EXP(-EXP(-INPUTS!$E$24*(4-INPUTS!$F$24))))-(EXP(-EXP(-INPUTS!$E$24*(3-INPUTS!$F$24)))))/((EXP(-EXP(-INPUTS!$E$24*(12-INPUTS!$F$24))))-(EXP(-EXP(-INPUTS!$E$24*(0-INPUTS!$F$24))))))) | D7: =(INPUTS!$B$25*(((1/(1+EXP(-INPUTS!$C$25*(4-INPUTS!$D$25))))-(1/(1+EXP(-INPUTS!$C$25*(3-INPUTS!$D$25)))))/((1/(1+EXP(-INPUTS!$C$25*(12-INPUTS!$D$25))))-(1/(1+EXP(-INPUTS!$C$25*(0-INPUTS!$D$25))))))+(1-INPUTS!$B$25)*(((EXP(-EXP(-INPUTS!$E$25*(4-INPUTS!$F$25))))-(EXP(-EXP(-INPUTS!$E$25*(3-INPUTS!$F$25)))))/((EXP(-EXP(-INPUTS!$E$25*(12-INPUTS!$F$25))))-(EXP(-EXP(-INPUTS!$E$25*(0-INPUTS!$F$25))))))) | E7: =(INPUTS!$B$26*(((1/(1+EXP(-INPUTS!$C$26*(4-INPUTS!$D$26))))-(1/(1+EXP(-INPUTS!$C$26*(3-INPUTS!$D$26)))))/((1/(1+EXP(-INPUTS!$C$26*(12-INPUTS!$D$26))))-(1/(1+EXP(-INPUTS!$C$26*(0-INPUTS!$D$26))))))+(1-INPUTS!$B$26)*(((EXP(-EXP(-INPUTS!$E$26*(4-INPUTS!$F$26))))-(EXP(-EXP(-INPUTS!$E$26*(3-INPUTS!$F$26)))))/((EXP(-EXP(-INPUTS!$E$26*(12-INPUTS!$F$26))))-(EXP(-EXP(-INPUTS!$E$26*(0-INPUTS!$F$26)))))))
A8: 5 | B8: =(INPUTS!$B$23*(((1/(1+EXP(-INPUTS!$C$23*(5-INPUTS!$D$23))))-(1/(1+EXP(-INPUTS!$C$23*(4-INPUTS!$D$23)))))/((1/(1+EXP(-INPUTS!$C$23*(12-INPUTS!$D$23))))-(1/(1+EXP(-INPUTS!$C$23*(0-INPUTS!$D$23))))))+(1-INPUTS!$B$23)*(((EXP(-EXP(-INPUTS!$E$23*(5-INPUTS!$F$23))))-(EXP(-EXP(-INPUTS!$E$23*(4-INPUTS!$F$23)))))/((EXP(-EXP(-INPUTS!$E$23*(12-INPUTS!$F$23))))-(EXP(-EXP(-INPUTS!$E$23*(0-INPUTS!$F$23))))))) | C8: =(INPUTS!$B$24*(((1/(1+EXP(-INPUTS!$C$24*(5-INPUTS!$D$24))))-(1/(1+EXP(-INPUTS!$C$24*(4-INPUTS!$D$24)))))/((1/(1+EXP(-INPUTS!$C$24*(12-INPUTS!$D$24))))-(1/(1+EXP(-INPUTS!$C$24*(0-INPUTS!$D$24))))))+(1-INPUTS!$B$24)*(((EXP(-EXP(-INPUTS!$E$24*(5-INPUTS!$F$24))))-(EXP(-EXP(-INPUTS!$E$24*(4-INPUTS!$F$24)))))/((EXP(-EXP(-INPUTS!$E$24*(12-INPUTS!$F$24))))-(EXP(-EXP(-INPUTS!$E$24*(0-INPUTS!$F$24))))))) | D8: =(INPUTS!$B$25*(((1/(1+EXP(-INPUTS!$C$25*(5-INPUTS!$D$25))))-(1/(1+EXP(-INPUTS!$C$25*(4-INPUTS!$D$25)))))/((1/(1+EXP(-INPUTS!$C$25*(12-INPUTS!$D$25))))-(1/(1+EXP(-INPUTS!$C$25*(0-INPUTS!$D$25))))))+(1-INPUTS!$B$25)*(((EXP(-EXP(-INPUTS!$E$25*(5-INPUTS!$F$25))))-(EXP(-EXP(-INPUTS!$E$25*(4-INPUTS!$F$25)))))/((EXP(-EXP(-INPUTS!$E$25*(12-INPUTS!$F$25))))-(EXP(-EXP(-INPUTS!$E$25*(0-INPUTS!$F$25))))))) | E8: =(INPUTS!$B$26*(((1/(1+EXP(-INPUTS!$C$26*(5-INPUTS!$D$26))))-(1/(1+EXP(-INPUTS!$C$26*(4-INPUTS!$D$26)))))/((1/(1+EXP(-INPUTS!$C$26*(12-INPUTS!$D$26))))-(1/(1+EXP(-INPUTS!$C$26*(0-INPUTS!$D$26))))))+(1-INPUTS!$B$26)*(((EXP(-EXP(-INPUTS!$E$26*(5-INPUTS!$F$26))))-(EXP(-EXP(-INPUTS!$E$26*(4-INPUTS!$F$26)))))/((EXP(-EXP(-INPUTS!$E$26*(12-INPUTS!$F$26))))-(EXP(-EXP(-INPUTS!$E$26*(0-INPUTS!$F$26)))))))
A9: 6 | B9: =(INPUTS!$B$23*(((1/(1+EXP(-INPUTS!$C$23*(6-INPUTS!$D$23))))-(1/(1+EXP(-INPUTS!$C$23*(5-INPUTS!$D$23)))))/((1/(1+EXP(-INPUTS!$C$23*(12-INPUTS!$D$23))))-(1/(1+EXP(-INPUTS!$C$23*(0-INPUTS!$D$23))))))+(1-INPUTS!$B$23)*(((EXP(-EXP(-INPUTS!$E$23*(6-INPUTS!$F$23))))-(EXP(-EXP(-INPUTS!$E$23*(5-INPUTS!$F$23)))))/((EXP(-EXP(-INPUTS!$E$23*(12-INPUTS!$F$23))))-(EXP(-EXP(-INPUTS!$E$23*(0-INPUTS!$F$23))))))) | C9: =(INPUTS!$B$24*(((1/(1+EXP(-INPUTS!$C$24*(6-INPUTS!$D$24))))-(1/(1+EXP(-INPUTS!$C$24*(5-INPUTS!$D$24)))))/((1/(1+EXP(-INPUTS!$C$24*(12-INPUTS!$D$24))))-(1/(1+EXP(-INPUTS!$C$24*(0-INPUTS!$D$24))))))+(1-INPUTS!$B$24)*(((EXP(-EXP(-INPUTS!$E$24*(6-INPUTS!$F$24))))-(EXP(-EXP(-INPUTS!$E$24*(5-INPUTS!$F$24)))))/((EXP(-EXP(-INPUTS!$E$24*(12-INPUTS!$F$24))))-(EXP(-EXP(-INPUTS!$E$24*(0-INPUTS!$F$24))))))) | D9: =(INPUTS!$B$25*(((1/(1+EXP(-INPUTS!$C$25*(6-INPUTS!$D$25))))-(1/(1+EXP(-INPUTS!$C$25*(5-INPUTS!$D$25)))))/((1/(1+EXP(-INPUTS!$C$25*(12-INPUTS!$D$25))))-(1/(1+EXP(-INPUTS!$C$25*(0-INPUTS!$D$25))))))+(1-INPUTS!$B$25)*(((EXP(-EXP(-INPUTS!$E$25*(6-INPUTS!$F$25))))-(EXP(-EXP(-INPUTS!$E$25*(5-INPUTS!$F$25)))))/((EXP(-EXP(-INPUTS!$E$25*(12-INPUTS!$F$25))))-(EXP(-EXP(-INPUTS!$E$25*(0-INPUTS!$F$25))))))) | E9: =(INPUTS!$B$26*(((1/(1+EXP(-INPUTS!$C$26*(6-INPUTS!$D$26))))-(1/(1+EXP(-INPUTS!$C$26*(5-INPUTS!$D$26)))))/((1/(1+EXP(-INPUTS!$C$26*(12-INPUTS!$D$26))))-(1/(1+EXP(-INPUTS!$C$26*(0-INPUTS!$D$26))))))+(1-INPUTS!$B$26)*(((EXP(-EXP(-INPUTS!$E$26*(6-INPUTS!$F$26))))-(EXP(-EXP(-INPUTS!$E$26*(5-INPUTS!$F$26)))))/((EXP(-EXP(-INPUTS!$E$26*(12-INPUTS!$F$26))))-(EXP(-EXP(-INPUTS!$E$26*(0-INPUTS!$F$26)))))))
A10: 7 | B10: =(INPUTS!$B$23*(((1/(1+EXP(-INPUTS!$C$23*(7-INPUTS!$D$23))))-(1/(1+EXP(-INPUTS!$C$23*(6-INPUTS!$D$23)))))/((1/(1+EXP(-INPUTS!$C$23*(12-INPUTS!$D$23))))-(1/(1+EXP(-INPUTS!$C$23*(0-INPUTS!$D$23))))))+(1-INPUTS!$B$23)*(((EXP(-EXP(-INPUTS!$E$23*(7-INPUTS!$F$23))))-(EXP(-EXP(-INPUTS!$E$23*(6-INPUTS!$F$23)))))/((EXP(-EXP(-INPUTS!$E$23*(12-INPUTS!$F$23))))-(EXP(-EXP(-INPUTS!$E$23*(0-INPUTS!$F$23))))))) | C10: =(INPUTS!$B$24*(((1/(1+EXP(-INPUTS!$C$24*(7-INPUTS!$D$24))))-(1/(1+EXP(-INPUTS!$C$24*(6-INPUTS!$D$24)))))/((1/(1+EXP(-INPUTS!$C$24*(12-INPUTS!$D$24))))-(1/(1+EXP(-INPUTS!$C$24*(0-INPUTS!$D$24))))))+(1-INPUTS!$B$24)*(((EXP(-EXP(-INPUTS!$E$24*(7-INPUTS!$F$24))))-(EXP(-EXP(-INPUTS!$E$24*(6-INPUTS!$F$24)))))/((EXP(-EXP(-INPUTS!$E$24*(12-INPUTS!$F$24))))-(EXP(-EXP(-INPUTS!$E$24*(0-INPUTS!$F$24))))))) | D10: =(INPUTS!$B$25*(((1/(1+EXP(-INPUTS!$C$25*(7-INPUTS!$D$25))))-(1/(1+EXP(-INPUTS!$C$25*(6-INPUTS!$D$25)))))/((1/(1+EXP(-INPUTS!$C$25*(12-INPUTS!$D$25))))-(1/(1+EXP(-INPUTS!$C$25*(0-INPUTS!$D$25))))))+(1-INPUTS!$B$25)*(((EXP(-EXP(-INPUTS!$E$25*(7-INPUTS!$F$25))))-(EXP(-EXP(-INPUTS!$E$25*(6-INPUTS!$F$25)))))/((EXP(-EXP(-INPUTS!$E$25*(12-INPUTS!$F$25))))-(EXP(-EXP(-INPUTS!$E$25*(0-INPUTS!$F$25))))))) | E10: =(INPUTS!$B$26*(((1/(1+EXP(-INPUTS!$C$26*(7-INPUTS!$D$26))))-(1/(1+EXP(-INPUTS!$C$26*(6-INPUTS!$D$26)))))/((1/(1+EXP(-INPUTS!$C$26*(12-INPUTS!$D$26))))-(1/(1+EXP(-INPUTS!$C$26*(0-INPUTS!$D$26))))))+(1-INPUTS!$B$26)*(((EXP(-EXP(-INPUTS!$E$26*(7-INPUTS!$F$26))))-(EXP(-EXP(-INPUTS!$E$26*(6-INPUTS!$F$26)))))/((EXP(-EXP(-INPUTS!$E$26*(12-INPUTS!$F$26))))-(EXP(-EXP(-INPUTS!$E$26*(0-INPUTS!$F$26)))))))
A11: 8 | B11: =(INPUTS!$B$23*(((1/(1+EXP(-INPUTS!$C$23*(8-INPUTS!$D$23))))-(1/(1+EXP(-INPUTS!$C$23*(7-INPUTS!$D$23)))))/((1/(1+EXP(-INPUTS!$C$23*(12-INPUTS!$D$23))))-(1/(1+EXP(-INPUTS!$C$23*(0-INPUTS!$D$23))))))+(1-INPUTS!$B$23)*(((EXP(-EXP(-INPUTS!$E$23*(8-INPUTS!$F$23))))-(EXP(-EXP(-INPUTS!$E$23*(7-INPUTS!$F$23)))))/((EXP(-EXP(-INPUTS!$E$23*(12-INPUTS!$F$23))))-(EXP(-EXP(-INPUTS!$E$23*(0-INPUTS!$F$23))))))) | C11: =(INPUTS!$B$24*(((1/(1+EXP(-INPUTS!$C$24*(8-INPUTS!$D$24))))-(1/(1+EXP(-INPUTS!$C$24*(7-INPUTS!$D$24)))))/((1/(1+EXP(-INPUTS!$C$24*(12-INPUTS!$D$24))))-(1/(1+EXP(-INPUTS!$C$24*(0-INPUTS!$D$24))))))+(1-INPUTS!$B$24)*(((EXP(-EXP(-INPUTS!$E$24*(8-INPUTS!$F$24))))-(EXP(-EXP(-INPUTS!$E$24*(7-INPUTS!$F$24)))))/((EXP(-EXP(-INPUTS!$E$24*(12-INPUTS!$F$24))))-(EXP(-EXP(-INPUTS!$E$24*(0-INPUTS!$F$24))))))) | D11: =(INPUTS!$B$25*(((1/(1+EXP(-INPUTS!$C$25*(8-INPUTS!$D$25))))-(1/(1+EXP(-INPUTS!$C$25*(7-INPUTS!$D$25)))))/((1/(1+EXP(-INPUTS!$C$25*(12-INPUTS!$D$25))))-(1/(1+EXP(-INPUTS!$C$25*(0-INPUTS!$D$25))))))+(1-INPUTS!$B$25)*(((EXP(-EXP(-INPUTS!$E$25*(8-INPUTS!$F$25))))-(EXP(-EXP(-INPUTS!$E$25*(7-INPUTS!$F$25)))))/((EXP(-EXP(-INPUTS!$E$25*(12-INPUTS!$F$25))))-(EXP(-EXP(-INPUTS!$E$25*(0-INPUTS!$F$25))))))) | E11: =(INPUTS!$B$26*(((1/(1+EXP(-INPUTS!$C$26*(8-INPUTS!$D$26))))-(1/(1+EXP(-INPUTS!$C$26*(7-INPUTS!$D$26)))))/((1/(1+EXP(-INPUTS!$C$26*(12-INPUTS!$D$26))))-(1/(1+EXP(-INPUTS!$C$26*(0-INPUTS!$D$26))))))+(1-INPUTS!$B$26)*(((EXP(-EXP(-INPUTS!$E$26*(8-INPUTS!$F$26))))-(EXP(-EXP(-INPUTS!$E$26*(7-INPUTS!$F$26)))))/((EXP(-EXP(-INPUTS!$E$26*(12-INPUTS!$F$26))))-(EXP(-EXP(-INPUTS!$E$26*(0-INPUTS!$F$26)))))))
A12: 9 | B12: =(INPUTS!$B$23*(((1/(1+EXP(-INPUTS!$C$23*(9-INPUTS!$D$23))))-(1/(1+EXP(-INPUTS!$C$23*(8-INPUTS!$D$23)))))/((1/(1+EXP(-INPUTS!$C$23*(12-INPUTS!$D$23))))-(1/(1+EXP(-INPUTS!$C$23*(0-INPUTS!$D$23))))))+(1-INPUTS!$B$23)*(((EXP(-EXP(-INPUTS!$E$23*(9-INPUTS!$F$23))))-(EXP(-EXP(-INPUTS!$E$23*(8-INPUTS!$F$23)))))/((EXP(-EXP(-INPUTS!$E$23*(12-INPUTS!$F$23))))-(EXP(-EXP(-INPUTS!$E$23*(0-INPUTS!$F$23))))))) | C12: =(INPUTS!$B$24*(((1/(1+EXP(-INPUTS!$C$24*(9-INPUTS!$D$24))))-(1/(1+EXP(-INPUTS!$C$24*(8-INPUTS!$D$24)))))/((1/(1+EXP(-INPUTS!$C$24*(12-INPUTS!$D$24))))-(1/(1+EXP(-INPUTS!$C$24*(0-INPUTS!$D$24))))))+(1-INPUTS!$B$24)*(((EXP(-EXP(-INPUTS!$E$24*(9-INPUTS!$F$24))))-(EXP(-EXP(-INPUTS!$E$24*(8-INPUTS!$F$24)))))/((EXP(-EXP(-INPUTS!$E$24*(12-INPUTS!$F$24))))-(EXP(-EXP(-INPUTS!$E$24*(0-INPUTS!$F$24))))))) | D12: =(INPUTS!$B$25*(((1/(1+EXP(-INPUTS!$C$25*(9-INPUTS!$D$25))))-(1/(1+EXP(-INPUTS!$C$25*(8-INPUTS!$D$25)))))/((1/(1+EXP(-INPUTS!$C$25*(12-INPUTS!$D$25))))-(1/(1+EXP(-INPUTS!$C$25*(0-INPUTS!$D$25))))))+(1-INPUTS!$B$25)*(((EXP(-EXP(-INPUTS!$E$25*(9-INPUTS!$F$25))))-(EXP(-EXP(-INPUTS!$E$25*(8-INPUTS!$F$25)))))/((EXP(-EXP(-INPUTS!$E$25*(12-INPUTS!$F$25))))-(EXP(-EXP(-INPUTS!$E$25*(0-INPUTS!$F$25))))))) | E12: =(INPUTS!$B$26*(((1/(1+EXP(-INPUTS!$C$26*(9-INPUTS!$D$26))))-(1/(1+EXP(-INPUTS!$C$26*(8-INPUTS!$D$26)))))/((1/(1+EXP(-INPUTS!$C$26*(12-INPUTS!$D$26))))-(1/(1+EXP(-INPUTS!$C$26*(0-INPUTS!$D$26))))))+(1-INPUTS!$B$26)*(((EXP(-EXP(-INPUTS!$E$26*(9-INPUTS!$F$26))))-(EXP(-EXP(-INPUTS!$E$26*(8-INPUTS!$F$26)))))/((EXP(-EXP(-INPUTS!$E$26*(12-INPUTS!$F$26))))-(EXP(-EXP(-INPUTS!$E$26*(0-INPUTS!$F$26)))))))
A13: 10 | B13: =(INPUTS!$B$23*(((1/(1+EXP(-INPUTS!$C$23*(10-INPUTS!$D$23))))-(1/(1+EXP(-INPUTS!$C$23*(9-INPUTS!$D$23)))))/((1/(1+EXP(-INPUTS!$C$23*(12-INPUTS!$D$23))))-(1/(1+EXP(-INPUTS!$C$23*(0-INPUTS!$D$23))))))+(1-INPUTS!$B$23)*(((EXP(-EXP(-INPUTS!$E$23*(10-INPUTS!$F$23))))-(EXP(-EXP(-INPUTS!$E$23*(9-INPUTS!$F$23)))))/((EXP(-EXP(-INPUTS!$E$23*(12-INPUTS!$F$23))))-(EXP(-EXP(-INPUTS!$E$23*(0-INPUTS!$F$23))))))) | C13: =(INPUTS!$B$24*(((1/(1+EXP(-INPUTS!$C$24*(10-INPUTS!$D$24))))-(1/(1+EXP(-INPUTS!$C$24*(9-INPUTS!$D$24)))))/((1/(1+EXP(-INPUTS!$C$24*(12-INPUTS!$D$24))))-(1/(1+EXP(-INPUTS!$C$24*(0-INPUTS!$D$24))))))+(1-INPUTS!$B$24)*(((EXP(-EXP(-INPUTS!$E$24*(10-INPUTS!$F$24))))-(EXP(-EXP(-INPUTS!$E$24*(9-INPUTS!$F$24)))))/((EXP(-EXP(-INPUTS!$E$24*(12-INPUTS!$F$24))))-(EXP(-EXP(-INPUTS!$E$24*(0-INPUTS!$F$24))))))) | D13: =(INPUTS!$B$25*(((1/(1+EXP(-INPUTS!$C$25*(10-INPUTS!$D$25))))-(1/(1+EXP(-INPUTS!$C$25*(9-INPUTS!$D$25)))))/((1/(1+EXP(-INPUTS!$C$25*(12-INPUTS!$D$25))))-(1/(1+EXP(-INPUTS!$C$25*(0-INPUTS!$D$25))))))+(1-INPUTS!$B$25)*(((EXP(-EXP(-INPUTS!$E$25*(10-INPUTS!$F$25))))-(EXP(-EXP(-INPUTS!$E$25*(9-INPUTS!$F$25)))))/((EXP(-EXP(-INPUTS!$E$25*(12-INPUTS!$F$25))))-(EXP(-EXP(-INPUTS!$E$25*(0-INPUTS!$F$25))))))) | E13: =(INPUTS!$B$26*(((1/(1+EXP(-INPUTS!$C$26*(10-INPUTS!$D$26))))-(1/(1+EXP(-INPUTS!$C$26*(9-INPUTS!$D$26)))))/((1/(1+EXP(-INPUTS!$C$26*(12-INPUTS!$D$26))))-(1/(1+EXP(-INPUTS!$C$26*(0-INPUTS!$D$26))))))+(1-INPUTS!$B$26)*(((EXP(-EXP(-INPUTS!$E$26*(10-INPUTS!$F$26))))-(EXP(-EXP(-INPUTS!$E$26*(9-INPUTS!$F$26)))))/((EXP(-EXP(-INPUTS!$E$26*(12-INPUTS!$F$26))))-(EXP(-EXP(-INPUTS!$E$26*(0-INPUTS!$F$26)))))))
A14: 11 | B14: =(INPUTS!$B$23*(((1/(1+EXP(-INPUTS!$C$23*(11-INPUTS!$D$23))))-(1/(1+EXP(-INPUTS!$C$23*(10-INPUTS!$D$23)))))/((1/(1+EXP(-INPUTS!$C$23*(12-INPUTS!$D$23))))-(1/(1+EXP(-INPUTS!$C$23*(0-INPUTS!$D$23))))))+(1-INPUTS!$B$23)*(((EXP(-EXP(-INPUTS!$E$23*(11-INPUTS!$F$23))))-(EXP(-EXP(-INPUTS!$E$23*(10-INPUTS!$F$23)))))/((EXP(-EXP(-INPUTS!$E$23*(12-INPUTS!$F$23))))-(EXP(-EXP(-INPUTS!$E$23*(0-INPUTS!$F$23))))))) | C14: =(INPUTS!$B$24*(((1/(1+EXP(-INPUTS!$C$24*(11-INPUTS!$D$24))))-(1/(1+EXP(-INPUTS!$C$24*(10-INPUTS!$D$24)))))/((1/(1+EXP(-INPUTS!$C$24*(12-INPUTS!$D$24))))-(1/(1+EXP(-INPUTS!$C$24*(0-INPUTS!$D$24))))))+(1-INPUTS!$B$24)*(((EXP(-EXP(-INPUTS!$E$24*(11-INPUTS!$F$24))))-(EXP(-EXP(-INPUTS!$E$24*(10-INPUTS!$F$24)))))/((EXP(-EXP(-INPUTS!$E$24*(12-INPUTS!$F$24))))-(EXP(-EXP(-INPUTS!$E$24*(0-INPUTS!$F$24))))))) | D14: =(INPUTS!$B$25*(((1/(1+EXP(-INPUTS!$C$25*(11-INPUTS!$D$25))))-(1/(1+EXP(-INPUTS!$C$25*(10-INPUTS!$D$25)))))/((1/(1+EXP(-INPUTS!$C$25*(12-INPUTS!$D$25))))-(1/(1+EXP(-INPUTS!$C$25*(0-INPUTS!$D$25))))))+(1-INPUTS!$B$25)*(((EXP(-EXP(-INPUTS!$E$25*(11-INPUTS!$F$25))))-(EXP(-EXP(-INPUTS!$E$25*(10-INPUTS!$F$25)))))/((EXP(-EXP(-INPUTS!$E$25*(12-INPUTS!$F$25))))-(EXP(-EXP(-INPUTS!$E$25*(0-INPUTS!$F$25))))))) | E14: =(INPUTS!$B$26*(((1/(1+EXP(-INPUTS!$C$26*(11-INPUTS!$D$26))))-(1/(1+EXP(-INPUTS!$C$26*(10-INPUTS!$D$26)))))/((1/(1+EXP(-INPUTS!$C$26*(12-INPUTS!$D$26))))-(1/(1+EXP(-INPUTS!$C$26*(0-INPUTS!$D$26))))))+(1-INPUTS!$B$26)*(((EXP(-EXP(-INPUTS!$E$26*(11-INPUTS!$F$26))))-(EXP(-EXP(-INPUTS!$E$26*(10-INPUTS!$F$26)))))/((EXP(-EXP(-INPUTS!$E$26*(12-INPUTS!$F$26))))-(EXP(-EXP(-INPUTS!$E$26*(0-INPUTS!$F$26)))))))
A15: 12 | B15: =(INPUTS!$B$23*(((1/(1+EXP(-INPUTS!$C$23*(12-INPUTS!$D$23))))-(1/(1+EXP(-INPUTS!$C$23*(11-INPUTS!$D$23)))))/((1/(1+EXP(-INPUTS!$C$23*(12-INPUTS!$D$23))))-(1/(1+EXP(-INPUTS!$C$23*(0-INPUTS!$D$23))))))+(1-INPUTS!$B$23)*(((EXP(-EXP(-INPUTS!$E$23*(12-INPUTS!$F$23))))-(EXP(-EXP(-INPUTS!$E$23*(11-INPUTS!$F$23)))))/((EXP(-EXP(-INPUTS!$E$23*(12-INPUTS!$F$23))))-(EXP(-EXP(-INPUTS!$E$23*(0-INPUTS!$F$23))))))) | C15: =(INPUTS!$B$24*(((1/(1+EXP(-INPUTS!$C$24*(12-INPUTS!$D$24))))-(1/(1+EXP(-INPUTS!$C$24*(11-INPUTS!$D$24)))))/((1/(1+EXP(-INPUTS!$C$24*(12-INPUTS!$D$24))))-(1/(1+EXP(-INPUTS!$C$24*(0-INPUTS!$D$24))))))+(1-INPUTS!$B$24)*(((EXP(-EXP(-INPUTS!$E$24*(12-INPUTS!$F$24))))-(EXP(-EXP(-INPUTS!$E$24*(11-INPUTS!$F$24)))))/((EXP(-EXP(-INPUTS!$E$24*(12-INPUTS!$F$24))))-(EXP(-EXP(-INPUTS!$E$24*(0-INPUTS!$F$24))))))) | D15: =(INPUTS!$B$25*(((1/(1+EXP(-INPUTS!$C$25*(12-INPUTS!$D$25))))-(1/(1+EXP(-INPUTS!$C$25*(11-INPUTS!$D$25)))))/((1/(1+EXP(-INPUTS!$C$25*(12-INPUTS!$D$25))))-(1/(1+EXP(-INPUTS!$C$25*(0-INPUTS!$D$25))))))+(1-INPUTS!$B$25)*(((EXP(-EXP(-INPUTS!$E$25*(12-INPUTS!$F$25))))-(EXP(-EXP(-INPUTS!$E$25*(11-INPUTS!$F$25)))))/((EXP(-EXP(-INPUTS!$E$25*(12-INPUTS!$F$25))))-(EXP(-EXP(-INPUTS!$E$25*(0-INPUTS!$F$25))))))) | E15: =(INPUTS!$B$26*(((1/(1+EXP(-INPUTS!$C$26*(12-INPUTS!$D$26))))-(1/(1+EXP(-INPUTS!$C$26*(11-INPUTS!$D$26)))))/((1/(1+EXP(-INPUTS!$C$26*(12-INPUTS!$D$26))))-(1/(1+EXP(-INPUTS!$C$26*(0-INPUTS!$D$26))))))+(1-INPUTS!$B$26)*(((EXP(-EXP(-INPUTS!$E$26*(12-INPUTS!$F$26))))-(EXP(-EXP(-INPUTS!$E$26*(11-INPUTS!$F$26)))))/((EXP(-EXP(-INPUTS!$E$26*(12-INPUTS!$F$26))))-(EXP(-EXP(-INPUTS!$E$26*(0-INPUTS!$F$26)))))))
A18: Cumulative | B18: 2026 | C18: 2027 | D18: 2028 | E18: 2029
A19: 1 | B19: =B4 | C19: =C4 | D19: =D4 | E19: =E4
A20: 2 | B20: =B19+B5 | C20: =C19+C5 | D20: =D19+D5 | E20: =E19+E5
A21: 3 | B21: =B20+B6 | C21: =C20+C6 | D21: =D20+D6 | E21: =E20+E6
A22: 4 | B22: =B21+B7 | C22: =C21+C7 | D22: =D21+D7 | E22: =E21+E7
A23: 5 | B23: =B22+B8 | C23: =C22+C8 | D23: =D22+D8 | E23: =E22+E8
A24: 6 | B24: =B23+B9 | C24: =C23+C9 | D24: =D23+D9 | E24: =E23+E9
A25: 7 | B25: =B24+B10 | C25: =C24+C10 | D25: =D24+D10 | E25: =E24+E10
A26: 8 | B26: =B25+B11 | C26: =C25+C11 | D26: =D25+D11 | E26: =E25+E11
A27: 9 | B27: =B26+B12 | C27: =C26+C12 | D27: =D26+D12 | E27: =E26+E12
A28: 10 | B28: =B27+B13 | C28: =C27+C13 | D28: =D27+D13 | E28: =E27+E13
A29: 11 | B29: =B28+B14 | C29: =C28+C14 | D29: =D28+D14 | E29: =E28+E14
A30: 12 | B30: =B29+B15 | C30: =C29+C15 | D30: =D29+D15 | E30: =E29+E15

Sheet CAPEX_MONTHLY
A1: MONTHLY CAPEX CASH FLOW
A3: KPI | B3: Value | C3: Units | D3: Comment
A4: Total CAPEX | B4: =SUM(F13:F60) | C4: EUR | D4: Should match canonical total.
A5: Peak monthly draw | B5: =MAX(F13:F60) | C5: EUR | D5: Peak cash requirement.
A6: Peak month | B6: =INDEX(A13:A60,MATCH(MAX(F13:F60),F13:F60,0)) | D6: Date of peak draw.
A11: Date | B11: Year | C11: Month # | D11: Annual CAPEX | E11: Weight | F11: Monthly CAPEX | G11: Cumulative CAPEX | H11: Cumulative % | I11: Year-to-date CAPEX
A13: 46023 | B13: 2026 | C13: 1 | D13: =INDEX(INPUTS!$B$13:$B$16,MATCH(B13,INPUTS!$A$13:$A$16,0)) | E13: =INDEX(S_CURVE!$B$4:$E$15,C13,MATCH(B13,S_CURVE!$B$3:$E$3,0)) | F13: =D13*E13 | G13: =F13 | H13: =G13/INPUTS!$B$6 | I13: =F13
A14: 46054 | B14: 2026 | C14: 2 | D14: =INDEX(INPUTS!$B$13:$B$16,MATCH(B14,INPUTS!$A$13:$A$16,0)) | E14: =INDEX(S_CURVE!$B$4:$E$15,C14,MATCH(B14,S_CURVE!$B$3:$E$3,0)) | F14: =D14*E14 | G14: =G13+F14 | H14: =G14/INPUTS!$B$6 | I14: =IF(B14=B13,I13+F14,F14)
A15: 46082 | B15: 2026 | C15: 3 | D15: =INDEX(INPUTS!$B$13:$B$16,MATCH(B15,INPUTS!$A$13:$A$16,0)) | E15: =INDEX(S_CURVE!$B$4:$E$15,C15,MATCH(B15,S_CURVE!$B$3:$E$3,0)) | F15: =D15*E15 | G15: =G14+F15 | H15: =G15/INPUTS!$B$6 | I15: =IF(B15=B14,I14+F15,F15)
A16: 46113 | B16: 2026 | C16: 4 | D16: =INDEX(INPUTS!$B$13:$B$16,MATCH(B16,INPUTS!$A$13:$A$16,0)) | E16: =INDEX(S_CURVE!$B$4:$E$15,C16,MATCH(B16,S_CURVE!$B$3:$E$3,0)) | F16: =D16*E16 | G16: =G15+F16 | H16: =G16/INPUTS!$B$6 | I16: =IF(B16=B15,I15+F16,F16)
A17: 46143 | B17: 2026 | C17: 5 | D17: =INDEX(INPUTS!$B$13:$B$16,MATCH(B17,INPUTS!$A$13:$A$16,0)) | E17: =INDEX(S_CURVE!$B$4:$E$15,C17,MATCH(B17,S_CURVE!$B$3:$E$3,0)) | F17: =D17*E17 | G17: =G16+F17 | H17: =G17/INPUTS!$B$6 | I17: =IF(B17=B16,I16+F17,F17)
A18: 46174 | B18: 2026 | C18: 6 | D18: =INDEX(INPUTS!$B$13:$B$16,MATCH(B18,INPUTS!$A$13:$A$16,0)) | E18: =INDEX(S_CURVE!$B$4:$E$15,C18,MATCH(B18,S_CURVE!$B$3:$E$3,0)) | F18: =D18*E18 | G18: =G17+F18 | H18: =G18/INPUTS!$B$6 | I18: =IF(B18=B17,I17+F18,F18)
A19: 46204 | B19: 2026 | C19: 7 | D19: =INDEX(INPUTS!$B$13:$B$16,MATCH(B19,INPUTS!$A$13:$A$16,0)) | E19: =INDEX(S_CURVE!$B$4:$E$15,C19,MATCH(B19,S_CURVE!$B$3:$E$3,0)) | F19: =D19*E19 | G19: =G18+F19 | H19: =G19/INPUTS!$B$6 | I19: =IF(B19=B18,I18+F19,F19)
A20: 46235 | B20: 2026 | C20: 8 | D20: =INDEX(INPUTS!$B$13:$B$16,MATCH(B20,INPUTS!$A$13:$A$16,0)) | E20: =INDEX(S_CURVE!$B$4:$E$15,C20,MATCH(B20,S_CURVE!$B$3:$E$3,0)) | F20: =D20*E20 | G20: =G19+F20 | H20: =G20/INPUTS!$B$6 | I20: =IF(B20=B19,I19+F20,F20)
A21: 46266 | B21: 2026 | C21: 9 | D21: =INDEX(INPUTS!$B$13:$B$16,MATCH(B21,INPUTS!$A$13:$A$16,0)) | E21: =INDEX(S_CURVE!$B$4:$E$15,C21,MATCH(B21,S_CURVE!$B$3:$E$3,0)) | F21: =D21*E21 | G21: =G20+F21 | H21: =G21/INPUTS!$B$6 | I21: =IF(B21=B20,I20+F21,F21)
A22: 46296 | B22: 2026 | C22: 10 | D22: =INDEX(INPUTS!$B$13:$B$16,MATCH(B22,INPUTS!$A$13:$A$16,0)) | E22: =INDEX(S_CURVE!$B$4:$E$15,C22,MATCH(B22,S_CURVE!$B$3:$E$3,0)) | F22: =D22*E22 | G22: =G21+F22 | H22: =G22/INPUTS!$B$6 | I22: =IF(B22=B21,I21+F22,F22)
A23: 46327 | B23: 2026 | C23: 11 | D23: =INDEX(INPUTS!$B$13:$B$16,MATCH(B23,INPUTS!$A$13:$A$16,0)) | E23: =INDEX(S_CURVE!$B$4:$E$15,C23,MATCH(B23,S_CURVE!$B$3:$E$3,0)) | F23: =D23*E23 | G23: =G22+F23 | H23: =G23/INPUTS!$B$6 | I23: =IF(B23=B22,I22+F23,F23)
A24: 46357 | B24: 2026 | C24: 12 | D24: =INDEX(INPUTS!$B$13:$B$16,MATCH(B24,INPUTS!$A$13:$A$16,0)) | E24: =INDEX(S_CURVE!$B$4:$E$15,C24,MATCH(B24,S_CURVE!$B$3:$E$3,0)) | F24: =D24*E24 | G24: =G23+F24 | H24: =G24/INPUTS!$B$6 | I24: =IF(B24=B23,I23+F24,F24)
A25: 46388 | B25: 2027 | C25: 1 | D25: =INDEX(INPUTS!$B$13:$B$16,MATCH(B25,INPUTS!$A$13:$A$16,0)) | E25: =INDEX(S_CURVE!$B$4:$E$15,C25,MATCH(B25,S_CURVE!$B$3:$E$3,0)) | F25: =D25*E25 | G25: =G24+F25 | H25: =G25/INPUTS!$B$6 | I25: =IF(B25=B24,I24+F25,F25)
... A60: 47453 | B60: 2029 | C60: 12 | D60: =INDEX(INPUTS!$B$13:$B$16,MATCH(B60,INPUTS!$A$13:$A$16,0)) | E60: =INDEX(S_CURVE!$B$4:$E$15,C60,MATCH(B60,S_CURVE!$B$3:$E$3,0)) | F60: =D60*E60 | G60: =G59+F60 | H60: =G60/INPUTS!$B$6 | I60: =IF(B60=B59,I59+F60,F60)

Sheet FUNDING_DRAWS
A1: MONTHLY FUNDING DRAW SCHEDULE
A3: Year | B3: CAPEX | C3: Grant | D3: Equity | E3: Debt | F3: IDC
A4: 2026 | B4: =SUM(B13:B24) | C4: =SUM(C13:C24) | D4: =SUM(E13:E24) | E4: =SUM(F13:F24) | F4: =SUM(H13:H24)
A5: 2027 | B5: =SUM(B25:B36) | C5: =SUM(C25:C36) | D5: =SUM(E25:E36) | E5: =SUM(F25:F36) | F5: =SUM(H25:H36)
A6: 2028 | B6: =SUM(B37:B48) | C6: =SUM(C37:C48) | D6: =SUM(E37:E48) | E6: =SUM(F37:F48) | F6: =SUM(H37:H48)
A7: 2029 | B7: =SUM(B49:B60) | C7: =SUM(C49:C60) | D7: =SUM(E49:E60) | E7: =SUM(F49:F60) | F7: =SUM(H49:H60)
A11: Date | B11: Direct CAPEX | C11: Grant Draw | D11: Net CAPEX | E11: Equity Draw | F11: Debt Draw | G11: Opening Debt | H11: IDC | I11: Closing Debt | J11: Cum Grants | K11: Cum Equity | L11: Cum Debt
A13: 46023 | B13: =CAPEX_MONTHLY!F13 | C13: =B13*INPUTS!$G$15 | D13: =B13-C13 | E13: =D13*INPUTS!$G$14/(INPUTS!$G$13+INPUTS!$G$14) | F13: =D13-E13 | G13: 0 | H13: =(G13+F13/2)*INPUTS!$G$17/12 | I13: =G13+F13+H13 | J13: =SUM($C$13:C13) | K13: =SUM($E$13:E13) | L13: =SUM($F$13:F13)
A14: 46054 | B14: =CAPEX_MONTHLY!F14 | C14: =B14*INPUTS!$G$15 | D14: =B14-C14 | E14: =D14*INPUTS!$G$14/(INPUTS!$G$13+INPUTS!$G$14) | F14: =D14-E14 | G14: =I13 | H14: =(G14+F14/2)*INPUTS!$G$17/12 | I14: =G14+F14+H14 | J14: =SUM($C$13:C14) | K14: =SUM($E$13:E14) | L14: =SUM($F$13:F14)
A15: 46082 | B15: =CAPEX_MONTHLY!F15 | C15: =B15*INPUTS!$G$15 | D15: =B15-C15 | E15: =D15*INPUTS!$G$14/(INPUTS!$G$13+INPUTS!$G$14) | F15: =D15-E15 | G15: =I14 | H15: =(G15+F15/2)*INPUTS!$G$17/12 | I15: =G15+F15+H15 | J15: =SUM($C$13:C15) | K15: =SUM($E$13:E15) | L15: =SUM($F$13:F15)
A16: 46113 | B16: =CAPEX_MONTHLY!F16 | C16: =B16*INPUTS!$G$15 | D16: =B16-C16 | E16: =D16*INPUTS!$G$14/(INPUTS!$G$13+INPUTS!$G$14) | F16: =D16-E16 | G16: =I15 | H16: =(G16+F16/2)*INPUTS!$G$17/12 | I16: =G16+F16+H16 | J16: =SUM($C$13:C16) | K16: =SUM($E$13:E16) | L16: =SUM($F$13:F16)
A17: 46143 | B17: =CAPEX_MONTHLY!F17 | C17: =B17*INPUTS!$G$15 | D17: =B17-C17 | E17: =D17*INPUTS!$G$14/(INPUTS!$G$13+INPUTS!$G$14) | F17: =D17-E17 | G17: =I16 | H17: =(G17+F17/2)*INPUTS!$G$17/12 | I17: =G17+F17+H17 | J17: =SUM($C$13:C17) | K17: =SUM($E$13:E17) | L17: =SUM($F$13:F17)
A18: 46174 | B18: =CAPEX_MONTHLY!F18 | C18: =B18*INPUTS!$G$15 | D18: =B18-C18 | E18: =D18*INPUTS!$G$14/(INPUTS!$G$13+INPUTS!$G$14) | F18: =D18-E18 | G18: =I17 | H18: =(G18+F18/2)*INPUTS!$G$17/12 | I18: =G18+F18+H18 | J18: =SUM($C$13:C18) | K18: =SUM($E$13:E18) | L18: =SUM($F$13:F18)
A19: 46204 | B19: =CAPEX_MONTHLY!F19 | C19: =B19*INPUTS!$G$15 | D19: =B19-C19 | E19: =D19*INPUTS!$G$14/(INPUTS!$G$13+INPUTS!$G$14) | F19: =D19-E19 | G19: =I18 | H19: =(G19+F19/2)*INPUTS!$G$17/12 | I19: =G19+F19+H19 | J19: =SUM($C$13:C19) | K19: =SUM($E$13:E19) | L19: =SUM($F$13:F19)
A20: 46235 | B20: =CAPEX_MONTHLY!F20 | C20: =B20*INPUTS!$G$15 | D20: =B20-C20 | E20: =D20*INPUTS!$G$14/(INPUTS!$G$13+INPUTS!$G$14) | F20: =D20-E20 | G20: =I19 | H20: =(G20+F20/2)*INPUTS!$G$17/12 | I20: =G20+F20+H20 | J20: =SUM($C$13:C20) | K20: =SUM($E$13:E20) | L20: =SUM($F$13:F20)
A21: 46266 | B21: =CAPEX_MONTHLY!F21 | C21: =B21*INPUTS!$G$15 | D21: =B21-C21 | E21: =D21*INPUTS!$G$14/(INPUTS!$G$13+INPUTS!$G$14) | F21: =D21-E21 | G21: =I20 | H21: =(G21+F21/2)*INPUTS!$G$17/12 | I21: =G21+F21+H21 | J21: =SUM($C$13:C21) | K21: =SUM($E$13:E21) | L21: =SUM($F$13:F21)
A22: 46296 | B22: =CAPEX_MONTHLY!F22 | C22: =B22*INPUTS!$G$15 | D22: =B22-C22 | E22: =D22*INPUTS!$G$14/(INPUTS!$G$13+INPUTS!$G$14) | F22: =D22-E22 | G22: =I21 | H22: =(G22+F22/2)*INPUTS!$G$17/12 | I22: =G22+F22+H22 | J22: =SUM($C$13:C22) | K22: =SUM($E$13:E22) | L22: =SUM($F$13:F22)
A23: 46327 | B23: =CAPEX_MONTHLY!F23 | C23: =B23*INPUTS!$G$15 | D23: =B23-C23 | E23: =D23*INPUTS!$G$14/(INPUTS!$G$13+INPUTS!$G$14) | F23: =D23-E23 | G23: =I22 | H23: =(G23+F23/2)*INPUTS!$G$17/12 | I23: =G23+F23+H23 | J23: =SUM($C$13:C23) | K23: =SUM($E$13:E23) | L23: =SUM($F$13:F23)
A24: 46357 | B24: =CAPEX_MONTHLY!F24 | C24: =B24*INPUTS!$G$15 | D24: =B24-C24 | E24: =D24*INPUTS!$G$14/(INPUTS!$G$13+INPUTS!$G$14) | F24: =D24-E24 | G24: =I23 | H24: =(G24+F24/2)*INPUTS!$G$17/12 | I24: =G24+F24+H24 | J24: =SUM($C$13:C24) | K24: =SUM($E$13:E24) | L24: =SUM($F$13:F24)
A25: 46388 | B25: =CAPEX_MONTHLY!F25 | C25: =B25*INPUTS!$G$15 | D25: =B25-C25 | E25: =D25*INPUTS!$G$14/(INPUTS!$G$13+INPUTS!$G$14) | F25: =D25-E25 | G25: =I24 | H25: =(G25+F25/2)*INPUTS!$G$17/12 | I25: =G25+F25+H25 | J25: =SUM($C$13:C25) | K25: =SUM($E$13:E25) | L25: =SUM($F$13:F25)
... A60: 47453 | B60: =CAPEX_MONTHLY!F60 | C60: =B60*INPUTS!$G$15 | D60: =B60-C60 | E60: =D60*INPUTS!$G$14/(INPUTS!$G$13+INPUTS!$G$14) | F60: =D60-E60 | G60: =I59 | H60: =(G60+F60/2)*INPUTS!$G$17/12 | I60: =G60+F60+H60 | J60: =SUM($C$13:C60) | K60: =SUM($E$13:E60) | L60: =SUM($F$13:F60)
A61: TOTAL | B61: =SUM(B13:B60) | C61: =SUM(C13:C60) | D61: =SUM(D13:D60) | E61: =SUM(E13:E60) | F61: =SUM(F13:F60) | G61: =SUM(G13:G60) | H61: =SUM(H13:H60)

Sheet DSCR_SCHEDULE
A1: DSCR-READY DEBT SCHEDULE
A3: Debt metric | B3: Value | C3: Units | D3: Comment
A4: First repayment year | B4: =INPUTS!$B$9 | C4: Year | D4: Linked.
A5: Repayment tenor | B5: =INPUTS!$G$18 | C5: Years | D5: Linked.
A6: Annual rate | B6: =INPUTS!$G$17 | C6: % | D6: Linked.
A7: Minimum DSCR | B7: =INPUTS!$G$19 | C7: x | D7: Linked.
A8: Opening debt at repayment start | B8: =H13 | C8: EUR | D8: Derived.
A9: Year | B9: =IF(B6=0,B8/B5,B8*B6/(1-(1+B6)^(-B5))) | C9: Debt Draw | D9: IDC | E9: Interest | F9: Debt Service | G9: Principal | H9: Closing Debt | I9: CFADS | J9: DSCR | K9: Covenant | L9: Comment
A10: 2026 | B10: 0 | C10: =FUNDING_DRAWS!E4 | D10: =FUNDING_DRAWS!F4 | E10: 0 | F10: 0 | G10: 0 | H10: =B10+C10+D10 | I10: 0 | L10: Construction period / debt capitalization.
A11: 2027 | B11: =H10 | C11: =FUNDING_DRAWS!E5 | D11: =FUNDING_DRAWS!F5 | E11: 0 | F11: 0 | G11: 0 | H11: =B11+C11+D11 | I11: 0 | L11: Construction period / debt capitalization.
A12: 2028 | B12: =H11 | C12: =FUNDING_DRAWS!E6 | D12: =FUNDING_DRAWS!F6 | E12: 0 | F12: 0 | G12: 0 | H12: =B12+C12+D12 | I12: 0 | L12: Construction period / debt capitalization.
A13: 2029 | B13: =H12 | C13: =FUNDING_DRAWS!E7 | D13: =FUNDING_DRAWS!F7 | E13: 0 | F13: 0 | G13: 0 | H13: =B13+C13+D13 | I13: 0 | L13: Construction period / debt capitalization.
A14: 2030 | B14: =H13 | C14: 0 | D14: 0 | E14: =B14*$B$6 | F14: =IF(AND(A14>=$B$4,A14<$B$4+$B$5),MIN($B$9,B14+E14),0) | G14: =F14-E14 | H14: =MAX(0,B14-G14) | I14: =INPUTS!$I$23 | J14: =IF(F14>0,I14/F14,"") | K14: =IF(J14="","",IF(J14>=INPUTS!$G$19,"OK","BREACH")) | L14: Operating period / annuity debt service.
A15: 2031 | B15: =H14 | C15: 0 | D15: 0 | E15: =B15*$B$6 | F15: =IF(AND(A15>=$B$4,A15<$B$4+$B$5),MIN($B$9,B15+E15),0) | G15: =F15-E15 | H15: =MAX(0,B15-G15) | I15: =INPUTS!$I$24 | J15: =IF(F15>0,I15/F15,"") | K15: =IF(J15="","",IF(J15>=INPUTS!$G$19,"OK","BREACH")) | L15: Operating period / annuity debt service.
A16: 2032 | B16: =H15 | C16: 0 | D16: 0 | E16: =B16*$B$6 | F16: =IF(AND(A16>=$B$4,A16<$B$4+$B$5),MIN($B$9,B16+E16),0) | G16: =F16-E16 | H16: =MAX(0,B16-G16) | I16: =INPUTS!$I$25 | J16: =IF(F16>0,I16/F16,"") | K16: =IF(J16="","",IF(J16>=INPUTS!$G$19,"OK","BREACH")) | L16: Operating period / annuity debt service.
A17: 2033 | B17: =H16 | C17: 0 | D17: 0 | E17: =B17*$B$6 | F17: =IF(AND(A17>=$B$4,A17<$B$4+$B$5),MIN($B$9,B17+E17),0) | G17: =F17-E17 | H17: =MAX(0,B17-G17) | I17: =INPUTS!$I$26 | J17: =IF(F17>0,I17/F17,"") | K17: =IF(J17="","",IF(J17>=INPUTS!$G$19,"OK","BREACH")) | L17: Operating period / annuity debt service.
A18: 2034 | B18: =H17 | C18: 0 | D18: 0 | E18: =B18*$B$6 | F18: =IF(AND(A18>=$B$4,A18<$B$4+$B$5),MIN($B$9,B18+E18),0) | G18: =F18-E18 | H18: =MAX(0,B18-G18) | I18: =INPUTS!$I$27 | J18: =IF(F18>0,I18/F18,"") | K18: =IF(J18="","",IF(J18>=INPUTS!$G$19,"OK","BREACH")) | L18: Operating period / annuity debt service.
A19: 2035 | B19: =H18 | C19: 0 | D19: 0 | E19: =B19*$B$6 | F19: =IF(AND(A19>=$B$4,A19<$B$4+$B$5),MIN($B$9,B19+E19),0) | G19: =F19-E19 | H19: =MAX(0,B19-G19) | I19: =INPUTS!$I$28 | J19: =IF(F19>0,I19/F19,"") | K19: =IF(J19="","",IF(J19>=INPUTS!$G$19,"OK","BREACH")) | L19: Operating period / annuity debt service.
A20: 2036 | B20: =H19 | C20: 0 | D20: 0 | E20: =B20*$B$6 | F20: =IF(AND(A20>=$B$4,A20<$B$4+$B$5),MIN($B$9,B20+E20),0) | G20: =F20-E20 | H20: =MAX(0,B20-G20) | I20: =INPUTS!$I$29 | J20: =IF(F20>0,I20/F20,"") | K20: =IF(J20="","",IF(J20>=INPUTS!$G$19,"OK","BREACH")) | L20: Operating period / annuity debt service.
A21: 2037 | B21: =H20 | C21: 0 | D21: 0 | E21: =B21*$B$6 | F21: =IF(AND(A21>=$B$4,A21<$B$4+$B$5),MIN($B$9,B21+E21),0) | G21: =F21-E21 | H21: =MAX(0,B21-G21) | I21: =INPUTS!$I$30 | J21: =IF(F21>0,I21/F21,"") | K21: =IF(J21="","",IF(J21>=INPUTS!$G$19,"OK","BREACH")) | L21: Operating period / annuity debt service.

Sheet MC_SEEDS
A1: Trial | B1: Delay Months | C1: Materials Shock | D1: Lead Event | E1: Commissioning Event
A2: 1 | B2: 3.84 | C2: 0 | D2: 0.06 | E2: 0.04
A3: 2 | B3: 4.42 | C3: 0.053754676 | D3: 0 | E3: 0.04
A4: 3 | B4: 2.53 | C4: 0 | D4: 0.06 | E4: 0
A5: 4 | B5: 0.16 | C5: 0.01462659 | D5: 0 | E5: 0
A6: 5 | B6: 1.32 | C6: 0.046769694 | D6: 0 | E6: 0.04
A7: 6 | B7: 4.83 | C7: 0.055571701 | D7: 0 | E7: 0.04
A8: 7 | B8: 5.74 | C8: 0.027346743 | D8: 0.06 | E8: 0.04
A9: 8 | B9: 5.08 | C9: 0.047890103 | D9: 0 | E9: 0
A10: 9 | B10: 3.22 | C10: 0.097860914 | D10: 0 | E10: 0
A11: 10 | B11: 4.98 | C11: 0.049047863 | D11: 0 | E11: 0
A12: 11 | B12: 4.23 | C12: 0 | D12: 0.06 | E12: 0
A13: 12 | B13: 0.48 | C13: 0.018109402 | D13: 0.06 | E13: 0
... A501: 500 | B501: 3.59 | C501: 0.05340746 | D501: 0 | E501: 0

Sheet MONTE_CARLO
A1: MONTE CARLO CONTINGENCY SIMULATOR
A3: Metric | B3: Value | C3: Units | D3: Comment
A4: Base total CAPEX | B4: =INPUTS!$B$6 | C4: EUR | D4: Canonical total.
A5: Base contingency reserve | B5: =INPUTS!$B$7 | C5: EUR | D5: Embedded in baseline.
A6: Expected additional overrun | B6: =AVERAGE(H13:H512) | C6: EUR | D6: Mean overrun above baseline.
A7: P50 total CAPEX | B7: =PERCENTILE.INC(G13:G512,0.5) | C7: EUR | D7: Median simulated total.
A8: P75 total CAPEX | B8: =PERCENTILE.INC(G13:G512,0.75) | C8: EUR | D8: Upside stress.
A9: P90 total CAPEX | B9: =PERCENTILE.INC(G13:G512,0.9) | C9: EUR | D9: Conservative stress.
A10: Probability reserve exhausted | B10: =COUNTIF(I13:I512,">0")/INPUTS!$G$33 | C10: % | D10: Residual funding gap > 0.
A11: Trial | B11: Delay Months | C11: Materials Shock | D11: Lead Event | E11: Commissioning Event | F11: Overrun % | G11: Total CAPEX | H11: Additional Overrun | I11: Residual Funding Gap | K11: Bin | L11: Count
K12: 0 | L12: =COUNTIFS($F$13:$F$512,">="&K12,$F$13:$F$512,"<"&K13)
A13: =MC_SEEDS!A2 | B13: =MC_SEEDS!B2 | C13: =MC_SEEDS!C2 | D13: =MC_SEEDS!D2 | E13: =MC_SEEDS!E2 | F13: =B13*INPUTS!$G$35*INPUTS!$G$42 + C13*INPUTS!$G$42 + D13*INPUTS!$G$43 + E13*INPUTS!$G$44 | G13: =INPUTS!$B$6*(1+F13) | H13: =G13-INPUTS!$B$6 | I13: =MAX(0,H13-INPUTS!$B$7) | K13: 0.02 | L13: =COUNTIFS($F$13:$F$512,">="&K13,$F$13:$F$512,"<"&K14)
A14: =MC_SEEDS!A3 | B14: =MC_SEEDS!B3 | C14: =MC_SEEDS!C3 | D14: =MC_SEEDS!D3 | E14: =MC_SEEDS!E3 | F14: =B14*INPUTS!$G$35*INPUTS!$G$42 + C14*INPUTS!$G$42 + D14*INPUTS!$G$43 + E14*INPUTS!$G$44 | G14: =INPUTS!$B$6*(1+F14) | H14: =G14-INPUTS!$B$6 | I14: =MAX(0,H14-INPUTS!$B$7) | K14: 0.04 | L14: =COUNTIFS($F$13:$F$512,">="&K14,$F$13:$F$512,"<"&K15)
A15: =MC_SEEDS!A4 | B15: =MC_SEEDS!B4 | C15: =MC_SEEDS!C4 | D15: =MC_SEEDS!D4 | E15: =MC_SEEDS!E4 | F15: =B15*INPUTS!$G$35*INPUTS!$G$42 + C15*INPUTS!$G$42 + D15*INPUTS!$G$43 + E15*INPUTS!$G$44 | G15: =INPUTS!$B$6*(1+F15) | H15: =G15-INPUTS!$B$6 | I15: =MAX(0,H15-INPUTS!$B$7) | K15: 0.06 | L15: =COUNTIFS($F$13:$F$512,">="&K15,$F$13:$F$512,"<"&K16)
A16: =MC_SEEDS!A5 | B16: =MC_SEEDS!B5 | C16: =MC_SEEDS!C5 | D16: =MC_SEEDS!D5 | E16: =MC_SEEDS!E5 | F16: =B16*INPUTS!$G$35*INPUTS!$G$42 + C16*INPUTS!$G$42 + D16*INPUTS!$G$43 + E16*INPUTS!$G$44 | G16: =INPUTS!$B$6*(1+F16) | H16: =G16-INPUTS!$B$6 | I16: =MAX(0,H16-INPUTS!$B$7) | K16: 0.08 | L16: =COUNTIFS($F$13:$F$512,">="&K16,$F$13:$F$512,"<"&K17)
A17: =MC_SEEDS!A6 | B17: =MC_SEEDS!B6 | C17: =MC_SEEDS!C6 | D17: =MC_SEEDS!D6 | E17: =MC_SEEDS!E6 | F17: =B17*INPUTS!$G$35*INPUTS!$G$42 + C17*INPUTS!$G$42 + D17*INPUTS!$G$43 + E17*INPUTS!$G$44 | G17: =INPUTS!$B$6*(1+F17) | H17: =G17-INPUTS!$B$6 | I17: =MAX(0,H17-INPUTS!$B$7) | K17: 0.1 | L17: =COUNTIFS($F$13:$F$512,">="&K17,$F$13:$F$512,"<"&K18)
A18: =MC_SEEDS!A7 | B18: =MC_SEEDS!B7 | C18: =MC_SEEDS!C7 | D18: =MC_SEEDS!D7 | E18: =MC_SEEDS!E7 | F18: =B18*INPUTS!$G$35*INPUTS!$G$42 + C18*INPUTS!$G$42 + D18*INPUTS!$G$43 + E18*INPUTS!$G$44 | G18: =INPUTS!$B$6*(1+F18) | H18: =G18-INPUTS!$B$6 | I18: =MAX(0,H18-INPUTS!$B$7) | K18: 0.12 | L18: =COUNTIF($F$13:$F$512,">="&K18)
A19: =MC_SEEDS!A8 | B19: =MC_SEEDS!B8 | C19: =MC_SEEDS!C8 | D19: =MC_SEEDS!D8 | E19: =MC_SEEDS!E8 | F19: =B19*INPUTS!$G$35*INPUTS!$G$42 + C19*INPUTS!$G$42 + D19*INPUTS!$G$43 + E19*INPUTS!$G$44 | G19: =INPUTS!$B$6*(1+F19) | H19: =G19-INPUTS!$B$6 | I19: =MAX(0,H19-INPUTS!$B$7)
A20: =MC_SEEDS!A9 | B20: =MC_SEEDS!B9 | C20: =MC_SEEDS!C9 | D20: =MC_SEEDS!D9 | E20: =MC_SEEDS!E9 | F20: =B20*INPUTS!$G$35*INPUTS!$G$42 + C20*INPUTS!$G$42 + D20*INPUTS!$G$43 + E20*INPUTS!$G$44 | G20: =INPUTS!$B$6*(1+F20) | H20: =G20-INPUTS!$B$6 | I20: =MAX(0,H20-INPUTS!$B$7)
A21: =MC_SEEDS!A10 | B21: =MC_SEEDS!B10 | C21: =MC_SEEDS!C10 | D21: =MC_SEEDS!D10 | E21: =MC_SEEDS!E10 | F21: =B21*INPUTS!$G$35*INPUTS!$G$42 + C21*INPUTS!$G$42 + D21*INPUTS!$G$43 + E21*INPUTS!$G$44 | G21: =INPUTS!$B$6*(1+F21) | H21: =G21-INPUTS!$B$6 | I21: =MAX(0,H21-INPUTS!$B$7)
A22: =MC_SEEDS!A11 | B22: =MC_SEEDS!B11 | C22: =MC_SEEDS!C11 | D22: =MC_SEEDS!D11 | E22: =MC_SEEDS!E11 | F22: =B22*INPUTS!$G$35*INPUTS!$G$42 + C22*INPUTS!$G$42 + D22*INPUTS!$G$43 + E22*INPUTS!$G$44 | G22: =INPUTS!$B$6*(1+F22) | H22: =G22-INPUTS!$B$6 | I22: =MAX(0,H22-INPUTS!$B$7)
A23: =MC_SEEDS!A12 | B23: =MC_SEEDS!B12 | C23: =MC_SEEDS!C12 | D23: =MC_SEEDS!D12 | E23: =MC_SEEDS!E12 | F23: =B23*INPUTS!$G$35*INPUTS!$G$42 + C23*INPUTS!$G$42 + D23*INPUTS!$G$43 + E23*INPUTS!$G$44 | G23: =INPUTS!$B$6*(1+F23) | H23: =G23-INPUTS!$B$6 | I23: =MAX(0,H23-INPUTS!$B$7)
A24: =MC_SEEDS!A13 | B24: =MC_SEEDS!B13 | C24: =MC_SEEDS!C13 | D24: =MC_SEEDS!D13 | E24: =MC_SEEDS!E13 | F24: =B24*INPUTS!$G$35*INPUTS!$G$42 + C24*INPUTS!$G$42 + D24*INPUTS!$G$43 + E24*INPUTS!$G$44 | G24: =INPUTS!$B$6*(1+F24) | H24: =G24-INPUTS!$B$6 | I24: =MAX(0,H24-INPUTS!$B$7)
A25: =MC_SEEDS!A14 | B25: =MC_SEEDS!B14 | C25: =MC_SEEDS!C14 | D25: =MC_SEEDS!D14 | E25: =MC_SEEDS!E14 | F25: =B25*INPUTS!$G$35*INPUTS!$G$42 + C25*INPUTS!$G$42 + D25*INPUTS!$G$43 + E25*INPUTS!$G$44 | G25: =INPUTS!$B$6*(1+F25) | H25: =G25-INPUTS!$B$6 | I25: =MAX(0,H25-INPUTS!$B$7)
A26: =MC_SEEDS!A15 | B26: =MC_SEEDS!B15 | C26: =MC_SEEDS!C15 | D26: =MC_SEEDS!D15 | E26: =MC_SEEDS!E15 | F26: =B26*INPUTS!$G$35*INPUTS!$G$42 + C26*INPUTS!$G$42 + D26*INPUTS!$G$43 + E26*INPUTS!$G$44 | G26: =INPUTS!$B$6*(1+F26) | H26: =G26-INPUTS!$B$6 | I26: =MAX(0,H26-INPUTS!$B$7)
A27: =MC_SEEDS!A16 | B27: =MC_SEEDS!B16 | C27: =MC_SEEDS!C16 | D27: =MC_SEEDS!D16 | E27: =MC_SEEDS!E16 | F27: =B27*INPUTS!$G$35*INPUTS!$G$42 + C27*INPUTS!$G$42 + D27*INPUTS!$G$43 + E27*INPUTS!$G$44 | G27: =INPUTS!$B$6*(1+F27) | H27: =G27-INPUTS!$B$6 | I27: =MAX(0,H27-INPUTS!$B$7)
A28: =MC_SEEDS!A17 | B28: =MC_SEEDS!B17 | C28: =MC_SEEDS!C17 | D28: =MC_SEEDS!D17 | E28: =MC_SEEDS!E17 | F28: =B28*INPUTS!$G$35*INPUTS!$G$42 + C28*INPUTS!$G$42 + D28*INPUTS!$G$43 + E28*INPUTS!$G$44 | G28: =INPUTS!$B$6*(1+F28) | H28: =G28-INPUTS!$B$6 | I28: =MAX(0,H28-INPUTS!$B$7)
A29: =MC_SEEDS!A18 | B29: =MC_SEEDS!B18 | C29: =MC_SEEDS!C18 | D29: =MC_SEEDS!D18 | E29: =MC_SEEDS!E18 | F29: =B29*INPUTS!$G$35*INPUTS!$G$42 + C29*INPUTS!$G$42 + D29*INPUTS!$G$43 + E29*INPUTS!$G$44 | G29: =INPUTS!$B$6*(1+F29) | H29: =G29-INPUTS!$B$6 | I29: =MAX(0,H29-INPUTS!$B$7)
A30: =MC_SEEDS!A19 | B30: =MC_SEEDS!B19 | C30: =MC_SEEDS!C19 | D30: =MC_SEEDS!D19 | E30: =MC_SEEDS!E19 | F30: =B30*INPUTS!$G$35*INPUTS!$G$42 + C30*INPUTS!$G$42 + D30*INPUTS!$G$43 + E30*INPUTS!$G$44 | G30: =INPUTS!$B$6*(1+F30) | H30: =G30-INPUTS!$B$6 | I30: =MAX(0,H30-INPUTS!$B$7)
... A512: =MC_SEEDS!A501 | B512: =MC_SEEDS!B501 | C512: =MC_SEEDS!C501 | D512: =MC_SEEDS!D501 | E512: =MC_SEEDS!E501 | F512: =B512*INPUTS!$G$35*INPUTS!$G$42 + C512*INPUTS!$G$42 + D512*INPUTS!$G$43 + E512*INPUTS!$G$44 | G512: =INPUTS!$B$6*(1+F512) | H512: =G512-INPUTS!$B$6 | I512: =MAX(0,H512-INPUTS!$B$7)

Sheet DASHBOARD
A1: CAPEX CONTROL TOWER DASHBOARD
A3: Base CAPEX | D3: Peak monthly draw | G3: Debt facility | J3: Equity commitment
A4: =INPUTS!$B$6 | D4: =CAPEX_MONTHLY!$B$5 | G4: =SUM(FUNDING_DRAWS!E4:E7) | J4: =SUM(FUNDING_DRAWS!D4:D7)
A6: Grants | D6: COD debt balance | G6: Minimum DSCR | J6: P90 CAPEX
A7: =SUM(FUNDING_DRAWS!C4:C7) | D7: =INDEX(DSCR_SCHEDULE!H10:H21,MATCH(INPUTS!$B$9-1,DSCR_SCHEDULE!A10:A21,0)) | G7: =MIN(DSCR_SCHEDULE!J14:J21) | J7: =MONTE_CARLO!B9
A9: Reserve exhaustion prob.
A10: =MONTE_CARLO!B10
A12: This dashboard is formula-linked to the canonical memory sheets. Debt/Equity/Grant, S-curve timing and DSCR placeholders can be adjusted centrally in INPUTS.
