Workbook

Sheet Navigation_Index
A1: BANK-GRADE FINANCIAL MODEL TEMPLATE
A3: Sheet | B3: Purpose
A4: Inputs | B4: Core user inputs only
A5: Drivers_Assumptions | B5: Operational and macro drivers
A6: CAPEX_Master | B6: CAPEX phasing and totals
A7: OPEX_Master | B7: Operating cost build-up
A8: Revenue_Schedule | B8: Volume x price revenue model
A9: Debt_Schedule | B9: Debt drawdown, interest, repayment, DSCR debt service
A10: Equity_Grant_Schedule | B10: Funding sources timing
A11: Cash_Flow | B11: Unlevered and levered cash flow
A12: EBITDA_PnL | B12: P&L bridge and EBITDA
A13: Balance_Sheet | B13: Simplified balance sheet
A14: KPIs_Metrics | B14: Headline KPIs and dashboard
A15: Checks_Audit | B15: Error checks and integrity controls

Sheet Inputs
A1: Category | B1: Parameter | C1: Value | D1: Unit | E1: Type | F1: Source | G1: Frequency | H1: Notes | N1: Back to Index
A2: General | B2: Start Year | C2: 2026 | D2: year | E2: Input | F2: Management | G2: Once | H2: Base year
A3: General | B3: Tax Rate | C3: 0.09 | D3: % | E3: Input | F3: Management | G3: Annual | H3: Corporate tax
A4: General | B4: Discount Rate / WACC | C4: 0.12 | D4: % | E4: Input | F4: Management | G4: Annual | H4: For NPV
A5: Revenue | B5: Base Volume Y1 | C5: 1000 | D5: units | E5: Input | F5: Commercial | G5: Annual | H5: Starting volume
A6: Revenue | B6: Base Price Y1 | C6: 1500 | D6: EUR/unit | E6: Input | F6: Commercial | G6: Annual | H6: Average sales price
A7: Costs | B7: Base OPEX Y1 | C7: 900000 | D7: EUR | E7: Input | F7: Operations | G7: Annual | H7: Base operating cost
A8: CAPEX | B8: Total CAPEX Budget | C8: 5000000 | D8: EUR | E8: Input | F8: Engineering | G8: Once | H8: Total development cost
A9: Financing | B9: Debt Share | C9: 0.6 | D9: % | E9: Input | F9: Finance | G9: Once | H9: Senior debt share
A10: Financing | B10: Grant Share | C10: 0.1 | D10: % | E10: Input | F10: Finance | G10: Once | H10: Grant share of uses
A11: Financing | B11: Interest Rate | C11: 0.065 | D11: % | E11: Input | F11: Finance | G11: Annual | H11: Senior debt cost
A12: Financing | B12: Debt Tenor | C12: 8 | D12: years | E12: Input | F12: Finance | G12: Once | H12: Amortisation tenor
A13: Financing | B13: Grace Period | C13: 2 | D13: years | E13: Input | F13: Finance | G13: Once | H13: Construction/grace

Sheet Drivers_Assumptions
A1: Driver | B1: Y1 | C1: Y2 | D1: Y3 | E1: Y4 | F1: Y5 | G1: Y6 | H1: Y7 | I1: Y8 | J1: Y9 | K1: Y10 | L1: Unit | M1: Notes | N1: Back to Index
A2: Revenue growth | B2: 0 | C2: 0.05 | D2: 0.05 | E2: 0.04 | F2: 0.04 | G2: 0.03 | H2: 0.03 | I2: 0.03 | J2: 0.03 | K2: 0.03 | L2: % | M2: Price escalation
A3: Volume growth | B3: 0 | C3: 0.2 | D3: 0.15 | E3: 0.1 | F3: 0.05 | G3: 0.03 | H3: 0.03 | I3: 0.02 | J3: 0.02 | K3: 0.02 | L3: % | M3: Ramp-up
A4: OPEX growth | B4: 0 | C4: 0.04 | D4: 0.04 | E4: 0.03 | F4: 0.03 | G4: 0.03 | H4: 0.03 | I4: 0.03 | J4: 0.03 | K4: 0.03 | L4: % | M4: Inflation
A5: Maintenance capex | B5: 0.01 | C5: 0.01 | D5: 0.01 | E5: 0.01 | F5: 0.01 | G5: 0.01 | H5: 0.01 | I5: 0.01 | J5: 0.01 | K5: 0.01 | L5: % of sales | M5: Recurring reinvestment
A6: Working capital | B6: 0.08 | C6: 0.08 | D6: 0.08 | E6: 0.08 | F6: 0.08 | G6: 0.08 | H6: 0.08 | I6: 0.08 | J6: 0.08 | K6: 0.08 | L6: % of revenue | M6: Net WC as % sales

Sheet CAPEX_Master
A1: CAPEX Item | B1: Y1 | C1: Y2 | D1: Y3 | E1: Y4 | F1: Y5 | G1: Y6 | H1: Y7 | I1: Y8 | J1: Y9 | K1: Y10 | L1: Total | N1: Back to Index
A2: Land | B2: 500000 | C2: 0 | D2: 0 | E2: 0 | F2: 0 | G2: 0 | H2: 0 | I2: 0 | J2: 0 | K2: 0 | L2: =SUM(B2:K2)
A3: Building | B3: 1000000 | C3: 1200000 | D3: 800000 | E3: 0 | F3: 0 | G3: 0 | H3: 0 | I3: 0 | J3: 0 | K3: 0 | L3: =SUM(B3:K3)
A4: Machinery | B4: 600000 | C4: 900000 | D4: 700000 | E4: 300000 | F4: 0 | G4: 0 | H4: 0 | I4: 0 | J4: 0 | K4: 0 | L4: =SUM(B4:K4)
A5: Engineering | B5: 200000 | C5: 150000 | D5: 50000 | E5: 0 | F5: 0 | G5: 0 | H5: 0 | I5: 0 | J5: 0 | K5: 0 | L5: =SUM(B5:K5)
A6: Contingency | B6: 230000 | C6: 225000 | D6: 155000 | E6: 30000 | F6: 0 | G6: 0 | H6: 0 | I6: 0 | J6: 0 | K6: 0 | L6: =SUM(B6:K6)
A7: Total CAPEX | B7: =SUM(B2:B6) | C7: =SUM(C2:C6) | D7: =SUM(D2:D6) | E7: =SUM(E2:E6) | F7: =SUM(F2:F6) | G7: =SUM(G2:G6) | H7: =SUM(H2:H6) | I7: =SUM(I2:I6) | ... L7: =SUM(L2:L6)

Sheet OPEX_Master
A1: OPEX Item | B1: Y1 | C1: Y2 | D1: Y3 | E1: Y4 | F1: Y5 | G1: Y6 | H1: Y7 | I1: Y8 | J1: Y9 | K1: Y10 | L1: Total | N1: Back to Index
A2: Payroll | B2: =280000 | C2: =B2*(1+Drivers_Assumptions!C$4) | D2: =C2*(1+Drivers_Assumptions!D$4) | E2: =D2*(1+Drivers_Assumptions!E$4) | F2: =E2*(1+Drivers_Assumptions!F$4) | G2: =F2*(1+Drivers_Assumptions!G$4) | H2: =G2*(1+Drivers_Assumptions!H$4) | I2: =H2*(1+Drivers_Assumptions!I$4) | J2: =I2*(1+Drivers_Assumptions!J$4) | K2: =J2*(1+Drivers_Assumptions!K$4) | L2: =SUM(B2:K2)
A3: Utilities | B3: =180000 | C3: =B3*(1+Drivers_Assumptions!C$4) | D3: =C3*(1+Drivers_Assumptions!D$4) | E3: =D3*(1+Drivers_Assumptions!E$4) | F3: =E3*(1+Drivers_Assumptions!F$4) | G3: =F3*(1+Drivers_Assumptions!G$4) | H3: =G3*(1+Drivers_Assumptions!H$4) | I3: =H3*(1+Drivers_Assumptions!I$4) | J3: =I3*(1+Drivers_Assumptions!J$4) | K3: =J3*(1+Drivers_Assumptions!K$4) | L3: =SUM(B3:K3)
A4: Maintenance | B4: =90000 | C4: =B4*(1+Drivers_Assumptions!C$4) | D4: =C4*(1+Drivers_Assumptions!D$4) | E4: =D4*(1+Drivers_Assumptions!E$4) | F4: =E4*(1+Drivers_Assumptions!F$4) | G4: =F4*(1+Drivers_Assumptions!G$4) | H4: =G4*(1+Drivers_Assumptions!H$4) | I4: =H4*(1+Drivers_Assumptions!I$4) | J4: =I4*(1+Drivers_Assumptions!J$4) | K4: =J4*(1+Drivers_Assumptions!K$4) | L4: =SUM(B4:K4)
A5: SG&A | B5: =120000 | C5: =B5*(1+Drivers_Assumptions!C$4) | D5: =C5*(1+Drivers_Assumptions!D$4) | E5: =D5*(1+Drivers_Assumptions!E$4) | F5: =E5*(1+Drivers_Assumptions!F$4) | G5: =F5*(1+Drivers_Assumptions!G$4) | H5: =G5*(1+Drivers_Assumptions!H$4) | I5: =H5*(1+Drivers_Assumptions!I$4) | J5: =I5*(1+Drivers_Assumptions!J$4) | K5: =J5*(1+Drivers_Assumptions!K$4) | L5: =SUM(B5:K5)
A6: Insurance | B6: =40000 | C6: =B6*(1+Drivers_Assumptions!C$4) | D6: =C6*(1+Drivers_Assumptions!D$4) | E6: =D6*(1+Drivers_Assumptions!E$4) | F6: =E6*(1+Drivers_Assumptions!F$4) | G6: =F6*(1+Drivers_Assumptions!G$4) | H6: =G6*(1+Drivers_Assumptions!H$4) | I6: =H6*(1+Drivers_Assumptions!I$4) | J6: =I6*(1+Drivers_Assumptions!J$4) | K6: =J6*(1+Drivers_Assumptions!K$4) | L6: =SUM(B6:K6)
A7: Total OPEX | B7: =SUM(B2:B6) | C7: =SUM(C2:C6) | D7: =SUM(D2:D6) | E7: =SUM(E2:E6) | F7: =SUM(F2:F6) | G7: =SUM(G2:G6) | H7: =SUM(H2:H6) | I7: =SUM(I2:I6) | ... L7: =SUM(L2:L6)

Sheet Revenue_Schedule
A1: Metric | B1: Y1 | C1: Y2 | D1: Y3 | E1: Y4 | F1: Y5 | G1: Y6 | H1: Y7 | I1: Y8 | J1: Y9 | K1: Y10 | L1: Total | N1: Back to Index
A2: Volume | B2: =Inputs!$C$5 | C2: =B2*(1+Drivers_Assumptions!C$3) | D2: =C2*(1+Drivers_Assumptions!D$3) | E2: =D2*(1+Drivers_Assumptions!E$3) | F2: =E2*(1+Drivers_Assumptions!F$3) | G2: =F2*(1+Drivers_Assumptions!G$3) | H2: =G2*(1+Drivers_Assumptions!H$3) | I2: =H2*(1+Drivers_Assumptions!I$3) | J2: =I2*(1+Drivers_Assumptions!J$3) | K2: =J2*(1+Drivers_Assumptions!K$3) | L2: =SUM(B2:K2)
A3: Price | B3: =Inputs!$C$6 | C3: =B3*(1+Drivers_Assumptions!C$2) | D3: =C3*(1+Drivers_Assumptions!D$2) | E3: =D3*(1+Drivers_Assumptions!E$2) | F3: =E3*(1+Drivers_Assumptions!F$2) | G3: =F3*(1+Drivers_Assumptions!G$2) | H3: =G3*(1+Drivers_Assumptions!H$2) | I3: =H3*(1+Drivers_Assumptions!I$2) | J3: =I3*(1+Drivers_Assumptions!J$2) | K3: =J3*(1+Drivers_Assumptions!K$2) | L3: =SUM(B3:K3)
A4: Revenue | B4: =B2*B3 | C4: =C2*C3 | D4: =D2*D3 | E4: =E2*E3 | F4: =F2*F3 | G4: =G2*G3 | H4: =H2*H3 | I4: =I2*I3 | ... K4: =K2*K3 | L4: =SUM(B4:K4)

Sheet Debt_Schedule
A1: Metric | B1: Y1 | C1: Y2 | D1: Y3 | E1: Y4 | F1: Y5 | G1: Y6 | H1: Y7 | I1: Y8 | J1: Y9 | K1: Y10 | L1: Total | N1: Back to Index
A2: Opening Debt | B2: 0 | C2: =B7 | D2: =C7 | E2: =D7 | F2: =E7 | G2: =F7 | H2: =G7 | I2: =H7 | J2: =I7 | K2: =J7 | L2: =SUM(B2:K2)
A3: Drawdown | B3: =IF(COLUMN()<=5,CAPEX_Master!B$7*Inputs!$C$8,0) | C3: =IF(COLUMN()<=5,CAPEX_Master!C$7*Inputs!$C$8,0) | D3: =IF(COLUMN()<=5,CAPEX_Master!D$7*Inputs!$C$8,0) | E3: =IF(COLUMN()<=5,CAPEX_Master!E$7*Inputs!$C$8,0) | F3: =IF(COLUMN()<=5,CAPEX_Master!F$7*Inputs!$C$8,0) | G3: =IF(COLUMN()<=5,CAPEX_Master!G$7*Inputs!$C$8,0) | H3: =IF(COLUMN()<=5,CAPEX_Master!H$7*Inputs!$C$8,0) | I3: =IF(COLUMN()<=5,CAPEX_Master!I$7*Inputs!$C$8,0) | ... K3: =IF(COLUMN()<=5,CAPEX_Master!K$7*Inputs!$C$8,0) | L3: =SUM(B3:K3)
A4: Interest | B4: =(B2+B3)*Inputs!$C$10 | C4: =(C2+C3)*Inputs!$C$10 | D4: =(D2+D3)*Inputs!$C$10 | E4: =(E2+E3)*Inputs!$C$10 | F4: =(F2+F3)*Inputs!$C$10 | G4: =(G2+G3)*Inputs!$C$10 | H4: =(H2+H3)*Inputs!$C$10 | I4: =(I2+I3)*Inputs!$C$10 | ... K4: =(K2+K3)*Inputs!$C$10 | L4: =SUM(B4:K4)
A5: Principal Repayment | B5: =IF(COLUMN()<=3+Inputs!$C$11+Inputs!$C$12,0,(B2+B3)/MAX(1,Inputs!$C$11)) | C5: =IF(COLUMN()<=3+Inputs!$C$11+Inputs!$C$12,0,(C2+C3)/MAX(1,Inputs!$C$11)) | D5: =IF(COLUMN()<=3+Inputs!$C$11+Inputs!$C$12,0,(D2+D3)/MAX(1,Inputs!$C$11)) | E5: =IF(COLUMN()<=3+Inputs!$C$11+Inputs!$C$12,0,(E2+E3)/MAX(1,Inputs!$C$11)) | F5: =IF(COLUMN()<=3+Inputs!$C$11+Inputs!$C$12,0,(F2+F3)/MAX(1,Inputs!$C$11)) | G5: =IF(COLUMN()<=3+Inputs!$C$11+Inputs!$C$12,0,(G2+G3)/MAX(1,Inputs!$C$11)) | H5: =IF(COLUMN()<=3+Inputs!$C$11+Inputs!$C$12,0,(H2+H3)/MAX(1,Inputs!$C$11)) | I5: =IF(COLUMN()<=3+Inputs!$C$11+Inputs!$C$12,0,(I2+I3)/MAX(1,Inputs!$C$11)) | ... K5: =IF(COLUMN()<=3+Inputs!$C$11+Inputs!$C$12,0,(K2+K3)/MAX(1,Inputs!$C$11)) | L5: =SUM(B5:K5)
A6: Debt Service | B6: =B4+B5 | C6: =C4+C5 | D6: =D4+D5 | E6: =E4+E5 | F6: =F4+F5 | G6: =G4+G5 | H6: =H4+H5 | I6: =I4+I5 | ... K6: =K4+K5 | L6: =SUM(B6:K6)
A7: Closing Debt | B7: =MAX(0,B2+B3-B5) | C7: =MAX(0,C2+C3-C5) | D7: =MAX(0,D2+D3-D5) | E7: =MAX(0,E2+E3-E5) | F7: =MAX(0,F2+F3-F5) | G7: =MAX(0,G2+G3-G5) | H7: =MAX(0,H2+H3-H5) | I7: =MAX(0,I2+I3-I5) | ... K7: =MAX(0,K2+K3-K5) | L7: =SUM(B7:K7)

Sheet Equity_Grant_Schedule
A1: Metric | B1: Y1 | C1: Y2 | D1: Y3 | E1: Y4 | F1: Y5 | G1: Y6 | H1: Y7 | I1: Y8 | J1: Y9 | K1: Y10 | L1: Total | N1: Back to Index
A2: Total Uses | B2: =CAPEX_Master!B$7 | C2: =CAPEX_Master!C$7 | D2: =CAPEX_Master!D$7 | E2: =CAPEX_Master!E$7 | F2: =CAPEX_Master!F$7 | G2: =CAPEX_Master!G$7 | H2: =CAPEX_Master!H$7 | I2: =CAPEX_Master!I$7 | ... K2: =CAPEX_Master!K$7 | L2: =SUM(B2:K2)
A3: Debt | B3: =Debt_Schedule!B$3 | C3: =Debt_Schedule!C$3 | D3: =Debt_Schedule!D$3 | E3: =Debt_Schedule!E$3 | F3: =Debt_Schedule!F$3 | G3: =Debt_Schedule!G$3 | H3: =Debt_Schedule!H$3 | I3: =Debt_Schedule!I$3 | ... K3: =Debt_Schedule!K$3 | L3: =SUM(B3:K3)
A4: Grant | B4: =Inputs!$C$9*B2 | C4: =Inputs!$C$9*C2 | D4: =Inputs!$C$9*D2 | E4: =Inputs!$C$9*E2 | F4: =Inputs!$C$9*F2 | G4: =Inputs!$C$9*G2 | H4: =Inputs!$C$9*H2 | I4: =Inputs!$C$9*I2 | ... K4: =Inputs!$C$9*K2 | L4: =SUM(B4:K4)
A5: Equity | B5: =MAX(0,B2-B3-B4) | C5: =MAX(0,C2-C3-C4) | D5: =MAX(0,D2-D3-D4) | E5: =MAX(0,E2-E3-E4) | F5: =MAX(0,F2-F3-F4) | G5: =MAX(0,G2-G3-G4) | H5: =MAX(0,H2-H3-H4) | I5: =MAX(0,I2-I3-I4) | ... K5: =MAX(0,K2-K3-K4) | L5: =SUM(B5:K5)

Sheet Cash_Flow
A1: Metric | B1: Y1 | C1: Y2 | D1: Y3 | E1: Y4 | F1: Y5 | G1: Y6 | H1: Y7 | I1: Y8 | J1: Y9 | K1: Y10 | L1: Total | N1: Back to Index
A2: EBITDA | B2: =EBITDA_PnL!B$4 | C2: =EBITDA_PnL!C$4 | D2: =EBITDA_PnL!D$4 | E2: =EBITDA_PnL!E$4 | F2: =EBITDA_PnL!F$4 | G2: =EBITDA_PnL!G$4 | H2: =EBITDA_PnL!H$4 | I2: =EBITDA_PnL!I$4 | ... K2: =EBITDA_PnL!K$4 | L2: =SUM(B2:K2)
A3: Taxes | B3: =EBITDA_PnL!B$7 | C3: =EBITDA_PnL!C$7 | D3: =EBITDA_PnL!D$7 | E3: =EBITDA_PnL!E$7 | F3: =EBITDA_PnL!F$7 | G3: =EBITDA_PnL!G$7 | H3: =EBITDA_PnL!H$7 | I3: =EBITDA_PnL!I$7 | ... K3: =EBITDA_PnL!K$7 | L3: =SUM(B3:K3)
A4: CAPEX | B4: =-CAPEX_Master!B$7 | C4: =-CAPEX_Master!C$7 | D4: =-CAPEX_Master!D$7 | E4: =-CAPEX_Master!E$7 | F4: =-CAPEX_Master!F$7 | G4: =-CAPEX_Master!G$7 | H4: =-CAPEX_Master!H$7 | I4: =-CAPEX_Master!I$7 | ... K4: =-CAPEX_Master!K$7 | L4: =SUM(B4:K4)
A5: Change in Working Capital | B5: =-(Revenue_Schedule!B$4*Drivers_Assumptions!B$6) | C5: =-(Revenue_Schedule!C$4*Drivers_Assumptions!C$6- Revenue_Schedule!B$4*Drivers_Assumptions!B$6) | D5: =-(Revenue_Schedule!D$4*Drivers_Assumptions!D$6- Revenue_Schedule!C$4*Drivers_Assumptions!C$6) | E5: =-(Revenue_Schedule!E$4*Drivers_Assumptions!E$6- Revenue_Schedule!D$4*Drivers_Assumptions!D$6) | F5: =-(Revenue_Schedule!F$4*Drivers_Assumptions!F$6- Revenue_Schedule!E$4*Drivers_Assumptions!E$6) | G5: =-(Revenue_Schedule!G$4*Drivers_Assumptions!G$6- Revenue_Schedule!F$4*Drivers_Assumptions!F$6) | H5: =-(Revenue_Schedule!H$4*Drivers_Assumptions!H$6- Revenue_Schedule!G$4*Drivers_Assumptions!G$6) | I5: =-(Revenue_Schedule!I$4*Drivers_Assumptions!I$6- Revenue_Schedule!H$4*Drivers_Assumptions!H$6) | J5: =-(Revenue_Schedule!J$4*Drivers_Assumptions!J$6- Revenue_Schedule!I$4*Drivers_Assumptions!I$6) | K5: =-(Revenue_Schedule!K$4*Drivers_Assumptions!K$6- Revenue_Schedule!J$4*Drivers_Assumptions!J$6) | L5: =SUM(B5:K5)
A6: Operating Cash Flow | B6: =SUM(B2:B5) | C6: =SUM(C2:C5) | D6: =SUM(D2:D5) | E6: =SUM(E2:E5) | F6: =SUM(F2:F5) | G6: =SUM(G2:G5) | H6: =SUM(H2:H5) | I6: =SUM(I2:I5) | ... K6: =SUM(K2:K5) | L6: =SUM(B6:K6)
A7: Debt Service | B7: =-Debt_Schedule!B$6 | C7: =-Debt_Schedule!C$6 | D7: =-Debt_Schedule!D$6 | E7: =-Debt_Schedule!E$6 | F7: =-Debt_Schedule!F$6 | G7: =-Debt_Schedule!G$6 | H7: =-Debt_Schedule!H$6 | I7: =-Debt_Schedule!I$6 | ... K7: =-Debt_Schedule!K$6 | L7: =SUM(B7:K7)
A8: Equity Injection | B8: =Equity_Grant_Schedule!B$5 | C8: =Equity_Grant_Schedule!C$5 | D8: =Equity_Grant_Schedule!D$5 | E8: =Equity_Grant_Schedule!E$5 | F8: =Equity_Grant_Schedule!F$5 | G8: =Equity_Grant_Schedule!G$5 | H8: =Equity_Grant_Schedule!H$5 | I8: =Equity_Grant_Schedule!I$5 | ... K8: =Equity_Grant_Schedule!K$5 | L8: =SUM(B8:K8)
A9: Grant Inflow | B9: =Equity_Grant_Schedule!B$4 | C9: =Equity_Grant_Schedule!C$4 | D9: =Equity_Grant_Schedule!D$4 | E9: =Equity_Grant_Schedule!E$4 | F9: =Equity_Grant_Schedule!F$4 | G9: =Equity_Grant_Schedule!G$4 | H9: =Equity_Grant_Schedule!H$4 | I9: =Equity_Grant_Schedule!I$4 | ... K9: =Equity_Grant_Schedule!K$4 | L9: =SUM(B9:K9)
A10: Net Cash Flow | B10: =SUM(B6:B9) | C10: =SUM(C6:C9) | D10: =SUM(D6:D9) | E10: =SUM(E6:E9) | F10: =SUM(F6:F9) | G10: =SUM(G6:G9) | H10: =SUM(H6:H9) | I10: =SUM(I6:I9) | ... K10: =SUM(K6:K9) | L10: =SUM(B10:K10)

Sheet EBITDA_PnL
A1: Metric | B1: Y1 | C1: Y2 | D1: Y3 | E1: Y4 | F1: Y5 | G1: Y6 | H1: Y7 | I1: Y8 | J1: Y9 | K1: Y10 | L1: Total | N1: Back to Index
A2: Revenue | B2: =Revenue_Schedule!B$4 | C2: =Revenue_Schedule!C$4 | D2: =Revenue_Schedule!D$4 | E2: =Revenue_Schedule!E$4 | F2: =Revenue_Schedule!F$4 | G2: =Revenue_Schedule!G$4 | H2: =Revenue_Schedule!H$4 | I2: =Revenue_Schedule!I$4 | ... K2: =Revenue_Schedule!K$4 | L2: =SUM(B2:K2)
A3: OPEX | B3: =OPEX_Master!B$7 | C3: =OPEX_Master!C$7 | D3: =OPEX_Master!D$7 | E3: =OPEX_Master!E$7 | F3: =OPEX_Master!F$7 | G3: =OPEX_Master!G$7 | H3: =OPEX_Master!H$7 | I3: =OPEX_Master!I$7 | ... K3: =OPEX_Master!K$7 | L3: =SUM(B3:K3)
A4: EBITDA | B4: =B2-B3 | C4: =C2-C3 | D4: =D2-D3 | E4: =E2-E3 | F4: =F2-F3 | G4: =G2-G3 | H4: =H2-H3 | I4: =I2-I3 | ... K4: =K2-K3 | L4: =SUM(B4:K4)
A5: Depreciation | B5: =CAPEX_Master!$L$7/10 | C5: =CAPEX_Master!$L$7/10 | D5: =CAPEX_Master!$L$7/10 | E5: =CAPEX_Master!$L$7/10 | F5: =CAPEX_Master!$L$7/10 | G5: =CAPEX_Master!$L$7/10 | H5: =CAPEX_Master!$L$7/10 | I5: =CAPEX_Master!$L$7/10 | ... K5: =CAPEX_Master!$L$7/10 | L5: =SUM(B5:K5)
A6: EBIT | B6: =B4-B5 | C6: =C4-C5 | D6: =D4-D5 | E6: =E4-E5 | F6: =F4-F5 | G6: =G4-G5 | H6: =H4-H5 | I6: =I4-I5 | ... K6: =K4-K5 | L6: =SUM(B6:K6)
A7: Tax | B7: =MAX(0,B6*Inputs!$C$3) | C7: =MAX(0,C6*Inputs!$C$3) | D7: =MAX(0,D6*Inputs!$C$3) | E7: =MAX(0,E6*Inputs!$C$3) | F7: =MAX(0,F6*Inputs!$C$3) | G7: =MAX(0,G6*Inputs!$C$3) | H7: =MAX(0,H6*Inputs!$C$3) | I7: =MAX(0,I6*Inputs!$C$3) | ... K7: =MAX(0,K6*Inputs!$C$3) | L7: =SUM(B7:K7)
A8: Net Income | B8: =B6-B7 | C8: =C6-C7 | D8: =D6-D7 | E8: =E6-E7 | F8: =F6-F7 | G8: =G6-G7 | H8: =H6-H7 | I8: =I6-I7 | ... K8: =K6-K7 | L8: =SUM(B8:K8)

Sheet Balance_Sheet
A1: Metric | B1: Y1 | C1: Y2 | D1: Y3 | E1: Y4 | F1: Y5 | G1: Y6 | H1: Y7 | I1: Y8 | J1: Y9 | K1: Y10 | L1: Total | N1: Back to Index
A2: Net Fixed Assets | B2: =CAPEX_Master!B$7-EBITDA_PnL!B$5 | C2: =B2+CAPEX_Master!C$7-EBITDA_PnL!C$5 | D2: =C2+CAPEX_Master!D$7-EBITDA_PnL!D$5 | E2: =D2+CAPEX_Master!E$7-EBITDA_PnL!E$5 | F2: =E2+CAPEX_Master!F$7-EBITDA_PnL!F$5 | G2: =F2+CAPEX_Master!G$7-EBITDA_PnL!G$5 | H2: =G2+CAPEX_Master!H$7-EBITDA_PnL!H$5 | I2: =H2+CAPEX_Master!I$7-EBITDA_PnL!I$5 | J2: =I2+CAPEX_Master!J$7-EBITDA_PnL!J$5 | K2: =J2+CAPEX_Master!K$7-EBITDA_PnL!K$5 | L2: =SUM(B2:K2)
A3: Working Capital | B3: =Revenue_Schedule!B$4*Drivers_Assumptions!B$6 | C3: =Revenue_Schedule!C$4*Drivers_Assumptions!C$6 | D3: =Revenue_Schedule!D$4*Drivers_Assumptions!D$6 | E3: =Revenue_Schedule!E$4*Drivers_Assumptions!E$6 | F3: =Revenue_Schedule!F$4*Drivers_Assumptions!F$6 | G3: =Revenue_Schedule!G$4*Drivers_Assumptions!G$6 | H3: =Revenue_Schedule!H$4*Drivers_Assumptions!H$6 | I3: =Revenue_Schedule!I$4*Drivers_Assumptions!I$6 | ... K3: =Revenue_Schedule!K$4*Drivers_Assumptions!K$6 | L3: =SUM(B3:K3)
A4: Cash | B4: =Cash_Flow!B$10 | C4: =MAX(0,B4+Cash_Flow!C$10) | D4: =MAX(0,C4+Cash_Flow!D$10) | E4: =MAX(0,D4+Cash_Flow!E$10) | F4: =MAX(0,E4+Cash_Flow!F$10) | G4: =MAX(0,F4+Cash_Flow!G$10) | H4: =MAX(0,G4+Cash_Flow!H$10) | I4: =MAX(0,H4+Cash_Flow!I$10) | J4: =MAX(0,I4+Cash_Flow!J$10) | K4: =MAX(0,J4+Cash_Flow!K$10) | L4: =SUM(B4:K4)
A5: Debt | B5: =Debt_Schedule!B$7 | C5: =Debt_Schedule!C$7 | D5: =Debt_Schedule!D$7 | E5: =Debt_Schedule!E$7 | F5: =Debt_Schedule!F$7 | G5: =Debt_Schedule!G$7 | H5: =Debt_Schedule!H$7 | I5: =Debt_Schedule!I$7 | ... K5: =Debt_Schedule!K$7 | L5: =SUM(B5:K5)
A6: Equity | B6: =Equity_Grant_Schedule!B$5+EBITDA_PnL!B$8 | C6: =B6+Equity_Grant_Schedule!C$5+EBITDA_PnL!C$8 | D6: =C6+Equity_Grant_Schedule!D$5+EBITDA_PnL!D$8 | E6: =D6+Equity_Grant_Schedule!E$5+EBITDA_PnL!E$8 | F6: =E6+Equity_Grant_Schedule!F$5+EBITDA_PnL!F$8 | G6: =F6+Equity_Grant_Schedule!G$5+EBITDA_PnL!G$8 | H6: =G6+Equity_Grant_Schedule!H$5+EBITDA_PnL!H$8 | I6: =H6+Equity_Grant_Schedule!I$5+EBITDA_PnL!I$8 | J6: =I6+Equity_Grant_Schedule!J$5+EBITDA_PnL!J$8 | K6: =J6+Equity_Grant_Schedule!K$5+EBITDA_PnL!K$8 | L6: =SUM(B6:K6)
A7: Check Balance | B7: =(B2+B3+B4)-(B5+B6) | C7: =(C2+C3+C4)-(C5+C6) | D7: =(D2+D3+D4)-(D5+D6) | E7: =(E2+E3+E4)-(E5+E6) | F7: =(F2+F3+F4)-(F5+F6) | G7: =(G2+G3+G4)-(G5+G6) | H7: =(H2+H3+H4)-(H5+H6) | I7: =(I2+I3+I4)-(I5+I6) | ... K7: =(K2+K3+K4)-(K5+K6) | L7: =SUM(B7:K7)

Sheet KPIs_Metrics
A1: KPI | B1: Value | C1: Status | E1: DSCR by Year | F1: Y1 | G1: Y2 | H1: Y3 | I1: Y4 | J1: Y5 | K1: Y6 | L1: Y7 | M1: Y8 | N1: Back to Index | O1: Y10
A2: Project IRR | B2: =IRR(Cash_Flow!B10:K10) | C2: =IF(B2>=0.15,"PASS","WATCH") | E2: CFADS | F2: =Cash_Flow!B6 | G2: =Cash_Flow!C6 | H2: =Cash_Flow!D6 | I2: =Cash_Flow!E6 | J2: =Cash_Flow!F6 | K2: =Cash_Flow!G6 | L2: =Cash_Flow!H6 | M2: =Cash_Flow!I6 | ... O2: =Cash_Flow!K6
A3: NPV | B3: =NPV(Inputs!$C$4,Cash_Flow!C10:K10)+Cash_Flow!B10 | C3: =IF(B3>0,"INFO","CHECK") | E3: Debt Service | F3: =Debt_Schedule!B6 | G3: =Debt_Schedule!C6 | H3: =Debt_Schedule!D6 | I3: =Debt_Schedule!E6 | J3: =Debt_Schedule!F6 | K3: =Debt_Schedule!G6 | L3: =Debt_Schedule!H6 | M3: =Debt_Schedule!I6 | ... O3: =Debt_Schedule!K6
A4: Avg DSCR | B4: =AVERAGE(B8:K8) | C4: =IF(B4>=1.30,"PASS","FAIL") | E4: DSCR | F4: =IFERROR(F2/F3,0) | G4: =IFERROR(G2/G3,0) | H4: =IFERROR(H2/H3,0) | I4: =IFERROR(I2/I3,0) | J4: =IFERROR(J2/J3,0) | K4: =IFERROR(K2/K3,0) | L4: =IFERROR(L2/L3,0) | M4: =IFERROR(M2/M3,0) | ... O4: =IFERROR(O2/O3,0)
A5: Min DSCR | B5: =MIN(B8:K8) | C5: =IF(B5>=1.15,"PASS","FAIL")
A6: EBITDA Margin Y1 | B6: =EBITDA_PnL!B4/EBITDA_PnL!B2 | C6: =IF(B6>=0.20,"PASS","WATCH")

Sheet Checks_Audit
A1: Check | B1: Formula / Logic | C1: Result | D1: Status | E1: Comment | N1: Back to Index
A2: Sources equal uses total | B2: =Equity_Grant_Schedule!L3+Equity_Grant_Schedule!L4+Equity_Grant_Schedule!L5-Equity_Grant_Schedule!L2 | C2: =Equity_Grant_Schedule!L3+Equity_Grant_Schedule!L4+Equity_Grant_Schedule!L5-Equity_Grant_Schedule!L2 | D2: =IF(OR(AND(A2="Sources equal uses total",ABS(C2)<0.01),AND(A2="Balance sheet closes total",ABS(C2)<0.01),AND(A2<>"Sources equal uses total",A2<>"Balance sheet closes total",C2>=0)),"PASS","FAIL") | E2: Should equal 0
A3: Balance sheet closes total | B3: =ABS(Balance_Sheet!L7) | C3: =ABS(Balance_Sheet!L7) | D3: =IF(OR(AND(A3="Sources equal uses total",ABS(C3)<0.01),AND(A3="Balance sheet closes total",ABS(C3)<0.01),AND(A3<>"Sources equal uses total",A3<>"Balance sheet closes total",C3>=0)),"PASS","FAIL") | E3: Should equal 0
A4: Min DSCR threshold | B4: =KPIs_Metrics!B5-1.15 | C4: =KPIs_Metrics!B5-1.15 | D4: =IF(OR(AND(A4="Sources equal uses total",ABS(C4)<0.01),AND(A4="Balance sheet closes total",ABS(C4)<0.01),AND(A4<>"Sources equal uses total",A4<>"Balance sheet closes total",C4>=0)),"PASS","FAIL") | E4: Should be >=0
A5: No negative closing debt | B5: =MIN(Debt_Schedule!B7:K7) | C5: =MIN(Debt_Schedule!B7:K7) | D5: =IF(OR(AND(A5="Sources equal uses total",ABS(C5)<0.01),AND(A5="Balance sheet closes total",ABS(C5)<0.01),AND(A5<>"Sources equal uses total",A5<>"Balance sheet closes total",C5>=0)),"PASS","FAIL") | E5: Should be >=0
A6: No negative cash | B6: =MIN(Balance_Sheet!B4:K4) | C6: =MIN(Balance_Sheet!B4:K4) | D6: =IF(OR(AND(A6="Sources equal uses total",ABS(C6)<0.01),AND(A6="Balance sheet closes total",ABS(C6)<0.01),AND(A6<>"Sources equal uses total",A6<>"Balance sheet closes total",C6>=0)),"PASS","FAIL") | E6: Should be >=0
