Workbook

Sheet Cover
A1: ARS CAPEX Civil Packages – Harmonized Workbook
A3: Project | B3: ARS Metal Industries
A4: Module | B4: CAPEX_Master
A5: Sub-Module | B5: Civil_Packages
A6: Version | B6: v1.1 Harmonized
A7: Prepared for | B7: Internal use / investor preparation
A8: Model status | B8: Remediated working model; not a full project finance model
A9: Civil CAPEX | B9: 18255000
A10: Total Project CAPEX | B10: 58275000
A11: Civil Share | B11: =B9/B10
A12: Notes | B12: Workbook harmonized after formula audit: fixed control totals, live-linked category summary, direct phasing link, stronger checks, MAREL ecosystem bridge, and corrected Cover civil share formula.
A13: Institutional baseline note | B13: Civil CAPEX €18.255m reflects the wider MAREL industrial platform and ecosystem build-out.
A14: SPV baseline note | B14: The TITAN Grid SPV institutional baseline remains the ring-fenced smart-factory CAPEX only; allocate the applicable civil subset at SPV level per Institutional Baseline v1.
A15: Data room footnote | B15: Civil CAPEX €18.255m reflects full MAREL platform; €X.Xm allocated to TITAN Grid SPV (ring-fenced) per Institutional Baseline v1.

Sheet Index
A1: Section | B1: Go to sheet | C1: Description
A2: Cover | B2: Cover | C2: Workbook cover and status
A3: Assumptions | B3: Assumptions | C3: Key numeric drivers and validation assumptions
A4: Civil Packages | B4: Civil_Packages_Master | C4: Detailed civil packages and formulas
A5: Category Summary | B5: Category_Summary | C5: Live-linked summary by category
A6: CAPEX Checks | B6: CAPEX_Check | C6: Independent control checks
A7: Phasing | B7: Phasing_Link | C7: CAPEX phasing linked to verified total
A8: Asset Register | B8: Asset_Register_Link | C8: Cost and depreciation bridge
A9: Ecosystem | B9: Ecosystem_Link | C9: Civil CAPEX positioning within MAREL ecosystem

Sheet Assumptions
A1: Metric | B1: Value | C1: Unit | D1: Comment
A2: Area estimate | B2: 25000 | C2: m² | D2: Midpoint estimate
A3: Low cost benchmark | B3: 730 | C3: EUR/m² | D3: Benchmark range from user source
A4: High cost benchmark | B4: 920 | C4: EUR/m² | D4: Benchmark range from user source
A5: Civil CAPEX total | B5: =Civil_Packages_Master!E21 | C5: EUR | D5: Verified detailed total
A6: Total project CAPEX | B6: 58275000 | C6: EUR | D6: From user-provided total project CAPEX
A7: Civil share of total | B7: =B5/B6 | C7: % | D7: Civil CAPEX / total project CAPEX
A8: Contingency amount | B8: =SUMIFS(Civil_Packages_Master!$E$2:$E$20,Civil_Packages_Master!$K$2:$K$20,$A$10) | C8: EUR | D8: Package 19
A9: Contingency base | B9: =B5-B8 | C9: EUR | D9: Civil CAPEX excluding contingency
A10: CONT group code | B10: CONT | C10: code | D10: Helper code for SUMIFS
A11: Actual contingency % | B11: =IFERROR(B8/B9,0) | C11: % | D11: Compared against base excluding contingency
A12: Target contingency min | B12: 0.1 | C12: % | D12: Management target
A13: Target contingency max | B13: 0.15 | C13: % | D13: Management target
A14: Coverage flag | B14: =IF(AND(B11>=B12,B11<=B13),"OK","OUTSIDE TARGET") | D14: Should be within target range
A15: Phasing 2026 | B15: 0.2 | C15: % | D15: Input
A16: Phasing 2027 | B16: 0.45 | C16: % | D16: Input
A17: Phasing 2028 | B17: 0.35 | C17: % | D17: Input
A18: Phasing total | B18: =SUM(B15:B17) | C18: % | D18: Must equal 100%

Sheet Civil_Packages_Master
A1: Package ID | B1: Description | C1: Unit Cost | D1: Qty | E1: CAPEX | F1: Zone | G1: Function | H1: Criticality | I1: Lifetime (yrs) | J1: Maintenance % | K1: Category Code
A2: 1 | B2: Projektovanje i dozvole | C2: 625000 | D2: 1 | E2: =C2*D2 | F2: Whole | G2: Planning | H2: High | I2: 5 | J2: 0.01 | K2: PLAN_PREP
A3: 2 | B3: Zemljani radovi | C3: 800000 | D3: 1 | E3: =C3*D3 | F3: Site | G3: Site prep | H3: Critical | I3: 40 | J3: 0.005 | K3: PLAN_PREP
A4: 3 | B4: Temelji | C4: 1450000 | D4: 1 | E4: =C4*D4 | F4: Foundations | G4: Structure | H4: Critical | I4: 50 | J4: 0.005 | K4: FOUND_FLOOR
A5: 4 | B5: Industrijski pod | C5: 1750000 | D5: 1 | E5: =C5*D5 | F5: Production | G5: Heavy floor | H5: Critical | I5: 30 | J5: 0.01 | K5: FOUND_FLOOR
A6: 5 | B6: Čelična konstrukcija | C6: 2800000 | D6: 1 | E6: =C6*D6 | F6: Hall | G6: Structure | H6: Critical | I6: 40 | J6: 0.015 | K6: STRUCT_ENV
A7: 6 | B7: Krovni sistem | C7: 1075000 | D7: 1 | E7: =C7*D7 | F7: Roof | G7: Roofing | H7: High | I7: 25 | J7: 0.01 | K7: STRUCT_ENV
A8: 7 | B8: Fasada | C8: 1150000 | D8: 1 | E8: =C8*D8 | F8: Envelope | G8: Cladding | H8: High | I8: 30 | J8: 0.01 | K8: STRUCT_ENV
A9: 8 | B9: Industrijska vrata | C9: 525000 | D9: 1 | E9: =C9*D9 | F9: Envelope | G9: Access | H9: Medium | I9: 20 | J9: 0.01 | K9: DOORS_INT
A10: 9 | B10: Prozori / glazing | C10: 390000 | D10: 1 | E10: =C10*D10 | F10: Office | G10: Daylight | H10: Medium | I10: 25 | J10: 0.01 | K10: DOORS_INT
A11: 10 | B11: Elektro instalacije | C11: 1200000 | D11: 1 | E11: =C11*D11 | F11: Whole | G11: Electrical | H11: Critical | I11: 25 | J11: 0.02 | K11: ELEC_MECH
A12: 11 | B12: HVAC | C12: 875000 | D12: 1 | E12: =C12*D12 | F12: Whole | G12: Climate | H12: High | I12: 20 | J12: 0.02 | K12: ELEC_MECH
A13: 12 | B13: Fire protection | C13: 925000 | D13: 1 | E13: =C13*D13 | F13: Whole | G13: Safety | H13: Critical | I13: 25 | J13: 0.02 | K13: SAFETY_UTIL
... A19: 18 | B19: Security systems | C19: 315000 | D19: 1 | E19: =C19*D19 | F19: Whole | G19: CCTV/access | H19: Medium | I19: 15 | J19: 0.01 | K19: IT_SEC
A20: 19 | B20: Contingency | C20: 1400000 | D20: 1 | E20: =C20*D20 | F20: Whole | G20: Risk buffer | H20: High | K20: CONT
D21: TOTAL | E21: =SUM(E2:E20)

Sheet Category_Summary
A1: Category Code | B1: Category Label | C1: Packages | D1: CAPEX
A2: PLAN_PREP | B2: Planning & Prep | C2: 1-2 | D2: =SUMIFS(Civil_Packages_Master!$E$2:$E$20,Civil_Packages_Master!$K$2:$K$20,A2)
A3: FOUND_FLOOR | B3: Foundations & Flooring | C3: 3-4 | D3: =SUMIFS(Civil_Packages_Master!$E$2:$E$20,Civil_Packages_Master!$K$2:$K$20,A3)
A4: STRUCT_ENV | B4: Structure & Envelope | C4: 5-7 | D4: =SUMIFS(Civil_Packages_Master!$E$2:$E$20,Civil_Packages_Master!$K$2:$K$20,A4)
A5: DOORS_INT | B5: Doors, Windows & Interiors | C5: 8-9,16 | D5: =SUMIFS(Civil_Packages_Master!$E$2:$E$20,Civil_Packages_Master!$K$2:$K$20,A5)
A6: ELEC_MECH | B6: Electrical & Mechanical | C6: 10-11 | D6: =SUMIFS(Civil_Packages_Master!$E$2:$E$20,Civil_Packages_Master!$K$2:$K$20,A6)
A7: SAFETY_UTIL | B7: Safety & Utilities | C7: 12-14 | D7: =SUMIFS(Civil_Packages_Master!$E$2:$E$20,Civil_Packages_Master!$K$2:$K$20,A7)
A8: SPECIAL_EXT | B8: Specialized Prep & Externals | C8: 15,17 | D8: =SUMIFS(Civil_Packages_Master!$E$2:$E$20,Civil_Packages_Master!$K$2:$K$20,A8)
A9: IT_SEC | B9: IT / Security | C9: 18 | D9: =SUMIFS(Civil_Packages_Master!$E$2:$E$20,Civil_Packages_Master!$K$2:$K$20,A9)
A10: CONT | B10: Contingency | C10: 19 | D10: =SUMIFS(Civil_Packages_Master!$E$2:$E$20,Civil_Packages_Master!$K$2:$K$20,A10)
C11: TOTAL | D11: =SUM(D2:D10)

Sheet CAPEX_Check
A1: Check | B1: Formula / Source | C1: Result | D1: Status
A2: Detailed CAPEX total | B2: =Civil_Packages_Master!E21 | C2: =Civil_Packages_Master!E21 | D2: =IF(C2>0,"OK","ERROR")
A3: Category summary total | B3: =Category_Summary!D11 | C3: =Category_Summary!D11 | D3: =IF(C3>0,"OK","ERROR")
A4: Difference: detail vs summary | B4: =C2-C3 | C4: =C2-C3 | D4: =IF(ABS(C4)<0.5,"OK","CHECK")
A5: Phasing total | B5: =SUM(Phasing_Link!C2:C4) | C5: =SUM(Phasing_Link!C2:C4) | D5: =IF(C5>0,"OK","ERROR")
A6: Difference: detail vs phasing | B6: =C2-C5 | C6: =C2-C5 | D6: =IF(ABS(C6)<0.5,"OK","CHECK")
A7: Phasing % total | B7: =Assumptions!B18 | C7: =Assumptions!B18 | D7: =IF(ABS(C7-1)<0.00001,"OK","CHECK")
A8: Actual contingency % | B8: =Assumptions!B11 | C8: =Assumptions!B11 | D8: =IF(AND(C8>=Assumptions!B12,C8<=Assumptions!B13),"OK","OUTSIDE TARGET")
A9: Audit note | B9: Control totals now reference explicit ranges / verified totals only.

Sheet Phasing_Link
A1: Year | B1: % of Civil CAPEX | C1: Amount
A2: 2026 | B2: =Assumptions!B15 | C2: =Civil_Packages_Master!$E$21*B2
A3: 2027 | B3: =Assumptions!B16 | C3: =Civil_Packages_Master!$E$21*B3
A4: 2028 | B4: =Assumptions!B17 | C4: =Civil_Packages_Master!$E$21*B4
A5: TOTAL | B5: =SUM(B2:B4) | C5: =SUM(C2:C4)

Sheet Asset_Register_Link
A1: Package ID | B1: Description | C1: CAPEX | D1: Asset Class | E1: Useful Life (yrs) | F1: Annual Depreciation
A2: 1 | B2: =Civil_Packages_Master!B2 | C2: =Civil_Packages_Master!E2 | D2: Intangible / Predevelopment | E2: =Civil_Packages_Master!I2 | F2: =IFERROR(C2/E2,"")
A3: 2 | B3: =Civil_Packages_Master!B3 | C3: =Civil_Packages_Master!E3 | D3: Land Improvements | E3: =Civil_Packages_Master!I3 | F3: =IFERROR(C3/E3,"")
A4: 3 | B4: =Civil_Packages_Master!B4 | C4: =Civil_Packages_Master!E4 | D4: Buildings | E4: =Civil_Packages_Master!I4 | F4: =IFERROR(C4/E4,"")
A5: 4 | B5: =Civil_Packages_Master!B5 | C5: =Civil_Packages_Master!E5 | D5: Infrastructure | E5: =Civil_Packages_Master!I5 | F5: =IFERROR(C5/E5,"")
A6: 5 | B6: =Civil_Packages_Master!B6 | C6: =Civil_Packages_Master!E6 | D6: Buildings | E6: =Civil_Packages_Master!I6 | F6: =IFERROR(C6/E6,"")
A7: 6 | B7: =Civil_Packages_Master!B7 | C7: =Civil_Packages_Master!E7 | D7: Buildings | E7: =Civil_Packages_Master!I7 | F7: =IFERROR(C7/E7,"")
A8: 7 | B8: =Civil_Packages_Master!B8 | C8: =Civil_Packages_Master!E8 | D8: Buildings | E8: =Civil_Packages_Master!I8 | F8: =IFERROR(C8/E8,"")
A9: 8 | B9: =Civil_Packages_Master!B9 | C9: =Civil_Packages_Master!E9 | D9: Building Fixtures | E9: =Civil_Packages_Master!I9 | F9: =IFERROR(C9/E9,"")
A10: 9 | B10: =Civil_Packages_Master!B10 | C10: =Civil_Packages_Master!E10 | D10: Building Fixtures | E10: =Civil_Packages_Master!I10 | F10: =IFERROR(C10/E10,"")
A11: 10 | B11: =Civil_Packages_Master!B11 | C11: =Civil_Packages_Master!E11 | D11: Electrical | E11: =Civil_Packages_Master!I11 | F11: =IFERROR(C11/E11,"")
A12: 11 | B12: =Civil_Packages_Master!B12 | C12: =Civil_Packages_Master!E12 | D12: Mechanical | E12: =Civil_Packages_Master!I12 | F12: =IFERROR(C12/E12,"")
A13: 12 | B13: =Civil_Packages_Master!B13 | C13: =Civil_Packages_Master!E13 | D13: Safety Systems | E13: =Civil_Packages_Master!I13 | F13: =IFERROR(C13/E13,"")
... A19: 18 | B19: =Civil_Packages_Master!B19 | C19: =Civil_Packages_Master!E19 | D19: IT / Security | E19: =Civil_Packages_Master!I19 | F19: =IFERROR(C19/E19,"")
A20: TOTAL DEPRECIABLE BASE | C20: =SUM(C2:C19) | F20: =SUM(F2:F19)

Sheet Ecosystem_Link
A1: Metric | B1: Value | C1: Comment
A2: MAREL ecosystem view
A3: Civil CAPEX | B3: =Civil_Packages_Master!E21 | C3: This workbook
A4: Non-civil CAPEX | B4: =Assumptions!B6-Assumptions!B5 | C4: Implied remainder of project CAPEX
A5: Total industrial asset / project CAPEX | B5: =Assumptions!B6 | C5: User-provided project CAPEX
A6: Civil share | B6: =Assumptions!B7 | C6: Civil as % of total project CAPEX
A7: Institutional harmonization | B7: See Harmonization_Note | C7: Use footnote to distinguish full-platform civil CAPEX from TITAN Grid SPV baseline.
A8: SPV allocation placeholder | B8: €X.Xm | C8: Populate once ring-fenced civil subset is approved in Institutional Baseline v1.
A9: Readiness flag | B9: =IF(AND(CAPEX_Check!D4="OK",CAPEX_Check!D6="OK"),"CORE CAPEX LINKED","REVIEW REQUIRED") | C9: High-level linkage check

Sheet Harmonization_Note
A1: Project TITAN / ARS Metal Industries
A2: Civil CAPEX Institutional Harmonization Note
A4: Purpose | B4: Clarify the difference between full-platform civil CAPEX and the TITAN Grid SPV ring-fenced baseline used in institutional materials.
A6: Full-platform civil CAPEX | B6: 18255000 | C6: EUR | D6: ARS / MAREL ecosystem-wide civil infrastructure reflected in this workbook.
A7: Total project CAPEX | B7: 58275000 | C7: EUR | D7: Referenced ecosystem / industrial platform total CAPEX in the workbook assumptions.
A8: TITAN Grid SPV baseline | B8: Per Institutional Baseline v1 | D8: Ring-fenced smart-factory CAPEX only; civil subset to be allocated at SPV level.
A10: Recommended footnote for Data Room ID 8 and related model tabs | B10: Civil CAPEX €18.255m reflects full MAREL platform; €X.Xm allocated to TITAN Grid SPV (ring-fenced) per Institutional Baseline v1.
A12: Contingency note | B12: Contingency of €1.4m (7.7%) is already included in Package 19. Any OUTSIDE TARGET flag tied to a 10–15% range is a control-threshold artifact, not a missing contingency.
A14: Recommended use | B14: Populate Data Room ID 8 – Capital Requirement Summary; Data Room IDs 37–50 – Financial Model; Data Room IDs 61–85 – Technical DD; and Data Room IDs 13–22 – Ecosystem & Expansion Strategy.
