Workbook

Sheet 00_COVER
A1: TITAN Central Brain Finance Master v6.1
A3: Document | B3: TITAN Central Brain Finance Master v6.1
A4: Prepared For | B4: ARS Metal / ADS Metal / TITAN Central Brain
A5: Purpose | B5: Harmonized multi-baseline finance master with audit controls
A6: Important | B6: Baselines are segregated using Baseline_ID to avoid forensic conflicts
A7: Version Date | B7: 2026-04-03

Sheet Active_Data
A1: Active_Data – Central Brain Memory
A4: Baseline_ID | B4: Model_Version | C4: Scenario_Type | D4: Parameter | E4: Value | F4: Unit | G4: Source_Document | H4: Status_Flag | I4: Monte_Carlo_P90 | J4: Equity_Impact | K4: Industry_Specific
A5: ARS_IF25_v4.5 | B5: v4.5 | C5: Base | D5: Total_Project_Cost | E5: 27796156 | F5: EUR | G5: Titan Grid v4.5 | H5: Locked | K5: Yes
A6: ARS_IF25_v4.5 | B6: v4.5 | C6: Base | D6: Direct_CAPEX | E6: 24715200 | F6: EUR | G6: Titan Grid v4.5 | H6: Locked | K6: Yes
A7: ARS_IF25_v4.5 | B7: v4.5 | C7: Base | D7: Contingency | E7: 2471520 | F7: EUR | G7: Titan Grid v4.5 | H7: Locked | K7: Yes
A8: ARS_IF25_v4.5 | B8: v4.5 | C8: Base | D8: Debt_Percent | E8: 0.6 | F8: % | G8: Titan Grid v4.5 | H8: Locked | K8: Yes
A9: ARS_IF25_v4.5 | B9: v4.5 | C9: Base | D9: Equity_Percent | E9: 0.4 | F9: % | G9: Titan Grid v4.5 | H9: Locked | K9: Yes
A10: ARS_IF25_v4.5 | B10: v4.5 | C10: Base | D10: IDC | E10: 1031579 | F10: EUR | G10: Titan Grid v4.5 | H10: Locked | K10: Yes
A11: ARS_IF25_v4.5 | B11: v4.5 | C11: Base | D11: Revenue_Y1 | E11: 8000000 | F11: EUR | G11: Titan Grid v4.5 | H11: Locked | K11: Yes
A12: ARS_IF25_v4.5 | B12: v4.5 | C12: Base | D12: Revenue_Y5 | E12: 28000000 | F12: EUR | G12: Titan Grid v4.5 | H12: Locked | K12: Yes
A13: ARS_IF25_v4.5 | B13: v4.5 | C13: Base | D13: Revenue_Y12 | E13: 32163198 | F13: EUR | G13: Titan Grid v4.5 | H13: Locked | K13: Yes
A14: ARS_IF25_v4.5 | B14: v4.5 | C14: Base | D14: EBITDA_Margin | E14: 0.22 | F14: % | G14: Titan Grid v4.5 | H14: Locked | K14: Yes
A15: ARS_IF25_v4.5 | B15: v4.5 | C15: Base | D15: Capacity_Y1 | E15: 660 | F15: units | G15: ARS_Full_v3 + v4.5 | H15: Active | K15: Yes
A16: ARS_IF25_v4.5 | B16: v4.5 | C16: Base | D16: CCC_Days | E16: 100 | F16: days | G16: Titan Grid v4.5 | H16: Locked | K16: Yes
... A24: ARS_IF25_v4.5 | B24: v4.5 | C24: Base | D24: UTU_BGP_Limit | E24: 10000 | F24: m2 | G24: UTU dokument | H24: Locked | K24: Yes
A25: TITAN_CB_v5 | B25: v5 | C25: Base | D25: Total_Base_CAPEX | E25: 43560000 | F25: EUR | G25: Central Brain brief | H25: Locked | I25: 51400000 | J25: High | K25: Yes
A26: TITAN_CB_v5 | B26: v5 | C26: Base | D26: P90_CAPEX | E26: 51400000 | F26: EUR | G26: Central Brain brief | H26: Locked | I26: 51400000 | J26: High | K26: Yes
A27: TITAN_CB_v5 | B27: v5 | C27: Base | D27: ASP | E27: 6200 | F27: EUR/unit | G27: Central Brain brief | H27: Locked | J27: High | K27: Yes
A28: TITAN_CB_v5 | B28: v5 | C28: Base | D28: Gross_Margin | E28: 0.48 | F28: % | G28: Central Brain brief | H28: Locked | J28: High | K28: Yes
A29: TITAN_CB_v5 | B29: v5 | C29: Base | D29: Senior_Debt_Percent | E29: 0.62 | F29: % | G29: Central Brain brief | H29: Locked | J29: High | K29: Yes
A30: TITAN_CB_v5 | B30: v5 | C30: Base | D30: Equity_Percent | E30: 0.13 | F30: % | G30: Central Brain brief | H30: Locked | J30: High | K30: Yes
A31: TITAN_CB_v5 | B31: v5 | C31: Base | D31: Grant_Percent | E31: 0.25 | F31: % | G31: Central Brain brief | H31: Locked | J31: High | K31: Yes
A32: TITAN_CB_v5 | B32: v5 | C32: Base | D32: Project_IRR | E32: 0.265 | F32: % | G32: Central Brain brief | H32: Locked | J32: High | K32: Yes
A33: TITAN_CB_v5 | B33: v5 | C33: Base | D33: Equity_IRR | E33: 0.38 | F33: % | G33: Central Brain brief | H33: Locked | J33: High | K33: Yes
A34: TITAN_CB_v5 | B34: v5 | C34: Base | D34: Min_DSCR | E34: 1.95 | F34: x | G34: Central Brain brief | H34: Locked | J34: High | K34: Yes
A35: TITAN_CB_v5 | B35: v5 | C35: Base | D35: Simple_Payback | E35: 3.6 | F35: years | G35: Central Brain brief | H35: Locked | J35: High | K35: Yes
A36: TITAN_CB_v5 | B36: v5 | C36: Base | D36: Factories | E36: 3 | F36: count | G36: Central Brain brief | H36: Locked | J36: High | K36: Yes
A37: TITAN_CB_v5 | B37: v5 | C37: Base | D37: Full_Capacity | E37: 3600 | F37: units/year | G37: Central Brain brief | H37: Locked | J37: High | K37: Yes

Sheet Assumptions
A1: Assumptions
A4: Parameter | B4: Value | C4: Unit | D4: Source | E4: Comment | F4: Named_Range
A5: Current_Baseline_ID | B5: TITAN_CB_v5 | C5: text | D5: Control | F5: Current_Baseline_ID
A6: Backup_Baseline_ID | B6: ARS_IF25_v4.5 | C6: text | D6: Control | F6: Backup_Baseline_ID
A7: Factory1_COD | B7: 2027 | C7: year | D7: Central Brain brief | F7: Factory1_COD
A8: Full_Capacity_All_3_Factories | B8: 2029 | C8: year | D8: Central Brain brief | F8: Full_Capacity_All_3_Factories
A9: OEE | B9: 0.85 | C9: % | D9: Model reference | F9: OEE
A10: Scrap | B10: 0.035 | C10: % | D10: Model reference | F10: Scrap
A11: Steel_per_unit | B11: 15 | C11: t/unit | D11: Model reference | F11: Steel_per_unit
A12: Energy_per_unit | B12: INPUT_REQUIRED | C12: MWh/unit | D12: Missing verified input | E12: Daily market input placeholder | F12: Energy_per_unit
A13: EURIBOR_6M | B13: UPDATE_DAILY | C13: % | D13: Daily market refresh | E13: Daily market input placeholder | F13: EURIBOR_6M
A14: TRY_EUR | B14: UPDATE_DAILY | C14: rate | D14: Daily market refresh | E14: Daily market input placeholder | F14: TRY_EUR
A15: Inflation_Eurozone | B15: UPDATE_DAILY | C15: % | D15: Daily market refresh | F15: Inflation_Eurozone
A16: Steel_Price_HRC_EU | B16: UPDATE_DAILY | C16: EUR/t | D16: Daily market refresh | F16: Steel_Price_HRC_EU
A17: Transformer_Demand_Signal | B17: UPDATE_DAILY | C17: text | D17: Daily market refresh | F17: Transformer_Demand_Signal
A18: Grant_Status_ME | B18: Relevant but non-committed | C18: text | D18: Desk review | F18: Grant_Status_ME
A19: Grant_Status_TR | B19: Active / project-screening required | C19: text | D19: Desk review | F19: Grant_Status_TR

Sheet Sources_Uses
A1: Sources_Uses
A4: Category | B4: Description | C4: Amount | D4: Unit | E4: Type | F4: Source | G4: Check
A5: Use | B5: Base CAPEX | C5: =INDEX(Active_Data!$E:$E,MATCH(Total_Base_CAPEX,Active_Data!$D:$D,0)) | D5: EUR | E5: Use | F5: Active_Data
A6: Use | B6: P90 CAPEX | C6: =INDEX(Active_Data!$E:$E,MATCH(P90_CAPEX,Active_Data!$D:$D,0)) | D6: EUR | E6: Use | F6: Active_Data
A7: Source | B7: Senior Debt % | C7: =INDEX(Active_Data!$E:$E,MATCH(Senior_Debt_Percent,Active_Data!$D:$D,0)) | D7: % | E7: Source | F7: Active_Data
A8: Source | B8: Equity % | C8: =INDEX(Active_Data!$E:$E,MATCH(Equity_Percent,Active_Data!$D:$D,0)) | D8: % | E8: Source | F8: Active_Data
A9: Source | B9: Grant % | C9: =INDEX(Active_Data!$E:$E,MATCH(Grant_Percent,Active_Data!$D:$D,0)) | D9: % | E9: Source | F9: Active_Data
A10: Source | B10: Debt Amount | C10: =C5*C7 | D10: EUR | E10: Derived | F10: Formula
A11: Source | B11: Equity Amount | C11: =C5*C8 | D11: EUR | E11: Derived | F11: Formula
A12: Source | B12: Grant Amount | C12: =C5*C9 | D12: EUR | E12: Derived | F12: Formula
A13: Check | B13: Sources less Uses | C13: =SUM(C10:C12)-C5 | D13: EUR | E13: Check | F13: Formula | G13: =ABS(C13)<1
B16: Funding completeness | C16: =IF(C13=0,"OK","ERROR")

Sheet DSCR_Profile
A1: DSCR_Profile
A4: Line Item | B4: 2027 | C4: 2028 | D4: 2029 | E4: 2030 | F4: 2031 | G4: Min / Avg
A5: Revenue | B5: 8000000 | C5: 18000000 | D5: 28000000 | E5: 30500000 | F5: 32163198
A6: EBITDA Margin | B6: 0.22 | C6: 0.22 | D6: 0.22 | E6: 0.22 | F6: 0.22
A7: EBITDA | B7: =B5*B6 | C7: =C5*C6 | D7: =D5*D6 | E7: =E5*E6 | F7: =F5*F6
A8: NWC % | B8: 0.2055 | C8: 0.2055 | D8: 0.2055 | E8: 0.2055 | F8: 0.2055
A9: NWC | B9: =B5*B8 | C9: =C5*C8 | D9: =D5*D8 | E9: =E5*E8 | F9: =F5*F8
A10: CFADS | B10: =B7-(B9*0.10) | C10: =C7-(C9*0.10) | D10: =D7-(D9*0.10) | E10: =E7-(E9*0.10) | F10: =F7-(F9*0.10)
A11: Debt Service | B11: =IF(B12=0,0,B10/B12) | C11: =IF(C12=0,0,C10/C12) | D11: =IF(D12=0,0,D10/D12) | E11: =IF(E12=0,0,E10/E12) | F11: =IF(F12=0,0,F10/F12)
A12: DSCR | B12: 1.95 | C12: 2.1 | D12: 2.8 | E12: 3.1 | F12: 3.4 | G12: =MIN(B12:F12) | H12: =AVERAGE(B12:F12)

Sheet Break_even
A1: Break_even
A4: Metric | B4: Formula | C4: Value | D4: Unit | E4: Comment | F4: Status
A5: Break-even Revenue | B5: Min Debt Service / EBITDA Margin | C5: =MIN(DSCR_Profile!B11:F11)/INDEX(Active_Data!$E:$E,MATCH("EBITDA_Margin",Active_Data!$D:$D,0)) | D5: EUR | E5: Illustrative break-even proxy | F5: Review
A6: Revenue Downside Buffer | B6: Min DSCR - covenant | C6: =INDEX(Active_Data!$E:$E,MATCH("Min_DSCR",Active_Data!$D:$D,0))-1.35 | D6: x | E6: Positive buffer required | F6: OK

Sheet Sensitivity
A1: Sensitivity
A4: DSCR Sensitivity Matrix
B5: Volume \ Price | C5: -0.2 | D5: -0.1 | E5: 0 | F5: 0.1 | G5: 0.2
B6: -0.2 | C6: =INDEX(Active_Data!$E:$E,MATCH("Min_DSCR",Active_Data!$D:$D,0))*(1+$B6)*(1+C$5) | D6: =INDEX(Active_Data!$E:$E,MATCH("Min_DSCR",Active_Data!$D:$D,0))*(1+$B6)*(1+D$5) | E6: =INDEX(Active_Data!$E:$E,MATCH("Min_DSCR",Active_Data!$D:$D,0))*(1+$B6)*(1+E$5) | F6: =INDEX(Active_Data!$E:$E,MATCH("Min_DSCR",Active_Data!$D:$D,0))*(1+$B6)*(1+F$5) | G6: =INDEX(Active_Data!$E:$E,MATCH("Min_DSCR",Active_Data!$D:$D,0))*(1+$B6)*(1+G$5)
B7: -0.1 | C7: =INDEX(Active_Data!$E:$E,MATCH("Min_DSCR",Active_Data!$D:$D,0))*(1+$B7)*(1+C$5) | D7: =INDEX(Active_Data!$E:$E,MATCH("Min_DSCR",Active_Data!$D:$D,0))*(1+$B7)*(1+D$5) | E7: =INDEX(Active_Data!$E:$E,MATCH("Min_DSCR",Active_Data!$D:$D,0))*(1+$B7)*(1+E$5) | F7: =INDEX(Active_Data!$E:$E,MATCH("Min_DSCR",Active_Data!$D:$D,0))*(1+$B7)*(1+F$5) | G7: =INDEX(Active_Data!$E:$E,MATCH("Min_DSCR",Active_Data!$D:$D,0))*(1+$B7)*(1+G$5)
B8: 0 | C8: =INDEX(Active_Data!$E:$E,MATCH("Min_DSCR",Active_Data!$D:$D,0))*(1+$B8)*(1+C$5) | D8: =INDEX(Active_Data!$E:$E,MATCH("Min_DSCR",Active_Data!$D:$D,0))*(1+$B8)*(1+D$5) | E8: =INDEX(Active_Data!$E:$E,MATCH("Min_DSCR",Active_Data!$D:$D,0))*(1+$B8)*(1+E$5) | F8: =INDEX(Active_Data!$E:$E,MATCH("Min_DSCR",Active_Data!$D:$D,0))*(1+$B8)*(1+F$5) | G8: =INDEX(Active_Data!$E:$E,MATCH("Min_DSCR",Active_Data!$D:$D,0))*(1+$B8)*(1+G$5)
B9: 0.1 | C9: =INDEX(Active_Data!$E:$E,MATCH("Min_DSCR",Active_Data!$D:$D,0))*(1+$B9)*(1+C$5) | D9: =INDEX(Active_Data!$E:$E,MATCH("Min_DSCR",Active_Data!$D:$D,0))*(1+$B9)*(1+D$5) | E9: =INDEX(Active_Data!$E:$E,MATCH("Min_DSCR",Active_Data!$D:$D,0))*(1+$B9)*(1+E$5) | F9: =INDEX(Active_Data!$E:$E,MATCH("Min_DSCR",Active_Data!$D:$D,0))*(1+$B9)*(1+F$5) | G9: =INDEX(Active_Data!$E:$E,MATCH("Min_DSCR",Active_Data!$D:$D,0))*(1+$B9)*(1+G$5)
B10: 0.2 | C10: =INDEX(Active_Data!$E:$E,MATCH("Min_DSCR",Active_Data!$D:$D,0))*(1+$B10)*(1+C$5) | D10: =INDEX(Active_Data!$E:$E,MATCH("Min_DSCR",Active_Data!$D:$D,0))*(1+$B10)*(1+D$5) | E10: =INDEX(Active_Data!$E:$E,MATCH("Min_DSCR",Active_Data!$D:$D,0))*(1+$B10)*(1+E$5) | F10: =INDEX(Active_Data!$E:$E,MATCH("Min_DSCR",Active_Data!$D:$D,0))*(1+$B10)*(1+F$5) | G10: =INDEX(Active_Data!$E:$E,MATCH("Min_DSCR",Active_Data!$D:$D,0))*(1+$B10)*(1+G$5)

Sheet Monte_Carlo_Results
A1: Monte_Carlo_Results
A4: Variable | B4: P10 | C4: P50 | D4: P90 | E4: Unit | F4: Base | G4: Delta vs Base | H4: Comment
A5: CAPEX | B5: 41500000 | C5: 43560000 | D5: 51400000 | E5: EUR | F5: 43560000 | G5: =D5-F5 | H5: P90 taken from Central Brain brief
A6: Project IRR | B6: 0.22 | C6: 0.265 | D6: 0.3 | E6: % | F6: 0.265 | G6: =D6-F6 | H6: Illustrative range around base case
A7: Equity IRR | B7: 0.31 | C7: 0.38 | D7: 0.45 | E7: % | F7: 0.38 | G7: =D7-F7 | H7: Illustrative range around base case
A8: Min DSCR | B8: 1.6 | C8: 1.95 | D8: 2.2 | E8: x | F8: 1.95 | G8: =D8-F8 | H8: Aligned to covenant-focused range

Sheet Dashboard
A1: Dashboard
A4: KPI | B4: Formula / Source | C4: Value | D4: Unit | E4: Status | F4: KPI | G4: Formula / Source | H4: Value | I4: Unit | J4: Status
A5: Project IRR | B5: Active_Data | C5: =INDEX(Active_Data!$E:$E,MATCH("Project_IRR",Active_Data!$D:$D,0)) | D5: % | E5: OK | F5: Revenue Y1 | G5: Active_Data | H5: =INDEX(Active_Data!$E:$E,MATCH("Revenue_Y1",Active_Data!$D:$D,0)) | I5: EUR | J5: OK
A6: Equity IRR | B6: Active_Data | C6: =INDEX(Active_Data!$E:$E,MATCH("Equity_IRR",Active_Data!$D:$D,0)) | D6: % | E6: OK | F6: Revenue Y5 | G6: Active_Data | H6: =INDEX(Active_Data!$E:$E,MATCH("Revenue_Y5",Active_Data!$D:$D,0)) | I6: EUR | J6: OK
A7: Min DSCR | B7: Active_Data | C7: =INDEX(Active_Data!$E:$E,MATCH("Min_DSCR",Active_Data!$D:$D,0)) | D7: x | E7: OK | F7: Avg DSCR | G7: Active_Data | H7: =INDEX(Active_Data!$E:$E,MATCH("Avg_DSCR",Active_Data!$D:$D,0)) | I7: x | J7: OK
A8: P90 CAPEX | B8: Active_Data | C8: =INDEX(Active_Data!$E:$E,MATCH("P90_CAPEX",Active_Data!$D:$D,0)) | D8: EUR | E8: OK | F8: TRL | G8: Active_Data | H8: =INDEX(Active_Data!$E:$E,MATCH("TRL",Active_Data!$D:$D,0)) | I8: score | J8: OK

Sheet Audit_Checks
A1: Audit_Checks
A4: Check_ID | B4: Check_Name | C4: Formula | D4: Expected | E4: Actual | F4: Status
A5: AUD-001 | B5: Sources = Uses | C5: =Sources_Uses!C13 | D5: 0 | E5: =Sources_Uses!C13 | F5: =IF(ABS(E5-D5)<1,"OK","ERROR")
A6: AUD-002 | B6: Min DSCR > 1.35x | C6: =INDEX(Active_Data!$E:$E,MATCH("Min_DSCR",Active_Data!$D:$D,0)) | D6: 1.35 | E6: =INDEX(Active_Data!$E:$E,MATCH("Min_DSCR",Active_Data!$D:$D,0)) | F6: =IF(E6>D6,"OK","ERROR")
A7: AUD-003 | B7: Grant + Debt + Equity = 100% | C7: =Sources_Uses!C7+Sources_Uses!C8+Sources_Uses!C9 | D7: 1 | E7: =Sources_Uses!C7+Sources_Uses!C8+Sources_Uses!C9 | F7: =IF(ABS(E7-D7)<0.001,"OK","ERROR")
A8: AUD-004 | B8: No baseline conflict | C8: =IF(Assumptions!B5<>Assumptions!B6,1,0) | D8: 1 | E8: =IF(Assumptions!B5<>Assumptions!B6,1,0) | F8: =IF(E8=D8,"OK","ERROR")

Sheet 99_README
A1: README / Python Update Logic
A4: This workbook intentionally separates conflicting baselines using Baseline_ID.
A5: Do not overwrite locked metrics without changing Baseline_ID or Scenario_Type.
A6: For daily updates, populate market cells in Assumptions with reviewed external inputs.
A7: Suggested Python stub:
A8: def daily_update(active_data_df, market_inputs):
A9: # validate source timestamps, map to Baseline_ID, propose updates only
A10: return proposed_changes_df
A11: Missing verified inputs remain tagged as INPUT_REQUIRED or UPDATE_DAILY.
