Workbook

Sheet Summary_Dashboard
A1: Titan Grid - Fully Linked Project Finance Model v3.4
A3: Metric | B3: Value | C3: Source / Comment
A4: Total Project Cost | B4: =Sources_Assumptions!C4 -> 27796156 | C4: Locked v4.5
A5: Direct CAPEX | B5: =Sources_Assumptions!C5 -> 24715200 | C5: Locked v4.5
A6: Contingency | B6: =Sources_Assumptions!C6 -> 2471520 | C6: Locked v4.5
A7: Escalation | B7: =Sources_Assumptions!C7 -> 609436 | C7: Locked v4.5
A8: Debt | B8: =Sources_Assumptions!C8 -> 16677694 | C8: Locked v4.5
A9: Equity | B9: =Sources_Assumptions!C9 -> 11118462 | C9: Locked v4.5
A10: IDC | B10: =Sources_Assumptions!C10 -> 1031579 | C10: Locked v4.5
A11: Revenue Year 1 | B11: =Revenue_Model!C4 -> 8000000 | C11: Scenario-linked
A12: Revenue Year 5 | B12: =Revenue_Model!C8 -> 28000000 | C12: Scenario-linked
A13: Revenue Year 12 | B13: =Revenue_Model!C15 -> 32163198 | C13: Scenario-linked
A14: Steady EBITDA Margin | B14: =IF(Scenario_Manager!B8="Base",Sources_Assumptions!C17,Sources_Assumptions!C40) -> 0.22 | C14: Scenario-linked
A15: Net Working Capital Year 5 | B15: =Working_Capital!H8 -> 5039876.7 | C15: Scenario-linked
A16: Target NWC Y5 (Locked) | B16: =Sources_Assumptions!C19 -> 5753425 | C16: Locked v4.5
A17: Base DSCR Target | B17: =Sources_Assumptions!C24 -> 1.5 | C17: Assumption
A18: Average Model DSCR | B18: =AVERAGEIF(Debt_Schedule!I4:I15,">0") -> 1.4709035 | C18: Calculated
A19: Minimum Model DSCR | B19: =MIN(Debt_Schedule!I4:INDEX(Debt_Schedule!I:I,Sources_Assumptions!C22+3)) -> 1.1866956 | C19: Calculated
A20: Debt Capacity | B20: =Debt_Sizing!H4 -> 29150219 | C20: Calculated
A21: Sizing Headroom / (Shortfall) | B21: =Debt_Sizing!H9 -> 12472525 | C21: Calculated
A22: Project IRR | B22: =IRR_Payback!D4 -> 0.15048252 | C22: Calculated
A23: Funding Gap / (Surplus) | B23: =Sources_Uses!E8 -> 1031579 | C23: Calculated

Sheet Sources_Uses
A1: Sources & Uses
A3: Uses | B3: EUR | D3: Sources | E3: EUR
A4: Direct CAPEX | B4: =Sources_Assumptions!C5 -> 24715200 | D4: Debt | E4: =Sources_Assumptions!C8 -> 16677694
A5: Contingency | B5: =Sources_Assumptions!C6 -> 2471520 | D5: Equity | E5: =Sources_Assumptions!C9 -> 11118462
A6: Escalation | B6: =Sources_Assumptions!C7 -> 609436 | D6: Total Sources | E6: =SUM(E4:E5) -> 27796156
A7: IDC | B7: =Sources_Assumptions!C10 -> 1031579
A8: Total Uses | B8: =SUM(B4:B7) -> 28827735 | D8: Funding Gap / (Surplus) | E8: =B8-E6 -> 1031579

Sheet Sources_Assumptions
A1: Titan Grid Project Brain v2.0 - v4.5 locked inputs
A3: Category | B3: Item | C3: Value | D3: Unit | E3: Note
A4: Locked v4.5 | B4: Total Project Cost | C4: 27796156 | D4: EUR | E4: Locked input
A5: Locked v4.5 | B5: Direct CAPEX | C5: 24715200 | D5: EUR | E5: Locked input
A6: Locked v4.5 | B6: Contingency | C6: 2471520 | D6: EUR | E6: Locked input
A7: Locked v4.5 | B7: Escalation | C7: 609436 | D7: EUR | E7: Locked input
A8: Locked v4.5 | B8: Debt | C8: 16677694 | D8: EUR | E8: Locked input
A9: Locked v4.5 | B9: Equity | C9: 11118462 | D9: EUR | E9: Locked input
A10: Locked v4.5 | B10: Total IDC | C10: 1031579 | D10: EUR | E10: Locked input
A11: Locked v4.5 | B11: Average DSCR | C11: 3.07 | D11: x | E11: Locked reference metric
A12: Locked v4.5 | B12: Minimum DSCR | C12: 1.68 | D12: x | E12: Locked reference metric
A13: Locked v4.5 | B13: Minimum DSCR Year | C13: 2 | D13: Year | E13: Locked reference metric
A14: Locked v4.5 | B14: Revenue Year 1 | C14: 8000000 | D14: EUR | E14: Locked input
A15: Locked v4.5 | B15: Revenue Year 5 | C15: 28000000 | D15: EUR | E15: Locked input
... A41: TO CONFIRM | B41: Downside CCC | C41: 110 | D41: days | E41: EBRD-style downside

Sheet Scenario_Manager
A1: Scenario Manager
A3: Driver | B3: Base | C3: Downside
A4: Revenue Multiplier | B4: 1 | C4: =Sources_Assumptions!C39 -> 0.85
A5: Steady EBITDA Margin | B5: =Sources_Assumptions!C17 -> 0.22 | C5: =Sources_Assumptions!C40 -> 0.18
A6: CCC Days | B6: =Sources_Assumptions!C18 -> 100 | C6: =Sources_Assumptions!C41 -> 110
A8: Selected Scenario | B8: Base
A10: Active Revenue Multiplier | B10: =IF(B8="Base",B4,C4) -> 1
A11: Active Steady EBITDA Margin | B11: =IF(B8="Base",B5,C5) -> 0.22
A12: Active CCC Days | B12: =IF(B8="Base",B6,C6) -> 100

Sheet Revenue_Model
A1: Revenue Model
A3: Year | B3: Base Revenue | C3: Scenario Revenue | D3: Base EBITDA Margin | E3: Scenario EBITDA Margin | F3: EBITDA
A4: 1 | B4: =Sources_Assumptions!C14 -> 8000000 | C4: =B4*Scenario_Manager!B10 -> 8000000 | D4: =Sources_Assumptions!C32 -> 0.12 | E4: =D4 -> 0.12 | F4: =C4*E4 -> 960000
A5: 2 | B5: =Sources_Assumptions!C29 -> 13000000 | C5: =B5*Scenario_Manager!B10 -> 13000000 | D5: =Sources_Assumptions!C33 -> 0.16 | E5: =D5 -> 0.16 | F5: =C5*E5 -> 2080000
A6: 3 | B6: =Sources_Assumptions!C30 -> 18000000 | C6: =B6*Scenario_Manager!B10 -> 18000000 | D6: =Sources_Assumptions!C34 -> 0.18 | E6: =D6 -> 0.18 | F6: =C6*E6 -> 3240000
A7: 4 | B7: =Sources_Assumptions!C31 -> 23000000 | C7: =B7*Scenario_Manager!B10 -> 23000000 | D7: =Sources_Assumptions!C35 -> 0.2 | E7: =D7 -> 0.2 | F7: =C7*E7 -> 4600000
A8: 5 | B8: =Sources_Assumptions!C15 -> 28000000 | C8: =B8*Scenario_Manager!B10 -> 28000000 | D8: =Sources_Assumptions!C17 -> 0.22 | E8: =IF(Scenario_Manager!B8="Base",D8,Scenario_Manager!C5) -> 0.22 | F8: =C8*E8 -> 6160000
A9: 6 | B9: =B8*1.02 -> 28560000 | C9: =B9*Scenario_Manager!B10 -> 28560000 | D9: =Sources_Assumptions!C17 -> 0.22 | E9: =IF(Scenario_Manager!B8="Base",D9,Scenario_Manager!C5) -> 0.22 | F9: =C9*E9 -> 6283200
A10: 7 | B10: =B9*1.02 -> 29131200 | C10: =B10*Scenario_Manager!B10 -> 29131200 | D10: =Sources_Assumptions!C17 -> 0.22 | E10: =IF(Scenario_Manager!B8="Base",D10,Scenario_Manager!C5) -> 0.22 | F10: =C10*E10 -> 6408864
A11: 8 | B11: =B10*1.02 -> 29713824 | C11: =B11*Scenario_Manager!B10 -> 29713824 | D11: =Sources_Assumptions!C17 -> 0.22 | E11: =IF(Scenario_Manager!B8="Base",D11,Scenario_Manager!C5) -> 0.22 | F11: =C11*E11 -> 6537041.3
A12: 9 | B12: =B11*1.02 -> 30308100 | C12: =B12*Scenario_Manager!B10 -> 30308100 | D12: =Sources_Assumptions!C17 -> 0.22 | E12: =IF(Scenario_Manager!B8="Base",D12,Scenario_Manager!C5) -> 0.22 | F12: =C12*E12 -> 6667782.1
A13: 10 | B13: =B12*1.02 -> 30914262 | C13: =B13*Scenario_Manager!B10 -> 30914262 | D13: =Sources_Assumptions!C17 -> 0.22 | E13: =IF(Scenario_Manager!B8="Base",D13,Scenario_Manager!C5) -> 0.22 | F13: =C13*E13 -> 6801137.7
A14: 11 | B14: =B13*1.02 -> 31532548 | C14: =B14*Scenario_Manager!B10 -> 31532548 | D14: =Sources_Assumptions!C17 -> 0.22 | E14: =IF(Scenario_Manager!B8="Base",D14,Scenario_Manager!C5) -> 0.22 | F14: =C14*E14 -> 6937160.5
A15: 12 | B15: =Sources_Assumptions!C16 -> 32163198 | C15: =B15*Scenario_Manager!B10 -> 32163198 | D15: =Sources_Assumptions!C17 -> 0.22 | E15: =IF(Scenario_Manager!B8="Base",D15,Scenario_Manager!C5) -> 0.22 | F15: =C15*E15 -> 7075903.6

Sheet COGS_OPEX
A1: COGS & OPEX
A3: Year | B3: Revenue | C3: EBITDA Margin | D3: EBITDA | E3: OPEX | F3: COGS | G3: COGS % | H3: OPEX %
A4: 1 | B4: =Revenue_Model!C4 -> 8000000 | C4: =Revenue_Model!E4 -> 0.12 | D4: =Revenue_Model!F4 -> 960000 | E4: =1200000 -> 1200000 | F4: =B4-D4-E4 -> 5840000 | G4: =IFERROR(F4/B4,0) -> 0.73 | H4: =IFERROR(E4/B4,0) -> 0.15
A5: 2 | B5: =Revenue_Model!C5 -> 13000000 | C5: =Revenue_Model!E5 -> 0.16 | D5: =Revenue_Model!F5 -> 2080000 | E5: =1500000 -> 1500000 | F5: =B5-D5-E5 -> 9420000 | G5: =IFERROR(F5/B5,0) -> 0.72461538 | H5: =IFERROR(E5/B5,0) -> 0.11538462
A6: 3 | B6: =Revenue_Model!C6 -> 18000000 | C6: =Revenue_Model!E6 -> 0.18 | D6: =Revenue_Model!F6 -> 3240000 | E6: =1800000 -> 1800000 | F6: =B6-D6-E6 -> 12960000 | G6: =IFERROR(F6/B6,0) -> 0.72 | H6: =IFERROR(E6/B6,0) -> 0.1
A7: 4 | B7: =Revenue_Model!C7 -> 23000000 | C7: =Revenue_Model!E7 -> 0.2 | D7: =Revenue_Model!F7 -> 4600000 | E7: =2100000 -> 2100000 | F7: =B7-D7-E7 -> 16300000 | G7: =IFERROR(F7/B7,0) -> 0.70869565 | H7: =IFERROR(E7/B7,0) -> 0.091304348
A8: 5 | B8: =Revenue_Model!C8 -> 28000000 | C8: =Revenue_Model!E8 -> 0.22 | D8: =Revenue_Model!F8 -> 6160000 | E8: =2500000 -> 2500000 | F8: =B8-D8-E8 -> 19340000 | G8: =IFERROR(F8/B8,0) -> 0.69071429 | H8: =IFERROR(E8/B8,0) -> 0.089285714
A9: 6 | B9: =Revenue_Model!C9 -> 28560000 | C9: =Revenue_Model!E9 -> 0.22 | D9: =Revenue_Model!F9 -> 6283200 | E9: =E8*1.02 -> 2550000 | F9: =B9-D9-E9 -> 19726800 | G9: =IFERROR(F9/B9,0) -> 0.69071429 | H9: =IFERROR(E9/B9,0) -> 0.089285714
A10: 7 | B10: =Revenue_Model!C10 -> 29131200 | C10: =Revenue_Model!E10 -> 0.22 | D10: =Revenue_Model!F10 -> 6408864 | E10: =E9*1.02 -> 2601000 | F10: =B10-D10-E10 -> 20121336 | G10: =IFERROR(F10/B10,0) -> 0.69071429 | H10: =IFERROR(E10/B10,0) -> 0.089285714
A11: 8 | B11: =Revenue_Model!C11 -> 29713824 | C11: =Revenue_Model!E11 -> 0.22 | D11: =Revenue_Model!F11 -> 6537041.3 | E11: =E10*1.02 -> 2653020 | F11: =B11-D11-E11 -> 20523763 | G11: =IFERROR(F11/B11,0) -> 0.69071429 | H11: =IFERROR(E11/B11,0) -> 0.089285714
A12: 9 | B12: =Revenue_Model!C12 -> 30308100 | C12: =Revenue_Model!E12 -> 0.22 | D12: =Revenue_Model!F12 -> 6667782.1 | E12: =E11*1.02 -> 2706080.4 | F12: =B12-D12-E12 -> 20934238 | G12: =IFERROR(F12/B12,0) -> 0.69071429 | H12: =IFERROR(E12/B12,0) -> 0.089285714
A13: 10 | B13: =Revenue_Model!C13 -> 30914262 | C13: =Revenue_Model!E13 -> 0.22 | D13: =Revenue_Model!F13 -> 6801137.7 | E13: =E12*1.02 -> 2760202 | F13: =B13-D13-E13 -> 21352923 | G13: =IFERROR(F13/B13,0) -> 0.69071429 | H13: =IFERROR(E13/B13,0) -> 0.089285714
A14: 11 | B14: =Revenue_Model!C14 -> 31532548 | C14: =Revenue_Model!E14 -> 0.22 | D14: =Revenue_Model!F14 -> 6937160.5 | E14: =E13*1.02 -> 2815406 | F14: =B14-D14-E14 -> 21779981 | G14: =IFERROR(F14/B14,0) -> 0.69071429 | H14: =IFERROR(E14/B14,0) -> 0.089285714
A15: 12 | B15: =Revenue_Model!C15 -> 32163198 | C15: =Revenue_Model!E15 -> 0.22 | D15: =Revenue_Model!F15 -> 7075903.6 | E15: =E14*1.02 -> 2871714.2 | F15: =B15-D15-E15 -> 22215580 | G15: =IFERROR(F15/B15,0) -> 0.69071428 | H15: =IFERROR(E15/B15,0) -> 0.089285716

Sheet Working_Capital
A1: Working Capital
A3: Year | B3: Revenue | C3: COGS | D3: CCC Days | E3: AR | F3: Inventory | G3: AP | H3: Net Working Capital | I3: NWC % Revenue | J3: Delta NWC | K3: Check vs Y5 Locked
A4: 1 | B4: =COGS_OPEX!B4 -> 8000000 | C4: =COGS_OPEX!F4 -> 5840000 | D4: =Scenario_Manager!B12 -> 100 | E4: =B4*(D4*Sources_Assumptions!C36)/365 -> 1315068.5 | F4: =C4*(D4*Sources_Assumptions!C37)/365 -> 800000 | G4: =C4*(D4*Sources_Assumptions!C38)/365 -> 668000 | H4: =E4+F4-G4 -> 1447068.5 | I4: =IFERROR(H4/B4,0) -> 0.18088356 | J4: =H4 -> 1447068.5
A5: 2 | B5: =COGS_OPEX!B5 -> 13000000 | C5: =COGS_OPEX!F5 -> 9420000 | D5: =Scenario_Manager!B12 -> 100 | E5: =B5*(D5*Sources_Assumptions!C36)/365 -> 2136986.3 | F5: =C5*(D5*Sources_Assumptions!C37)/365 -> 1290411 | G5: =C5*(D5*Sources_Assumptions!C38)/365 -> 1077493.2 | H5: =E5+F5-G5 -> 2349904.1 | I5: =IFERROR(H5/B5,0) -> 0.18076185 | J5: =H5-H4 -> 902835.62
A6: 3 | B6: =COGS_OPEX!B6 -> 18000000 | C6: =COGS_OPEX!F6 -> 12960000 | D6: =Scenario_Manager!B12 -> 100 | E6: =B6*(D6*Sources_Assumptions!C36)/365 -> 2958904.1 | F6: =C6*(D6*Sources_Assumptions!C37)/365 -> 1775342.5 | G6: =C6*(D6*Sources_Assumptions!C38)/365 -> 1482411 | H6: =E6+F6-G6 -> 3251835.6 | I6: =IFERROR(H6/B6,0) -> 0.18065753 | J6: =H6-H5 -> 901931.51
A7: 4 | B7: =COGS_OPEX!B7 -> 23000000 | C7: =COGS_OPEX!F7 -> 16300000 | D7: =Scenario_Manager!B12 -> 100 | E7: =B7*(D7*Sources_Assumptions!C36)/365 -> 3780821.9 | F7: =C7*(D7*Sources_Assumptions!C37)/365 -> 2232876.7 | G7: =C7*(D7*Sources_Assumptions!C38)/365 -> 1864452.1 | H7: =E7+F7-G7 -> 4149246.6 | I7: =IFERROR(H7/B7,0) -> 0.18040203 | J7: =H7-H6 -> 897410.96
A8: 5 | B8: =COGS_OPEX!B8 -> 28000000 | C8: =COGS_OPEX!F8 -> 19340000 | D8: =Scenario_Manager!B12 -> 100 | E8: =B8*(D8*Sources_Assumptions!C36)/365 -> 4602739.7 | F8: =C8*(D8*Sources_Assumptions!C37)/365 -> 2649315.1 | G8: =C8*(D8*Sources_Assumptions!C38)/365 -> 2212178.1 | H8: =E8+F8-G8 -> 5039876.7 | I8: =IFERROR(H8/B8,0) -> 0.1799956 | J8: =H8-H7 -> 890630.14 | K8: =H8-Sources_Assumptions!C19 -> -713548.29
A9: 6 | B9: =COGS_OPEX!B9 -> 28560000 | C9: =COGS_OPEX!F9 -> 19726800 | D9: =Scenario_Manager!B12 -> 100 | E9: =B9*(D9*Sources_Assumptions!C36)/365 -> 4694794.5 | F9: =C9*(D9*Sources_Assumptions!C37)/365 -> 2702301.4 | G9: =C9*(D9*Sources_Assumptions!C38)/365 -> 2256421.6 | H9: =E9+F9-G9 -> 5140674.2 | I9: =IFERROR(H9/B9,0) -> 0.1799956 | J9: =H9-H8 -> 100797.53
A10: 7 | B10: =COGS_OPEX!B10 -> 29131200 | C10: =COGS_OPEX!F10 -> 20121336 | D10: =Scenario_Manager!B12 -> 100 | E10: =B10*(D10*Sources_Assumptions!C36)/365 -> 4788690.4 | F10: =C10*(D10*Sources_Assumptions!C37)/365 -> 2756347.4 | G10: =C10*(D10*Sources_Assumptions!C38)/365 -> 2301550.1 | H10: =E10+F10-G10 -> 5243487.7 | I10: =IFERROR(H10/B10,0) -> 0.1799956 | J10: =H10-H9 -> 102813.48
A11: 8 | B11: =COGS_OPEX!B11 -> 29713824 | C11: =COGS_OPEX!F11 -> 20523763 | D11: =Scenario_Manager!B12 -> 100 | E11: =B11*(D11*Sources_Assumptions!C36)/365 -> 4884464.2 | F11: =C11*(D11*Sources_Assumptions!C37)/365 -> 2811474.3 | G11: =C11*(D11*Sources_Assumptions!C38)/365 -> 2347581.1 | H11: =E11+F11-G11 -> 5348357.5 | I11: =IFERROR(H11/B11,0) -> 0.1799956 | J11: =H11-H10 -> 104869.75
A12: 9 | B12: =COGS_OPEX!B12 -> 30308100 | C12: =COGS_OPEX!F12 -> 20934238 | D12: =Scenario_Manager!B12 -> 100 | E12: =B12*(D12*Sources_Assumptions!C36)/365 -> 4982153.5 | F12: =C12*(D12*Sources_Assumptions!C37)/365 -> 2867703.8 | G12: =C12*(D12*Sources_Assumptions!C38)/365 -> 2394532.7 | H12: =E12+F12-G12 -> 5455324.6 | I12: =IFERROR(H12/B12,0) -> 0.1799956 | J12: =H12-H11 -> 106967.15
A13: 10 | B13: =COGS_OPEX!B13 -> 30914262 | C13: =COGS_OPEX!F13 -> 21352923 | D13: =Scenario_Manager!B12 -> 100 | E13: =B13*(D13*Sources_Assumptions!C36)/365 -> 5081796.6 | F13: =C13*(D13*Sources_Assumptions!C37)/365 -> 2925057.9 | G13: =C13*(D13*Sources_Assumptions!C38)/365 -> 2442423.4 | H13: =E13+F13-G13 -> 5564431.1 | I13: =IFERROR(H13/B13,0) -> 0.1799956 | J13: =H13-H12 -> 109106.49
A14: 11 | B14: =COGS_OPEX!B14 -> 31532548 | C14: =COGS_OPEX!F14 -> 21779981 | D14: =Scenario_Manager!B12 -> 100 | E14: =B14*(D14*Sources_Assumptions!C36)/365 -> 5183432.5 | F14: =C14*(D14*Sources_Assumptions!C37)/365 -> 2983559.1 | G14: =C14*(D14*Sources_Assumptions!C38)/365 -> 2491271.8 | H14: =E14+F14-G14 -> 5675719.8 | I14: =IFERROR(H14/B14,0) -> 0.1799956 | J14: =H14-H13 -> 111288.62
A15: 12 | B15: =COGS_OPEX!B15 -> 32163198 | C15: =COGS_OPEX!F15 -> 22215580 | D15: =Scenario_Manager!B12 -> 100 | E15: =B15*(D15*Sources_Assumptions!C36)/365 -> 5287101 | F15: =C15*(D15*Sources_Assumptions!C37)/365 -> 3043230.2 | G15: =C15*(D15*Sources_Assumptions!C38)/365 -> 2541097.2 | H15: =E15+F15-G15 -> 5789234 | I15: =IFERROR(H15/B15,0) -> 0.1799956 | J15: =H15-H14 -> 113514.27

Sheet CFADS
A1: CFADS
L2: Annual Depreciation | M2: =Sources_Assumptions!C4/15 -> 1853077.1
A3: Year | B3: Revenue | C3: EBITDA | D3: Depreciation | E3: EBIT | F3: Tax | G3: Delta NWC | H3: CFADS | I3: Reference Avg DSCR | J3: Reference Min DSCR
A4: 1 | B4: =COGS_OPEX!B4 -> 8000000 | C4: =COGS_OPEX!D4 -> 960000 | D4: =$M$2 -> 1853077.1 | E4: =C4-D4 -> -893077.07 | F4: =MAX(0,E4*Sources_Assumptions!C20) -> 0 | G4: =Working_Capital!J4 -> 1447068.5 | H4: =C4-F4-G4+D4 -> 1366008.6 | I4: =Sources_Assumptions!C11 -> 3.07 | J4: =Sources_Assumptions!C12 -> 1.68
A5: 2 | B5: =COGS_OPEX!B5 -> 13000000 | C5: =COGS_OPEX!D5 -> 2080000 | D5: =$M$2 -> 1853077.1 | E5: =C5-D5 -> 226922.93 | F5: =MAX(0,E5*Sources_Assumptions!C20) -> 20423.064 | G5: =Working_Capital!J5 -> 902835.62 | H5: =C5-F5-G5+D5 -> 3009818.4 | I5: =Sources_Assumptions!C11 -> 3.07 | J5: =Sources_Assumptions!C12 -> 1.68
A6: 3 | B6: =COGS_OPEX!B6 -> 18000000 | C6: =COGS_OPEX!D6 -> 3240000 | D6: =$M$2 -> 1853077.1 | E6: =C6-D6 -> 1386922.9 | F6: =MAX(0,E6*Sources_Assumptions!C20) -> 124823.06 | G6: =Working_Capital!J6 -> 901931.51 | H6: =C6-F6-G6+D6 -> 4066322.5 | I6: =Sources_Assumptions!C11 -> 3.07 | J6: =Sources_Assumptions!C12 -> 1.68
A7: 4 | B7: =COGS_OPEX!B7 -> 23000000 | C7: =COGS_OPEX!D7 -> 4600000 | D7: =$M$2 -> 1853077.1 | E7: =C7-D7 -> 2746922.9 | F7: =MAX(0,E7*Sources_Assumptions!C20) -> 247223.06 | G7: =Working_Capital!J7 -> 897410.96 | H7: =C7-F7-G7+D7 -> 5308443 | I7: =Sources_Assumptions!C11 -> 3.07 | J7: =Sources_Assumptions!C12 -> 1.68
A8: 5 | B8: =COGS_OPEX!B8 -> 28000000 | C8: =COGS_OPEX!D8 -> 6160000 | D8: =$M$2 -> 1853077.1 | E8: =C8-D8 -> 4306922.9 | F8: =MAX(0,E8*Sources_Assumptions!C20) -> 387623.06 | G8: =Working_Capital!J8 -> 890630.14 | H8: =C8-F8-G8+D8 -> 6734823.9 | I8: =Sources_Assumptions!C11 -> 3.07 | J8: =Sources_Assumptions!C12 -> 1.68
A9: 6 | B9: =COGS_OPEX!B9 -> 28560000 | C9: =COGS_OPEX!D9 -> 6283200 | D9: =$M$2 -> 1853077.1 | E9: =C9-D9 -> 4430122.9 | F9: =MAX(0,E9*Sources_Assumptions!C20) -> 398711.06 | G9: =Working_Capital!J9 -> 100797.53 | H9: =C9-F9-G9+D9 -> 7636768.5 | I9: =Sources_Assumptions!C11 -> 3.07 | J9: =Sources_Assumptions!C12 -> 1.68
A10: 7 | B10: =COGS_OPEX!B10 -> 29131200 | C10: =COGS_OPEX!D10 -> 6408864 | D10: =$M$2 -> 1853077.1 | E10: =C10-D10 -> 4555786.9 | F10: =MAX(0,E10*Sources_Assumptions!C20) -> 410020.82 | G10: =Working_Capital!J10 -> 102813.48 | H10: =C10-F10-G10+D10 -> 7749106.8 | I10: =Sources_Assumptions!C11 -> 3.07 | J10: =Sources_Assumptions!C12 -> 1.68
A11: 8 | B11: =COGS_OPEX!B11 -> 29713824 | C11: =COGS_OPEX!D11 -> 6537041.3 | D11: =$M$2 -> 1853077.1 | E11: =C11-D11 -> 4683964.2 | F11: =MAX(0,E11*Sources_Assumptions!C20) -> 421556.78 | G11: =Working_Capital!J11 -> 104869.75 | H11: =C11-F11-G11+D11 -> 7863691.8 | I11: =Sources_Assumptions!C11 -> 3.07 | J11: =Sources_Assumptions!C12 -> 1.68
A12: 9 | B12: =COGS_OPEX!B12 -> 30308100 | C12: =COGS_OPEX!D12 -> 6667782.1 | D12: =$M$2 -> 1853077.1 | E12: =C12-D12 -> 4814705 | F12: =MAX(0,E12*Sources_Assumptions!C20) -> 433323.45 | G12: =Working_Capital!J12 -> 106967.15 | H12: =C12-F12-G12+D12 -> 7980568.6 | I12: =Sources_Assumptions!C11 -> 3.07 | J12: =Sources_Assumptions!C12 -> 1.68
A13: 10 | B13: =COGS_OPEX!B13 -> 30914262 | C13: =COGS_OPEX!D13 -> 6801137.7 | D13: =$M$2 -> 1853077.1 | E13: =C13-D13 -> 4948060.7 | F13: =MAX(0,E13*Sources_Assumptions!C20) -> 445325.46 | G13: =Working_Capital!J13 -> 109106.49 | H13: =C13-F13-G13+D13 -> 8099782.9 | I13: =Sources_Assumptions!C11 -> 3.07 | J13: =Sources_Assumptions!C12 -> 1.68
A14: 11 | B14: =COGS_OPEX!B14 -> 31532548 | C14: =COGS_OPEX!D14 -> 6937160.5 | D14: =$M$2 -> 1853077.1 | E14: =C14-D14 -> 5084083.4 | F14: =MAX(0,E14*Sources_Assumptions!C20) -> 457567.51 | G14: =Working_Capital!J14 -> 111288.62 | H14: =C14-F14-G14+D14 -> 8221381.4 | I14: =Sources_Assumptions!C11 -> 3.07 | J14: =Sources_Assumptions!C12 -> 1.68
A15: 12 | B15: =COGS_OPEX!B15 -> 32163198 | C15: =COGS_OPEX!D15 -> 7075903.6 | D15: =$M$2 -> 1853077.1 | E15: =C15-D15 -> 5222826.5 | F15: =MAX(0,E15*Sources_Assumptions!C20) -> 470054.38 | G15: =Working_Capital!J15 -> 113514.27 | H15: =C15-F15-G15+D15 -> 8345412 | I15: =Sources_Assumptions!C11 -> 3.07 | J15: =Sources_Assumptions!C12 -> 1.68

Sheet Debt_Sizing
A1: Debt Sizing
A3: Year | B3: CFADS | C3: Target DSCR | D3: Max Debt Service | E3: Discount Rate | F3: PV Factor | G3: PV of Max Debt Service | H3: Total Debt Capacity
A4: 1 | B4: =CFADS!H4 -> 1366008.6 | C4: =Sources_Assumptions!C24 -> 1.5 | D4: =IFERROR(B4/C4,0) -> 910672.38 | E4: =Sources_Assumptions!C28 -> 0.08 | F4: =1/(1+E4)^A4 -> 0.92592593 | G4: =D4*F4 -> 843215.17 | H4: =SUM(G4:G15) -> 29150219
A5: 2 | B5: =CFADS!H5 -> 3009818.4 | C5: =Sources_Assumptions!C24 -> 1.5 | D5: =IFERROR(B5/C5,0) -> 2006545.6 | E5: =Sources_Assumptions!C28 -> 0.08 | F5: =1/(1+E5)^A5 -> 0.85733882 | G5: =D5*F5 -> 1720289.4
A6: 3 | B6: =CFADS!H6 -> 4066322.5 | C6: =Sources_Assumptions!C24 -> 1.5 | D6: =IFERROR(B6/C6,0) -> 2710881.7 | E6: =Sources_Assumptions!C28 -> 0.08 | F6: =1/(1+E6)^A6 -> 0.79383224 | G6: =D6*F6 -> 2151985.3 | H6: Locked Debt
A7: 4 | B7: =CFADS!H7 -> 5308443 | C7: =Sources_Assumptions!C24 -> 1.5 | D7: =IFERROR(B7/C7,0) -> 3538962 | E7: =Sources_Assumptions!C28 -> 0.08 | F7: =1/(1+E7)^A7 -> 0.73502985 | G7: =D7*F7 -> 2601242.7 | H7: =Sources_Assumptions!C8 -> 16677694
A8: 5 | B8: =CFADS!H8 -> 6734823.9 | C8: =Sources_Assumptions!C24 -> 1.5 | D8: =IFERROR(B8/C8,0) -> 4489882.6 | E8: =Sources_Assumptions!C28 -> 0.08 | F8: =1/(1+E8)^A8 -> 0.6805832 | G8: =D8*F8 -> 3055738.6 | H8: Sizing Headroom / (Shortfall)
A9: 6 | B9: =CFADS!H9 -> 7636768.5 | C9: =Sources_Assumptions!C24 -> 1.5 | D9: =IFERROR(B9/C9,0) -> 5091179 | E9: =Sources_Assumptions!C28 -> 0.08 | F9: =1/(1+E9)^A9 -> 0.63016963 | G9: =D9*F9 -> 3208306.4 | H9: =H4-H7 -> 12472525
A10: 7 | B10: =CFADS!H10 -> 7749106.8 | C10: =Sources_Assumptions!C24 -> 1.5 | D10: =IFERROR(B10/C10,0) -> 5166071.2 | E10: =Sources_Assumptions!C28 -> 0.08 | F10: =1/(1+E10)^A10 -> 0.5834904 | G10: =D10*F10 -> 3014352.9
A11: 8 | B11: =CFADS!H11 -> 7863691.8 | C11: =Sources_Assumptions!C24 -> 1.5 | D11: =IFERROR(B11/C11,0) -> 5242461.2 | E11: =Sources_Assumptions!C28 -> 0.08 | F11: =1/(1+E11)^A11 -> 0.54026888 | G11: =D11*F11 -> 2832338.7
A12: 9 | B12: =CFADS!H12 -> 7980568.6 | C12: =Sources_Assumptions!C24 -> 1.5 | D12: =IFERROR(B12/C12,0) -> 5320379 | E12: =Sources_Assumptions!C28 -> 0.08 | F12: =1/(1+E12)^A12 -> 0.50024897 | G12: =D12*F12 -> 2661514.1
A13: 10 | B13: =CFADS!H13 -> 8099782.9 | C13: =Sources_Assumptions!C24 -> 1.5 | D13: =IFERROR(B13/C13,0) -> 5399855.2 | E13: =Sources_Assumptions!C28 -> 0.08 | F13: =1/(1+E13)^A13 -> 0.46319349 | G13: =D13*F13 -> 2501177.8
A14: 11 | B14: =CFADS!H14 -> 8221381.4 | C14: =Sources_Assumptions!C24 -> 1.5 | D14: =IFERROR(B14/C14,0) -> 5480921 | E14: =Sources_Assumptions!C28 -> 0.08 | F14: =1/(1+E14)^A14 -> 0.42888286 | G14: =D14*F14 -> 2350673.1
A15: 12 | B15: =CFADS!H15 -> 8345412 | C15: =Sources_Assumptions!C24 -> 1.5 | D15: =IFERROR(B15/C15,0) -> 5563608 | E15: =Sources_Assumptions!C28 -> 0.08 | F15: =1/(1+E15)^A15 -> 0.39711376 | G15: =D15*F15 -> 2209385.3

Sheet Debt_Schedule
A1: Debt Schedule
A3: Year | B3: Opening Debt | C3: Interest Rate | D3: Interest | E3: Scheduled Debt Service | F3: Principal | G3: Closing Debt | H3: CFADS | I3: DSCR | J3: IDC Added to Opening Debt?
A4: 1 | B4: =Sources_Assumptions!C8+Sources_Assumptions!C10 -> 17709273 | C4: =Sources_Assumptions!C21 -> 0.065 | D4: =B4*C4 -> 1151102.7 | E4: =IF(A4>Sources_Assumptions!C22,0,IF(A4<=Sources_Assumptions!C23,D4,MIN(Debt_Sizing!D4,B4+D4))) -> 1151102.7 | F4: =MAX(0,E4-D4) -> 0 | G4: =MAX(0,B4-F4) -> 17709273 | H4: =CFADS!H4 -> 1366008.6 | I4: =IF(E4=0,"",H4/E4) -> 1.1866956 | J4: "YES"
A5: 2 | B5: =G4 -> 17709273 | C5: =Sources_Assumptions!C21 -> 0.065 | D5: =B5*C5 -> 1151102.7 | E5: =IF(A5>Sources_Assumptions!C22,0,IF(A5<=Sources_Assumptions!C23,D5,MIN(Debt_Sizing!D5,B5+D5))) -> 2006545.6 | F5: =MAX(0,E5-D5) -> 855442.85 | G5: =MAX(0,B5-F5) -> 16853830 | H5: =CFADS!H5 -> 3009818.4 | I5: =IF(E5=0,"",H5/E5) -> 1.5 | J5: "NO"
A6: 3 | B6: =G5 -> 16853830 | C6: =Sources_Assumptions!C21 -> 0.065 | D6: =B6*C6 -> 1095499 | E6: =IF(A6>Sources_Assumptions!C22,0,IF(A6<=Sources_Assumptions!C23,D6,MIN(Debt_Sizing!D6,B6+D6))) -> 2710881.7 | F6: =MAX(0,E6-D6) -> 1615382.7 | G6: =MAX(0,B6-F6) -> 15238447 | H6: =CFADS!H6 -> 4066322.5 | I6: =IF(E6=0,"",H6/E6) -> 1.5 | J6: "NO"
A7: 4 | B7: =G6 -> 15238447 | C7: =Sources_Assumptions!C21 -> 0.065 | D7: =B7*C7 -> 990499.08 | E7: =IF(A7>Sources_Assumptions!C22,0,IF(A7<=Sources_Assumptions!C23,D7,MIN(Debt_Sizing!D7,B7+D7))) -> 3538962 | F7: =MAX(0,E7-D7) -> 2548462.9 | G7: =MAX(0,B7-F7) -> 12689985 | H7: =CFADS!H7 -> 5308443 | I7: =IF(E7=0,"",H7/E7) -> 1.5 | J7: "NO"
A8: 5 | B8: =G7 -> 12689985 | C8: =Sources_Assumptions!C21 -> 0.065 | D8: =B8*C8 -> 824848.99 | E8: =IF(A8>Sources_Assumptions!C22,0,IF(A8<=Sources_Assumptions!C23,D8,MIN(Debt_Sizing!D8,B8+D8))) -> 4489882.6 | F8: =MAX(0,E8-D8) -> 3665033.6 | G8: =MAX(0,B8-F8) -> 9024950.9 | H8: =CFADS!H8 -> 6734823.9 | I8: =IF(E8=0,"",H8/E8) -> 1.5 | J8: "NO"
A9: 6 | B9: =G8 -> 9024950.9 | C9: =Sources_Assumptions!C21 -> 0.065 | D9: =B9*C9 -> 586621.81 | E9: =IF(A9>Sources_Assumptions!C22,0,IF(A9<=Sources_Assumptions!C23,D9,MIN(Debt_Sizing!D9,B9+D9))) -> 5091179 | F9: =MAX(0,E9-D9) -> 4504557.2 | G9: =MAX(0,B9-F9) -> 4520393.8 | H9: =CFADS!H9 -> 7636768.5 | I9: =IF(E9=0,"",H9/E9) -> 1.5 | J9: "NO"
A10: 7 | B10: =G9 -> 4520393.8 | C10: =Sources_Assumptions!C21 -> 0.065 | D10: =B10*C10 -> 293825.59 | E10: =IF(A10>Sources_Assumptions!C22,0,IF(A10<=Sources_Assumptions!C23,D10,MIN(Debt_Sizing!D10,B10+D10))) -> 4814219.3 | F10: =MAX(0,E10-D10) -> 4520393.8 | G10: =MAX(0,B10-F10) -> 0 | H10: =CFADS!H10 -> 7749106.8 | I10: =IF(E10=0,"",H10/E10) -> 1.6096289 | J10: "NO"
A11: 8 | B11: =G10 -> 0 | C11: =Sources_Assumptions!C21 -> 0.065 | D11: =B11*C11 -> 0 | E11: =IF(A11>Sources_Assumptions!C22,0,IF(A11<=Sources_Assumptions!C23,D11,MIN(Debt_Sizing!D11,B11+D11))) -> 0 | F11: =MAX(0,E11-D11) -> 0 | G11: =MAX(0,B11-F11) -> 0 | H11: =CFADS!H11 -> 7863691.8 | I11: =IF(E11=0,"",H11/E11) | J11: "NO"
A12: 9 | B12: =G11 -> 0 | C12: =Sources_Assumptions!C21 -> 0.065 | D12: =B12*C12 -> 0 | E12: =IF(A12>Sources_Assumptions!C22,0,IF(A12<=Sources_Assumptions!C23,D12,MIN(Debt_Sizing!D12,B12+D12))) -> 0 | F12: =MAX(0,E12-D12) -> 0 | G12: =MAX(0,B12-F12) -> 0 | H12: =CFADS!H12 -> 7980568.6 | I12: =IF(E12=0,"",H12/E12) | J12: "NO"
A13: 10 | B13: =G12 -> 0 | C13: =Sources_Assumptions!C21 -> 0.065 | D13: =B13*C13 -> 0 | E13: =IF(A13>Sources_Assumptions!C22,0,IF(A13<=Sources_Assumptions!C23,D13,MIN(Debt_Sizing!D13,B13+D13))) -> 0 | F13: =MAX(0,E13-D13) -> 0 | G13: =MAX(0,B13-F13) -> 0 | H13: =CFADS!H13 -> 8099782.9 | I13: =IF(E13=0,"",H13/E13) | J13: "NO"
A14: 11 | B14: =G13 -> 0 | C14: =Sources_Assumptions!C21 -> 0.065 | D14: =B14*C14 -> 0 | E14: =IF(A14>Sources_Assumptions!C22,0,IF(A14<=Sources_Assumptions!C23,D14,MIN(Debt_Sizing!D14,B14+D14))) -> 0 | F14: =MAX(0,E14-D14) -> 0 | G14: =MAX(0,B14-F14) -> 0 | H14: =CFADS!H14 -> 8221381.4 | I14: =IF(E14=0,"",H14/E14) | J14: "NO"
A15: 12 | B15: =G14 -> 0 | C15: =Sources_Assumptions!C21 -> 0.065 | D15: =B15*C15 -> 0 | E15: =IF(A15>Sources_Assumptions!C22,0,IF(A15<=Sources_Assumptions!C23,D15,MIN(Debt_Sizing!D15,B15+D15))) -> 0 | F15: =MAX(0,E15-D15) -> 0 | G15: =MAX(0,B15-F15) -> 0 | H15: =CFADS!H15 -> 8345412 | I15: =IF(E15=0,"",H15/E15) | J15: "NO"

Sheet Covenant_Test
A1: Covenant Test
A3: Year | B3: DSCR | C3: DSCR Test | D3: Lock-up Test | E3: Opening Debt | F3: EBITDA | G3: Debt/EBITDA | H3: Debt/EBITDA Test | I3: PV of CFADS | J3: LLCR | K3: LLCR Test
A4: 1 | B4: =Debt_Schedule!I4 -> 1.1866956 | C4: =IF(B4="","",IF(B4>=Sources_Assumptions!C24,"OK","BREACH")) -> BREACH | D4: =IF(B4="","",IF(B4>=Sources_Assumptions!C25,"OK","LOCK-UP")) -> LOCK-UP | E4: =Debt_Schedule!B4 -> 17709273 | F4: =CFADS!C4 -> 960000 | G4: =IFERROR(E4/F4,0) -> 18.447159 | H4: =IF(E4=0,"",IF(G4<=Sources_Assumptions!C26,"OK","BREACH")) -> BREACH | I4: =NPV(Sources_Assumptions!C28,CFADS!H4:H15) -> 43725329 | J4: =IF(E4=0,"",IFERROR(I4/E4,0)) -> 2.469064 | K4: =IF(J4="","",IF(J4>=Sources_Assumptions!C27,"OK","BREACH")) -> OK
A5: 2 | B5: =Debt_Schedule!I5 -> 1.5 | C5: =IF(B5="","",IF(B5>=Sources_Assumptions!C24,"OK","BREACH")) -> OK | D5: =IF(B5="","",IF(B5>=Sources_Assumptions!C25,"OK","LOCK-UP")) -> OK | E5: =Debt_Schedule!B5 -> 17709273 | F5: =CFADS!C5 -> 2080000 | G5: =IFERROR(E5/F5,0) -> 8.5140736 | H5: =IF(E5=0,"",IF(G5<=Sources_Assumptions!C26,"OK","BREACH")) -> BREACH | I5: =NPV(Sources_Assumptions!C28,CFADS!H5:H15) -> 45857347 | J5: =IF(E5=0,"",IFERROR(I5/E5,0)) -> 2.5894539 | K5: =IF(J5="","",IF(J5>=Sources_Assumptions!C27,"OK","BREACH")) -> OK
A6: 3 | B6: =Debt_Schedule!I6 -> 1.5 | C6: =IF(B6="","",IF(B6>=Sources_Assumptions!C24,"OK","BREACH")) -> OK | D6: =IF(B6="","",IF(B6>=Sources_Assumptions!C25,"OK","LOCK-UP")) -> OK | E6: =Debt_Schedule!B6 -> 16853830 | F6: =CFADS!C6 -> 3240000 | G6: =IFERROR(E6/F6,0) -> 5.2017994 | H6: =IF(E6=0,"",IF(G6<=Sources_Assumptions!C26,"OK","BREACH")) -> BREACH | I6: =NPV(Sources_Assumptions!C28,CFADS!H6:H15) -> 46516116 | J6: =IF(E6=0,"",IFERROR(I6/E6,0)) -> 2.759973 | K6: =IF(J6="","",IF(J6>=Sources_Assumptions!C27,"OK","BREACH")) -> OK
A7: 4 | B7: =Debt_Schedule!I7 -> 1.5 | C7: =IF(B7="","",IF(B7>=Sources_Assumptions!C24,"OK","BREACH")) -> OK | D7: =IF(B7="","",IF(B7>=Sources_Assumptions!C25,"OK","LOCK-UP")) -> OK | E7: =Debt_Schedule!B7 -> 15238447 | F7: =CFADS!C7 -> 4600000 | G7: =IFERROR(E7/F7,0) -> 3.312706 | H7: =IF(E7=0,"",IF(G7<=Sources_Assumptions!C26,"OK","BREACH")) -> OK | I7: =NPV(Sources_Assumptions!C28,CFADS!H7:H15) -> 46171083 | J7: =IF(E7=0,"",IFERROR(I7/E7,0)) -> 3.0299073 | K7: =IF(J7="","",IF(J7>=Sources_Assumptions!C27,"OK","BREACH")) -> OK
A8: 5 | B8: =Debt_Schedule!I8 -> 1.5 | C8: =IF(B8="","",IF(B8>=Sources_Assumptions!C24,"OK","BREACH")) -> OK | D8: =IF(B8="","",IF(B8>=Sources_Assumptions!C25,"OK","LOCK-UP")) -> OK | E8: =Debt_Schedule!B8 -> 12689985 | F8: =CFADS!C8 -> 6160000 | G8: =IFERROR(E8/F8,0) -> 2.0600624 | H8: =IF(E8=0,"",IF(G8<=Sources_Assumptions!C26,"OK","BREACH")) -> OK | I8: =NPV(Sources_Assumptions!C28,CFADS!H8:H15) -> 44556327 | J8: =IF(E8=0,"",IFERROR(I8/E8,0)) -> 3.5111411 | K8: =IF(J8="","",IF(J8>=Sources_Assumptions!C27,"OK","BREACH")) -> OK
A9: 6 | B9: =Debt_Schedule!I9 -> 1.5 | C9: =IF(B9="","",IF(B9>=Sources_Assumptions!C24,"OK","BREACH")) -> OK | D9: =IF(B9="","",IF(B9>=Sources_Assumptions!C25,"OK","LOCK-UP")) -> OK | E9: =Debt_Schedule!B9 -> 9024950.9 | F9: =CFADS!C9 -> 6283200 | G9: =IFERROR(E9/F9,0) -> 1.4363622 | H9: =IF(E9=0,"",IF(G9<=Sources_Assumptions!C26,"OK","BREACH")) -> OK | I9: =NPV(Sources_Assumptions!C28,CFADS!H9:H15) -> 41386009 | J9: =IF(E9=0,"",IFERROR(I9/E9,0)) -> 4.5857323 | K9: =IF(J9="","",IF(J9>=Sources_Assumptions!C27,"OK","BREACH")) -> OK
A10: 7 | B10: =Debt_Schedule!I10 -> 1.6096289 | C10: =IF(B10="","",IF(B10>=Sources_Assumptions!C24,"OK","BREACH")) -> OK | D10: =IF(B10="","",IF(B10>=Sources_Assumptions!C25,"OK","LOCK-UP")) -> OK | E10: =Debt_Schedule!B10 -> 4520393.8 | F10: =CFADS!C10 -> 6408864 | G10: =IFERROR(E10/F10,0) -> 0.70533464 | H10: =IF(E10=0,"",IF(G10<=Sources_Assumptions!C26,"OK","BREACH")) -> OK | I10: =NPV(Sources_Assumptions!C28,CFADS!H10:H15) -> 37060121 | J10: =IF(E10=0,"",IFERROR(I10/E10,0)) -> 8.1984277 | K10: =IF(J10="","",IF(J10>=Sources_Assumptions!C27,"OK","BREACH")) -> OK
A11: 8 | B11: =Debt_Schedule!I11 | C11: =IF(B11="","",IF(B11>=Sources_Assumptions!C24,"OK","BREACH")) | D11: =IF(B11="","",IF(B11>=Sources_Assumptions!C25,"OK","LOCK-UP")) | E11: =Debt_Schedule!B11 -> 0 | F11: =CFADS!C11 -> 6537041.3 | G11: =IFERROR(E11/F11,0) -> 0 | H11: =IF(E11=0,"",IF(G11<=Sources_Assumptions!C26,"OK","BREACH")) | I11: =NPV(Sources_Assumptions!C28,CFADS!H11:H15) -> 32275824 | J11: =IF(E11=0,"",IFERROR(I11/E11,0)) | K11: =IF(J11="","",IF(J11>=Sources_Assumptions!C27,"OK","BREACH"))
A12: 9 | B12: =Debt_Schedule!I12 | C12: =IF(B12="","",IF(B12>=Sources_Assumptions!C24,"OK","BREACH")) | D12: =IF(B12="","",IF(B12>=Sources_Assumptions!C25,"OK","LOCK-UP")) | E12: =Debt_Schedule!B12 -> 0 | F12: =CFADS!C12 -> 6667782.1 | G12: =IFERROR(E12/F12,0) -> 0 | H12: =IF(E12=0,"",IF(G12<=Sources_Assumptions!C26,"OK","BREACH")) | I12: =NPV(Sources_Assumptions!C28,CFADS!H12:H15) -> 26994198 | J12: =IF(E12=0,"",IFERROR(I12/E12,0)) | K12: =IF(J12="","",IF(J12>=Sources_Assumptions!C27,"OK","BREACH"))
A13: 10 | B13: =Debt_Schedule!I13 | C13: =IF(B13="","",IF(B13>=Sources_Assumptions!C24,"OK","BREACH")) | D13: =IF(B13="","",IF(B13>=Sources_Assumptions!C25,"OK","LOCK-UP")) | E13: =Debt_Schedule!B13 -> 0 | F13: =CFADS!C13 -> 6801137.7 | G13: =IFERROR(E13/F13,0) -> 0 | H13: =IF(E13=0,"",IF(G13<=Sources_Assumptions!C26,"OK","BREACH")) | I13: =NPV(Sources_Assumptions!C28,CFADS!H13:H15) -> 21173165 | J13: =IF(E13=0,"",IFERROR(I13/E13,0)) | K13: =IF(J13="","",IF(J13>=Sources_Assumptions!C27,"OK","BREACH"))
A14: 11 | B14: =Debt_Schedule!I14 | C14: =IF(B14="","",IF(B14>=Sources_Assumptions!C24,"OK","BREACH")) | D14: =IF(B14="","",IF(B14>=Sources_Assumptions!C25,"OK","LOCK-UP")) | E14: =Debt_Schedule!B14 -> 0 | F14: =CFADS!C14 -> 6937160.5 | G14: =IFERROR(E14/F14,0) -> 0 | H14: =IF(E14=0,"",IF(G14<=Sources_Assumptions!C26,"OK","BREACH")) | I14: =NPV(Sources_Assumptions!C28,CFADS!H14:H15) -> 14767236 | J14: =IF(E14=0,"",IFERROR(I14/E14,0)) | K14: =IF(J14="","",IF(J14>=Sources_Assumptions!C27,"OK","BREACH"))
A15: 12 | B15: =Debt_Schedule!I15 | C15: =IF(B15="","",IF(B15>=Sources_Assumptions!C24,"OK","BREACH")) | D15: =IF(B15="","",IF(B15>=Sources_Assumptions!C25,"OK","LOCK-UP")) | E15: =Debt_Schedule!B15 -> 0 | F15: =CFADS!C15 -> 7075903.6 | G15: =IFERROR(E15/F15,0) -> 0 | H15: =IF(E15=0,"",IF(G15<=Sources_Assumptions!C26,"OK","BREACH")) | I15: =NPV(Sources_Assumptions!C28,CFADS!H15) -> 7727233.3 | J15: =IF(E15=0,"",IFERROR(I15/E15,0)) | K15: =IF(J15="","",IF(J15>=Sources_Assumptions!C27,"OK","BREACH"))

Sheet IRR_Payback
A1: IRR & Payback
A3: Period | B3: Cash Flow | C3: Cumulative CF | D3: Project IRR | E3: Simple Payback | F3: Note
A4: Year 0 | B4: =-Sources_Uses!B8 -> -28827735 | C4: =B4 -> -28827735 | D4: =IRR(B4:B16) -> 0.15048252 | E4: Manual review from cumulative CF crossover | F4: Payback year is first year where cumulative CF turns positive
A5: Year 1 | B5: =CFADS!H4 -> 1366008.6 | C5: =C4+B5 -> -27461726
A6: Year 2 | B6: =CFADS!H5 -> 3009818.4 | C6: =C5+B6 -> -24451908
A7: Year 3 | B7: =CFADS!H6 -> 4066322.5 | C7: =C6+B7 -> -20385586
A8: Year 4 | B8: =CFADS!H7 -> 5308443 | C8: =C7+B8 -> -15077143
A9: Year 5 | B9: =CFADS!H8 -> 6734823.9 | C9: =C8+B9 -> -8342318.6
A10: Year 6 | B10: =CFADS!H9 -> 7636768.5 | C10: =C9+B10 -> -705550.17
A11: Year 7 | B11: =CFADS!H10 -> 7749106.8 | C11: =C10+B11 -> 7043556.6
A12: Year 8 | B12: =CFADS!H11 -> 7863691.8 | C12: =C11+B12 -> 14907248
A13: Year 9 | B13: =CFADS!H12 -> 7980568.6 | C13: =C12+B13 -> 22887817
A14: Year 10 | B14: =CFADS!H13 -> 8099782.9 | C14: =C13+B14 -> 30987600
A15: Year 11 | B15: =CFADS!H14 -> 8221381.4 | C15: =C14+B15 -> 39208981
A16: Year 12 | B16: =CFADS!H15 -> 8345412 | C16: =C15+B16 -> 47554393
