Workbook

Sheet Cover
B2: TITAN GRID / ARS METAL INDUSTRIES LIVE LENDER LINKAGE PACK v6.2
B7: Document Type | C7: Integrated lender model workbook
B8: Purpose | C8: Credit committee / lender linkage pack
B9: Version | C9: v6.2
B10: Date | C10: 20 Mar 2026
B11: Status | C11: Internal draft – export ready
B14: Workbook Map
B15: Assumptions | C15: Editable core drivers
B16: Production_Margin | C16: Unit economics and EBITDA bridge
B17: Debt_Schedule | C17: Debt draw and repayment simplification
B18: Covenant_Dashboard | C18: DSCR / LLCR / PLCR / flags
B19: DSCR_Snapshot | C19: Annual CFADS and DSCR
B20: IC_Voting | C20: Credit committee action page
B21: Document_Control | C21: Issue control and revision log

Sheet Index
B2: Navigation Index
B3: Sheet | C3: Description | D3: Owner | E3: Status
B4: Assumptions | C4: Core drivers for price, cost, CAPEX, debt, tax and covenant thresholds | D4: Finance | E4: Active
B5: Production_Margin | C5: Unit margin build, EBITDA and yearly throughput | D5: Finance | E5: Active
B6: Debt_Schedule | C6: Debt funding, grace, repayment and interest | D6: Finance | E6: Active
B7: DSCR_Snapshot | C7: CFADS and DSCR by year | D7: Finance | E7: Active
B8: Covenant_Dashboard | C8: Lender ratios and flags | D8: Finance | E8: Active
B9: IC_Voting | C9: Approval grid and action items | D9: IC Secretariat | E9: Draft
B10: Document_Control | C10: Revision history and notes | D10: PMO | E10: Active

Sheet Assumptions
B2: Model Control
B3: Model Currency | C3: EUR
B4: Base Year | C4: 2029
B5: Tax Rate | C5: 0.09
B6: Discount Rate | C6: 0.12
B7: Target Minimum DSCR | C7: 1.25
B8: Target Minimum LLCR | C8: 1.4
B9: Target Minimum PLCR | C9: 1.5
B11: Operating Drivers
B12: Nameplate Throughput (t) | C12: 12000
B13: Ramp-Up 2029 | C13: 0.6
B14: Ramp-Up 2030 | C14: 0.75
B15: Ramp-Up 2031 | C15: 0.85
B16: Ramp-Up 2032 | C16: 0.9
B17: Ramp-Up 2033 | C17: 0.92
B18: Average Revenue per Ton | C18: 2400
B19: Steel Cost % of Revenue | C19: 0.55
B20: Variable Ops % of Revenue | C20: 0.125
B21: Fixed Opex 2029 | C21: 1200000
B22: Fixed Opex Growth | C22: 0.03
B23: Maintenance Capex % Revenue | C23: 0.015
B26: Funding & Debt Drivers
B27: Total CAPEX | C27: 16000000
B28: Debt Share | C28: 0.6
B29: Equity Share | C29: 0.25
B30: Grant Share | C30: 0.15
B31: Debt Interest Rate | C31: 0.065
B32: Debt Tenor (years) | C32: 8
B33: Grace Period (years) | C33: 2
B34: DSRA Months | C34: 6

Sheet Production_Margin
A2: Production & Margin Build
B4: 2029 | C4: 2030 | D4: 2031 | E4: 2032 | F4: 2033
A5: Ramp-Up | B5: =Assumptions!$C$13 | C5: =Assumptions!$C$14 | D5: =Assumptions!$C$15 | E5: =Assumptions!$C$16 | F5: =Assumptions!$C$17
A6: Production (t) | B6: =Assumptions!$C$12*B5 | C6: =Assumptions!$C$12*C5 | D6: =Assumptions!$C$12*D5 | E6: =Assumptions!$C$12*E5 | F6: =Assumptions!$C$12*F5
A7: Revenue / t | B7: =Assumptions!$C$18 | C7: =Assumptions!$C$18 | D7: =Assumptions!$C$18 | E7: =Assumptions!$C$18 | F7: =Assumptions!$C$18
A8: Revenue (€) | B8: =B6*B7 | C8: =C6*C7 | D8: =D6*D7 | E8: =E6*E7 | F8: =F6*F7
A9: Steel Cost (€) | B9: =B8*Assumptions!$C$19 | C9: =C8*Assumptions!$C$19 | D9: =D8*Assumptions!$C$19 | E9: =E8*Assumptions!$C$19 | F9: =F8*Assumptions!$C$19
A10: Variable Ops (€) | B10: =B8*Assumptions!$C$20 | C10: =C8*Assumptions!$C$20 | D10: =D8*Assumptions!$C$20 | E10: =E8*Assumptions!$C$20 | F10: =F8*Assumptions!$C$20
A11: Contribution Margin (€) | B11: =B8-B9-B10 | C11: =C8-C9-C10 | D11: =D8-D9-D10 | E11: =E8-E9-E10 | F11: =F8-F9-F10
A12: Fixed Opex (€) | B12: =Assumptions!$C$21 | C12: =B12*(1+Assumptions!$C$22) | D12: =C12*(1+Assumptions!$C$22) | E12: =D12*(1+Assumptions!$C$22) | F12: =E12*(1+Assumptions!$C$22)
A13: EBITDA (€) | B13: =B11-B12 | C13: =C11-C12 | D13: =D11-D12 | E13: =E11-E12 | F13: =F11-F12
A14: EBITDA Margin | B14: =IFERROR(B13/B8,0) | C14: =IFERROR(C13/C8,0) | D14: =IFERROR(D13/D8,0) | E14: =IFERROR(E13/E8,0) | F14: =IFERROR(F13/F8,0)
A15: Maintenance Capex (€) | B15: =B8*Assumptions!$C$23 | C15: =C8*Assumptions!$C$23 | D15: =D8*Assumptions!$C$23 | E15: =E8*Assumptions!$C$23 | F15: =F8*Assumptions!$C$23

Sheet Debt_Schedule
A2: Debt Schedule
B4: 2029 | C4: 2030 | D4: 2031 | E4: 2032 | F4: 2033
A5: Opening Debt | B5: =0 | C5: =B9 | D5: =C9 | E5: =D9 | F5: =E9
A6: Drawdown | B6: =Assumptions!$C$27*Assumptions!$C$28 | C6: =0 | D6: =0 | E6: =0 | F6: =0
A7: Principal Repayment | B7: =0 | C7: =0 | D7: =0 | E7: =IF(E$4<=2031,0,$B$9/MAX(Assumptions!$C$32-Assumptions!$C$33,1)) | F7: =IF(F$4<=2031,0,$B$9/MAX(Assumptions!$C$32-Assumptions!$C$33,1))
A8: Interest Expense | B8: =((B5+B6)-B7)*Assumptions!$C$31 | C8: =(((C5+C6)-C7)+C5)/2*Assumptions!$C$31 | D8: =(((D5+D6)-D7)+D5)/2*Assumptions!$C$31 | E8: =(((E5+E6)-E7)+E5)/2*Assumptions!$C$31 | F8: =(((F5+F6)-F7)+F5)/2*Assumptions!$C$31
A9: Closing Debt | B9: =B5+B6-B7 | C9: =C5+C6-C7 | D9: =D5+D6-D7 | E9: =E5+E6-E7 | F9: =F5+F6-F7
A10: Debt Service | B10: =B7+B8 | C10: =C7+C8 | D10: =D7+D8 | E10: =E7+E8 | F10: =F7+F8
A11: DSRA Target | B11: =B10*Assumptions!$C$33/12 | C11: =C10*Assumptions!$C$33/12 | D11: =D10*Assumptions!$C$33/12 | E11: =E10*Assumptions!$C$33/12 | F11: =F10*Assumptions!$C$33/12

Sheet DSCR_Snapshot
A2: CFADS / DSCR Snapshot
B4: 2029 | C4: 2030 | D4: 2031 | E4: 2032 | F4: 2033
A5: EBITDA (€) | B5: =Production_Margin!B13 | C5: =Production_Margin!C13 | D5: =Production_Margin!D13 | E5: =Production_Margin!E13 | F5: =Production_Margin!F13
A6: Less: Taxes (€) | B6: =MAX((B5-Debt_Schedule!B8),0)*Assumptions!$C$4 | C6: =MAX((C5-Debt_Schedule!C8),0)*Assumptions!$C$4 | D6: =MAX((D5-Debt_Schedule!D8),0)*Assumptions!$C$4 | E6: =MAX((E5-Debt_Schedule!E8),0)*Assumptions!$C$4 | F6: =MAX((F5-Debt_Schedule!F8),0)*Assumptions!$C$4
A7: Less: Maintenance Capex (€) | B7: =Production_Margin!B15 | C7: =Production_Margin!C15 | D7: =Production_Margin!D15 | E7: =Production_Margin!E15 | F7: =Production_Margin!F15
A8: CFADS (€) | B8: =B5-B6-B7 | C8: =C5-C6-C7 | D8: =D5-D6-D7 | E8: =E5-E6-E7 | F8: =F5-F6-F7
A9: Debt Service (€) | B9: =Debt_Schedule!B10 | C9: =Debt_Schedule!C10 | D9: =Debt_Schedule!D10 | E9: =Debt_Schedule!E10 | F9: =Debt_Schedule!F10
A10: DSCR | B10: =IFERROR(B8/B9,0) | C10: =IFERROR(C8/C9,0) | D10: =IFERROR(D8/D9,0) | E10: =IFERROR(E8/E9,0) | F10: =IFERROR(F8/F9,0)
A12: Discount Factor | B12: =1/(1+Assumptions!$C$5)^1 | C12: =1/(1+Assumptions!$C$5)^2 | D12: =1/(1+Assumptions!$C$5)^3 | E12: =1/(1+Assumptions!$C$5)^4 | F12: =1/(1+Assumptions!$C$5)^5

Sheet Covenant_Dashboard
A2: Lender Covenant Dashboard
A4: Metric | B4: Threshold | C4: Actual | D4: Status | E4: Comment | F4: Source
A5: Minimum DSCR | B5: =Assumptions!$C$5 | C5: =MIN(DSCR_Snapshot!B10:F10) | D5: =IF(C5>=B5,"PASS","FAIL") | E5: Annual minimum | F5: Linked
A6: Average DSCR | B6: n/a | C6: =AVERAGE(DSCR_Snapshot!B10:F10) | D6: =IF(C6>=1.30,"PASS","WATCH") | E6: Mean annual | F6: Linked
A7: LLCR | B7: =Assumptions!$C$6 | C7: =SUMPRODUCT(DSCR_Snapshot!B8:F8,DSCR_Snapshot!B12:F12)/Debt_Schedule!B9 | D7: =IF(C7>=B7,"PASS","FAIL") | E7: PV CFADS / opening debt | F7: Model
A8: PLCR | B8: =Assumptions!$C$7 | C8: =(SUMPRODUCT(DSCR_Snapshot!B8:F8,DSCR_Snapshot!B12:F12)+MAX(0,Production_Margin!F13*4)*DSCR_Snapshot!F12)/Debt_Schedule!B9 | D8: =IF(C8>=B8,"PASS","FAIL") | E8: Project life cover incl. tail value | F8: Model
A9: DSRA Requirement | B9: n/a | C9: =MAX(Debt_Schedule!B11:F11) | D9: =IF(C9>0,"SET","CHECK") | E9: 6-month debt service reserve | F9: Linked

Sheet IC_Voting
B2: Credit Committee Decision Pack
B4: Item | C4: Value | D4: Decision Gate | E4: Owner | F4: Due | G4: Comments
B5: Project | C5: TITAN GRID / ARS
B6: Base EBITDA Margin | C6: =Production_Margin!F14 | D6: Approve if >=20% | E6: Finance
B7: Minimum DSCR | C7: =Covenant_Dashboard!C5 | D7: Approve if >=1.25x | E7: Finance
B8: LLCR | C8: =Covenant_Dashboard!C7 | D8: Approve if >=1.40x | E8: Finance
B9: PLCR | C9: =Covenant_Dashboard!C8 | D9: Approve if >=1.50x | E9: Finance
B10: Overall Recommendation | C10: =IF(AND(Covenant_Dashboard!D5="PASS",Covenant_Dashboard!D7="PASS",Covenant_Dashboard!D8="PASS"),"APPROVE SUBJECT TO DD","CONDITIONAL / HOLD") | D10: IC Chair | E10: IC | G10: Final
B13: IC Voting Grid
B14: Member | C14: Vote | D14: Condition / Reservation | E14: Sign-off | F14: Date | G14: Notes
B15: Chair
B16: Risk
B17: Finance
B18: Technical
B19: Legal
B22: Decision Summary | C22: =COUNTIF(C15:C19,"APPROVE") | D22: approvals

Sheet Document_Control
B2: Document Control
B4: Rev | C4: Date | D4: Owner | E4: Summary | F4: Status
B5: v6.0 | C5: 20 Mar 2026 | D5: Finance | E5: Base credit committee pack created | F5: Superseded
B6: v6.1 | C6: 20 Mar 2026 | D6: Finance | E6: Model-integrated committee pack memo | F6: Superseded
B7: v6.2 | C7: 20 Mar 2026 | D7: Finance | E7: Live lender linkage workbook export (.xlsx) | F7: Current
