Workbook

Sheet Project_Summary
A1: Item | B1: Value | C1: Notes
A2: Project Name | B2: ARS Metal Industries – Transformer Tank Factory
A3: Location | B3: Tuzi, Montenegro
A4: Total CAPEX (€) | B4: 12000000 | C4: Base scenario
A5: CAPEX High Scenario (€) | B5: 15000000
A6: Expected EU Grants (€) | B6: 4000000 | C6: Weighted expectation
A7: Bank Debt (€) | B7: 5400000 | C7: Indicative 45% debt share
A8: Equity (€) | B8: 2600000 | C8: Sponsor equity
A9: Loan Tenor (years) | B9: 10
A10: Interest Rate (%) | B10: 5.5

Sheet Revenue_Model
A1: Year | B1: Production (units) | C1: Average Price (€) | D1: Revenue (€)
A2: 2027 | B2: 600 | C2: 9000 | D2: =B2*C2
A3: 2028 | B3: 1000 | C3: 9000 | D3: =B3*C3
A4: 2029 | B4: 1400 | C4: 9000 | D4: =B4*C4
A5: 2030 | B5: 1600 | C5: 9000 | D5: =B5*C5
A6: 2031 | B6: 1800 | C6: 9000 | D6: =B6*C6

Sheet EBITDA_Model
A1: Year | B1: Revenue (€) | C1: EBITDA Margin % | D1: EBITDA (€)
A2: 2027 | B2: =Revenue_Model!D2 | C2: 22 | D2: =B2*C2/100
A3: 2028 | B3: =Revenue_Model!D3 | C3: 22 | D3: =B3*C3/100
A4: 2029 | B4: =Revenue_Model!D4 | C4: 22 | D4: =B4*C4/100
A5: 2030 | B5: =Revenue_Model!D5 | C5: 22 | D5: =B5*C5/100
A6: 2031 | B6: =Revenue_Model!D6 | C6: 22 | D6: =B6*C6/100

Sheet Debt_Model
A1: Year | B1: EBITDA (€) | C1: Debt Service (€) | D1: DSCR
A2: 2027 | B2: =EBITDA_Model!D2 | C2: 800000 | D2: =B2/C2
A3: 2028 | B3: =EBITDA_Model!D3 | C3: 800000 | D3: =B3/C3
A4: 2029 | B4: =EBITDA_Model!D4 | C4: 800000 | D4: =B4/C4
A5: 2030 | B5: =EBITDA_Model!D5 | C5: 800000 | D5: =B5/C5
A6: 2031 | B6: =EBITDA_Model!D6 | C6: 800000 | D6: =B6/C6

Sheet Bank_Dashboard
A1: EBRD / Bank Credit Memo Dashboard
A3: Average DSCR | B3: =AVERAGE(Debt_Model!D2:D6)
A4: Minimum DSCR | B4: =MIN(Debt_Model!D2:D6)
A6: Interpretation
A7: DSCR above 1.30 is typically acceptable for project finance.
