Workbook

Sheet 000_Cover
A1: ARS QUANT INDUSTRIAL MODEL
A3: Project | B3: ARS Metal Industries – Transformer Tank Factory
A4: Model Type | B4: Quantitative Industrial Project Finance / Risk / Digital Twin Framework
A5: Standard | B5: Bank-grade / fund-grade / infrastructure-grade workbook architecture
A6: Version | B6: v1.0
A7: Scope | B7: 100+ sheets covering operations, CAPEX, financing, valuation, risk, AI forecasting, controls

Sheet 001_Index
A1: Workbook Navigation Index
A3: Sheet No. | B3: Sheet Name | C3: Module | D3: Purpose
A4: 1 | B4: 000_Cover | C4: Cover | D4: Navigation / module sheet
A5: 2 | B5: 001_Index | C5: Index | D5: Navigation / module sheet
A6: 3 | B6: 002_Master_Assumptions | C6: Master_Assumptions | D6: Navigation / module sheet
A7: 4 | B7: 003_Scenario_Manager | C7: Scenario_Manager | D7: Navigation / module sheet
A8: 5 | B8: 004_Timebase | C8: Timebase | D8: Navigation / module sheet
A9: 6 | B9: 010_Production_Model | C9: Production_Model | D9: Navigation / module sheet
A10: 7 | B10: 011_Revenue_Model | C10: Revenue_Model | D10: Navigation / module sheet
A11: 8 | B11: 012_COGS_Model | C11: COGS_Model | D11: Navigation / module sheet
A12: 9 | B12: 013_OPEX_Model | C12: OPEX_Model | D12: Navigation / module sheet
A13: 10 | B13: 014_CAPEX_Model | C13: CAPEX_Model | D13: Navigation / module sheet
A14: 11 | B14: 015_Financing_Model | C14: Financing_Model | D14: Navigation / module sheet
A15: 12 | B15: 016_Debt_Schedule | C15: Debt_Schedule | D15: Navigation / module sheet
... A126: 123 | B126: 150_Management_Report | C126: Management_Report | D126: Navigation / module sheet

Sheet 002_Master_Assumptions
A1: Master Assumptions
A2: Core driver sheet for production, pricing, costs, financing and tax
A4: Category | B4: Parameter | C4: Base | D4: Low | E4: High | F4: Unit | G4: Source / Note | H4: Input Type
A5: Production | B5: Installed capacity | C5: 1800 | D5: 1500 | E5: 2000 | F5: units/year | G5: Factory design assumption | H5: Input
A6: Production | B6: Utilization Y1 | C6: 0.4 | D6: 0.3 | E6: 0.5 | F6: % | G6: Ramp-up curve | H6: Input
A7: Production | B7: Utilization Y2 | C7: 0.6 | D7: 0.5 | E7: 0.7 | F7: % | G7: Ramp-up curve | H7: Input
A8: Production | B8: Utilization Y3 | C8: 0.8 | D8: 0.7 | E8: 0.9 | F8: % | G8: Ramp-up curve | H8: Input
A9: Production | B9: Utilization stable | C9: 0.9 | D9: 0.8 | E9: 0.95 | F9: % | G9: Steady-state | H9: Input
A10: Pricing | B10: ASP | C10: 9000 | D10: 8200 | E10: 9800 | F10: €/unit | G10: Average selling price | H10: Input
A11: COGS | B11: Steel per unit | C11: 4200 | D11: 3800 | E11: 4700 | F11: €/unit | G11: Raw material | H11: Input
A12: COGS | B12: Energy per unit | C12: 350 | D12: 300 | E12: 420 | F12: €/unit | G12: Direct energy | H12: Input
A13: COGS | B13: Direct labor per unit | C13: 650 | D13: 600 | E13: 720 | F13: €/unit | G13: Direct labor | H13: Input
A14: COGS | B14: Manufacturing OH per unit | C14: 400 | D14: 360 | E14: 450 | F14: €/unit | G14: Factory overhead | H14: Input
A15: OPEX | B15: Admin costs | C15: 1200000 | D15: 1100000 | E15: 1300000 | F15: €/year | G15: SG&A | H15: Input
A16: OPEX | B16: Sales costs | C16: 350000 | D16: 300000 | E16: 420000 | F16: €/year | G16: Commercial | H16: Input
... A27: Valuation | B27: Discount rate / WACC | C27: 0.1 | D27: 0.09 | E27: 0.12 | F27: % | G27: Project discount rate | H27: Input

Sheet 003_Scenario_Manager
A1: Scenario Manager
A2: Select case multipliers for revenue, cost, CAPEX and financing
A4: Scenario | B4: Revenue Mult. | C4: COGS Mult. | D4: OPEX Mult. | E4: CAPEX Mult. | F4: Rate Shock | G4: Comment
A5: Base | B5: 1 | C5: 1 | D5: 1 | E5: 1 | F5: 0 | G5: Central case
A6: Downside | B6: 0.9 | C6: 1.08 | D6: 1.05 | E6: 1.1 | F6: 0.01 | G6: Demand / inflation shock
A7: Upside | B7: 1.08 | C7: 0.97 | D7: 0.98 | E7: 0.98 | F7: -0.005 | G7: Strong pricing and efficiency
A9: Selected Scenario | B9: Base

Sheet 004_Timebase
A1: Timebase
A2: Operating years Y1-Y15
A4: Metric | B4: Y1 | C4: Y2 | D4: Y3 | E4: Y4 | F4: Y5 | G4: Y6 | H4: Y7 | I4: Y8 | J4: Y9 | K4: Y10 | L4: Y11 | M4: Y12 | N4: Y13 | O4: Y14 | P4: Y15
A5: Calendar Year | B5: 2027 | C5: 2028 | D5: 2029 | E5: 2030 | F5: 2031 | G5: 2032 | H5: 2033 | I5: 2034 | J5: 2035 | K5: 2036 | L5: 2037 | M5: 2038 | N5: 2039 | O5: 2040 | P5: 2041
A6: Operating Flag | B6: 1 | C6: 1 | D6: 1 | E6: 1 | F6: 1 | G6: 1 | H6: 1 | I6: 1 | J6: 1 | K6: 1 | L6: 1 | M6: 1 | N6: 1 | O6: 1 | P6: 1
A7: Construction Flag | B7: 0 | C7: 0 | D7: 0 | E7: 0 | F7: 0 | G7: 0 | H7: 0 | I7: 0 | J7: 0 | K7: 0 | L7: 0 | M7: 0 | N7: 0 | O7: 0 | P7: 0

Sheet 010_Production_Model
A1: Production Model
A2: Units produced by year
A4: Metric | B4: Y1 | C4: Y2 | D4: Y3 | E4: Y4 | F4: Y5 | G4: Y6 | H4: Y7 | I4: Y8 | J4: Y9 | K4: Y10 | L4: Y11 | M4: Y12 | N4: Y13 | O4: Y14 | P4: Y15
A5: Installed Capacity | B5: ='002_Master_Assumptions'!C5 | C5: ='002_Master_Assumptions'!C5 | D5: ='002_Master_Assumptions'!C5 | E5: ='002_Master_Assumptions'!C5 | F5: ='002_Master_Assumptions'!C5 | G5: ='002_Master_Assumptions'!C5 | H5: ='002_Master_Assumptions'!C5 | I5: ='002_Master_Assumptions'!C5 | J5: ='002_Master_Assumptions'!C5 | K5: ='002_Master_Assumptions'!C5 | L5: ='002_Master_Assumptions'!C5 | M5: ='002_Master_Assumptions'!C5 | N5: ='002_Master_Assumptions'!C5 | O5: ='002_Master_Assumptions'!C5 | P5: ='002_Master_Assumptions'!C5
A6: Utilization | B6: ='002_Master_Assumptions'!C2 | C6: ='002_Master_Assumptions'!C3 | D6: ='002_Master_Assumptions'!C4 | E6: ='002_Master_Assumptions'!C5 | F6: ='002_Master_Assumptions'!C5 | G6: ='002_Master_Assumptions'!C5 | H6: ='002_Master_Assumptions'!C5 | I6: ='002_Master_Assumptions'!C5 | J6: ='002_Master_Assumptions'!C5 | K6: ='002_Master_Assumptions'!C5 | L6: ='002_Master_Assumptions'!C5 | M6: ='002_Master_Assumptions'!C5 | N6: ='002_Master_Assumptions'!C5 | O6: ='002_Master_Assumptions'!C5 | P6: ='002_Master_Assumptions'!C5
A7: Units Produced | B7: =B5*B6 | C7: =C5*C6 | D7: =D5*D6 | E7: =E5*E6 | F7: =F5*F6 | G7: =G5*G6 | H7: =H5*H6 | I7: =I5*I6 | ... P7: =P5*P6
A9: Source note: linked to Master Assumptions

Sheet 011_Revenue_Model
A1: Revenue Model
A2: Units × ASP
A4: Metric | B4: Y1 | C4: Y2 | D4: Y3 | E4: Y4 | F4: Y5 | G4: Y6 | H4: Y7 | I4: Y8 | J4: Y9 | K4: Y10 | L4: Y11 | M4: Y12 | N4: Y13 | O4: Y14 | P4: Y15
A5: Units Sold | B5: ='010_Production_Model'!B7 | C5: ='010_Production_Model'!C7 | D5: ='010_Production_Model'!D7 | E5: ='010_Production_Model'!E7 | F5: ='010_Production_Model'!F7 | G5: ='010_Production_Model'!G7 | H5: ='010_Production_Model'!H7 | I5: ='010_Production_Model'!I7 | ... P5: ='010_Production_Model'!P7
A6: ASP | B6: ='002_Master_Assumptions'!C10 | C6: ='002_Master_Assumptions'!C10 | D6: ='002_Master_Assumptions'!C10 | E6: ='002_Master_Assumptions'!C10 | F6: ='002_Master_Assumptions'!C10 | G6: ='002_Master_Assumptions'!C10 | H6: ='002_Master_Assumptions'!C10 | I6: ='002_Master_Assumptions'!C10 | J6: ='002_Master_Assumptions'!C10 | K6: ='002_Master_Assumptions'!C10 | L6: ='002_Master_Assumptions'!C10 | M6: ='002_Master_Assumptions'!C10 | N6: ='002_Master_Assumptions'!C10 | O6: ='002_Master_Assumptions'!C10 | P6: ='002_Master_Assumptions'!C10
A7: Revenue | B7: =B5*B6 | C7: =C5*C6 | D7: =D5*D6 | E7: =E5*E6 | F7: =F5*F6 | G7: =G5*G6 | H7: =H5*H6 | I7: =I5*I6 | ... P7: =P5*P6

Sheet 012_COGS_Model
A1: COGS Model
A2: Unit costs and total cost of goods sold
A4: Metric | B4: Y1 | C4: Y2 | D4: Y3 | E4: Y4 | F4: Y5 | G4: Y6 | H4: Y7 | I4: Y8 | J4: Y9 | K4: Y10 | L4: Y11 | M4: Y12 | N4: Y13 | O4: Y14 | P4: Y15
A5: Units | B5: ='010_Production_Model'!B7 | C5: ='010_Production_Model'!C7 | D5: ='010_Production_Model'!D7 | E5: ='010_Production_Model'!E7 | F5: ='010_Production_Model'!F7 | G5: ='010_Production_Model'!G7 | H5: ='010_Production_Model'!H7 | I5: ='010_Production_Model'!I7 | ... P5: ='010_Production_Model'!P7
A6: Steel/unit | B6: ='002_Master_Assumptions'!C11 | C6: ='002_Master_Assumptions'!C11 | D6: ='002_Master_Assumptions'!C11 | E6: ='002_Master_Assumptions'!C11 | F6: ='002_Master_Assumptions'!C11 | G6: ='002_Master_Assumptions'!C11 | H6: ='002_Master_Assumptions'!C11 | I6: ='002_Master_Assumptions'!C11 | J6: ='002_Master_Assumptions'!C11 | K6: ='002_Master_Assumptions'!C11 | L6: ='002_Master_Assumptions'!C11 | M6: ='002_Master_Assumptions'!C11 | N6: ='002_Master_Assumptions'!C11 | O6: ='002_Master_Assumptions'!C11 | P6: ='002_Master_Assumptions'!C11
A7: Energy/unit | B7: ='002_Master_Assumptions'!C12 | C7: ='002_Master_Assumptions'!C12 | D7: ='002_Master_Assumptions'!C12 | E7: ='002_Master_Assumptions'!C12 | F7: ='002_Master_Assumptions'!C12 | G7: ='002_Master_Assumptions'!C12 | H7: ='002_Master_Assumptions'!C12 | I7: ='002_Master_Assumptions'!C12 | J7: ='002_Master_Assumptions'!C12 | K7: ='002_Master_Assumptions'!C12 | L7: ='002_Master_Assumptions'!C12 | M7: ='002_Master_Assumptions'!C12 | N7: ='002_Master_Assumptions'!C12 | O7: ='002_Master_Assumptions'!C12 | P7: ='002_Master_Assumptions'!C12
A8: Labor/unit | B8: ='002_Master_Assumptions'!C13 | C8: ='002_Master_Assumptions'!C13 | D8: ='002_Master_Assumptions'!C13 | E8: ='002_Master_Assumptions'!C13 | F8: ='002_Master_Assumptions'!C13 | G8: ='002_Master_Assumptions'!C13 | H8: ='002_Master_Assumptions'!C13 | I8: ='002_Master_Assumptions'!C13 | J8: ='002_Master_Assumptions'!C13 | K8: ='002_Master_Assumptions'!C13 | L8: ='002_Master_Assumptions'!C13 | M8: ='002_Master_Assumptions'!C13 | N8: ='002_Master_Assumptions'!C13 | O8: ='002_Master_Assumptions'!C13 | P8: ='002_Master_Assumptions'!C13
A9: OH/unit | B9: ='002_Master_Assumptions'!C14 | C9: ='002_Master_Assumptions'!C14 | D9: ='002_Master_Assumptions'!C14 | E9: ='002_Master_Assumptions'!C14 | F9: ='002_Master_Assumptions'!C14 | G9: ='002_Master_Assumptions'!C14 | H9: ='002_Master_Assumptions'!C14 | I9: ='002_Master_Assumptions'!C14 | J9: ='002_Master_Assumptions'!C14 | K9: ='002_Master_Assumptions'!C14 | L9: ='002_Master_Assumptions'!C14 | M9: ='002_Master_Assumptions'!C14 | N9: ='002_Master_Assumptions'!C14 | O9: ='002_Master_Assumptions'!C14 | P9: ='002_Master_Assumptions'!C14
A10: Total COGS | B10: =B5*SUM(B6:B9) | C10: =C5*SUM(C6:C9) | D10: =D5*SUM(D6:D9) | E10: =E5*SUM(E6:E9) | F10: =F5*SUM(F6:F9) | G10: =G5*SUM(G6:G9) | H10: =H5*SUM(H6:H9) | I10: =I5*SUM(I6:I9) | ... P10: =P5*SUM(P6:P9)

Sheet 013_OPEX_Model
A1: OPEX Model
A2: Operating expenses
A4: Metric | B4: Y1 | C4: Y2 | D4: Y3 | E4: Y4 | F4: Y5 | G4: Y6 | H4: Y7 | I4: Y8 | J4: Y9 | K4: Y10 | L4: Y11 | M4: Y12 | N4: Y13 | O4: Y14 | P4: Y15
A5: Admin | B5: ='002_Master_Assumptions'!C15 | C5: ='002_Master_Assumptions'!C15 | D5: ='002_Master_Assumptions'!C15 | E5: ='002_Master_Assumptions'!C15 | F5: ='002_Master_Assumptions'!C15 | G5: ='002_Master_Assumptions'!C15 | H5: ='002_Master_Assumptions'!C15 | I5: ='002_Master_Assumptions'!C15 | J5: ='002_Master_Assumptions'!C15 | K5: ='002_Master_Assumptions'!C15 | L5: ='002_Master_Assumptions'!C15 | M5: ='002_Master_Assumptions'!C15 | N5: ='002_Master_Assumptions'!C15 | O5: ='002_Master_Assumptions'!C15 | P5: ='002_Master_Assumptions'!C15
A6: Sales | B6: ='002_Master_Assumptions'!C16 | C6: ='002_Master_Assumptions'!C16 | D6: ='002_Master_Assumptions'!C16 | E6: ='002_Master_Assumptions'!C16 | F6: ='002_Master_Assumptions'!C16 | G6: ='002_Master_Assumptions'!C16 | H6: ='002_Master_Assumptions'!C16 | I6: ='002_Master_Assumptions'!C16 | J6: ='002_Master_Assumptions'!C16 | K6: ='002_Master_Assumptions'!C16 | L6: ='002_Master_Assumptions'!C16 | M6: ='002_Master_Assumptions'!C16 | N6: ='002_Master_Assumptions'!C16 | O6: ='002_Master_Assumptions'!C16 | P6: ='002_Master_Assumptions'!C16
A7: Maintenance | B7: ='002_Master_Assumptions'!C17 | C7: ='002_Master_Assumptions'!C17 | D7: ='002_Master_Assumptions'!C17 | E7: ='002_Master_Assumptions'!C17 | F7: ='002_Master_Assumptions'!C17 | G7: ='002_Master_Assumptions'!C17 | H7: ='002_Master_Assumptions'!C17 | I7: ='002_Master_Assumptions'!C17 | J7: ='002_Master_Assumptions'!C17 | K7: ='002_Master_Assumptions'!C17 | L7: ='002_Master_Assumptions'!C17 | M7: ='002_Master_Assumptions'!C17 | N7: ='002_Master_Assumptions'!C17 | O7: ='002_Master_Assumptions'!C17 | P7: ='002_Master_Assumptions'!C17
A8: Total OPEX | B8: =SUM(B5:B7) | C8: =SUM(C5:C7) | D8: =SUM(D5:D7) | E8: =SUM(E5:E7) | F8: =SUM(F5:F7) | G8: =SUM(G5:G7) | H8: =SUM(H5:H7) | I8: =SUM(I5:I7) | ... P8: =SUM(P5:P7)

Sheet 014_CAPEX_Model
A1: CAPEX Model
A2: Base CAPEX and contingency
A4: Metric | B4: Value
A5: Land | B5: ='002_Master_Assumptions'!C18
A6: Construction | B6: ='002_Master_Assumptions'!C19
A7: Machinery | B7: ='002_Master_Assumptions'!C20
A8: Infrastructure | B8: ='002_Master_Assumptions'!C21
A9: Base CAPEX | B9: =SUM(B5:B8)
A10: Contingency % | B10: ='002_Master_Assumptions'!C22
A11: Contingency | B11: =B9*B10
A12: Total CAPEX | B12: =B9+B11

Sheet 015_Financing_Model
A1: Financing Model
A2: Sources and debt sizing
A4: Metric | B4: Value
A5: Total CAPEX | B5: ='014_CAPEX_Model'!B12
A6: Debt Ratio | B6: ='002_Master_Assumptions'!C23
A7: Debt Amount | B7: =B5*B6
A8: Equity Amount | B8: =B5-B7
A9: Interest Rate | B9: ='002_Master_Assumptions'!C24
A10: Loan Tenor | B10: ='002_Master_Assumptions'!C25

Sheet 016_Debt_Schedule
A1: Debt Schedule
A2: Straight-line debt repayment example
A4: Metric | B4: Y1 | C4: Y2 | D4: Y3 | E4: Y4 | F4: Y5 | G4: Y6 | H4: Y7 | I4: Y8 | J4: Y9 | K4: Y10 | L4: Y11 | M4: Y12 | N4: Y13 | O4: Y14 | P4: Y15
A5: Opening Debt | B5: ='015_Financing_Model'!B7 | C5: =B9 | D5: =C9 | E5: =D9 | F5: =E9 | G5: =F9 | H5: =G9 | I5: =H9 | J5: =I9 | ... P5: =O9
A6: Interest | B6: =B5*'015_Financing_Model'!B9 | C6: =C5*'015_Financing_Model'!B9 | D6: =D5*'015_Financing_Model'!B9 | E6: =E5*'015_Financing_Model'!B9 | F6: =F5*'015_Financing_Model'!B9 | G6: =G5*'015_Financing_Model'!B9 | H6: =H5*'015_Financing_Model'!B9 | I6: =I5*'015_Financing_Model'!B9 | J6: =J5*'015_Financing_Model'!B9 | K6: =K5*'015_Financing_Model'!B9 | L6: =L5*'015_Financing_Model'!B9 | M6: =M5*'015_Financing_Model'!B9 | N6: =N5*'015_Financing_Model'!B9 | O6: =O5*'015_Financing_Model'!B9 | P6: =P5*'015_Financing_Model'!B9
A7: Principal | B7: =IF(COLUMN()<=11,'015_Financing_Model'!B7/'015_Financing_Model'!B10,0) | C7: =IF(COLUMN()<=11,'015_Financing_Model'!B7/'015_Financing_Model'!B10,0) | D7: =IF(COLUMN()<=11,'015_Financing_Model'!B7/'015_Financing_Model'!B10,0) | E7: =IF(COLUMN()<=11,'015_Financing_Model'!B7/'015_Financing_Model'!B10,0) | F7: =IF(COLUMN()<=11,'015_Financing_Model'!B7/'015_Financing_Model'!B10,0) | G7: =IF(COLUMN()<=11,'015_Financing_Model'!B7/'015_Financing_Model'!B10,0) | H7: =IF(COLUMN()<=11,'015_Financing_Model'!B7/'015_Financing_Model'!B10,0) | I7: =IF(COLUMN()<=11,'015_Financing_Model'!B7/'015_Financing_Model'!B10,0) | J7: =IF(COLUMN()<=11,'015_Financing_Model'!B7/'015_Financing_Model'!B10,0) | K7: =IF(COLUMN()<=11,'015_Financing_Model'!B7/'015_Financing_Model'!B10,0) | L7: =IF(COLUMN()<=11,'015_Financing_Model'!B7/'015_Financing_Model'!B10,0) | M7: =IF(COLUMN()<=11,'015_Financing_Model'!B7/'015_Financing_Model'!B10,0) | N7: =IF(COLUMN()<=11,'015_Financing_Model'!B7/'015_Financing_Model'!B10,0) | O7: =IF(COLUMN()<=11,'015_Financing_Model'!B7/'015_Financing_Model'!B10,0) | P7: =IF(COLUMN()<=11,'015_Financing_Model'!B7/'015_Financing_Model'!B10,0)
A8: Debt Service | B8: =B6+B7 | C8: =C6+C7 | D8: =D6+D7 | E8: =E6+E7 | F8: =F6+F7 | G8: =G6+G7 | H8: =H6+H7 | I8: =I6+I7 | ... P8: =P6+P7
A9: Closing Debt | B9: =MAX(0,B5-B7) | C9: =MAX(0,C5-C7) | D9: =MAX(0,D5-D7) | E9: =MAX(0,E5-E7) | F9: =MAX(0,F5-F7) | G9: =MAX(0,G5-G7) | H9: =MAX(0,H5-H7) | I9: =MAX(0,I5-I7) | ... P9: =MAX(0,P5-P7)

Sheet 020_Income_Statement
A1: Income Statement
A2: P&L build
A4: Metric | B4: Y1 | C4: Y2 | D4: Y3 | E4: Y4 | F4: Y5 | G4: Y6 | H4: Y7 | I4: Y8 | J4: Y9 | K4: Y10 | L4: Y11 | M4: Y12 | N4: Y13 | O4: Y14 | P4: Y15
A5: Revenue | B5: ='011_Revenue_Model'!B7 | C5: ='011_Revenue_Model'!C7 | D5: ='011_Revenue_Model'!D7 | E5: ='011_Revenue_Model'!E7 | F5: ='011_Revenue_Model'!F7 | G5: ='011_Revenue_Model'!G7 | H5: ='011_Revenue_Model'!H7 | I5: ='011_Revenue_Model'!I7 | ... P5: ='011_Revenue_Model'!P7
A6: COGS | B6: ='012_COGS_Model'!B10 | C6: ='012_COGS_Model'!C10 | D6: ='012_COGS_Model'!D10 | E6: ='012_COGS_Model'!E10 | F6: ='012_COGS_Model'!F10 | G6: ='012_COGS_Model'!G10 | H6: ='012_COGS_Model'!H10 | I6: ='012_COGS_Model'!I10 | ... P6: ='012_COGS_Model'!P10
A7: Gross Profit | B7: =B5-B6 | C7: =C5-C6 | D7: =D5-D6 | E7: =E5-E6 | F7: =F5-F6 | G7: =G5-G6 | H7: =H5-H6 | I7: =I5-I6 | ... P7: =P5-P6
A8: OPEX | B8: ='013_OPEX_Model'!B8 | C8: ='013_OPEX_Model'!C8 | D8: ='013_OPEX_Model'!D8 | E8: ='013_OPEX_Model'!E8 | F8: ='013_OPEX_Model'!F8 | G8: ='013_OPEX_Model'!G8 | H8: ='013_OPEX_Model'!H8 | I8: ='013_OPEX_Model'!I8 | ... P8: ='013_OPEX_Model'!P8
A9: EBITDA | B9: =B7-B8 | C9: =C7-C8 | D9: =D7-D8 | E9: =E7-E8 | F9: =F7-F8 | G9: =G7-G8 | H9: =H7-H8 | I9: =I7-I8 | ... P9: =P7-P8
A10: Depreciation | B10: =0 | C10: =0 | D10: =0 | E10: =0 | F10: =0 | G10: =0 | H10: =0 | I10: =0 | ... P10: =0
A11: EBIT | B11: =B9-B10 | C11: =C9-C10 | D11: =D9-D10 | E11: =E9-E10 | F11: =F9-F10 | G11: =G9-G10 | H11: =H9-H10 | I11: =I9-I10 | ... P11: =P9-P10
A12: Interest | B12: ='016_Debt_Schedule'!B6 | C12: ='016_Debt_Schedule'!C6 | D12: ='016_Debt_Schedule'!D6 | E12: ='016_Debt_Schedule'!E6 | F12: ='016_Debt_Schedule'!F6 | G12: ='016_Debt_Schedule'!G6 | H12: ='016_Debt_Schedule'!H6 | I12: ='016_Debt_Schedule'!I6 | ... P12: ='016_Debt_Schedule'!P6
A13: PBT | B13: =B11-B12 | C13: =C11-C12 | D13: =D11-D12 | E13: =E11-E12 | F13: =F11-F12 | G13: =G11-G12 | H13: =H11-H12 | I13: =I11-I12 | ... P13: =P11-P12
A14: Tax | B14: =MAX(0,B13)*'002_Master_Assumptions'!C26 | C14: =MAX(0,C13)*'002_Master_Assumptions'!C26 | D14: =MAX(0,D13)*'002_Master_Assumptions'!C26 | E14: =MAX(0,E13)*'002_Master_Assumptions'!C26 | F14: =MAX(0,F13)*'002_Master_Assumptions'!C26 | G14: =MAX(0,G13)*'002_Master_Assumptions'!C26 | H14: =MAX(0,H13)*'002_Master_Assumptions'!C26 | I14: =MAX(0,I13)*'002_Master_Assumptions'!C26 | J14: =MAX(0,J13)*'002_Master_Assumptions'!C26 | K14: =MAX(0,K13)*'002_Master_Assumptions'!C26 | L14: =MAX(0,L13)*'002_Master_Assumptions'!C26 | M14: =MAX(0,M13)*'002_Master_Assumptions'!C26 | N14: =MAX(0,N13)*'002_Master_Assumptions'!C26 | O14: =MAX(0,O13)*'002_Master_Assumptions'!C26 | P14: =MAX(0,P13)*'002_Master_Assumptions'!C26
A15: Net Income | B15: =B13-B14 | C15: =C13-C14 | D15: =D13-D14 | E15: =E13-E14 | F15: =F13-F14 | G15: =G13-G14 | H15: =H13-H14 | I15: =I13-I14 | ... P15: =P13-P14

Sheet 021_Cash_Flow
A1: Cash Flow Statement
A2: Simplified project cash flow
A4: Metric | B4: Y1 | C4: Y2 | D4: Y3 | E4: Y4 | F4: Y5 | G4: Y6 | H4: Y7 | I4: Y8 | J4: Y9 | K4: Y10 | L4: Y11 | M4: Y12 | N4: Y13 | O4: Y14 | P4: Y15
A5: EBITDA | B5: ='020_Income_Statement'!B9 | C5: ='020_Income_Statement'!C9 | D5: ='020_Income_Statement'!D9 | E5: ='020_Income_Statement'!E9 | F5: ='020_Income_Statement'!F9 | G5: ='020_Income_Statement'!G9 | H5: ='020_Income_Statement'!H9 | I5: ='020_Income_Statement'!I9 | ... P5: ='020_Income_Statement'!P9
A6: Taxes | B6: ='020_Income_Statement'!B14 | C6: ='020_Income_Statement'!C14 | D6: ='020_Income_Statement'!D14 | E6: ='020_Income_Statement'!E14 | F6: ='020_Income_Statement'!F14 | G6: ='020_Income_Statement'!G14 | H6: ='020_Income_Statement'!H14 | I6: ='020_Income_Statement'!I14 | ... P6: ='020_Income_Statement'!P14
A7: CAPEX | B7: =0 | C7: =0 | D7: =0 | E7: =0 | F7: =0 | G7: =0 | H7: =0 | I7: =0 | ... P7: =0
A8: Debt Service | B8: ='016_Debt_Schedule'!B8 | C8: ='016_Debt_Schedule'!C8 | D8: ='016_Debt_Schedule'!D8 | E8: ='016_Debt_Schedule'!E8 | F8: ='016_Debt_Schedule'!F8 | G8: ='016_Debt_Schedule'!G8 | H8: ='016_Debt_Schedule'!H8 | I8: ='016_Debt_Schedule'!I8 | ... P8: ='016_Debt_Schedule'!P8
A9: Free Cash Flow | B9: =B5-B6-B7-B8 | C9: =C5-C6-C7-C8 | D9: =D5-D6-D7-D8 | E9: =E5-E6-E7-E8 | F9: =F5-F6-F7-F8 | G9: =G5-G6-G7-G8 | H9: =H5-H6-H7-H8 | I9: =I5-I6-I7-I8 | ... P9: =P5-P6-P7-P8

Sheet 022_Balance_Sheet
A1: Balance Sheet
A2: Placeholder BS structure
A4: Metric | B4: Y1 | C4: Y2 | D4: Y3 | E4: Y4 | F4: Y5 | G4: Y6 | H4: Y7 | I4: Y8 | J4: Y9 | K4: Y10 | L4: Y11 | M4: Y12 | N4: Y13 | O4: Y14 | P4: Y15
A5: Cash | B5: ='021_Cash_Flow'!B9 | C5: ='021_Cash_Flow'!C9 | D5: ='021_Cash_Flow'!D9 | E5: ='021_Cash_Flow'!E9 | F5: ='021_Cash_Flow'!F9 | G5: ='021_Cash_Flow'!G9 | H5: ='021_Cash_Flow'!H9 | I5: ='021_Cash_Flow'!I9 | ... P5: ='021_Cash_Flow'!P9
A6: PP&E Net | B6: ='014_CAPEX_Model'!B12 | C6: ='014_CAPEX_Model'!B12 | D6: ='014_CAPEX_Model'!B12 | E6: ='014_CAPEX_Model'!B12 | F6: ='014_CAPEX_Model'!B12 | G6: ='014_CAPEX_Model'!B12 | H6: ='014_CAPEX_Model'!B12 | I6: ='014_CAPEX_Model'!B12 | J6: ='014_CAPEX_Model'!B12 | K6: ='014_CAPEX_Model'!B12 | L6: ='014_CAPEX_Model'!B12 | M6: ='014_CAPEX_Model'!B12 | N6: ='014_CAPEX_Model'!B12 | O6: ='014_CAPEX_Model'!B12 | P6: ='014_CAPEX_Model'!B12
A7: Total Assets | B7: =B5+B6 | C7: =C5+C6 | D7: =D5+D6 | E7: =E5+E6 | F7: =F5+F6 | G7: =G5+G6 | H7: =H5+H6 | I7: =I5+I6 | ... P7: =P5+P6
A8: Debt | B8: ='016_Debt_Schedule'!B9 | C8: ='016_Debt_Schedule'!C9 | D8: ='016_Debt_Schedule'!D9 | E8: ='016_Debt_Schedule'!E9 | F8: ='016_Debt_Schedule'!F9 | G8: ='016_Debt_Schedule'!G9 | H8: ='016_Debt_Schedule'!H9 | I8: ='016_Debt_Schedule'!I9 | ... P8: ='016_Debt_Schedule'!P9
A9: Equity | B9: =B7-B8 | C9: =C7-C8 | D9: =D7-D8 | E9: =E7-E8 | F9: =F7-F8 | G9: =G7-G8 | H9: =H7-H8 | I9: =I7-I8 | ... P9: =P7-P8
A10: Total Liabilities + Equity | B10: =B8+B9 | C10: =C8+C9 | D10: =D8+D9 | E10: =E8+E9 | F10: =F8+F9 | G10: =G8+G9 | H10: =H8+H9 | I10: =I8+I9 | ... P10: =P8+P9

Sheet 030_Project_Finance_Metrics
A1: Project Finance Metrics
A2: Core project and lender KPIs
A4: Metric | B4: Formula / Value
A5: EBITDA Margin Y1 | B5: =IF('020_Income_Statement'!B5=0,0,'020_Income_Statement'!B9/'020_Income_Statement'!B5)
A6: Project NPV | B6: =NPV('002_Master_Assumptions'!C27,'021_Cash_Flow'!B9:P9)
A7: Project IRR | B7: =IRR('021_Cash_Flow'!B9:P9)
A8: Average DSCR | B8: =AVERAGE('031_DSCR_Model'!B5:P5)
A9: Payback Note | B9: Cumulative FCF turns positive year noted in dashboard

Sheet 031_DSCR_Model
A1: DSCR Model
A2: Cash available for debt service / debt service
A4: Metric | B4: Y1 | C4: Y2 | D4: Y3 | E4: Y4 | F4: Y5 | G4: Y6 | H4: Y7 | I4: Y8 | J4: Y9 | K4: Y10 | L4: Y11 | M4: Y12 | N4: Y13 | O4: Y14 | P4: Y15
A5: CFADS | B5: ='021_Cash_Flow'!B9 | C5: ='021_Cash_Flow'!C9 | D5: ='021_Cash_Flow'!D9 | E5: ='021_Cash_Flow'!E9 | F5: ='021_Cash_Flow'!F9 | G5: ='021_Cash_Flow'!G9 | H5: ='021_Cash_Flow'!H9 | I5: ='021_Cash_Flow'!I9 | ... P5: ='021_Cash_Flow'!P9
A6: Debt Service | B6: ='016_Debt_Schedule'!B8 | C6: ='016_Debt_Schedule'!C8 | D6: ='016_Debt_Schedule'!D8 | E6: ='016_Debt_Schedule'!E8 | F6: ='016_Debt_Schedule'!F8 | G6: ='016_Debt_Schedule'!G8 | H6: ='016_Debt_Schedule'!H8 | I6: ='016_Debt_Schedule'!I8 | ... P6: ='016_Debt_Schedule'!P8
A7: DSCR | B7: =IFERROR(B5/B6,0) | C7: =IFERROR(C5/C6,0) | D7: =IFERROR(D5/D6,0) | E7: =IFERROR(E5/E6,0) | F7: =IFERROR(F5/F6,0) | G7: =IFERROR(G5/G6,0) | H7: =IFERROR(H5/H6,0) | I7: =IFERROR(I5/I6,0) | ... P7: =IFERROR(P5/P6,0)

Sheet 099_Dashboard
A1: Executive Dashboard
A2: Headline investor and lender KPIs
A4: KPI | B4: Value
A5: Revenue Y1 | B5: ='020_Income_Statement'!B5
A6: EBITDA Y1 | B6: ='020_Income_Statement'!B9
A7: Net Income Y1 | B7: ='020_Income_Statement'!B15
A8: Project NPV | B8: ='030_Project_Finance_Metrics'!B6
A9: Project IRR | B9: ='030_Project_Finance_Metrics'!B7
A10: Average DSCR | B10: ='030_Project_Finance_Metrics'!B8

Sheet 040_CAPEX_01
A1: 040 CAPEX 01
A2: Structured placeholder module for expansion
A4: Item | B4: Input | C4: Calc | D4: Output | E4: Notes
A5: Line 1
A6: Line 2
A7: Line 3
A8: Line 4
A9: Line 5
A10: Line 6
A11: Line 7
A12: Line 8
A13: Line 9
A14: Line 10
A15: Line 11
A16: Line 12
... A24: Line 20

Sheet 040_CAPEX_02
A1: 040 CAPEX 02
A2: Structured placeholder module for expansion
A4: Item | B4: Input | C4: Calc | D4: Output | E4: Notes
A5: Line 1
A6: Line 2
A7: Line 3
A8: Line 4
A9: Line 5
A10: Line 6
A11: Line 7
A12: Line 8
A13: Line 9
A14: Line 10
A15: Line 11
A16: Line 12
... A24: Line 20

Sheet 040_CAPEX_03
A1: 040 CAPEX 03
A2: Structured placeholder module for expansion
A4: Item | B4: Input | C4: Calc | D4: Output | E4: Notes
A5: Line 1
A6: Line 2
A7: Line 3
A8: Line 4
A9: Line 5
A10: Line 6
A11: Line 7
A12: Line 8
A13: Line 9
A14: Line 10
A15: Line 11
A16: Line 12
... A24: Line 20

Sheet 040_CAPEX_04
A1: 040 CAPEX 04
A2: Structured placeholder module for expansion
A4: Item | B4: Input | C4: Calc | D4: Output | E4: Notes
A5: Line 1
A6: Line 2
A7: Line 3
A8: Line 4
A9: Line 5
A10: Line 6
A11: Line 7
A12: Line 8
A13: Line 9
A14: Line 10
A15: Line 11
A16: Line 12
... A24: Line 20

Sheet 040_CAPEX_05
A1: 040 CAPEX 05
A2: Structured placeholder module for expansion
A4: Item | B4: Input | C4: Calc | D4: Output | E4: Notes
A5: Line 1
A6: Line 2
A7: Line 3
A8: Line 4
A9: Line 5
A10: Line 6
A11: Line 7
A12: Line 8
A13: Line 9
A14: Line 10
A15: Line 11
A16: Line 12
... A24: Line 20

Sheet 040_CAPEX_06
A1: 040 CAPEX 06
A2: Structured placeholder module for expansion
A4: Item | B4: Input | C4: Calc | D4: Output | E4: Notes
A5: Line 1
A6: Line 2
A7: Line 3
A8: Line 4
A9: Line 5
A10: Line 6
A11: Line 7
A12: Line 8
A13: Line 9
A14: Line 10
A15: Line 11
A16: Line 12
... A24: Line 20

Sheet 040_CAPEX_07
A1: 040 CAPEX 07
A2: Structured placeholder module for expansion
A4: Item | B4: Input | C4: Calc | D4: Output | E4: Notes
A5: Line 1
A6: Line 2
A7: Line 3
A8: Line 4
A9: Line 5
A10: Line 6
A11: Line 7
A12: Line 8
A13: Line 9
A14: Line 10
A15: Line 11
A16: Line 12
... A24: Line 20

Sheet 040_CAPEX_08
A1: 040 CAPEX 08
A2: Structured placeholder module for expansion
A4: Item | B4: Input | C4: Calc | D4: Output | E4: Notes
A5: Line 1
A6: Line 2
A7: Line 3
A8: Line 4
A9: Line 5
A10: Line 6
A11: Line 7
A12: Line 8
A13: Line 9
A14: Line 10
A15: Line 11
A16: Line 12
... A24: Line 20

Sheet 050_Operations_01
A1: 050 Operations 01
A2: Structured placeholder module for expansion
A4: Driver | B4: Input | C4: Calc | D4: Output | E4: Notes
A5: Line 1
A6: Line 2
A7: Line 3
A8: Line 4
A9: Line 5
A10: Line 6
A11: Line 7
A12: Line 8
A13: Line 9
A14: Line 10
A15: Line 11
A16: Line 12
... A24: Line 20

Sheet 050_Operations_02
A1: 050 Operations 02
A2: Structured placeholder module for expansion
A4: Driver | B4: Input | C4: Calc | D4: Output | E4: Notes
A5: Line 1
A6: Line 2
A7: Line 3
A8: Line 4
A9: Line 5
A10: Line 6
A11: Line 7
A12: Line 8
A13: Line 9
A14: Line 10
A15: Line 11
A16: Line 12
... A24: Line 20

Sheet 050_Operations_03
A1: 050 Operations 03
A2: Structured placeholder module for expansion
A4: Driver | B4: Input | C4: Calc | D4: Output | E4: Notes
A5: Line 1
A6: Line 2
A7: Line 3
A8: Line 4
A9: Line 5
A10: Line 6
A11: Line 7
A12: Line 8
A13: Line 9
A14: Line 10
A15: Line 11
A16: Line 12
... A24: Line 20

Sheet 050_Operations_04
A1: 050 Operations 04
A2: Structured placeholder module for expansion
A4: Driver | B4: Input | C4: Calc | D4: Output | E4: Notes
A5: Line 1
A6: Line 2
A7: Line 3
A8: Line 4
A9: Line 5
A10: Line 6
A11: Line 7
A12: Line 8
A13: Line 9
A14: Line 10
A15: Line 11
A16: Line 12
... A24: Line 20

Sheet 050_Operations_05
A1: 050 Operations 05
A2: Structured placeholder module for expansion
A4: Driver | B4: Input | C4: Calc | D4: Output | E4: Notes
A5: Line 1
A6: Line 2
A7: Line 3
A8: Line 4
A9: Line 5
A10: Line 6
A11: Line 7
A12: Line 8
A13: Line 9
A14: Line 10
A15: Line 11
A16: Line 12
... A24: Line 20

Sheet 050_Operations_06
A1: 050 Operations 06
A2: Structured placeholder module for expansion
A4: Driver | B4: Input | C4: Calc | D4: Output | E4: Notes
A5: Line 1
A6: Line 2
A7: Line 3
A8: Line 4
A9: Line 5
A10: Line 6
A11: Line 7
A12: Line 8
A13: Line 9
A14: Line 10
A15: Line 11
A16: Line 12
... A24: Line 20

Sheet 050_Operations_07
A1: 050 Operations 07
A2: Structured placeholder module for expansion
A4: Driver | B4: Input | C4: Calc | D4: Output | E4: Notes
A5: Line 1
A6: Line 2
A7: Line 3
A8: Line 4
A9: Line 5
A10: Line 6
A11: Line 7
A12: Line 8
A13: Line 9
A14: Line 10
A15: Line 11
A16: Line 12
... A24: Line 20

Sheet 050_Operations_08
A1: 050 Operations 08
A2: Structured placeholder module for expansion
A4: Driver | B4: Input | C4: Calc | D4: Output | E4: Notes
A5: Line 1
A6: Line 2
A7: Line 3
A8: Line 4
A9: Line 5
A10: Line 6
A11: Line 7
A12: Line 8
A13: Line 9
A14: Line 10
A15: Line 11
A16: Line 12
... A24: Line 20

Sheet 050_Operations_09
A1: 050 Operations 09
A2: Structured placeholder module for expansion
A4: Driver | B4: Input | C4: Calc | D4: Output | E4: Notes
A5: Line 1
A6: Line 2
A7: Line 3
A8: Line 4
A9: Line 5
A10: Line 6
A11: Line 7
A12: Line 8
A13: Line 9
A14: Line 10
A15: Line 11
A16: Line 12
... A24: Line 20

Sheet 050_Operations_10
A1: 050 Operations 10
A2: Structured placeholder module for expansion
A4: Driver | B4: Input | C4: Calc | D4: Output | E4: Notes
A5: Line 1
A6: Line 2
A7: Line 3
A8: Line 4
A9: Line 5
A10: Line 6
A11: Line 7
A12: Line 8
A13: Line 9
A14: Line 10
A15: Line 11
A16: Line 12
... A24: Line 20

Sheet 060_Commodity_01
A1: 060 Commodity 01
A2: Structured placeholder module for expansion
A4: Variable | B4: Base | C4: Low | D4: High | E4: Notes
A5: Line 1
A6: Line 2
A7: Line 3
A8: Line 4
A9: Line 5
A10: Line 6
A11: Line 7
A12: Line 8
A13: Line 9
A14: Line 10
A15: Line 11
A16: Line 12
... A24: Line 20

Sheet 060_Commodity_02
A1: 060 Commodity 02
A2: Structured placeholder module for expansion
A4: Variable | B4: Base | C4: Low | D4: High | E4: Notes
A5: Line 1
A6: Line 2
A7: Line 3
A8: Line 4
A9: Line 5
A10: Line 6
A11: Line 7
A12: Line 8
A13: Line 9
A14: Line 10
A15: Line 11
A16: Line 12
... A24: Line 20

Sheet 060_Commodity_03
A1: 060 Commodity 03
A2: Structured placeholder module for expansion
A4: Variable | B4: Base | C4: Low | D4: High | E4: Notes
A5: Line 1
A6: Line 2
A7: Line 3
A8: Line 4
A9: Line 5
A10: Line 6
A11: Line 7
A12: Line 8
A13: Line 9
A14: Line 10
A15: Line 11
A16: Line 12
... A24: Line 20

Sheet 060_Commodity_04
A1: 060 Commodity 04
A2: Structured placeholder module for expansion
A4: Variable | B4: Base | C4: Low | D4: High | E4: Notes
A5: Line 1
A6: Line 2
A7: Line 3
A8: Line 4
A9: Line 5
A10: Line 6
A11: Line 7
A12: Line 8
A13: Line 9
A14: Line 10
A15: Line 11
A16: Line 12
... A24: Line 20

Sheet 060_Commodity_05
A1: 060 Commodity 05
A2: Structured placeholder module for expansion
A4: Variable | B4: Base | C4: Low | D4: High | E4: Notes
A5: Line 1
A6: Line 2
A7: Line 3
A8: Line 4
A9: Line 5
A10: Line 6
A11: Line 7
A12: Line 8
A13: Line 9
A14: Line 10
A15: Line 11
A16: Line 12
... A24: Line 20

Sheet 060_Commodity_06
A1: 060 Commodity 06
A2: Structured placeholder module for expansion
A4: Variable | B4: Base | C4: Low | D4: High | E4: Notes
A5: Line 1
A6: Line 2
A7: Line 3
A8: Line 4
A9: Line 5
A10: Line 6
A11: Line 7
A12: Line 8
A13: Line 9
A14: Line 10
A15: Line 11
A16: Line 12
... A24: Line 20

Sheet 060_Commodity_07
A1: 060 Commodity 07
A2: Structured placeholder module for expansion
A4: Variable | B4: Base | C4: Low | D4: High | E4: Notes
A5: Line 1
A6: Line 2
A7: Line 3
A8: Line 4
A9: Line 5
A10: Line 6
A11: Line 7
A12: Line 8
A13: Line 9
A14: Line 10
A15: Line 11
A16: Line 12
... A24: Line 20

Sheet 060_Commodity_08
A1: 060 Commodity 08
A2: Structured placeholder module for expansion
A4: Variable | B4: Base | C4: Low | D4: High | E4: Notes
A5: Line 1
A6: Line 2
A7: Line 3
A8: Line 4
A9: Line 5
A10: Line 6
A11: Line 7
A12: Line 8
A13: Line 9
A14: Line 10
A15: Line 11
A16: Line 12
... A24: Line 20

Sheet 070_Working_Capital_01
A1: 070 Working Capital 01
A2: Structured placeholder module for expansion
A4: Metric | B4: Days | C4: Calc | D4: Output | E4: Notes
A5: Line 1
A6: Line 2
A7: Line 3
A8: Line 4
A9: Line 5
A10: Line 6
A11: Line 7
A12: Line 8
A13: Line 9
A14: Line 10
A15: Line 11
A16: Line 12
... A24: Line 20

Sheet 070_Working_Capital_02
A1: 070 Working Capital 02
A2: Structured placeholder module for expansion
A4: Metric | B4: Days | C4: Calc | D4: Output | E4: Notes
A5: Line 1
A6: Line 2
A7: Line 3
A8: Line 4
A9: Line 5
A10: Line 6
A11: Line 7
A12: Line 8
A13: Line 9
A14: Line 10
A15: Line 11
A16: Line 12
... A24: Line 20

Sheet 070_Working_Capital_03
A1: 070 Working Capital 03
A2: Structured placeholder module for expansion
A4: Metric | B4: Days | C4: Calc | D4: Output | E4: Notes
A5: Line 1
A6: Line 2
A7: Line 3
A8: Line 4
A9: Line 5
A10: Line 6
A11: Line 7
A12: Line 8
A13: Line 9
A14: Line 10
A15: Line 11
A16: Line 12
... A24: Line 20

Sheet 070_Working_Capital_04
A1: 070 Working Capital 04
A2: Structured placeholder module for expansion
A4: Metric | B4: Days | C4: Calc | D4: Output | E4: Notes
A5: Line 1
A6: Line 2
A7: Line 3
A8: Line 4
A9: Line 5
A10: Line 6
A11: Line 7
A12: Line 8
A13: Line 9
A14: Line 10
A15: Line 11
A16: Line 12
... A24: Line 20

Sheet 070_Working_Capital_05
A1: 070 Working Capital 05
A2: Structured placeholder module for expansion
A4: Metric | B4: Days | C4: Calc | D4: Output | E4: Notes
A5: Line 1
A6: Line 2
A7: Line 3
A8: Line 4
A9: Line 5
A10: Line 6
A11: Line 7
A12: Line 8
A13: Line 9
A14: Line 10
A15: Line 11
A16: Line 12
... A24: Line 20

Sheet 070_Working_Capital_06
A1: 070 Working Capital 06
A2: Structured placeholder module for expansion
A4: Metric | B4: Days | C4: Calc | D4: Output | E4: Notes
A5: Line 1
A6: Line 2
A7: Line 3
A8: Line 4
A9: Line 5
A10: Line 6
A11: Line 7
A12: Line 8
A13: Line 9
A14: Line 10
A15: Line 11
A16: Line 12
... A24: Line 20

Sheet 080_Financing_01
A1: 080 Financing 01
A2: Structured placeholder module for expansion
A4: Metric | B4: Input | C4: Calc | D4: Output | E4: Notes
A5: Line 1
A6: Line 2
A7: Line 3
A8: Line 4
A9: Line 5
A10: Line 6
A11: Line 7
A12: Line 8
A13: Line 9
A14: Line 10
A15: Line 11
A16: Line 12
... A24: Line 20

Sheet 080_Financing_02
A1: 080 Financing 02
A2: Structured placeholder module for expansion
A4: Metric | B4: Input | C4: Calc | D4: Output | E4: Notes
A5: Line 1
A6: Line 2
A7: Line 3
A8: Line 4
A9: Line 5
A10: Line 6
A11: Line 7
A12: Line 8
A13: Line 9
A14: Line 10
A15: Line 11
A16: Line 12
... A24: Line 20

Sheet 080_Financing_03
A1: 080 Financing 03
A2: Structured placeholder module for expansion
A4: Metric | B4: Input | C4: Calc | D4: Output | E4: Notes
A5: Line 1
A6: Line 2
A7: Line 3
A8: Line 4
A9: Line 5
A10: Line 6
A11: Line 7
A12: Line 8
A13: Line 9
A14: Line 10
A15: Line 11
A16: Line 12
... A24: Line 20

Sheet 080_Financing_04
A1: 080 Financing 04
A2: Structured placeholder module for expansion
A4: Metric | B4: Input | C4: Calc | D4: Output | E4: Notes
A5: Line 1
A6: Line 2
A7: Line 3
A8: Line 4
A9: Line 5
A10: Line 6
A11: Line 7
A12: Line 8
A13: Line 9
A14: Line 10
A15: Line 11
A16: Line 12
... A24: Line 20

Sheet 080_Financing_05
A1: 080 Financing 05
A2: Structured placeholder module for expansion
A4: Metric | B4: Input | C4: Calc | D4: Output | E4: Notes
A5: Line 1
A6: Line 2
A7: Line 3
A8: Line 4
A9: Line 5
A10: Line 6
A11: Line 7
A12: Line 8
A13: Line 9
A14: Line 10
A15: Line 11
A16: Line 12
... A24: Line 20

Sheet 080_Financing_06
A1: 080 Financing 06
A2: Structured placeholder module for expansion
A4: Metric | B4: Input | C4: Calc | D4: Output | E4: Notes
A5: Line 1
A6: Line 2
A7: Line 3
A8: Line 4
A9: Line 5
A10: Line 6
A11: Line 7
A12: Line 8
A13: Line 9
A14: Line 10
A15: Line 11
A16: Line 12
... A24: Line 20

Sheet 080_Financing_07
A1: 080 Financing 07
A2: Structured placeholder module for expansion
A4: Metric | B4: Input | C4: Calc | D4: Output | E4: Notes
A5: Line 1
A6: Line 2
A7: Line 3
A8: Line 4
A9: Line 5
A10: Line 6
A11: Line 7
A12: Line 8
A13: Line 9
A14: Line 10
A15: Line 11
A16: Line 12
... A24: Line 20

Sheet 080_Financing_08
A1: 080 Financing 08
A2: Structured placeholder module for expansion
A4: Metric | B4: Input | C4: Calc | D4: Output | E4: Notes
A5: Line 1
A6: Line 2
A7: Line 3
A8: Line 4
A9: Line 5
A10: Line 6
A11: Line 7
A12: Line 8
A13: Line 9
A14: Line 10
A15: Line 11
A16: Line 12
... A24: Line 20

Sheet 080_Financing_09
A1: 080 Financing 09
A2: Structured placeholder module for expansion
A4: Metric | B4: Input | C4: Calc | D4: Output | E4: Notes
A5: Line 1
A6: Line 2
A7: Line 3
A8: Line 4
A9: Line 5
A10: Line 6
A11: Line 7
A12: Line 8
A13: Line 9
A14: Line 10
A15: Line 11
A16: Line 12
... A24: Line 20

Sheet 080_Financing_10
A1: 080 Financing 10
A2: Structured placeholder module for expansion
A4: Metric | B4: Input | C4: Calc | D4: Output | E4: Notes
A5: Line 1
A6: Line 2
A7: Line 3
A8: Line 4
A9: Line 5
A10: Line 6
A11: Line 7
A12: Line 8
A13: Line 9
A14: Line 10
A15: Line 11
A16: Line 12
... A24: Line 20

Sheet 090_Risk_01
A1: 090 Risk 01
A2: Structured placeholder module for expansion
A4: Risk Driver | B4: Scenario | C4: Impact | D4: Mitigant | E4: Notes
A5: Line 1
A6: Line 2
A7: Line 3
A8: Line 4
A9: Line 5
A10: Line 6
A11: Line 7
A12: Line 8
A13: Line 9
A14: Line 10
A15: Line 11
A16: Line 12
... A24: Line 20

Sheet 090_Risk_02
A1: 090 Risk 02
A2: Structured placeholder module for expansion
A4: Risk Driver | B4: Scenario | C4: Impact | D4: Mitigant | E4: Notes
A5: Line 1
A6: Line 2
A7: Line 3
A8: Line 4
A9: Line 5
A10: Line 6
A11: Line 7
A12: Line 8
A13: Line 9
A14: Line 10
A15: Line 11
A16: Line 12
... A24: Line 20

Sheet 090_Risk_03
A1: 090 Risk 03
A2: Structured placeholder module for expansion
A4: Risk Driver | B4: Scenario | C4: Impact | D4: Mitigant | E4: Notes
A5: Line 1
A6: Line 2
A7: Line 3
A8: Line 4
A9: Line 5
A10: Line 6
A11: Line 7
A12: Line 8
A13: Line 9
A14: Line 10
A15: Line 11
A16: Line 12
... A24: Line 20

Sheet 090_Risk_04
A1: 090 Risk 04
A2: Structured placeholder module for expansion
A4: Risk Driver | B4: Scenario | C4: Impact | D4: Mitigant | E4: Notes
A5: Line 1
A6: Line 2
A7: Line 3
A8: Line 4
A9: Line 5
A10: Line 6
A11: Line 7
A12: Line 8
A13: Line 9
A14: Line 10
A15: Line 11
A16: Line 12
... A24: Line 20

Sheet 090_Risk_05
A1: 090 Risk 05
A2: Structured placeholder module for expansion
A4: Risk Driver | B4: Scenario | C4: Impact | D4: Mitigant | E4: Notes
A5: Line 1
A6: Line 2
A7: Line 3
A8: Line 4
A9: Line 5
A10: Line 6
A11: Line 7
A12: Line 8
A13: Line 9
A14: Line 10
A15: Line 11
A16: Line 12
... A24: Line 20

Sheet 090_Risk_06
A1: 090 Risk 06
A2: Structured placeholder module for expansion
A4: Risk Driver | B4: Scenario | C4: Impact | D4: Mitigant | E4: Notes
A5: Line 1
A6: Line 2
A7: Line 3
A8: Line 4
A9: Line 5
A10: Line 6
A11: Line 7
A12: Line 8
A13: Line 9
A14: Line 10
A15: Line 11
A16: Line 12
... A24: Line 20

Sheet 090_Risk_07
A1: 090 Risk 07
A2: Structured placeholder module for expansion
A4: Risk Driver | B4: Scenario | C4: Impact | D4: Mitigant | E4: Notes
A5: Line 1
A6: Line 2
A7: Line 3
A8: Line 4
A9: Line 5
A10: Line 6
A11: Line 7
A12: Line 8
A13: Line 9
A14: Line 10
A15: Line 11
A16: Line 12
... A24: Line 20

Sheet 090_Risk_08
A1: 090 Risk 08
A2: Structured placeholder module for expansion
A4: Risk Driver | B4: Scenario | C4: Impact | D4: Mitigant | E4: Notes
A5: Line 1
A6: Line 2
A7: Line 3
A8: Line 4
A9: Line 5
A10: Line 6
A11: Line 7
A12: Line 8
A13: Line 9
A14: Line 10
A15: Line 11
A16: Line 12
... A24: Line 20

Sheet 090_Risk_09
A1: 090 Risk 09
A2: Structured placeholder module for expansion
A4: Risk Driver | B4: Scenario | C4: Impact | D4: Mitigant | E4: Notes
A5: Line 1
A6: Line 2
A7: Line 3
A8: Line 4
A9: Line 5
A10: Line 6
A11: Line 7
A12: Line 8
A13: Line 9
A14: Line 10
A15: Line 11
A16: Line 12
... A24: Line 20

Sheet 090_Risk_10
A1: 090 Risk 10
A2: Structured placeholder module for expansion
A4: Risk Driver | B4: Scenario | C4: Impact | D4: Mitigant | E4: Notes
A5: Line 1
A6: Line 2
A7: Line 3
A8: Line 4
A9: Line 5
A10: Line 6
A11: Line 7
A12: Line 8
A13: Line 9
A14: Line 10
A15: Line 11
A16: Line 12
... A24: Line 20

Sheet 090_Risk_11
A1: 090 Risk 11
A2: Structured placeholder module for expansion
A4: Risk Driver | B4: Scenario | C4: Impact | D4: Mitigant | E4: Notes
A5: Line 1
A6: Line 2
A7: Line 3
A8: Line 4
A9: Line 5
A10: Line 6
A11: Line 7
A12: Line 8
A13: Line 9
A14: Line 10
A15: Line 11
A16: Line 12
... A24: Line 20

Sheet 090_Risk_12
A1: 090 Risk 12
A2: Structured placeholder module for expansion
A4: Risk Driver | B4: Scenario | C4: Impact | D4: Mitigant | E4: Notes
A5: Line 1
A6: Line 2
A7: Line 3
A8: Line 4
A9: Line 5
A10: Line 6
A11: Line 7
A12: Line 8
A13: Line 9
A14: Line 10
A15: Line 11
A16: Line 12
... A24: Line 20

Sheet 100_AI_Forecast_01
A1: 100 AI Forecast 01
A2: Structured placeholder module for expansion
A4: Forecast Driver | B4: Input | C4: Model Step | D4: Output | E4: Notes
A5: Line 1
A6: Line 2
A7: Line 3
A8: Line 4
A9: Line 5
A10: Line 6
A11: Line 7
A12: Line 8
A13: Line 9
A14: Line 10
A15: Line 11
A16: Line 12
... A24: Line 20

Sheet 100_AI_Forecast_02
A1: 100 AI Forecast 02
A2: Structured placeholder module for expansion
A4: Forecast Driver | B4: Input | C4: Model Step | D4: Output | E4: Notes
A5: Line 1
A6: Line 2
A7: Line 3
A8: Line 4
A9: Line 5
A10: Line 6
A11: Line 7
A12: Line 8
A13: Line 9
A14: Line 10
A15: Line 11
A16: Line 12
... A24: Line 20

Sheet 100_AI_Forecast_03
A1: 100 AI Forecast 03
A2: Structured placeholder module for expansion
A4: Forecast Driver | B4: Input | C4: Model Step | D4: Output | E4: Notes
A5: Line 1
A6: Line 2
A7: Line 3
A8: Line 4
A9: Line 5
A10: Line 6
A11: Line 7
A12: Line 8
A13: Line 9
A14: Line 10
A15: Line 11
A16: Line 12
... A24: Line 20

Sheet 100_AI_Forecast_04
A1: 100 AI Forecast 04
A2: Structured placeholder module for expansion
A4: Forecast Driver | B4: Input | C4: Model Step | D4: Output | E4: Notes
A5: Line 1
A6: Line 2
A7: Line 3
A8: Line 4
A9: Line 5
A10: Line 6
A11: Line 7
A12: Line 8
A13: Line 9
A14: Line 10
A15: Line 11
A16: Line 12
... A24: Line 20

Sheet 100_AI_Forecast_05
A1: 100 AI Forecast 05
A2: Structured placeholder module for expansion
A4: Forecast Driver | B4: Input | C4: Model Step | D4: Output | E4: Notes
A5: Line 1
A6: Line 2
A7: Line 3
A8: Line 4
A9: Line 5
A10: Line 6
A11: Line 7
A12: Line 8
A13: Line 9
A14: Line 10
A15: Line 11
A16: Line 12
... A24: Line 20

Sheet 100_AI_Forecast_06
A1: 100 AI Forecast 06
A2: Structured placeholder module for expansion
A4: Forecast Driver | B4: Input | C4: Model Step | D4: Output | E4: Notes
A5: Line 1
A6: Line 2
A7: Line 3
A8: Line 4
A9: Line 5
A10: Line 6
A11: Line 7
A12: Line 8
A13: Line 9
A14: Line 10
A15: Line 11
A16: Line 12
... A24: Line 20

Sheet 100_AI_Forecast_07
A1: 100 AI Forecast 07
A2: Structured placeholder module for expansion
A4: Forecast Driver | B4: Input | C4: Model Step | D4: Output | E4: Notes
A5: Line 1
A6: Line 2
A7: Line 3
A8: Line 4
A9: Line 5
A10: Line 6
A11: Line 7
A12: Line 8
A13: Line 9
A14: Line 10
A15: Line 11
A16: Line 12
... A24: Line 20

Sheet 100_AI_Forecast_08
A1: 100 AI Forecast 08
A2: Structured placeholder module for expansion
A4: Forecast Driver | B4: Input | C4: Model Step | D4: Output | E4: Notes
A5: Line 1
A6: Line 2
A7: Line 3
A8: Line 4
A9: Line 5
A10: Line 6
A11: Line 7
A12: Line 8
A13: Line 9
A14: Line 10
A15: Line 11
A16: Line 12
... A24: Line 20

Sheet 100_AI_Forecast_09
A1: 100 AI Forecast 09
A2: Structured placeholder module for expansion
A4: Forecast Driver | B4: Input | C4: Model Step | D4: Output | E4: Notes
A5: Line 1
A6: Line 2
A7: Line 3
A8: Line 4
A9: Line 5
A10: Line 6
A11: Line 7
A12: Line 8
A13: Line 9
A14: Line 10
A15: Line 11
A16: Line 12
... A24: Line 20

Sheet 100_AI_Forecast_10
A1: 100 AI Forecast 10
A2: Structured placeholder module for expansion
A4: Forecast Driver | B4: Input | C4: Model Step | D4: Output | E4: Notes
A5: Line 1
A6: Line 2
A7: Line 3
A8: Line 4
A9: Line 5
A10: Line 6
A11: Line 7
A12: Line 8
A13: Line 9
A14: Line 10
A15: Line 11
A16: Line 12
... A24: Line 20

Sheet 110_Control_01
A1: 110 Control 01
A2: Structured placeholder module for expansion
A4: Check | B4: Status | C4: Threshold | D4: Result | E4: Notes
A5: Line 1
A6: Line 2
A7: Line 3
A8: Line 4
A9: Line 5
A10: Line 6
A11: Line 7
A12: Line 8
A13: Line 9
A14: Line 10
A15: Line 11
A16: Line 12
... A24: Line 20

Sheet 110_Control_02
A1: 110 Control 02
A2: Structured placeholder module for expansion
A4: Check | B4: Status | C4: Threshold | D4: Result | E4: Notes
A5: Line 1
A6: Line 2
A7: Line 3
A8: Line 4
A9: Line 5
A10: Line 6
A11: Line 7
A12: Line 8
A13: Line 9
A14: Line 10
A15: Line 11
A16: Line 12
... A24: Line 20

Sheet 110_Control_03
A1: 110 Control 03
A2: Structured placeholder module for expansion
A4: Check | B4: Status | C4: Threshold | D4: Result | E4: Notes
A5: Line 1
A6: Line 2
A7: Line 3
A8: Line 4
A9: Line 5
A10: Line 6
A11: Line 7
A12: Line 8
A13: Line 9
A14: Line 10
A15: Line 11
A16: Line 12
... A24: Line 20

Sheet 110_Control_04
A1: 110 Control 04
A2: Structured placeholder module for expansion
A4: Check | B4: Status | C4: Threshold | D4: Result | E4: Notes
A5: Line 1
A6: Line 2
A7: Line 3
A8: Line 4
A9: Line 5
A10: Line 6
A11: Line 7
A12: Line 8
A13: Line 9
A14: Line 10
A15: Line 11
A16: Line 12
... A24: Line 20

Sheet 110_Control_05
A1: 110 Control 05
A2: Structured placeholder module for expansion
A4: Check | B4: Status | C4: Threshold | D4: Result | E4: Notes
A5: Line 1
A6: Line 2
A7: Line 3
A8: Line 4
A9: Line 5
A10: Line 6
A11: Line 7
A12: Line 8
A13: Line 9
A14: Line 10
A15: Line 11
A16: Line 12
... A24: Line 20

Sheet 110_Control_06
A1: 110 Control 06
A2: Structured placeholder module for expansion
A4: Check | B4: Status | C4: Threshold | D4: Result | E4: Notes
A5: Line 1
A6: Line 2
A7: Line 3
A8: Line 4
A9: Line 5
A10: Line 6
A11: Line 7
A12: Line 8
A13: Line 9
A14: Line 10
A15: Line 11
A16: Line 12
... A24: Line 20

Sheet 110_Control_07
A1: 110 Control 07
A2: Structured placeholder module for expansion
A4: Check | B4: Status | C4: Threshold | D4: Result | E4: Notes
A5: Line 1
A6: Line 2
A7: Line 3
A8: Line 4
A9: Line 5
A10: Line 6
A11: Line 7
A12: Line 8
A13: Line 9
A14: Line 10
A15: Line 11
A16: Line 12
... A24: Line 20

Sheet 110_Control_08
A1: 110 Control 08
A2: Structured placeholder module for expansion
A4: Check | B4: Status | C4: Threshold | D4: Result | E4: Notes
A5: Line 1
A6: Line 2
A7: Line 3
A8: Line 4
A9: Line 5
A10: Line 6
A11: Line 7
A12: Line 8
A13: Line 9
A14: Line 10
A15: Line 11
A16: Line 12
... A24: Line 20

Sheet 110_Control_09
A1: 110 Control 09
A2: Structured placeholder module for expansion
A4: Check | B4: Status | C4: Threshold | D4: Result | E4: Notes
A5: Line 1
A6: Line 2
A7: Line 3
A8: Line 4
A9: Line 5
A10: Line 6
A11: Line 7
A12: Line 8
A13: Line 9
A14: Line 10
A15: Line 11
A16: Line 12
... A24: Line 20

Sheet 110_Control_10
A1: 110 Control 10
A2: Structured placeholder module for expansion
A4: Check | B4: Status | C4: Threshold | D4: Result | E4: Notes
A5: Line 1
A6: Line 2
A7: Line 3
A8: Line 4
A9: Line 5
A10: Line 6
A11: Line 7
A12: Line 8
A13: Line 9
A14: Line 10
A15: Line 11
A16: Line 12
... A24: Line 20

Sheet 110_Control_11
A1: 110 Control 11
A2: Structured placeholder module for expansion
A4: Check | B4: Status | C4: Threshold | D4: Result | E4: Notes
A5: Line 1
A6: Line 2
A7: Line 3
A8: Line 4
A9: Line 5
A10: Line 6
A11: Line 7
A12: Line 8
A13: Line 9
A14: Line 10
A15: Line 11
A16: Line 12
... A24: Line 20

Sheet 110_Control_12
A1: 110 Control 12
A2: Structured placeholder module for expansion
A4: Check | B4: Status | C4: Threshold | D4: Result | E4: Notes
A5: Line 1
A6: Line 2
A7: Line 3
A8: Line 4
A9: Line 5
A10: Line 6
A11: Line 7
A12: Line 8
A13: Line 9
A14: Line 10
A15: Line 11
A16: Line 12
... A24: Line 20

Sheet 120_Reporting_01
A1: 120 Reporting 01
A2: Structured placeholder module for expansion
A4: Report Item | B4: Source | C4: Calc | D4: Output | E4: Notes
A5: Line 1
A6: Line 2
A7: Line 3
A8: Line 4
A9: Line 5
A10: Line 6
A11: Line 7
A12: Line 8
A13: Line 9
A14: Line 10
A15: Line 11
A16: Line 12
... A24: Line 20

Sheet 120_Reporting_02
A1: 120 Reporting 02
A2: Structured placeholder module for expansion
A4: Report Item | B4: Source | C4: Calc | D4: Output | E4: Notes
A5: Line 1
A6: Line 2
A7: Line 3
A8: Line 4
A9: Line 5
A10: Line 6
A11: Line 7
A12: Line 8
A13: Line 9
A14: Line 10
A15: Line 11
A16: Line 12
... A24: Line 20

Sheet 120_Reporting_03
A1: 120 Reporting 03
A2: Structured placeholder module for expansion
A4: Report Item | B4: Source | C4: Calc | D4: Output | E4: Notes
A5: Line 1
A6: Line 2
A7: Line 3
A8: Line 4
A9: Line 5
A10: Line 6
A11: Line 7
A12: Line 8
A13: Line 9
A14: Line 10
A15: Line 11
A16: Line 12
... A24: Line 20

Sheet 120_Reporting_04
A1: 120 Reporting 04
A2: Structured placeholder module for expansion
A4: Report Item | B4: Source | C4: Calc | D4: Output | E4: Notes
A5: Line 1
A6: Line 2
A7: Line 3
A8: Line 4
A9: Line 5
A10: Line 6
A11: Line 7
A12: Line 8
A13: Line 9
A14: Line 10
A15: Line 11
A16: Line 12
... A24: Line 20

Sheet 120_Reporting_05
A1: 120 Reporting 05
A2: Structured placeholder module for expansion
A4: Report Item | B4: Source | C4: Calc | D4: Output | E4: Notes
A5: Line 1
A6: Line 2
A7: Line 3
A8: Line 4
A9: Line 5
A10: Line 6
A11: Line 7
A12: Line 8
A13: Line 9
A14: Line 10
A15: Line 11
A16: Line 12
... A24: Line 20

Sheet 120_Reporting_06
A1: 120 Reporting 06
A2: Structured placeholder module for expansion
A4: Report Item | B4: Source | C4: Calc | D4: Output | E4: Notes
A5: Line 1
A6: Line 2
A7: Line 3
A8: Line 4
A9: Line 5
A10: Line 6
A11: Line 7
A12: Line 8
A13: Line 9
A14: Line 10
A15: Line 11
A16: Line 12
... A24: Line 20

Sheet 120_Reporting_07
A1: 120 Reporting 07
A2: Structured placeholder module for expansion
A4: Report Item | B4: Source | C4: Calc | D4: Output | E4: Notes
A5: Line 1
A6: Line 2
A7: Line 3
A8: Line 4
A9: Line 5
A10: Line 6
A11: Line 7
A12: Line 8
A13: Line 9
A14: Line 10
A15: Line 11
A16: Line 12
... A24: Line 20

Sheet 120_Reporting_08
A1: 120 Reporting 08
A2: Structured placeholder module for expansion
A4: Report Item | B4: Source | C4: Calc | D4: Output | E4: Notes
A5: Line 1
A6: Line 2
A7: Line 3
A8: Line 4
A9: Line 5
A10: Line 6
A11: Line 7
A12: Line 8
A13: Line 9
A14: Line 10
A15: Line 11
A16: Line 12
... A24: Line 20

Sheet 130_MonteCarlo_Variables
A1: 130 MonteCarlo Variables
A4: Parameter | B4: Input | C4: Calc | D4: Output | E4: Notes

Sheet 131_MonteCarlo_Simulations
A1: 131 MonteCarlo Simulations
A4: Parameter | B4: Input | C4: Calc | D4: Output | E4: Notes

Sheet 132_MonteCarlo_Distribution
A1: 132 MonteCarlo Distribution
A4: Parameter | B4: Input | C4: Calc | D4: Output | E4: Notes

Sheet 133_Tornado_Analysis
A1: 133 Tornado Analysis
A4: Parameter | B4: Input | C4: Calc | D4: Output | E4: Notes

Sheet 134_Steel_Stochastic_Model
A1: 134 Steel Stochastic Model
A4: Parameter | B4: Input | C4: Calc | D4: Output | E4: Notes

Sheet 135_Energy_Stochastic_Model
A1: 135 Energy Stochastic Model
A4: Parameter | B4: Input | C4: Calc | D4: Output | E4: Notes

Sheet 136_Demand_AI_Forecast
A1: 136 Demand AI Forecast
A4: Parameter | B4: Input | C4: Calc | D4: Output | E4: Notes

Sheet 137_Price_AI_Forecast
A1: 137 Price AI Forecast
A4: Parameter | B4: Input | C4: Calc | D4: Output | E4: Notes

Sheet 138_Exit_Valuation_Model
A1: 138 Exit Valuation Model
A4: Parameter | B4: Input | C4: Calc | D4: Output | E4: Notes

Sheet 139_Equity_Waterfall
A1: 139 Equity Waterfall
A4: Parameter | B4: Input | C4: Calc | D4: Output | E4: Notes

Sheet 140_Cash_Waterfall
A1: 140 Cash Waterfall
A4: Parameter | B4: Input | C4: Calc | D4: Output | E4: Notes

Sheet 141_MOIC_Model
A1: 141 MOIC Model
A4: Parameter | B4: Input | C4: Calc | D4: Output | E4: Notes

Sheet 142_LLCR_Model
A1: 142 LLCR Model
A4: Parameter | B4: Input | C4: Calc | D4: Output | E4: Notes

Sheet 143_PLCR_Model
A1: 143 PLCR Model
A4: Parameter | B4: Input | C4: Calc | D4: Output | E4: Notes

Sheet 144_Error_Check
A1: 144 Error Check
A4: Parameter | B4: Input | C4: Calc | D4: Output | E4: Notes

Sheet 145_Model_Assurance
A1: 145 Model Assurance
A4: Parameter | B4: Input | C4: Calc | D4: Output | E4: Notes

Sheet 146_Version_Control
A1: 146 Version Control
A4: Parameter | B4: Input | C4: Calc | D4: Output | E4: Notes

Sheet 147_Credit_Committee_Pack
A1: 147 Credit Committee Pack
A4: Parameter | B4: Input | C4: Calc | D4: Output | E4: Notes

Sheet 148_Investor_Pack_Data
A1: 148 Investor Pack Data
A4: Parameter | B4: Input | C4: Calc | D4: Output | E4: Notes

Sheet 149_Board_Report
A1: 149 Board Report
A4: Parameter | B4: Input | C4: Calc | D4: Output | E4: Notes

Sheet 150_Management_Report
A1: 150 Management Report
A4: Parameter | B4: Input | C4: Calc | D4: Output | E4: Notes
