Workbook

Sheet Assumptions
A1: Parameter | B1: Value | C1: Notes
A2: Total CAPEX (€) | B2: 12000000 | C2: Base investment
A3: Grant % | B3: 0.2 | C3: EU Grant
A4: Debt % | B4: 0.4 | C4: Bank Loan
A5: Equity % | B5: 0.15 | C5: Equity
A6: Shareholder Loan % | B6: 0.25 | C6: Subordinated
A7: Interest Rate | B7: 0.06 | C7: Annual
A8: Loan Tenor (years) | B8: 8 | C8: Repayment period
A9: Construction Months | B9: 24 | C9: Build duration
A10: Adj. Construction Months | B10: =B9+Scenario_Manager!$B$23 -> 24 | C10: Includes scenario delay
A11: Operational Drivers
A12: Start Year | B12: 2026 | C12: Model start (calendar year)
A13: Installed Capacity (t) - Y1 | B13: 8000 | C13: Nameplate capacity first year
A14: Installed Capacity (t) - Y2 | B14: 10000 | C14: After ramp/upgrade
A15: Installed Capacity (t) - Y3 | B15: 12000 | C15: Steady-state capacity
A16: Utilization % - Y1 | B16: 0.55 | C16: Ramp-up
A17: Utilization % - Y2 | B17: 0.7 | C17: Ramp-up
A18: Utilization % - Y3 | B18: 0.85 | C18: Steady-state
A19: Base Price (€/t) - Y1 | B19: 525 | C19: Avg selling price
A20: Price Escalation % | B20: 0.03 | C20: Annual escalation
A21: Energy Cost (€/t) - Y1 | B21: 45 | C21: Variable
A22: Labor Cost (€/t) - Y1 | B22: 35 | C22: Variable
A23: Materials & Other Var (€/t) - Y1 | B23: 280 | C23: Variable
... A26: Fixed Cost Escalation % | B26: 0.03 | C26: Annual escalation
A27: Scenario-adjusted totals
A28: Total CAPEX (Adj) | B28: =B2*Scenario_Manager!$B$22 -> 11760000 | C28: Base × scenario CAPEX factor
A29: CAPEX Split % - Y1 | B29: 0.6 | C29: Construction year 1 spend share
A30: CAPEX Split % - Y2 | B30: 0.4 | C30: Construction year 2 spend share
A31: CAPEX Split % - Y3 | B31: 0 | C31: Typically 0

Sheet Scenario_Manager
A1: SCENARIO MANAGER (Connected Planning Engine)
A3: Selected Scenario | B3: Base | D3: Last Update | E3: =NOW() -> 46085.683
A5: Scenario Multipliers
A6: Variable | B6: Base | C6: Optimistic | D6: Downside | E6: Delay | F6: Price_Shock
A7: Price Factor | B7: 1 | C7: 1.05 | D7: 0.85 | E7: 1 | F7: 0.7
A8: Volume / Utilization Factor | B8: 1 | C8: 1.1 | D8: 0.9 | E8: 0.85 | F8: 0.9
A9: Variable Cost Factor | B9: 1 | C9: 0.98 | D9: 1.1 | E9: 1.1 | F9: 1.25
A10: Fixed Cost Factor | B10: 1 | C10: 1 | D10: 1.05 | E10: 1.05 | F10: 1.1
A11: CAPEX Factor | B11: 1 | C11: 0.98 | D11: 1.05 | E11: 1.05 | F11: 1.1
A12: Construction Delay (months) | B12: 0 | C12: 0 | D12: 0 | E12: 6 | F12: 0
A13: Discount Rate (override)
A16: Active Multipliers (by Selected Scenario)
A17: Variable | B17: Active | D17: Scenario Column | E17: =MATCH($B$3,$B$6:$G$6,0)+1 -> 2
A18: Price Factor | B18: =INDEX($B$7:$G$12, MATCH(A18, $A$7:$A$12,0), $E$17) -> 1.05
A19: Volume / Utilization Factor | B19: =INDEX($B$7:$G$12, MATCH(A19, $A$7:$A$12,0), $E$17) -> 1.1
A20: Variable Cost Factor | B20: =INDEX($B$7:$G$12, MATCH(A20, $A$7:$A$12,0), $E$17) -> 0.98
A21: Fixed Cost Factor | B21: =INDEX($B$7:$G$12, MATCH(A21, $A$7:$A$12,0), $E$17) -> 1
A22: CAPEX Factor | B22: =INDEX($B$7:$G$12, MATCH(A22, $A$7:$A$12,0), $E$17) -> 0.98
A23: Construction Delay (months) | B23: =INDEX($B$7:$G$12, MATCH(A23, $A$7:$A$12,0), $E$17) -> 0

Sheet Production_Drivers
A1: PRODUCTION DRIVERS (Capacity → Utilization → Production)
A3: Year | B3: Installed Capacity (t) | C3: Utilization % | D3: Scenario Volume Factor | E3: Production (t)
A4: =Assumptions!$B$12+0 -> 2026 | B4: =Assumptions!$B$13 -> 8000 | C4: =Assumptions!$B$16 -> 0.55 | D4: =Scenario_Manager!$B$19 -> 1.1 | E4: =B4*C4*D4 -> 4840
A5: =Assumptions!$B$12+1 -> 2027 | B5: =Assumptions!$B$14 -> 10000 | C5: =Assumptions!$B$17 -> 0.7 | D5: =Scenario_Manager!$B$19 -> 1.1 | E5: =B5*C5*D5 -> 7700
A6: =Assumptions!$B$12+2 -> 2028 | B6: =Assumptions!$B$15 -> 12000 | C6: =Assumptions!$B$18 -> 0.85 | D6: =Scenario_Manager!$B$19 -> 1.1 | E6: =B6*C6*D6 -> 11220
A8: Notes
A9: Production is driven by nameplate capacity × utilization × scenario volume factor.

Sheet Sales_Drivers
A1: SALES DRIVERS (Production → Price → Revenue)
A3: Year | B3: Production (t) | C3: Base Price (€/t) | D3: Scenario Price Factor | E3: Realized Price (€/t) | F3: Revenue (€)
A4: =Assumptions!$B$12+0 -> 2026 | B4: =Production_Drivers!E4 -> 4840 | C4: =Assumptions!$B$19*(1+Assumptions!$B$20)^0 -> 525 | D4: =Scenario_Manager!$B$18 -> 1.05 | E4: =C4*D4 -> 551.25 | F4: =B4*E4 -> 2668050
A5: =Assumptions!$B$12+1 -> 2027 | B5: =Production_Drivers!E5 -> 7700 | C5: =Assumptions!$B$19*(1+Assumptions!$B$20)^1 -> 540.75 | D5: =Scenario_Manager!$B$18 -> 1.05 | E5: =C5*D5 -> 567.7875 | F5: =B5*E5 -> 4371963.8
A6: =Assumptions!$B$12+2 -> 2028 | B6: =Production_Drivers!E6 -> 11220 | C6: =Assumptions!$B$19*(1+Assumptions!$B$20)^2 -> 556.9725 | D6: =Scenario_Manager!$B$18 -> 1.05 | E6: =C6*D6 -> 584.82112 | F6: =B6*E6 -> 6561693
A8: 3-year CAGR (Revenue) | B8: =(F6/F4)^(1/2)-1 -> 0.56823439

Sheet Cost_Drivers
A1: COST DRIVERS (€/t → Total Costs → EBITDA)
A3: Year | B3: Production (t) | C3: Energy €/t | D3: Labor €/t | E3: Mat+Other €/t | F3: Var Cost Factor | G3: Total Variable (€) | H3: Fixed Costs (€) | I3: Total Costs (€) | J3: EBITDA (€)
A4: =Assumptions!$B$12+0 -> 2026 | B4: =Production_Drivers!E4 -> 4840 | C4: =Assumptions!$B$21*(1+Assumptions!$B$24)^0 -> 45 | D4: =Assumptions!$B$22*(1+Assumptions!$B$24)^0 -> 35 | E4: =Assumptions!$B$23*(1+Assumptions!$B$24)^0 -> 280 | F4: =Scenario_Manager!$B$20 -> 0.98 | G4: =B4*(C4+D4+E4)*F4 -> 1707552 | H4: =Assumptions!$B$25*(1+Assumptions!$B$26)^0*Scenario_Manager!$B$21 -> 850000 | I4: =G4+H4 -> 2557552 | J4: =Sales_Drivers!F4-I4 -> 110498
A5: =Assumptions!$B$12+1 -> 2027 | B5: =Production_Drivers!E5 -> 7700 | C5: =Assumptions!$B$21*(1+Assumptions!$B$24)^1 -> 46.125 | D5: =Assumptions!$B$22*(1+Assumptions!$B$24)^1 -> 35.875 | E5: =Assumptions!$B$23*(1+Assumptions!$B$24)^1 -> 287 | F5: =Scenario_Manager!$B$20 -> 0.98 | G5: =B5*(C5+D5+E5)*F5 -> 2784474 | H5: =Assumptions!$B$25*(1+Assumptions!$B$26)^1*Scenario_Manager!$B$21 -> 875500 | I5: =G5+H5 -> 3659974 | J5: =Sales_Drivers!F5-I5 -> 711989.75
A6: =Assumptions!$B$12+2 -> 2028 | B6: =Production_Drivers!E6 -> 11220 | C6: =Assumptions!$B$21*(1+Assumptions!$B$24)^2 -> 47.278125 | D6: =Assumptions!$B$22*(1+Assumptions!$B$24)^2 -> 36.771875 | E6: =Assumptions!$B$23*(1+Assumptions!$B$24)^2 -> 294.175 | F6: =Scenario_Manager!$B$20 -> 0.98 | G6: =B6*(C6+D6+E6)*F6 -> 4158810.8 | H6: =Assumptions!$B$25*(1+Assumptions!$B$26)^2*Scenario_Manager!$B$21 -> 901765 | I6: =G6+H6 -> 5060575.8 | J6: =Sales_Drivers!F6-I6 -> 1501117.2

Sheet CAPEX_Drivers
A1: CAPEX DRIVERS (Scenario CAPEX + Delay → S-curve)
A3: Base Total CAPEX (€) | B3: =Assumptions!B2 -> 12000000 | D3: CAPEX Spend (S-curve)
A4: Scenario CAPEX Factor | B4: =Scenario_Manager!$B$22 -> 0.98 | D4: Month | E4: Spend (€)
A5: Adj Total CAPEX (€) | B5: =Assumptions!$B$28 -> 11760000 | D5: =CAPEX_Scurve!A2 -> 1 | E5: =CAPEX_Scurve!B2 -> 490000
D6: =CAPEX_Scurve!A3 -> 2 | E6: =CAPEX_Scurve!B3 -> 490000
A7: Construction Months (Base) | B7: =Assumptions!$B$9 -> 24 | D7: =CAPEX_Scurve!A4 -> 3 | E7: =CAPEX_Scurve!B4 -> 490000
A8: Delay (months) | B8: =Scenario_Manager!$B$23 -> 0 | D8: =CAPEX_Scurve!A5 -> 4 | E8: =CAPEX_Scurve!B5 -> 490000
A9: Construction Months (Adj) | B9: =Assumptions!$B$10 -> 24 | D9: =CAPEX_Scurve!A6 -> 5 | E9: =CAPEX_Scurve!B6 -> 490000
D10: =CAPEX_Scurve!A7 -> 6 | E10: =CAPEX_Scurve!B7 -> 490000
A11: Monthly Spend (Avg) | B11: =B5/B9 -> 490000 | D11: =CAPEX_Scurve!A8 -> 7 | E11: =CAPEX_Scurve!B8 -> 490000
D12: =CAPEX_Scurve!A9 -> 8 | E12: =CAPEX_Scurve!B9 -> 490000
D13: =CAPEX_Scurve!A10 -> 9 | E13: =CAPEX_Scurve!B10 -> 490000
D14: =CAPEX_Scurve!A11 -> 10 | E14: =CAPEX_Scurve!B11 -> 490000
D15: =CAPEX_Scurve!A12 -> 11 | E15: =CAPEX_Scurve!B12 -> 490000
D16: =CAPEX_Scurve!A13 -> 12 | E16: =CAPEX_Scurve!B13 -> 490000
D17: =CAPEX_Scurve!A14 -> 13 | E17: =CAPEX_Scurve!B14 -> 490000
D18: =CAPEX_Scurve!A15 -> 14 | E18: =CAPEX_Scurve!B15 -> 490000
D19: =CAPEX_Scurve!A16 -> 15 | E19: =CAPEX_Scurve!B16 -> 490000
D20: =CAPEX_Scurve!A17 -> 16 | E20: =CAPEX_Scurve!B17 -> 490000
D21: =CAPEX_Scurve!A18 -> 17 | E21: =CAPEX_Scurve!B18 -> 490000
D22: =CAPEX_Scurve!A19 -> 18 | E22: =CAPEX_Scurve!B19 -> 490000
D23: =CAPEX_Scurve!A20 -> 19 | E23: =CAPEX_Scurve!B20 -> 490000
... D28: =CAPEX_Scurve!A25 -> 24 | E28: =CAPEX_Scurve!B25 -> 490000

Sheet Funding_Drivers
A1: FUNDING DRIVERS (Sources mix → Uses)
A3: Source | B3: % | C3: Amount (€) | D3: Notes
A4: EU Grant | B4: =Assumptions!B3 -> 0.2 | C4: =Assumptions!$B$28*B4 -> 2352000 | D4: EU grant %
A5: Senior Debt | B5: =Assumptions!B4 -> 0.4 | C5: =Assumptions!$B$28*B5 -> 4704000 | D5: Bank debt %
A6: Equity | B6: =Assumptions!B5 -> 0.15 | C6: =Assumptions!$B$28*B6 -> 1764000 | D6: Equity %
A7: Shareholder Loan | B7: =Assumptions!B6 -> 0.25 | C7: =Assumptions!$B$28*B7 -> 2940000 | D7: Subordinated %
A9: Check: Sources % = 100% | B9: =SUM(B4:B7) -> 1 | C9: =IF(ABS(B9-1)<0.0001,"OK","CHECK") -> OK

Sheet Automation_Hub
A1: AUTOMATION HUB (No macros) — 3-Step Runbook
A3: Step | B3: What to do
A4: 1) Select Scenario | B4: Go to Scenario_Manager and choose a scenario in cell B3.
A5: 2) Recalculate Model | B5: Press F9 (or Formulas → Calculate Now) to refresh scenario + Monte Carlo.
A6: 3) Review Dashboard 2.0 | B6: Go to Dashboard_2.0 to see KPIs, charts, DSCR, and cash metrics.
A8: Navigation
A9: Go to sheet | B9: Purpose
A10: Scenario_Manager | B10: Set scenario + multipliers
A11: Production_Drivers | B11: Capacity & utilization
A12: Sales_Drivers | B12: Price & revenue
A13: Cost_Drivers | B13: Costs & EBITDA
A14: CAPEX_Drivers | B14: CAPEX + delay
A15: Funding_Drivers | B15: Funding mix
A16: Dashboard_2.0 | B16: CFO cockpit
A17: Monte_Carlo | B17: Simulation (press F9)
A18: Bank_Pack | B18: Printable bank tables

Sheet Dashboard_2.0
A1: DASHBOARD 2.0 — ARS ULTRA CFO CONNECTED PLANNING
B3: Revenue (Y3) | C3: EBITDA (Y3) | D3: EBITDA Margin (Y3) | E3: Min DSCR | F3: IRR (Proxy) | G3: NPV (@8%)
B4: =Financials!B4 -> 6561693 | C4: =Financials!C4 -> 1501117.2 | D4: =IF(Financials!B4=0,"-",Financials!C4/Financials!B4) -> 0.2287698 | E4: =MIN(DSCR!D2:D4) -> 0.30693889 | F4: =NPV_IRR!B10 -> -0.7955527 | G4: =NPV_IRR!B9 -> -9546778.5
B6: Adj CAPEX Total | C6: Grant Amount | D6: Debt Amount | E6: Equity Amount | F6: SH Loan Amount | G6: Delay (months)
B7: =Assumptions!$B$28 -> 11760000 | C7: =Funding_Drivers!C4 -> 2352000 | D7: =Funding_Drivers!C5 -> 4704000 | E7: =Funding_Drivers!C6 -> 1764000 | F7: =Funding_Drivers!C7 -> 2940000 | G7: =Scenario_Manager!$B$23 -> 0
B10: Revenue & EBITDA | F10: DSCR
B11: Year | C11: Revenue | D11: EBITDA | F11: Year | G11: DSCR
B12: =Financials!A2 -> 2026 | C12: =Financials!B2 -> 2668050 | D12: =Financials!C2 -> 110498 | F12: =DSCR!A2 -> 2026 | G12: =DSCR!D2 -> 0.30693889
B13: =Financials!A3 -> 2027 | C13: =Financials!B3 -> 4371963.8 | D13: =Financials!C3 -> 711989.75 | F13: =DSCR!A3 -> 2027 | G13: =DSCR!D3 -> 1.9777493
B14: =Financials!A4 -> 2028 | C14: =Financials!B4 -> 6561693 | D14: =Financials!C4 -> 1501117.2 | F14: =DSCR!A4 -> 2028 | G14: =DSCR!D4 -> 4.9056118

Sheet CAPEX_Scurve
A1: Month | B1: CAPEX Spend (€)
A2: 1 | B2: =Assumptions!$B$28/Assumptions!$B$10 -> 490000
A3: 2 | B3: =Assumptions!$B$28/Assumptions!$B$10 -> 490000
A4: 3 | B4: =Assumptions!$B$28/Assumptions!$B$10 -> 490000
A5: 4 | B5: =Assumptions!$B$28/Assumptions!$B$10 -> 490000
A6: 5 | B6: =Assumptions!$B$28/Assumptions!$B$10 -> 490000
A7: 6 | B7: =Assumptions!$B$28/Assumptions!$B$10 -> 490000
A8: 7 | B8: =Assumptions!$B$28/Assumptions!$B$10 -> 490000
A9: 8 | B9: =Assumptions!$B$28/Assumptions!$B$10 -> 490000
A10: 9 | B10: =Assumptions!$B$28/Assumptions!$B$10 -> 490000
A11: 10 | B11: =Assumptions!$B$28/Assumptions!$B$10 -> 490000
A12: 11 | B12: =Assumptions!$B$28/Assumptions!$B$10 -> 490000
A13: 12 | B13: =Assumptions!$B$28/Assumptions!$B$10 -> 490000
... A25: 24 | B25: =Assumptions!$B$28/Assumptions!$B$10 -> 490000

Sheet Funding_Draw
A1: Source | B1: Amount (€)
A2: Grant | B2: =Assumptions!B2*Assumptions!B3 -> 2400000
A3: Debt | B3: =Assumptions!B2*Assumptions!B4 -> 4800000
A4: Equity | B4: =Assumptions!B2*Assumptions!B5 -> 1800000
A5: Shareholder Loan | B5: =Assumptions!B2*Assumptions!B6 -> 3000000

Sheet IDC
A1: Month | B1: Debt Draw (€) | C1: Interest (€)
A2: 1 | B2: =Funding_Draw!B2/24 -> 100000 | C2: =B2*Assumptions!B7/12 -> 500
A3: 2 | B3: =Funding_Draw!B2/24 -> 100000 | C3: =B2*Assumptions!B7/12 -> 500
A4: 3 | B4: =Funding_Draw!B2/24 -> 100000 | C4: =B2*Assumptions!B7/12 -> 500
A5: 4 | B5: =Funding_Draw!B2/24 -> 100000 | C5: =B2*Assumptions!B7/12 -> 500
A6: 5 | B6: =Funding_Draw!B2/24 -> 100000 | C6: =B2*Assumptions!B7/12 -> 500
A7: 6 | B7: =Funding_Draw!B2/24 -> 100000 | C7: =B2*Assumptions!B7/12 -> 500
A8: 7 | B8: =Funding_Draw!B2/24 -> 100000 | C8: =B2*Assumptions!B7/12 -> 500
A9: 8 | B9: =Funding_Draw!B2/24 -> 100000 | C9: =B2*Assumptions!B7/12 -> 500
A10: 9 | B10: =Funding_Draw!B2/24 -> 100000 | C10: =B2*Assumptions!B7/12 -> 500
A11: 10 | B11: =Funding_Draw!B2/24 -> 100000 | C11: =B2*Assumptions!B7/12 -> 500
A12: 11 | B12: =Funding_Draw!B2/24 -> 100000 | C12: =B2*Assumptions!B7/12 -> 500
A13: 12 | B13: =Funding_Draw!B2/24 -> 100000 | C13: =B2*Assumptions!B7/12 -> 500
A14: 13 | B14: =Funding_Draw!B2/24 -> 100000 | C14: =B2*Assumptions!B7/12 -> 500
A15: 14 | B15: =Funding_Draw!B2/24 -> 100000 | C15: =B2*Assumptions!B7/12 -> 500
A16: 15 | B16: =Funding_Draw!B2/24 -> 100000 | C16: =B2*Assumptions!B7/12 -> 500
A17: 16 | B17: =Funding_Draw!B2/24 -> 100000 | C17: =B2*Assumptions!B7/12 -> 500
A18: 17 | B18: =Funding_Draw!B2/24 -> 100000 | C18: =B2*Assumptions!B7/12 -> 500
A19: 18 | B19: =Funding_Draw!B2/24 -> 100000 | C19: =B2*Assumptions!B7/12 -> 500
A20: 19 | B20: =Funding_Draw!B2/24 -> 100000 | C20: =B2*Assumptions!B7/12 -> 500
A21: 20 | B21: =Funding_Draw!B2/24 -> 100000 | C21: =B2*Assumptions!B7/12 -> 500
A22: 21 | B22: =Funding_Draw!B2/24 -> 100000 | C22: =B2*Assumptions!B7/12 -> 500
A23: 22 | B23: =Funding_Draw!B2/24 -> 100000 | C23: =B2*Assumptions!B7/12 -> 500
A24: 23 | B24: =Funding_Draw!B2/24 -> 100000 | C24: =B2*Assumptions!B7/12 -> 500
A25: 24 | B25: =Funding_Draw!B2/24 -> 100000 | C25: =B2*Assumptions!B7/12 -> 500

Sheet Debt_Sculpt
A1: Year | B1: Opening Debt | C1: Debt Service | D1: Closing Debt
A2: 1 | B2: =Funding_Draw!B2 -> 2400000 | C2: =B2*0.15 -> 360000 | D2: =B2-C2 -> 2040000
A3: 2 | B3: =D2 -> 2040000 | C3: =B2*0.15 -> 360000 | D3: =B2-C2 -> 2040000
A4: 3 | B4: =D3 -> 2040000 | C4: =B3*0.15 -> 306000 | D4: =B3-C3 -> 1680000
A5: 4 | B5: =D4 -> 1680000 | C5: =B4*0.15 -> 306000 | D5: =B4-C4 -> 1734000
A6: 5 | B6: =D5 -> 1734000 | C6: =B5*0.15 -> 252000 | D6: =B5-C5 -> 1374000
A7: 6 | B7: =D6 -> 1374000 | C7: =B6*0.15 -> 260100 | D7: =B6-C6 -> 1482000
A8: 7 | B8: =D7 -> 1482000 | C8: =B7*0.15 -> 206100 | D8: =B7-C7 -> 1113900
A9: 8 | B9: =D8 -> 1113900 | C9: =B8*0.15 -> 222300 | D9: =B8-C8 -> 1275900

Sheet Financials
A1: Year | B1: Revenue | C1: EBITDA | D1: Debt Service
A2: =Assumptions!$B$12+0 -> 2026 | B2: =Sales_Drivers!F4 -> 2668050 | C2: =Cost_Drivers!J4 -> 110498 | D2: =Debt_Sculpt!C2 -> 360000
A3: =Assumptions!$B$12+1 -> 2027 | B3: =Sales_Drivers!F5 -> 4371963.8 | C3: =Cost_Drivers!J5 -> 711989.75 | D3: =Debt_Sculpt!C3 -> 360000
A4: =Assumptions!$B$12+2 -> 2028 | B4: =Sales_Drivers!F6 -> 6561693 | C4: =Cost_Drivers!J6 -> 1501117.2 | D4: =Debt_Sculpt!C4 -> 306000

Sheet DSCR
A1: Year | B1: EBITDA | C1: Debt Service | D1: DSCR
A2: =Assumptions!$B$12+0 -> 2026 | B2: =Financials!C2 -> 110498 | C2: =Financials!D2 -> 360000 | D2: =IF(C2=0,"-",B2/C2) -> 0.30693889
A3: =Assumptions!$B$12+1 -> 2027 | B3: =Financials!C3 -> 711989.75 | C3: =Financials!D3 -> 360000 | D3: =IF(C3=0,"-",B3/C3) -> 1.9777493
A4: =Assumptions!$B$12+2 -> 2028 | B4: =Financials!C4 -> 1501117.2 | C4: =Financials!D4 -> 306000 | D4: =IF(C4=0,"-",B4/C4) -> 4.9056118

Sheet NPV_IRR
A1: VALUATION (Connected Cash Flows → NPV / IRR)
A2: IRR | B2: =IRR(Financials!C2:C4) -> #VALUE!
A3: Year | B3: EBITDA | C3: CAPEX | D3: Debt Service | E3: Free Cash Flow
A4: =Assumptions!$B$12+0 -> 2026 | B4: =Financials!C2 -> 110498 | C4: =-Assumptions!$B$28*Assumptions!$B$29 -> -7056000 | D4: =-Financials!D2 -> -360000 | E4: =B4+C4+D4 -> -7305502
A5: =Assumptions!$B$12+1 -> 2027 | B5: =Financials!C3 -> 711989.75 | C5: =-Assumptions!$B$28*Assumptions!$B$30 -> -4704000 | D5: =-Financials!D3 -> -360000 | E5: =B5+C5+D5 -> -4352010.2
A6: =Assumptions!$B$12+2 -> 2028 | B6: =Financials!C4 -> 1501117.2 | C6: =-Assumptions!$B$28*Assumptions!$B$31 -> 0 | D6: =-Financials!D4 -> -306000 | E6: =B6+C6+D6 -> 1195117.2
A8: Discount Rate | B8: 0.08
A9: NPV | B9: =NPV($B$8,E4:E6) -> -9546778.5
A10: IRR | B10: =IRR(E4:E6) -> -0.7955527

Sheet Sensitivity
A1: Scenario | B1: Revenue Impact | C1: EBITDA Impact
A2: Base | B2: 1 | C2: 1
A3: Downside | B3: 0.9 | C3: 0.85
A4: Upside | B4: 1.1 | C4: 1.2

Sheet Dashboard
A1: KPI | B1: Value
A2: Total CAPEX | B2: =Assumptions!B2 -> 12000000
A3: Debt Amount | B3: =Funding_Draw!B2 -> 2400000
A4: Grant Amount | B4: =Funding_Draw!B1 -> Amount (€)
A5: IRR | B5: =NPV_IRR!B2 -> #VALUE!

Sheet Sources_Uses
A1: SOURCES & USES SUMMARY
A3: Sources | D3: Uses
A4: Equity | B4: 2000000 | D4: CAPEX | E4: 11000000 | G4: Check (Sources - Uses) | H4: =B8-E8 -> 0
A5: Senior Debt | B5: 6000000 | D5: IDC | E5: 500000
A6: Grant | B6: 4000000 | D6: Fees | E6: 500000
A8: Total Sources | B8: =SUM(B4:B6) -> 12000000 | D8: Total Uses | E8: =SUM(E4:E6) -> 12000000

Sheet DSRA
A1: DEBT SERVICE RESERVE ACCOUNT
A3: Period | B3: Debt Service | C3: DSRA Required (6M) | D3: Opening | E3: Funding | F3: Closing
A4: 1 | B4: 200000 | C4: =B4*0.5 -> 100000 | D4: 0 | E4: =MAX(0,C4-D4) -> 100000 | F4: =D4+E4 -> 100000
A5: 2 | B5: 200000 | C5: =B5*0.5 -> 100000 | D5: =F4 -> 100000 | E5: =MAX(0,C5-D5) -> 0 | F5: =D5+E5 -> 100000
A6: 3 | B6: 200000 | C6: =B6*0.5 -> 100000 | D6: =F5 -> 100000 | E6: =MAX(0,C6-D6) -> 0 | F6: =D6+E6 -> 100000
A7: 4 | B7: 200000 | C7: =B7*0.5 -> 100000 | D7: =F6 -> 100000 | E7: =MAX(0,C7-D7) -> 0 | F7: =D7+E7 -> 100000
A8: 5 | B8: 200000 | C8: =B8*0.5 -> 100000 | D8: =F7 -> 100000 | E8: =MAX(0,C8-D8) -> 0 | F8: =D8+E8 -> 100000
A9: 6 | B9: 200000 | C9: =B9*0.5 -> 100000 | D9: =F8 -> 100000 | E9: =MAX(0,C9-D9) -> 0 | F9: =D9+E9 -> 100000

Sheet Covenants
A1: COVENANT TESTING
A3: Period | B3: DSCR | C3: Min Required | D3: Status
A4: 1 | B4: 1.3 | C4: 1.2 | D4: =IF(B4>=C4,"OK","BREACH") -> OK
A5: 2 | B5: 1.3 | C5: 1.2 | D5: =IF(B5>=C5,"OK","BREACH") -> OK
A6: 3 | B6: 1.3 | C6: 1.2 | D6: =IF(B6>=C6,"OK","BREACH") -> OK
A7: 4 | B7: 1.3 | C7: 1.2 | D7: =IF(B7>=C7,"OK","BREACH") -> OK
A8: 5 | B8: 1.3 | C8: 1.2 | D8: =IF(B8>=C8,"OK","BREACH") -> OK
A9: 6 | B9: 1.3 | C9: 1.2 | D9: =IF(B9>=C9,"OK","BREACH") -> OK

Sheet Monte_Carlo
A1: MONTE CARLO (Formula-based) — Press F9 to Recalculate
A3: Inputs | B3: Revenue Factor | C3: Cost Factor | D3: IRR Result
A4: Iterations | B4: 200 | C4: =NORMINV(RAND(),1,0.1) -> 0.75710012 | D4: =RAND() -> 0.77962762
A5: Revenue Sigma (stdev) | B5: 0.1 | C5: =NORMINV(RAND(),1,0.1) -> 0.99526132 | D5: =RAND() -> 0.76569022
A6: Cost Sigma (stdev) | B6: 0.1 | C6: =NORMINV(RAND(),1,0.1) -> 1.0565801 | D6: =RAND() -> 0.35433665
A7: Discount Rate | B7: =NPV_IRR!B8 -> 0.08 | C7: =NORMINV(RAND(),1,0.1) -> 0.98629649 | D7: =RAND() -> 0.4448094
A8: 5 | B8: =NORMINV(RAND(),1,0.1) -> 0.80554898 | C8: =NORMINV(RAND(),1,0.1) -> 0.98407341 | D8: =RAND() -> 0.68757914
A9: Iter | B9: Rev Factor | C9: Cost Factor | D9: IRR | E9: NPV | F9: FCF Y1 | G9: FCF Y2 | H9: FCF Y3 | J9: Base FCF
A10: 1 | B10: =NORMINV(RAND(),1,$B$5) -> 0.71410099 | C10: =NORMINV(RAND(),1,$B$6) -> 0.89375569 | D10: =IFERROR(IRR(F10:H10),"") -> -2 | E10: =IFERROR(NPV($B$7,F10:H10),"") -> -7627771.3 | F10: =$J$10*B10/C10 -> -5837016 | G10: =$J$11*B10/C10 -> -3477208.5 | H10: =$J$12*B10/C10 -> 954885.54 | J10: =NPV_IRR!E4 -> -7305502
A11: 2 | B11: =NORMINV(RAND(),1,$B$5) -> 0.97291279 | C11: =NORMINV(RAND(),1,$B$6) -> 0.91671367 | D11: =IFERROR(IRR(F11:H11),"") -> -2 | E11: =IFERROR(NPV($B$7,F11:H11),"") -> -10132044 | F11: =$J$10*B11/C11 -> -7753365.7 | G11: =$J$11*B11/C11 -> -4618810.1 | H11: =$J$12*B11/C11 -> 1268383.8 | J11: =NPV_IRR!E5 -> -4352010.2
A12: 3 | B12: =NORMINV(RAND(),1,$B$5) -> 0.79294513 | C12: =NORMINV(RAND(),1,$B$6) -> 1.0966211 | D12: =IFERROR(IRR(F12:H12),"") -> -2 | E12: =IFERROR(NPV($B$7,F12:H12),"") -> -6903087.7 | F12: =$J$10*B12/C12 -> -5282464.8 | G12: =$J$11*B12/C12 -> -3146853 | H12: =$J$12*B12/C12 -> 864165.74 | J12: =NPV_IRR!E6 -> 1195117.2
A13: 4 | B13: =NORMINV(RAND(),1,$B$5) -> 1.0432069 | C13: =NORMINV(RAND(),1,$B$6) -> 0.86405457 | D13: =IFERROR(IRR(F13:H13),"") -> -2 | E13: =IFERROR(NPV($B$7,F13:H13),"") -> -11526200 | F13: =$J$10*B13/C13 -> -8820218.8 | G13: =$J$11*B13/C13 -> -5254352.5 | H13: =$J$12*B13/C13 -> 1442911.8
A14: 5 | B14: =NORMINV(RAND(),1,$B$5) -> 0.97224422 | C14: =NORMINV(RAND(),1,$B$6) -> 1.0253473 | D14: =IFERROR(IRR(F14:H14),"") -> -2 | E14: =IFERROR(NPV($B$7,F14:H14),"") -> -9052348 | F14: =$J$10*B14/C14 -> -6927147.9 | G14: =$J$11*B14/C14 -> -4126618.3 | H14: =$J$12*B14/C14 -> 1133221.7
A15: 6 | B15: =NORMINV(RAND(),1,$B$5) -> 1.084374 | C15: =NORMINV(RAND(),1,$B$6) -> 0.9449312 | D15: =IFERROR(IRR(F15:H15),"") -> -2 | E15: =IFERROR(NPV($B$7,F15:H15),"") -> -10955590 | F15: =$J$10*B15/C15 -> -8383569.6 | G15: =$J$11*B15/C15 -> -4994233.2 | H15: =$J$12*B15/C15 -> 1371479.8
A16: 7 | B16: =NORMINV(RAND(),1,$B$5) -> 1.0720414 | C16: =NORMINV(RAND(),1,$B$6) -> 1.0286345 | D16: =IFERROR(IRR(F16:H16),"") -> -2 | E16: =IFERROR(NPV($B$7,F16:H16),"") -> -9949639 | F16: =$J$10*B16/C16 -> -7613783.9 | G16: =$J$11*B16/C16 -> -4535658.9 | H16: =$J$12*B16/C16 -> 1245549.5
A17: 8 | B17: =NORMINV(RAND(),1,$B$5) -> 1.1179266 | C17: =NORMINV(RAND(),1,$B$6) -> 0.92009539 | D17: =IFERROR(IRR(F17:H17),"") -> -2 | E17: =IFERROR(NPV($B$7,F17:H17),"") -> -11599447 | F17: =$J$10*B17/C17 -> -8876270.2 | G17: =$J$11*B17/C17 -> -5287743.2 | H17: =$J$12*B17/C17 -> 1452081.4
A18: 9 | B18: =NORMINV(RAND(),1,$B$5) -> 0.85238346 | C18: =NORMINV(RAND(),1,$B$6) -> 1.1308624 | D18: =IFERROR(IRR(F18:H18),"") -> -2 | E18: =IFERROR(NPV($B$7,F18:H18),"") -> -7195849.6 | F18: =$J$10*B18/C18 -> -5506495.6 | G18: =$J$11*B18/C18 -> -3280311.9 | H18: =$J$12*B18/C18 -> 900815.26
A19: 10 | B19: =NORMINV(RAND(),1,$B$5) -> 1.0753881 | C19: =NORMINV(RAND(),1,$B$6) -> 1.0598552 | D19: =IFERROR(IRR(F19:H19),"") -> -2 | E19: =IFERROR(NPV($B$7,F19:H19),"") -> -9686693.4 | F19: =$J$10*B19/C19 -> -7412569.4 | G19: =$J$11*B19/C19 -> -4415792.1 | H19: =$J$12*B19/C19 -> 1212632.5
A20: 11 | B20: =NORMINV(RAND(),1,$B$5) -> 0.94838032 | C20: =NORMINV(RAND(),1,$B$6) -> 1.1397109 | D20: =IFERROR(IRR(F20:H20),"") -> -2 | E20: =IFERROR(NPV($B$7,F20:H20),"") -> -7944099.2 | F20: =$J$10*B20/C20 -> -6079080.3 | G20: =$J$11*B20/C20 -> -3621410.2 | H20: =$J$12*B20/C20 -> 994485.18
A21: 12 | B21: =NORMINV(RAND(),1,$B$5) -> 0.804067 | C21: =NORMINV(RAND(),1,$B$6) -> 1.0461718 | D21: =IFERROR(IRR(F21:H21),"") -> -2 | E21: =IFERROR(NPV($B$7,F21:H21),"") -> -7337465.2 | F21: =$J$10*B21/C21 -> -5614864.4 | G21: =$J$11*B21/C21 -> -3344869 | H21: =$J$12*B21/C21 -> 918543.46
A22: 13 | B22: =NORMINV(RAND(),1,$B$5) -> 1.0331901 | C22: =NORMINV(RAND(),1,$B$6) -> 0.91252622 | D22: =IFERROR(IRR(F22:H22),"") -> -2 | E22: =IFERROR(NPV($B$7,F22:H22),"") -> -10809154 | F22: =$J$10*B22/C22 -> -8271512.5 | G22: =$J$11*B22/C22 -> -4927478.9 | H22: =$J$12*B22/C22 -> 1353148.2
A23: 14 | B23: =NORMINV(RAND(),1,$B$5) -> 1.0740935 | C23: =NORMINV(RAND(),1,$B$6) -> 1.008719 | D23: =IFERROR(IRR(F23:H23),"") -> -2 | E23: =IFERROR(NPV($B$7,F23:H23),"") -> -10165500 | F23: =$J$10*B23/C23 -> -7778967.7 | G23: =$J$11*B23/C23 -> -4634061.7 | H23: =$J$12*B23/C23 -> 1272572.1
A24: 15 | B24: =NORMINV(RAND(),1,$B$5) -> 0.96404853 | C24: =NORMINV(RAND(),1,$B$6) -> 0.91607413 | D24: =IFERROR(IRR(F24:H24),"") -> -2 | E24: =IFERROR(NPV($B$7,F24:H24),"") -> -10046739 | F24: =$J$10*B24/C24 -> -7688087.9 | G24: =$J$11*B24/C24 -> -4579923.1 | H24: =$J$12*B24/C24 -> 1257705
... A209: 200 | B209: =NORMINV(RAND(),1,$B$5) | C209: =NORMINV(RAND(),1,$B$6) | D209: =IFERROR(IRR(F209:H209),"") | E209: =IFERROR(NPV($B$7,F209:H209),"") | F209: =$J$10*B209/C209 | G209: =$J$11*B209/C209 | H209: =$J$12*B209/C209
A212: Summary
A213: Metric | B213: P10 | C213: P50 | D213: P90
A214: IRR | B214: =_xludf.PERCENTILE.INC(D10:D209,0.1) | C214: =_xludf.PERCENTILE.INC(D10:D209,0.5) | D214: =_xludf.PERCENTILE.INC(D10:D209,0.9)
A215: NPV | B215: =_xludf.PERCENTILE.INC(E10:E209,0.1) | C215: =_xludf.PERCENTILE.INC(E10:E209,0.5) | D215: =_xludf.PERCENTILE.INC(E10:E209,0.9)

Sheet Sensitivity_Tornado
A1: TORNADO SENSITIVITY
A3: Variable | B3: Low IRR | C3: Base IRR | D3: High IRR
A4: Revenue | B4: 0.12 | C4: 0.15 | D4: 0.18
A5: CAPEX | B5: 0.12 | C5: 0.15 | D5: 0.18
A6: OPEX | B6: 0.12 | C6: 0.15 | D6: 0.18
A7: Interest Rate | B7: 0.12 | C7: 0.15 | D7: 0.18
A8: Production | B8: 0.12 | C8: 0.15 | D8: 0.18

Sheet Bank_Pack
A1: BANK PRESENTATION KPIs
A3: Metric | B3: Value
A4: Project IRR | B4: 0.18
A5: Equity IRR | B5: 0.22
A6: Min DSCR | B6: 1.35
A7: NPV | B7: 2500000
A8: Payback | B8: 6

Sheet CFADS_Module
A1: Year | B1: EBITDA | C1: Taxes | D1: Maintenance CAPEX | E1: Δ Working Capital | F1: Other Adjustments | G1: CFADS

Sheet Debt_Sculpt_DSCR
A1: Year | B1: Opening Debt | C1: Interest | D1: Allowed Debt Service (CFADS/Target) | E1: Principal | F1: Total Debt Service | G1: Closing Debt | H1: DSCR

Sheet S_Curve_Drawdown
A1: Month | B1: Base CAPEX | C1: S-Curve Factor | D1: Adjusted Draw

Sheet LLCR_PLCR
A1: Metric | B1: Value

Sheet Equity_Waterfall
A1: Year | B1: Equity Investment | C1: Dividends | D1: Exit Proceeds | E1: Equity Cash Flow | F1: Equity IRR

Sheet Credit_Committee_Pack
A1: KPI | B1: Value | C1: Threshold | D1: Status

Sheet CAPEX_Master
A1: CAPEX_Master_ID | B1: ID | C1: Faza | D1: CAPEX_Stavka | E1: Opis_kratko | F1: BS_kategorija | G1: BU_efekat | H1: Cijena_EUR | I1: Source_finansiranja | J1: Status | K1: Datum_plaćanja | L1: Napomena | M1: BOQ_link
A2: ARS-CAPEX-0001 | B2: 1.1 | C2: Osnivanje i priprema | D2: Registracija firme | E2: Troškovi registracije d.o.o. u CRPS, sudske takse i pečati | F2: Nematerijalna imovina | G2: Proizvodni pogon | H2: 2500 | I2: Sopstvena sredstva | J2: Plaćeno | K2: 44972 | L2: Minimalni za osnivanje | M2: BOQ_Permits
A3: ARS-CAPEX-0002 | B3: 1.2 | C3: Osnivanje i priprema | D3: Advokatske usluge | E3: Kompletna pravna podrška za statut, ugovore i registraciju | F3: Nematerijalna imovina | G3: Proizvodni pogon | H3: 4.5 | I3: Sopstvena sredstva | J3: Plaćeno | K3: 44986 | L3: Lokalna kancelarija | M3: BOQ_Permits
A4: ARS-CAPEX-0003 | B4: 1.3 | C4: Osnivanje i priprema | D4: Osnivački kapital | E4: Uplata minimalnog osnivačkog kapitala na račun firme | F4: Vlasnički kapital | G4: Proizvodni pogon | H4: 10 | I4: Sopstvena sredstva | J4: Plaćeno | K4: 44946 | L4: Neophodan za registraciju | M4: -
A5: ARS-CAPEX-0004 | B5: 1.4 | C5: Osnivanje i priprema | D5: Konsultantske usluge | E5: Poslovni plan, finansijski model i investiciona analiza | F5: Nematerijalna imovina | G5: Corporate | H5: 8 | I5: Sopstvena sredstva | J5: Plaćeno | K5: 45026 | L5: Priprema za investiciju | M5: BOQ_Admin
A6: ARS-CAPEX-0005 | B6: 1.5 | C6: Osnivanje i priprema | D6: Bankarske usluge | E6: Otvaranje računa, provizije i administracija | F6: Trošak perioda | G6: Corporate | H6: 600 | I6: Sopstvena sredstva | J6: Plaćeno | K6: 44975 | L6: Jednokratno | M6: -
A7: ARS-CAPEX-0006 | B7: 1.6 | C7: Osnivanje i priprema | D7: Troškovi licenciranja | E7: Industrijske dozvole i registracije djelatnosti | F7: Nematerijalna imovina | G7: Proizvodni pogon | H7: 3.2 | I7: Sopstvena sredstva | J7: Plaćeno | K7: 45051 | L7: Zakonski zahtjev | M7: BOQ_Permits
A8: ARS-CAPEX-0007 | B8: 1.7 | C8: Osnivanje i priprema | D8: Studija izvodljivosti | E8: Tehnička i ekonomska analiza projekta | F8: Nematerijalna imovina | G8: Proizvodni pogon | H8: 12 | I8: Sopstvena sredstva | J8: Plaćeno | K8: 45089 | L8: Investiciona osnova | M8: BOQ_Study
A9: ARS-CAPEX-0008 | B9: 1.8 | C9: Osnivanje i priprema | D9: Troškovi putovanja i sastanaka | E9: Putovanja investitora, pregovori sa partnerima | F9: Trošak perioda | G9: Corporate | H9: 5 | I9: Sopstvena sredstva | J9: Plaćeno | K9: 45108 | L9: Razvoj projekta | M9: -
A10: ARS-CAPEX-0009 | B10: 1.9 | C10: Osnivanje i priprema | D10: Marketing i prezentacija projekta | E10: Vizuali, prezentacije, promotivni materijal | F10: Nematerijalna imovina | G10: Corporate | H10: 3.5 | I10: Sopstvena sredstva | J10: Plaćeno | K10: 45127 | L10: Investitor pitch | M10: BOQ_Admin
A11: ARS-CAPEX-0010 | B11: 2.1 | C11: Kupovina zemljišta | D11: Kupoprodajna cijena zemljišta | E11: Nabavka 5.000 m² industrijskog zemljišta | F11: Dugotrajna imovina - Zemljište | G11: Proizvodni pogon | H11: 300 | I11: Bankarski kredit | J11: Plaćeno | K11: 45838 | L11: 60 €/m² | M11: BOQ_Land
A12: ARS-CAPEX-0011 | B12: 2.2 | C12: Kupovina zemljišta | D12: Notarske usluge | E12: Ovjera kupoprodajnog ugovora i upis u katastar | F12: Dugotrajna imovina - Zemljište | G12: Proizvodni pogon | H12: 6 | I12: Bankarski kredit | J12: Plaćeno | K12: 45843 | L12: Notar + katastar | M12: BOQ_Land
A13: ARS-CAPEX-0012 | B13: 2.3 | C13: Kupovina zemljišta | D13: Porez na promet nekretnina | E13: Porez 3 % na vrijednost transakcije | F13: Dugotrajna imovina - Zemljište | G13: Proizvodni pogon | H13: 9 | I13: Bankarski kredit | J13: Plaćeno | K13: 45848 | L13: Obavezan po zakonu | M13: BOQ_Land
... A16: ARS-CAPEX-0015 | B16: 2.6 | C16: Kupovina zemljišta | D16: Pravne provjere vlasništva | E16: Due diligence, provjera tereta i vlasničkih odnosa | F16: Dugotrajna imovina - Zemljište | G16: Corporate | H16: 4 | I16: Sopstvena sredstva | J16: Plaćeno | K16: 45828 | L16: Advokat | M16: BOQ_Land
A17: ARS-CAPEX-0016 | B17: 2.7 | C17: Kupovina zemljišta | D17: Troškovi prenamjene zemljišta | E17: Administrativni troškovi promjene namjene (ako je potrebno) | F17: Dugotrajna imovina - Zemljište | G17: Proizvodni pogon | H17: 15 | I17: Bankarski kredit | J17: Planirano | L17: Urbanistički zahtjevi | M17: BOQ_Land
A18: ARS-CAPEX-0017 | B18: 2.8 | C18: Kupovina zemljišta | D18: Komunalno opremanje parcele | E18: Priključci infrastrukture (voda, struja, pristupni put) | F18: Dugotrajna imovina - Zemljište | G18: Proizvodni pogon | H18: 25 | I18: Bankarski kredit | J18: Planirano | L18: Priprema za gradnju | M18: BOQ_Land
A19: ARS-CAPEX-0018 | B19: 3.1 | C19: Izrada betonske ograde i pripremni radovi | D19: Geodetsko snimanje | E19: Topografsko, katastarsko i geodetsko snimanje terena | F19: Dugotrajna imovina - Građevinski objekti | G19: Proizvodni pogon | H19: 4.5 | I19: Bankarski kredit | J19: Neplaćeno | K19: 46341 | L19: Neophodno za projektovanje | M19: BOQ_Civil
A20: ARS-CAPEX-0019 | B20: 3.2 | C20: Izrada betonske ograde i pripremni radovi | D20: Iskop i odvoz zemlje | E20: Iskop i odvoz 12.500 m³ zemlje (8,5 €/m³) | F20: Dugotrajna imovina - Građevinski objekti | G20: Proizvodni pogon | H20: 106.25 | I20: Bankarski kredit | J20: Neplaćeno | K20: 46461 | L20: Iz master modela | M20: BOQ_Civil
A21: ARS-CAPEX-0020 | B21: 3.3 | C21: Izrada betonske ograde i pripremni radovi | D21: Nasip i zbijanje | E21: Nasipanje i zbijanje 8.400 m³ (6,2 €/m³) | F21: Dugotrajna imovina - Građevinski objekti | G21: Proizvodni pogon | H21: 52.08 | I21: Bankarski kredit | J21: Neplaćeno | K21: 46478 | L21: Iz master modela | M21: BOQ_Civil
A22: ARS-CAPEX-0021 | B22: 3.4 | C22: Izrada betonske ograde i pripremni radovi | D22: Uklanjanje humusa | E22: Uklanjanje humusnog sloja sa 14.500 m² (1,8 €/m²) | F22: Dugotrajna imovina - Građevinski objekti | G22: Proizvodni pogon | H22: 26.1 | I22: Bankarski kredit | J22: Neplaćeno | K22: 46466 | L22: Iz master modela | M22: BOQ_Civil
A23: ARS-CAPEX-0022 | B23: 3.5 | C23: Izrada betonske ograde i pripremni radovi | D23: Izrada betonske ograde | E23: Betonska ograda oko parcele — temelj, stubovi i paneli | F23: Dugotrajna imovina - Građevinski objekti | G23: Proizvodni pogon | H23: 95 | I23: Bankarski kredit | J23: Neplaćeno | K23: 46507 | L23: Perimetarska zaštita | M23: BOQ_Civil
A24: ARS-CAPEX-0023 | B24: 3.6 | C24: Izrada betonske ograde i pripremni radovi | D24: Kapije i ulazni portal | E24: Industrijske klizne kapije, portirnica i kontrolni sistem | F24: Dugotrajna imovina - Građevinski objekti | G24: Proizvodni pogon | H24: 28 | I24: Bankarski kredit | J24: Neplaćeno | K24: 46517 | L24: Sigurnosni pristup | M24: BOQ_Civil
A25: ARS-CAPEX-0024 | B25: 3.7 | C25: Izrada betonske ograde i pripremni radovi | D25: Privremeni pristupni putevi | E25: Priprema gradilišnog pristupa i manipulativnih površina | F25: Dugotrajna imovina - Građevinski objekti | G25: Proizvodni pogon | H25: 18.5 | I25: Bankarski kredit | J25: Neplaćeno | K25: 46471 | L25: Logistika gradnje | M25: BOQ_Civil
A26: ARS-CAPEX-0025 | B26: 3.8 | C26: Izrada betonske ograde i pripremni radovi | D26: Privremeni priključci | E26: Privremeni priključak struje i vode za gradilište | F26: Dugotrajna imovina - Građevinski objekti | G26: Proizvodni pogon | H26: 12 | I26: Bankarski kredit | J26: Neplaćeno | K26: 46476 | L26: Gradilišni priključci | M26: BOQ_Civil
A27: ARS-CAPEX-0026 | B27: 3.9 | C27: Izrada betonske ograde i pripremni radovi | D27: Uređenje terena | E27: Nivelacija, tampon sloj, priprema za temelje | F27: Dugotrajna imovina - Građevinski objekti | G27: Proizvodni pogon | H27: 36 | I27: Bankarski kredit | J27: Neplaćeno | K27: 46487 | L27: Priprema za konstrukciju | M27: BOQ_Civil
A28: ARS-CAPEX-0027 | B28: 4.1 | C28: Projektovanje i Građevinska dozvola | D28: Idejni projekat | E28: Idejni arhitektonski i urbanistički projekat | F28: Nematerijalna imovina | G28: Proizvodni pogon | H28: 22 | I28: Sopstvena sredstva | J28: Plaćeno | K28: 46081 | L28: Arhitektonski biro | M28: BOQ_Permits
A29: ARS-CAPEX-0028 | B29: 4.2 | C29: Projektovanje i Građevinska dozvola | D29: Glavni projekat | E29: Glavni projekat (arhitektura + konstrukcija + instalacije) | F29: Nematerijalna imovina | G29: Proizvodni pogon | H29: 48 | I29: Bankarski kredit | J29: U toku | K29: 46203 | L29: Sve discipline | M29: BOQ_Permits
A30: ARS-CAPEX-0029 | B30: 4.3 | C30: Projektovanje i Građevinska dozvola | D30: Revizija projekta | E30: Nezavisna stručna revizija dokumentacije | F30: Nematerijalna imovina | G30: Proizvodni pogon | H30: 8.5 | I30: Bankarski kredit | J30: Neplaćeno | K30: 46249 | L30: Obavezna po zakonu | M30: BOQ_Permits
... A127: ARS-CAPEX-0126 | B127: TRN.5 | C127: Trening centar | D127: Sigurnosna oprema | E127: Zaštitna oprema za trening | F127: Dugotrajna imovina - Oprema | G127: HR | H127: 6.8 | I127: Kredit | J127: Planirano | K127: 47067 | L127: Safety training | M127: BOQ_Admin
