Workbook

Sheet Executive Summary
A1: ARS Metal Industries — Cash Conversion Cycle (CCC) Executive Summary
A3: Concept: Cash Conversion Cycle
A4: Cash Conversion Cycle (CCC) measures how many days cash is tied in operations before it returns as revenue. It combines inventory holding (DIO), receivables collection (DSO), and supplier payment timing (DPO). Formula: CCC = DIO + DSO − DPO
A8: Key CCC Indicators (linked to model)
A9: Metric | B9: Value | C9: Interpretation
A10: Current CCC (Year 1) | B10: ='Dashboard'!B4 | C10: Days cash is tied in operations today
A11: Target CCC | B11: ='Dashboard'!B5 | C11: Management target for optimized working capital
A12: CCC Improvement | B12: ='Dashboard'!B6 | C12: Reduction achieved by operational optimization
A13: Improvement % | B13: ='Dashboard'!B7 | C13: Relative improvement in liquidity cycle
A15: Operational Drivers of CCC (ARS Metal Industries)
A16: DIO (Inventory Days): driven primarily by steel stock strategy and WIP buffers. DSO (Receivable Days): influenced by EPC/OEM contract payment terms and milestone payments. DPO (Payable Days): negotiated supplier payment terms with steel mills and component suppliers. For ARS Metal Industries, optimizing these parameters directly improves working capital efficiency, reduces financing needs, and strengthens CFADS available for debt service and reinvestment.

Sheet Assumptions
A1: Cash Conversion Cycle (CCC) — Professional Model (ARS / Montenegro)
A3: Scenario | B3: Base | C3: Options: Base / Optimistic / Pessimistic
A5: Key Assumptions (editable inputs)
A6: Parameter | B6: Value | C6: Unit | D6: Notes
A7: Start Year | B7: 2026
A8: End Year | B8: 2030
A9: Days in Year | B9: 365 | D9: Use 365 unless you want 360 banking convention
A10: Revenue (Year 1) | B10: 5000000 | C10: €
A11: COGS (% of Revenue) | B11: =CHOOSE($B$23,$B$18,$C$18,$D$18) | C11: %
A12: Revenue Growth (YoY) | B12: =CHOOSE($B$23,$B$17,$C$17,$D$17) | C12: %
A13: Target CCC (days) | B13: 45 | C13: days | D13: Typical investor target: <45 days
A15: Scenario Inputs (optional overrides)
A16: Metric | B16: Base | C16: Optimistic | D16: Pessimistic | E16: Unit | F16: Notes
A17: Revenue Growth (YoY) | B17: 0.12 | C17: 0.15 | D17: 0.08 | E17: %
A18: COGS (% of Revenue) | B18: 0.65 | C18: 0.63 | D18: 0.68 | E18: %
A19: DSO shift (days) | B19: 0 | C19: -5 | D19: 10 | E19: days | F19: Scenario adjustment applied to yearly path
A20: DPO shift (days) | B20: 0 | C20: 5 | D20: -5 | E20: days | F20: Scenario adjustment applied to yearly path
A21: DIO shift (days) | B21: 0 | C21: -5 | D21: 10 | E21: days | F21: Scenario adjustment applied to yearly path
A23: Scenario Index | B23: =MATCH(B3,{"Base","Optimistic","Pessimistic"},0)
A25: Operational Working-Capital Targets by Year (editable)
A26: Year | B26: DIO (days) | C26: DSO (days) | D26: DPO (days) | E26: Notes
A27: 2026 | B27: =45 + CHOOSE($B$23,$B$21,$C$21,$D$21) | C27: =60 + CHOOSE($B$23,$B$19,$C$19,$D$19) | D27: =30 + CHOOSE($B$23,$B$20,$C$20,$D$20) | E27: Edit path (e.g., WMS, milestones, supplier terms)
A28: 2027 | B28: =41 + CHOOSE($B$23,$B$21,$C$21,$D$21) | C28: =56 + CHOOSE($B$23,$B$19,$C$19,$D$19) | D28: =34 + CHOOSE($B$23,$B$20,$C$20,$D$20) | E28: Edit path (e.g., WMS, milestones, supplier terms)
A29: 2028 | B29: =38 + CHOOSE($B$23,$B$21,$C$21,$D$21) | C29: =52 + CHOOSE($B$23,$B$19,$C$19,$D$19) | D29: =38 + CHOOSE($B$23,$B$20,$C$20,$D$20) | E29: Edit path (e.g., WMS, milestones, supplier terms)
A30: 2029 | B30: =34 + CHOOSE($B$23,$B$21,$C$21,$D$21) | C30: =48 + CHOOSE($B$23,$B$19,$C$19,$D$19) | D30: =42 + CHOOSE($B$23,$B$20,$C$20,$D$20) | E30: Edit path (e.g., WMS, milestones, supplier terms)
A31: 2030 | B31: =30 + CHOOSE($B$23,$B$21,$C$21,$D$21) | C31: =45 + CHOOSE($B$23,$B$19,$C$19,$D$19) | D31: =45 + CHOOSE($B$23,$B$20,$C$20,$D$20) | E31: Edit path (e.g., WMS, milestones, supplier terms)

Sheet CCC Calculation
A1: CCC Calculation (2026–2030) — standard formulas + audit trail
A3: Year | B3: Revenue (€) | C3: COGS (€) | D3: Avg Inventory (€) | E3: Avg AR (€) | F3: Avg AP (€) | G3: DIO (days) | H3: DSO (days) | I3: DPO (days) | J3: CCC (days) | K3: Notes
A4: 2026 | B4: =Assumptions!B10 | C4: =B4*Assumptions!B11 | D4: =(INDEX(Assumptions!$B$27:$B$31, MATCH(A4, Assumptions!$A$27:$A$31, 0))/Assumptions!B9)*C4 | E4: =(INDEX(Assumptions!$C$27:$C$31, MATCH(A4, Assumptions!$A$27:$A$31, 0))/Assumptions!B9)*B4 | F4: =(INDEX(Assumptions!$D$27:$D$31, MATCH(A4, Assumptions!$A$27:$A$31, 0))/Assumptions!B9)*C4 | G4: =(D4/C4)*Assumptions!B9 | H4: =(E4/B4)*Assumptions!B9 | I4: =(F4/C4)*Assumptions!B9 | J4: =G4+H4-I4 | K4: DIO/DSO/DPO computed from balances (audit-ready)
A5: 2027 | B5: =B4*(1+Assumptions!B12) | C5: =B5*Assumptions!B11 | D5: =(INDEX(Assumptions!$B$27:$B$31, MATCH(A5, Assumptions!$A$27:$A$31, 0))/Assumptions!B9)*C5 | E5: =(INDEX(Assumptions!$C$27:$C$31, MATCH(A5, Assumptions!$A$27:$A$31, 0))/Assumptions!B9)*B5 | F5: =(INDEX(Assumptions!$D$27:$D$31, MATCH(A5, Assumptions!$A$27:$A$31, 0))/Assumptions!B9)*C5 | G5: =(D5/C5)*Assumptions!B9 | H5: =(E5/B5)*Assumptions!B9 | I5: =(F5/C5)*Assumptions!B9 | J5: =G5+H5-I5 | K5: DIO/DSO/DPO computed from balances (audit-ready)
A6: 2028 | B6: =B5*(1+Assumptions!B12) | C6: =B6*Assumptions!B11 | D6: =(INDEX(Assumptions!$B$27:$B$31, MATCH(A6, Assumptions!$A$27:$A$31, 0))/Assumptions!B9)*C6 | E6: =(INDEX(Assumptions!$C$27:$C$31, MATCH(A6, Assumptions!$A$27:$A$31, 0))/Assumptions!B9)*B6 | F6: =(INDEX(Assumptions!$D$27:$D$31, MATCH(A6, Assumptions!$A$27:$A$31, 0))/Assumptions!B9)*C6 | G6: =(D6/C6)*Assumptions!B9 | H6: =(E6/B6)*Assumptions!B9 | I6: =(F6/C6)*Assumptions!B9 | J6: =G6+H6-I6 | K6: DIO/DSO/DPO computed from balances (audit-ready)
A7: 2029 | B7: =B6*(1+Assumptions!B12) | C7: =B7*Assumptions!B11 | D7: =(INDEX(Assumptions!$B$27:$B$31, MATCH(A7, Assumptions!$A$27:$A$31, 0))/Assumptions!B9)*C7 | E7: =(INDEX(Assumptions!$C$27:$C$31, MATCH(A7, Assumptions!$A$27:$A$31, 0))/Assumptions!B9)*B7 | F7: =(INDEX(Assumptions!$D$27:$D$31, MATCH(A7, Assumptions!$A$27:$A$31, 0))/Assumptions!B9)*C7 | G7: =(D7/C7)*Assumptions!B9 | H7: =(E7/B7)*Assumptions!B9 | I7: =(F7/C7)*Assumptions!B9 | J7: =G7+H7-I7 | K7: DIO/DSO/DPO computed from balances (audit-ready)
A8: 2030 | B8: =B7*(1+Assumptions!B12) | C8: =B8*Assumptions!B11 | D8: =(INDEX(Assumptions!$B$27:$B$31, MATCH(A8, Assumptions!$A$27:$A$31, 0))/Assumptions!B9)*C8 | E8: =(INDEX(Assumptions!$C$27:$C$31, MATCH(A8, Assumptions!$A$27:$A$31, 0))/Assumptions!B9)*B8 | F8: =(INDEX(Assumptions!$D$27:$D$31, MATCH(A8, Assumptions!$A$27:$A$31, 0))/Assumptions!B9)*C8 | G8: =(D8/C8)*Assumptions!B9 | H8: =(E8/B8)*Assumptions!B9 | I8: =(F8/C8)*Assumptions!B9 | J8: =G8+H8-I8 | K8: DIO/DSO/DPO computed from balances (audit-ready)

Sheet Dashboard
A1: Dashboard / Summary (Investor View)
A3: Key Indicators
A4: Current CCC (Year 1) | B4: ='CCC Calculation'!J4
A5: Target CCC (days) | B5: =Assumptions!B13
A6: Improvement (Year 1 → Year 5) | B6: ='CCC Calculation'!J4-'CCC Calculation'!J8
A7: Improvement (%) | B7: =IF('CCC Calculation'!J4=0,0,B6/'CCC Calculation'!J4)
A9: Interpretation (Cash Flow Meaning)
A10: CCC = Inventory + Receivables − Payables (in days). Lower CCC reduces working capital and improves liquidity.
A11: For ARS (material-heavy COGS), CCC materially drives CFADS, debt headroom, and IRR.
A12: Negative CCC is excellent; CCC > 60 days often signals higher liquidity risk.
A14: CCC Decomposition (Year 1)
A15: Component | B15: Days | C15: Effect on CCC
A16: DIO | B16: ='CCC Calculation'!G4 | C16: + increases CCC
A17: DSO | B17: ='CCC Calculation'!H4 | C17: + increases CCC
A18: DPO | B18: ='CCC Calculation'!I4 | C18: − reduces CCC
A19: CCC | B19: ='CCC Calculation'!J4 | C19: Result

Sheet Sensitivity
A1: Sensitivity Analysis — CCC impact of ±10 days changes (Year 1)
A3: Base (Year 1)
A4: DIO | B4: ='CCC Calculation'!G4
A5: DSO | B5: ='CCC Calculation'!H4
A6: DPO | B6: ='CCC Calculation'!I4
A7: CCC | B7: ='CCC Calculation'!J4
A9: One-way sensitivity (Year 1 CCC)
A10: Change (days) | B10: CCC vs DIO | C10: CCC vs DSO | D10: CCC vs DPO | F10: Two-way: CCC with DIO & DSO shifts (DPO fixed)
A11: -10 | B11: =($B$4+A11)+$B$5-$B$6 | C11: =$B$4+($B$5+A11)-$B$6 | D11: =$B$4+$B$5-($B$6+A11) | F11: DIO\DSO | G11: -10 | H11: -5 | I11: 0 | J11: 5 | K11: 10
A12: -5 | B12: =($B$4+A12)+$B$5-$B$6 | C12: =$B$4+($B$5+A12)-$B$6 | D12: =$B$4+$B$5-($B$6+A12) | F12: -10 | G12: =($B$4+-10)+($B$5+-10)-$B$6 | H12: =($B$4+-10)+($B$5+-5)-$B$6 | I12: =($B$4+-10)+($B$5+0)-$B$6 | J12: =($B$4+-10)+($B$5+5)-$B$6 | K12: =($B$4+-10)+($B$5+10)-$B$6
A13: 0 | B13: =($B$4+A13)+$B$5-$B$6 | C13: =$B$4+($B$5+A13)-$B$6 | D13: =$B$4+$B$5-($B$6+A13) | F13: -5 | G13: =($B$4+-5)+($B$5+-10)-$B$6 | H13: =($B$4+-5)+($B$5+-5)-$B$6 | I13: =($B$4+-5)+($B$5+0)-$B$6 | J13: =($B$4+-5)+($B$5+5)-$B$6 | K13: =($B$4+-5)+($B$5+10)-$B$6
A14: 5 | B14: =($B$4+A14)+$B$5-$B$6 | C14: =$B$4+($B$5+A14)-$B$6 | D14: =$B$4+$B$5-($B$6+A14) | F14: 0 | G14: =($B$4+0)+($B$5+-10)-$B$6 | H14: =($B$4+0)+($B$5+-5)-$B$6 | I14: =($B$4+0)+($B$5+0)-$B$6 | J14: =($B$4+0)+($B$5+5)-$B$6 | K14: =($B$4+0)+($B$5+10)-$B$6
A15: 10 | B15: =($B$4+A15)+$B$5-$B$6 | C15: =$B$4+($B$5+A15)-$B$6 | D15: =$B$4+$B$5-($B$6+A15) | F15: 5 | G15: =($B$4+5)+($B$5+-10)-$B$6 | H15: =($B$4+5)+($B$5+-5)-$B$6 | I15: =($B$4+5)+($B$5+0)-$B$6 | J15: =($B$4+5)+($B$5+5)-$B$6 | K15: =($B$4+5)+($B$5+10)-$B$6
F16: 10 | G16: =($B$4+10)+($B$5+-10)-$B$6 | H16: =($B$4+10)+($B$5+-5)-$B$6 | I16: =($B$4+10)+($B$5+0)-$B$6 | J16: =($B$4+10)+($B$5+5)-$B$6 | K16: =($B$4+10)+($B$5+10)-$B$6
